Workbook
Name Lake: PC!$B$467
Name b: 'Master List'!$A:$A
Name dragon: 'Master List'!$A$1661
Name assass: 'Master List'!$A$872
Name onrush: 'Master List'!$A$1157
Name Tiny: 'Xbox Game Studios'!$A$1
Name civ: PC!$A$1
Name gris: 'Master List'!$A$1564
Name PC: 'Master List'!$A$2
Name hellslinger: xCloud!$K$85
Name chain: 'Master List'!$A$1
Name persona: Removed!$H$288:$H$295
Name banjo: Removed!$I$110
Name banjo: 'Master List'!$I$1186
Name YEARDUR: LAMBDA(start, end, lambda(s, e, if(s > e, -1 , 1 ) * yearfrac(s, e, 4))(if(isblank(start),today(),start), if(isblank(end),today(),end)))
Name MONTHDUR: LAMBDA(start, end, YEARDUR(start, end) * 12)

Sheet Master List
A1: Complete Game Pass Master List by u/ABattleVet | B1: =COUNTIFS(D2:D2121,"Active",B2:B2121,"<>")+COUNTIF(D2:D2121,"Leaving Soon") -> 687 | C1: Games with Gold | E1: GPU | H1: Playstation Plus | L1: See suggestions tab for color coding | N1: The community can add games to cross play/play anywhere | P1: Public Notes | R1: GP Premium (10/1/25 Standard 9/12/24)
A2: Game | B2: System | C2: xCloud | D2: Status | E2: Added | F2: Removed | G2: Months | H2: Release | I2: Age | J2: Metacritic | K2: Completion | L2: Genre | M2: Series X|S | N2: Owner Notes | O2: ESRB | P2: ESRB Content Descriptors | Q2: Community Notes | R2: Status | S2: Added | T2: Delay
A3: The Outer Worlds 2 | B3: Xbox / PC | C3: Yes | D3: =IF(E3>TODAY(),"Coming Soon",IF(F3="","Active",IF(F3>TODAY(),"Leaving Soon","Removed"))) -> Coming Soon | E3: 45959 | G3: =MONTHDUR(E3,F3) -> -0.46666667 | H3: =E3 -> 45959 | I3: =YEARDUR(H3,E3) -> 0 | L3: RPG | M3: Exclusive | R3: =IF(S3="","TBD",IF(S3>TODAY(),"Coming Soon",IF(F3="","Active",IF(F3>TODAY(),"Leaving Soon","Removed")))) -> TBD | T3: =MONTHDUR(E3,S3) -> -0.46666667
A4: Evil West | B4: Xbox / PC | C4: Yes | D4: =IF(E4>TODAY(),"Coming Soon",IF(F4="","Active",IF(F4>TODAY(),"Leaving Soon","Removed"))) -> Coming Soon | E4: 45951 | G4: =MONTHDUR(E4,F4) -> -0.2 | H4: 44887 | I4: =YEARDUR(H4,E4) -> 2.9138889 | J4: 73 | K4: 11 | L4: Shooter | N4: Returning title: Joined 3/21/24, left 3/15/25 | O4: M | P4: Blood and Gore, Intense Violence, Strong Language | R4: =IF(S4="","TBD",IF(S4>TODAY(),"Coming Soon",IF(F4="","Active",IF(F4>TODAY(),"Leaving Soon","Removed")))) -> Active | S4: 45547 | T4: =MONTHDUR(E4,S4) -> -13.3
A5: Ninja Gaiden 4 | B5: Xbox / PC | C5: Yes | D5: =IF(E5>TODAY(),"Coming Soon",IF(F5="","Active",IF(F5>TODAY(),"Leaving Soon","Removed"))) -> Coming Soon | E5: 45951 | G5: =MONTHDUR(E5,F5) -> -0.2 | H5: =E5 -> 45951 | I5: =YEARDUR(H5,E5) -> 0 | L5: Action-Adventure | M5: Exclusive | R5: =IF(S5="","TBD",IF(S5>TODAY(),"Coming Soon",IF(F5="","Active",IF(F5>TODAY(),"Leaving Soon","Removed")))) -> TBD | T5: =MONTHDUR(E5,S5) -> -0.2
A6: Keeper | B6: Xbox / PC | C6: Yes | D6: =IF(E6>TODAY(),"Coming Soon",IF(F6="","Active",IF(F6>TODAY(),"Leaving Soon","Removed"))) -> Coming Soon | E6: 45947 | G6: =MONTHDUR(E6,F6) -> -0.066666667 | H6: =E6 -> 45947 | I6: =YEARDUR(H6,E6) -> 0 | L6: Action-Adventure | M6: Exclusive | R6: =IF(S6="","TBD",IF(S6>TODAY(),"Coming Soon",IF(F6="","Active",IF(F6>TODAY(),"Leaving Soon","Removed")))) -> TBD | T6: =MONTHDUR(E6,S6) -> -0.066666667
A7: Pax Dei | B7: PC | D7: =IF(E7>TODAY(),"Coming Soon",IF(F7="","Active",IF(F7>TODAY(),"Leaving Soon","Removed"))) -> Coming Soon | E7: 45946 | G7: =MONTHDUR(E7,F7) -> -0.033333333 | H7: =E7 -> 45946 | I7: =YEARDUR(H7,E7) -> 0 | L7: RPG | R7: =IF(S7="","TBD",IF(S7>TODAY(),"Coming Soon",IF(F7="","Active",IF(F7>TODAY(),"Leaving Soon","Removed")))) -> TBD | T7: =MONTHDUR(E7,S7) -> -0.033333333
A8: Ball x Pit | B8: Xbox / PC | C8: Yes | D8: =IF(E8>TODAY(),"Coming Soon",IF(F8="","Active",IF(F8>TODAY(),"Leaving Soon","Removed"))) -> Active | E8: 45945 | G8: =MONTHDUR(E8,F8) -> 0 | H8: =E8 -> 45945 | I8: =YEARDUR(H8,E8) -> 0 | L8: Shoot-'Em-Up | R8: =IF(S8="","TBD",IF(S8>TODAY(),"Coming Soon",IF(F8="","Active",IF(F8>TODAY(),"Leaving Soon","Removed")))) -> TBD | T8: =MONTHDUR(E8,S8) -> 0
A9: The Grinch: Christmas Adventures | B9: Xbox / PC | C9: Yes | D9: =IF(E9>TODAY(),"Coming Soon",IF(F9="","Active",IF(F9>TODAY(),"Leaving Soon","Removed"))) -> Active | E9: 45945 | G9: =MONTHDUR(E9,F9) -> 0 | H9: 45212 | I9: =YEARDUR(H9,E9) -> 2.0055556 | J9: =average(50,75,80) -> 68.333333 | K9: 3 | L9: Platformer | R9: =IF(S9="","TBD",IF(S9>TODAY(),"Coming Soon",IF(F9="","Active",IF(F9>TODAY(),"Leaving Soon","Removed")))) -> TBD | T9: =MONTHDUR(E9,S9) -> 0
A10: The Casting of Frank Stone | B10: Xbox / PC | C10: Yes | D10: =IF(E10>TODAY(),"Coming Soon",IF(F10="","Active",IF(F10>TODAY(),"Leaving Soon","Removed"))) -> Active | E10: 45944 | G10: =MONTHDUR(E10,F10) -> 0.033333333 | H10: 45538 | I10: =YEARDUR(H10,E10) -> 1.1138889 | J10: 68 | K10: 6 | L10: Action-Adventure | M10: Exclusive | R10: =IF(S10="","TBD",IF(S10>TODAY(),"Coming Soon",IF(F10="","Active",IF(F10>TODAY(),"Leaving Soon","Removed")))) -> TBD | T10: =MONTHDUR(E10,S10) -> 0.033333333
A11: Baldur's Gate and Baldur's Gate II: Enhanced Editions | B11: PC | D11: =IF(E11>TODAY(),"Coming Soon",IF(F11="","Active",IF(F11>TODAY(),"Leaving Soon","Removed"))) -> Active | E11: 45939 | G11: =MONTHDUR(E11,F11) -> 0.2 | H11: 43753 | I11: =YEARDUR(H11,E11) -> 5.9833333 | J11: 72 | K11: =31+45 -> 76 | L11: RPG | R11: =IF(S11="","TBD",IF(S11>TODAY(),"Coming Soon",IF(F11="","Active",IF(F11>TODAY(),"Leaving Soon","Removed")))) -> TBD | T11: =MONTHDUR(E11,S11) -> 0.2
A12: Little Rocket Lab | B12: Xbox / PC | C12: Yes | D12: =IF(E12>TODAY(),"Coming Soon",IF(F12="","Active",IF(F12>TODAY(),"Leaving Soon","Removed"))) -> Active | E12: 45938 | G12: =MONTHDUR(E12,F12) -> 0.23333333 | H12: 45937 | I12: =YEARDUR(H12,E12) -> 0.0027777778 | J12: 83 | L12: Sandbox | R12: =IF(S12="","TBD",IF(S12>TODAY(),"Coming Soon",IF(F12="","Active",IF(F12>TODAY(),"Leaving Soon","Removed")))) -> TBD | T12: =MONTHDUR(E12,S12) -> 0.23333333
A13: Supermarket Simulator | B13: Xbox / PC | C13: Yes | D13: =IF(E13>TODAY(),"Coming Soon",IF(F13="","Active",IF(F13>TODAY(),"Leaving Soon","Removed"))) -> Active | E13: 45938 | G13: =MONTHDUR(E13,F13) -> 0.23333333 | H13: 45827 | I13: =YEARDUR(H13,E13) -> 0.30277778 | L13: Simulation | R13: =IF(S13="","TBD",IF(S13>TODAY(),"Coming Soon",IF(F13="","Active",IF(F13>TODAY(),"Leaving Soon","Removed")))) -> TBD | T13: =MONTHDUR(E13,S13) -> 0.23333333
A14: Sopa: Tale of the Stolen Potato | B14: Xbox / PC | C14: Yes | D14: =IF(E14>TODAY(),"Coming Soon",IF(F14="","Active",IF(F14>TODAY(),"Leaving Soon","Removed"))) -> Active | E14: 45937 | G14: =MONTHDUR(E14,F14) -> 0.26666667 | H14: 45937 | I14: =YEARDUR(H14,E14) -> 0 | J14: 79 | K14: 3 | L14: Action-Adventure | R14: =IF(S14="","TBD",IF(S14>TODAY(),"Coming Soon",IF(F14="","Active",IF(F14>TODAY(),"Leaving Soon","Removed")))) -> TBD | T14: =MONTHDUR(E14,S14) -> 0.26666667
A15: Hogwarts Legacy | B15: Xbox / PC | C15: Yes | D15: =IF(E15>TODAY(),"Coming Soon",IF(F15="","Active",IF(F15>TODAY(),"Leaving Soon","Removed"))) -> Active | E15: 45931 | G15: =MONTHDUR(E15,F15) -> 0.46666667 | H15: 44964 | I15: =YEARDUR(H15,E15) -> 2.65 | J15: 84 | K15: 27 | L15: Action-Adventure | N15: Ubisoft games joining with price increase | R15: =IF(S15="","TBD",IF(S15>TODAY(),"Coming Soon",IF(F15="","Active",IF(F15>TODAY(),"Leaving Soon","Removed")))) -> Active | S15: 45931 | T15: =MONTHDUR(E15,S15) -> 0
A16: Assassin's Creed II | B16: PC | D16: =IF(E16>TODAY(),"Coming Soon",IF(F16="","Active",IF(F16>TODAY(),"Leaving Soon","Removed"))) -> Active | E16: 45931 | G16: =MONTHDUR(E16,F16) -> 0.46666667 | H16: 40134 | I16: =YEARDUR(H16,E16) -> 15.872222 | J16: 90 | K16: 19 | L16: Action-Adventure | N16: Ubisoft games joining with price increase | P16: 232 | R16: =IF(S16="","TBD",IF(S16>TODAY(),"Coming Soon",IF(F16="","Active",IF(F16>TODAY(),"Leaving Soon","Removed")))) -> TBD | T16: =MONTHDUR(E16,S16) -> 0.46666667
A17: Assassin's Creed III: Remastered | B17: Xbox / PC | C17: Yes | D17: =IF(E17>TODAY(),"Coming Soon",IF(F17="","Active",IF(F17>TODAY(),"Leaving Soon","Removed"))) -> Active | E17: 45931 | G17: =MONTHDUR(E17,F17) -> 0.46666667 | H17: 43553 | I17: =YEARDUR(H17,E17) -> 6.5055556 | J17: 72 | K17: 15 | L17: Action-Adventure | N17: Ubisoft games joining with price increase | R17: =IF(S17="","TBD",IF(S17>TODAY(),"Coming Soon",IF(F17="","Active",IF(F17>TODAY(),"Leaving Soon","Removed")))) -> TBD | T17: =MONTHDUR(E17,S17) -> 0.46666667
A18: Assassin's Creed IV Black Flag | B18: Xbox / PC | C18: Yes | D18: =IF(E18>TODAY(),"Coming Soon",IF(F18="","Active",IF(F18>TODAY(),"Leaving Soon","Removed"))) -> Active | E18: 45931 | G18: =MONTHDUR(E18,F18) -> 0.46666667 | H18: 41576 | I18: =YEARDUR(H18,E18) -> 11.922222 | J18: 88 | K18: 24 | L18: Action-Adventure | N18: Ubisoft games joining with price increase | R18: =IF(S18="","TBD",IF(S18>TODAY(),"Coming Soon",IF(F18="","Active",IF(F18>TODAY(),"Leaving Soon","Removed")))) -> TBD | T18: =MONTHDUR(E18,S18) -> 0.46666667
A19: Assassin's Creed IV Black Flag: Freedom Cry | B19: PC | D19: =IF(E19>TODAY(),"Coming Soon",IF(F19="","Active",IF(F19>TODAY(),"Leaving Soon","Removed"))) -> Active | E19: 45931 | G19: =MONTHDUR(E19,F19) -> 0.46666667 | H19: 41626 | I19: =YEARDUR(H19,E19) -> 11.786111 | J19: 71 | K19: 4 | L19: Action-Adventure | N19: Ubisoft games joining with price increase | R19: =IF(S19="","TBD",IF(S19>TODAY(),"Coming Soon",IF(F19="","Active",IF(F19>TODAY(),"Leaving Soon","Removed")))) -> TBD | T19: =MONTHDUR(E19,S19) -> 0.46666667
A20: Assassin's Creed Brotherhood | B20: PC | D20: =IF(E20>TODAY(),"Coming Soon",IF(F20="","Active",IF(F20>TODAY(),"Leaving Soon","Removed"))) -> Active | E20: 45931 | G20: =MONTHDUR(E20,F20) -> 0.46666667 | H20: 40498 | I20: =YEARDUR(H20,E20) -> 14.875 | J20: 89 | K20: 15 | L20: Action-Adventure | N20: Ubisoft games joining with price increase | R20: =IF(S20="","TBD",IF(S20>TODAY(),"Coming Soon",IF(F20="","Active",IF(F20>TODAY(),"Leaving Soon","Removed")))) -> TBD | T20: =MONTHDUR(E20,S20) -> 0.46666667
A21: Assassin's Creed Chronicles: China | B21: Xbox / PC | C21: Yes | D21: =IF(E21>TODAY(),"Coming Soon",IF(F21="","Active",IF(F21>TODAY(),"Leaving Soon","Removed"))) -> Active | E21: 45931 | G21: =MONTHDUR(E21,F21) -> 0.46666667 | H21: 42115 | I21: =YEARDUR(H21,E21) -> 10.444444 | J21: 69 | K21: 6 | L21: Action-Adventure | N21: Ubisoft games joining with price increase | R21: =IF(S21="","TBD",IF(S21>TODAY(),"Coming Soon",IF(F21="","Active",IF(F21>TODAY(),"Leaving Soon","Removed")))) -> TBD | T21: =MONTHDUR(E21,S21) -> 0.46666667
A22: Assassin's Creed Chronicles: India | B22: Xbox / PC | C22: Yes | D22: =IF(E22>TODAY(),"Coming Soon",IF(F22="","Active",IF(F22>TODAY(),"Leaving Soon","Removed"))) -> Active | E22: 45931 | G22: =MONTHDUR(E22,F22) -> 0.46666667 | H22: 42382 | I22: =YEARDUR(H22,E22) -> 9.7166667 | J22: 63 | K22: 6 | L22: Action-Adventure | N22: Ubisoft games joining with price increase | R22: =IF(S22="","TBD",IF(S22>TODAY(),"Coming Soon",IF(F22="","Active",IF(F22>TODAY(),"Leaving Soon","Removed")))) -> TBD | T22: =MONTHDUR(E22,S22) -> 0.46666667
A23: Assassin's Creed Chronicles: Russia | B23: Xbox / PC | C23: Yes | D23: =IF(E23>TODAY(),"Coming Soon",IF(F23="","Active",IF(F23>TODAY(),"Leaving Soon","Removed"))) -> Active | E23: 45931 | G23: =MONTHDUR(E23,F23) -> 0.46666667 | H23: 42409 | I23: =YEARDUR(H23,E23) -> 9.6444444 | J23: 62 | K23: 7 | L23: Action-Adventure | N23: Ubisoft games joining with price increase | R23: =IF(S23="","TBD",IF(S23>TODAY(),"Coming Soon",IF(F23="","Active",IF(F23>TODAY(),"Leaving Soon","Removed")))) -> TBD | T23: =MONTHDUR(E23,S23) -> 0.46666667
A24: Assassin's Creed Liberation HD | B24: PC | D24: =IF(E24>TODAY(),"Coming Soon",IF(F24="","Active",IF(F24>TODAY(),"Leaving Soon","Removed"))) -> Active | E24: 45931 | G24: =MONTHDUR(E24,F24) -> 0.46666667 | H24: 41654 | I24: =YEARDUR(H24,E24) -> 11.711111 | J24: 62 | K24: 8 | L24: Action-Adventure | N24: Ubisoft games joining with price increase | R24: =IF(S24="","TBD",IF(S24>TODAY(),"Coming Soon",IF(F24="","Active",IF(F24>TODAY(),"Leaving Soon","Removed")))) -> TBD | T24: =MONTHDUR(E24,S24) -> 0.46666667
A25: Assassin's Creed Revelations | B25: PC | D25: =IF(E25>TODAY(),"Coming Soon",IF(F25="","Active",IF(F25>TODAY(),"Leaving Soon","Removed"))) -> Active | E25: 45931 | G25: =MONTHDUR(E25,F25) -> 0.46666667 | H25: 40862 | I25: =YEARDUR(H25,E25) -> 13.877778 | J25: 80 | K25: 13 | L25: Action-Adventure | N25: Ubisoft games joining with price increase | R25: =IF(S25="","TBD",IF(S25>TODAY(),"Coming Soon",IF(F25="","Active",IF(F25>TODAY(),"Leaving Soon","Removed")))) -> TBD | T25: =MONTHDUR(E25,S25) -> 0.46666667
A26: Assassin's Creed Rogue: Remastered | B26: Xbox / PC | C26: Yes | D26: =IF(E26>TODAY(),"Coming Soon",IF(F26="","Active",IF(F26>TODAY(),"Leaving Soon","Removed"))) -> Active | E26: 45931 | G26: =MONTHDUR(E26,F26) -> 0.46666667 | H26: 43179 | I26: =YEARDUR(H26,E26) -> 7.5305556 | J26: 71 | K26: 11 | L26: Action-Adventure | N26: Ubisoft games joining with price increase | R26: =IF(S26="","TBD",IF(S26>TODAY(),"Coming Soon",IF(F26="","Active",IF(F26>TODAY(),"Leaving Soon","Removed")))) -> TBD | T26: =MONTHDUR(E26,S26) -> 0.46666667
A27: Assassin's Creed Syndicate | B27: Xbox / PC | C27: Yes | D27: =IF(E27>TODAY(),"Coming Soon",IF(F27="","Active",IF(F27>TODAY(),"Leaving Soon","Removed"))) -> Active | E27: 45931 | G27: =MONTHDUR(E27,F27) -> 0.46666667 | H27: 42300 | I27: =YEARDUR(H27,E27) -> 9.9388889 | J27: 76 | K27: 19 | L27: Action-Adventure | N27: Ubisoft games joining with price increase | R27: =IF(S27="","TBD",IF(S27>TODAY(),"Coming Soon",IF(F27="","Active",IF(F27>TODAY(),"Leaving Soon","Removed")))) -> TBD | T27: =MONTHDUR(E27,S27) -> 0.46666667
A28: Assassin's Creed: The Ezio Collection | B28: Xbox | C28: Yes | D28: =IF(E28>TODAY(),"Coming Soon",IF(F28="","Active",IF(F28>TODAY(),"Leaving Soon","Removed"))) -> Active | E28: 45931 | G28: =MONTHDUR(E28,F28) -> 0.46666667 | H28: 42689 | I28: =YEARDUR(H28,E28) -> 8.8777778 | J28: 72 | K28: 72 | L28: Action-Adventure | N28: Ubisoft games joining with price increase | R28: =IF(S28="","TBD",IF(S28>TODAY(),"Coming Soon",IF(F28="","Active",IF(F28>TODAY(),"Leaving Soon","Removed")))) -> TBD | T28: =MONTHDUR(E28,S28) -> 0.46666667
A29: Assassin's Creed Unity | B29: Xbox / PC | C29: Yes | D29: =IF(E29>TODAY(),"Coming Soon",IF(F29="","Active",IF(F29>TODAY(),"Leaving Soon","Removed"))) -> Active | E29: 45931 | G29: =MONTHDUR(E29,F29) -> 0.46666667 | H29: 41954 | I29: =YEARDUR(H29,E29) -> 10.888889 | J29: 72 | K29: 17 | L29: Action-Adventure | N29: Ubisoft games joining with price increase | R29: =IF(S29="","TBD",IF(S29>TODAY(),"Coming Soon",IF(F29="","Active",IF(F29>TODAY(),"Leaving Soon","Removed")))) -> TBD | T29: =MONTHDUR(E29,S29) -> 0.46666667
A30: Child of Light | B30: Xbox / PC | C30: Yes | D30: =IF(E30>TODAY(),"Coming Soon",IF(F30="","Active",IF(F30>TODAY(),"Leaving Soon","Removed"))) -> Active | E30: 45931 | G30: =MONTHDUR(E30,F30) -> 0.46666667 | H30: 41758 | I30: =YEARDUR(H30,E30) -> 11.422222 | J30: 82 | K30: 11 | L30: RPG | N30: Ubisoft games joining with price increase | R30: =IF(S30="","TBD",IF(S30>TODAY(),"Coming Soon",IF(F30="","Active",IF(F30>TODAY(),"Leaving Soon","Removed")))) -> TBD | T30: =MONTHDUR(E30,S30) -> 0.46666667
A31: Far Cry 3 | B31: Xbox / PC | C31: Yes | D31: =IF(E31>TODAY(),"Coming Soon",IF(F31="","Active",IF(F31>TODAY(),"Leaving Soon","Removed"))) -> Active | E31: 45931 | G31: =MONTHDUR(E31,F31) -> 0.46666667 | H31: 41247 | I31: =YEARDUR(H31,E31) -> 12.825 | J31: 88 | K31: 16 | L31: Action-Adventure | N31: Ubisoft games joining with price increase | R31: =IF(S31="","TBD",IF(S31>TODAY(),"Coming Soon",IF(F31="","Active",IF(F31>TODAY(),"Leaving Soon","Removed")))) -> TBD | T31: =MONTHDUR(E31,S31) -> 0.46666667
A32: Far Cry 3: Blood Dragon | B32: Xbox / PC | C32: Yes | D32: =IF(E32>TODAY(),"Coming Soon",IF(F32="","Active",IF(F32>TODAY(),"Leaving Soon","Removed"))) -> Active | E32: 45931 | G32: =MONTHDUR(E32,F32) -> 0.46666667 | H32: 41395 | I32: =YEARDUR(H32,E32) -> 12.416667 | J32: 80 | K32: 5 | L32: Action-Adventure | N32: Ubisoft games joining with price increase | R32: =IF(S32="","TBD",IF(S32>TODAY(),"Coming Soon",IF(F32="","Active",IF(F32>TODAY(),"Leaving Soon","Removed")))) -> TBD | T32: =MONTHDUR(E32,S32) -> 0.46666667
A33: Far Cry Primal | B33: Xbox / PC | C33: Yes | D33: =IF(E33>TODAY(),"Coming Soon",IF(F33="","Active",IF(F33>TODAY(),"Leaving Soon","Removed"))) -> Active | E33: 45931 | G33: =MONTHDUR(E33,F33) -> 0.46666667 | H33: 42423 | I33: =YEARDUR(H33,E33) -> 9.6055556 | J33: 76 | K33: 15 | L33: Action-Adventure | N33: Ubisoft games joining with price increase | R33: =IF(S33="","TBD",IF(S33>TODAY(),"Coming Soon",IF(F33="","Active",IF(F33>TODAY(),"Leaving Soon","Removed")))) -> TBD | T33: =MONTHDUR(E33,S33) -> 0.46666667
A34: Hungry Shark World | B34: Xbox / PC | C34: Yes | D34: =IF(E34>TODAY(),"Coming Soon",IF(F34="","Active",IF(F34>TODAY(),"Leaving Soon","Removed"))) -> Active | E34: 45931 | G34: =MONTHDUR(E34,F34) -> 0.46666667 | H34: 43298 | I34: =YEARDUR(H34,E34) -> 7.2055556 | J34: 58 | K34: 8 | L34: Action-Adventure | N34: Ubisoft games joining with price increase | R34: =IF(S34="","TBD",IF(S34>TODAY(),"Coming Soon",IF(F34="","Active",IF(F34>TODAY(),"Leaving Soon","Removed")))) -> TBD | T34: =MONTHDUR(E34,S34) -> 0.46666667
A35: Monopoly Madness | B35: Xbox / PC | C35: Yes | D35: =IF(E35>TODAY(),"Coming Soon",IF(F35="","Active",IF(F35>TODAY(),"Leaving Soon","Removed"))) -> Active | E35: 45931 | G35: =MONTHDUR(E35,F35) -> 0.46666667 | H35: 44914 | I35: =YEARDUR(H35,E35) -> 2.7833333 | K35: 6 | L35: Party | N35: Ubisoft games joining with price increase | R35: =IF(S35="","TBD",IF(S35>TODAY(),"Coming Soon",IF(F35="","Active",IF(F35>TODAY(),"Leaving Soon","Removed")))) -> TBD | T35: =MONTHDUR(E35,S35) -> 0.46666667
A36: Monopoly (2024) | B36: Xbox / PC | C36: Yes | D36: =IF(E36>TODAY(),"Coming Soon",IF(F36="","Active",IF(F36>TODAY(),"Leaving Soon","Removed"))) -> Active | E36: 45931 | G36: =MONTHDUR(E36,F36) -> 0.46666667 | H36: 45561 | I36: =YEARDUR(H36,E36) -> 1.0138889 | J36: 74 | K36: 14 | L36: Board | N36: Ubisoft games joining with price increase | R36: =IF(S36="","TBD",IF(S36>TODAY(),"Coming Soon",IF(F36="","Active",IF(F36>TODAY(),"Leaving Soon","Removed")))) -> TBD | T36: =MONTHDUR(E36,S36) -> 0.46666667
A37: OddBallers | B37: Xbox / PC | C37: Yes | D37: =IF(E37>TODAY(),"Coming Soon",IF(F37="","Active",IF(F37>TODAY(),"Leaving Soon","Removed"))) -> Active | E37: 45931 | G37: =MONTHDUR(E37,F37) -> 0.46666667 | H37: 44952 | I37: =YEARDUR(H37,E37) -> 2.6805556 | J37: 71 | K37: 8 | L37: Party | N37: Ubisoft games joining with price increase | R37: =IF(S37="","TBD",IF(S37>TODAY(),"Coming Soon",IF(F37="","Active",IF(F37>TODAY(),"Leaving Soon","Removed")))) -> TBD | T37: =MONTHDUR(E37,S37) -> 0.46666667
A38: Prince of Persia: The Lost Crown | B38: Xbox / PC | C38: Yes | D38: =IF(E38>TODAY(),"Coming Soon",IF(F38="","Active",IF(F38>TODAY(),"Leaving Soon","Removed"))) -> Active | E38: 45931 | G38: =MONTHDUR(E38,F38) -> 0.46666667 | H38: 45309 | I38: =YEARDUR(H38,E38) -> 1.7027778 | J38: 86 | K38: 17 | L38: Metroidvania | N38: Ubisoft games joining with price increase | R38: =IF(S38="","TBD",IF(S38>TODAY(),"Coming Soon",IF(F38="","Active",IF(F38>TODAY(),"Leaving Soon","Removed")))) -> TBD | T38: =MONTHDUR(E38,S38) -> 0.46666667
A39: Rabbids Invasion: The Interactive TV Show | B39: Xbox | C39: Yes | D39: =IF(E39>TODAY(),"Coming Soon",IF(F39="","Active",IF(F39>TODAY(),"Leaving Soon","Removed"))) -> Active | E39: 45931 | G39: =MONTHDUR(E39,F39) -> 0.46666667 | H39: 41951 | I39: =YEARDUR(H39,E39) -> 10.897222 | J39: 53 | K39: 10 | L39: Party | N39: Ubisoft games joining with price increase | R39: =IF(S39="","TBD",IF(S39>TODAY(),"Coming Soon",IF(F39="","Active",IF(F39>TODAY(),"Leaving Soon","Removed")))) -> TBD | T39: =MONTHDUR(E39,S39) -> 0.46666667
A40: Rabbids: Party of Legends | B40: Xbox / PC | C40: Yes | D40: =IF(E40>TODAY(),"Coming Soon",IF(F40="","Active",IF(F40>TODAY(),"Leaving Soon","Removed"))) -> Active | E40: 45931 | G40: =MONTHDUR(E40,F40) -> 0.46666667 | H40: 44742 | I40: =YEARDUR(H40,E40) -> 3.2527778 | J40: 69 | K40: 3 | L40: Party | N40: Ubisoft games joining with price increase | R40: =IF(S40="","TBD",IF(S40>TODAY(),"Coming Soon",IF(F40="","Active",IF(F40>TODAY(),"Leaving Soon","Removed")))) -> TBD | T40: =MONTHDUR(E40,S40) -> 0.46666667
A41: Rayman Legends | B41: Xbox / PC | C41: Yes | D41: =IF(E41>TODAY(),"Coming Soon",IF(F41="","Active",IF(F41>TODAY(),"Leaving Soon","Removed"))) -> Active | E41: 45931 | G41: =MONTHDUR(E41,F41) -> 0.46666667 | H41: 41520 | I41: =YEARDUR(H41,E41) -> 12.077778 | J41: 92 | K41: 10 | L41: Platformer | N41: Ubisoft games joining with price increase | R41: =IF(S41="","TBD",IF(S41>TODAY(),"Coming Soon",IF(F41="","Active",IF(F41>TODAY(),"Leaving Soon","Removed")))) -> TBD | T41: =MONTHDUR(E41,S41) -> 0.46666667
A42: Risk: Urban Assault | B42: Xbox | C42: Yes | D42: =IF(E42>TODAY(),"Coming Soon",IF(F42="","Active",IF(F42>TODAY(),"Leaving Soon","Removed"))) -> Active | E42: 45931 | G42: =MONTHDUR(E42,F42) -> 0.46666667 | H42: 42584 | I42: =YEARDUR(H42,E42) -> 9.1638889 | J42: 61 | K42: 4 | L42: Board | N42: Ubisoft games joining with price increase | R42: =IF(S42="","TBD",IF(S42>TODAY(),"Coming Soon",IF(F42="","Active",IF(F42>TODAY(),"Leaving Soon","Removed")))) -> TBD | T42: =MONTHDUR(E42,S42) -> 0.46666667
A43: Scott Pilgrim vs. The World: The Game | B43: Xbox / PC | C43: Yes | D43: =IF(E43>TODAY(),"Coming Soon",IF(F43="","Active",IF(F43>TODAY(),"Leaving Soon","Removed"))) -> Active | E43: 45931 | G43: =MONTHDUR(E43,F43) -> 0.46666667 | H43: 44210 | I43: =YEARDUR(H43,E43) -> 4.7138889 | J43: 79 | K43: 5 | L43: Beat-'Em-Up | N43: Ubisoft games joining with price increase | R43: =IF(S43="","TBD",IF(S43>TODAY(),"Coming Soon",IF(F43="","Active",IF(F43>TODAY(),"Leaving Soon","Removed")))) -> TBD | T43: =MONTHDUR(E43,S43) -> 0.46666667
A44: Skull and Bones | B44: Xbox / PC | C44: Yes | D44: =IF(E44>TODAY(),"Coming Soon",IF(F44="","Active",IF(F44>TODAY(),"Leaving Soon","Removed"))) -> Active | E44: 45931 | G44: =MONTHDUR(E44,F44) -> 0.46666667 | H44: 45338 | I44: =YEARDUR(H44,E44) -> 1.625 | J44: 59 | K44: 32 | L44: Action-Adventure | N44: Ubisoft games joining with price increase | R44: =IF(S44="","TBD",IF(S44>TODAY(),"Coming Soon",IF(F44="","Active",IF(F44>TODAY(),"Leaving Soon","Removed")))) -> TBD | T44: =MONTHDUR(E44,S44) -> 0.46666667
A45: South Park: The Stick of Truth | B45: Xbox / PC | C45: Yes | D45: =IF(E45>TODAY(),"Coming Soon",IF(F45="","Active",IF(F45>TODAY(),"Leaving Soon","Removed"))) -> Active | E45: 45931 | G45: =MONTHDUR(E45,F45) -> 0.46666667 | H45: 41702 | I45: =YEARDUR(H45,E45) -> 11.575 | J45: 85 | K45: 12 | L45: RPG | N45: Ubisoft games joining with price increase | R45: =IF(S45="","TBD",IF(S45>TODAY(),"Coming Soon",IF(F45="","Active",IF(F45>TODAY(),"Leaving Soon","Removed")))) -> TBD | T45: =MONTHDUR(E45,S45) -> 0.46666667
A46: Starlink: Battle for Atlas | B46: Xbox / PC | C46: Yes | D46: =IF(E46>TODAY(),"Coming Soon",IF(F46="","Active",IF(F46>TODAY(),"Leaving Soon","Removed"))) -> Active | E46: 45931 | G46: =MONTHDUR(E46,F46) -> 0.46666667 | H46: 43389 | I46: =YEARDUR(H46,E46) -> 6.9583333 | J46: 74 | K46: 15 | L46: Simulation | N46: Ubisoft games joining with price increase | R46: =IF(S46="","TBD",IF(S46>TODAY(),"Coming Soon",IF(F46="","Active",IF(F46>TODAY(),"Leaving Soon","Removed")))) -> TBD | T46: =MONTHDUR(E46,S46) -> 0.46666667
A47: Steep | B47: Xbox / PC | C47: Yes | D47: =IF(E47>TODAY(),"Coming Soon",IF(F47="","Active",IF(F47>TODAY(),"Leaving Soon","Removed"))) -> Active | E47: 45931 | G47: =MONTHDUR(E47,F47) -> 0.46666667 | H47: 42703 | I47: =YEARDUR(H47,E47) -> 8.8388889 | J47: 71 | K47: 12 | L47: Sports | N47: Ubisoft games joining with price increase | R47: =IF(S47="","TBD",IF(S47>TODAY(),"Coming Soon",IF(F47="","Active",IF(F47>TODAY(),"Leaving Soon","Removed")))) -> TBD | T47: =MONTHDUR(E47,S47) -> 0.46666667
... A50: Tom Clancy's Ghost Recon Breakpoint | B50: Xbox / PC | C50: Yes | D50: =IF(E50>TODAY(),"Coming Soon",IF(F50="","Active",IF(F50>TODAY(),"Leaving Soon","Removed"))) -> Active | E50: 45931 | G50: =MONTHDUR(E50,F50) -> 0.46666667 | H50: 43739 | I50: =YEARDUR(H50,E50) -> 6 | J50: 56 | K50: 23 | L50: Shooter | N50: Ubisoft games joining with price increase | R50: =IF(S50="","TBD",IF(S50>TODAY(),"Coming Soon",IF(F50="","Active",IF(F50>TODAY(),"Leaving Soon","Removed")))) -> TBD | T50: =MONTHDUR(E50,S50) -> 0.46666667
A51: Tom Clancy's Rainbow Six: Extraction | B51: Xbox / PC | C51: Yes | D51: =IF(E51>TODAY(),"Coming Soon",IF(F51="","Active",IF(F51>TODAY(),"Leaving Soon","Removed"))) -> Active | E51: 45931 | G51: =MONTHDUR(E51,F51) -> 0.46666667 | H51: 44581 | I51: =YEARDUR(H51,E51) -> 3.6972222 | J51: =average(71,72) -> 71.5 | K51: 8 | L51: Shooter | N51: Returning game: added 1/20/22, left 4/15/23. Ubisoft Connect launcher. Ubisoft games joining with price increase | O51: M | P51: Blood, Drug Reference, Strong Language, Violence | R51: =IF(S51="","TBD",IF(S51>TODAY(),"Coming Soon",IF(F51="","Active",IF(F51>TODAY(),"Leaving Soon","Removed")))) -> TBD | T51: =MONTHDUR(E51,S51) -> 0.46666667
A52: Tom Clancy's The Division | B52: Xbox / PC | C52: Yes | D52: =IF(E52>TODAY(),"Coming Soon",IF(F52="","Active",IF(F52>TODAY(),"Leaving Soon","Removed"))) -> Active | E52: 45931 | G52: =MONTHDUR(E52,F52) -> 0.46666667 | H52: 42437 | I52: =YEARDUR(H52,E52) -> 9.5638889 | J52: 80 | K52: 24 | L52: Shooter | N52: Ubisoft games joining with price increase | R52: =IF(S52="","TBD",IF(S52>TODAY(),"Coming Soon",IF(F52="","Active",IF(F52>TODAY(),"Leaving Soon","Removed")))) -> TBD | T52: =MONTHDUR(E52,S52) -> 0.46666667
A53: Trackmania Turbo | B53: Xbox / PC | C53: Yes | D53: =IF(E53>TODAY(),"Coming Soon",IF(F53="","Active",IF(F53>TODAY(),"Leaving Soon","Removed"))) -> Active | E53: 45931 | G53: =MONTHDUR(E53,F53) -> 0.46666667 | H53: 42451 | I53: =YEARDUR(H53,E53) -> 9.525 | J53: 81 | K53: 13 | L53: Racing | N53: Ubisoft games joining with price increase | R53: =IF(S53="","TBD",IF(S53>TODAY(),"Coming Soon",IF(F53="","Active",IF(F53>TODAY(),"Leaving Soon","Removed")))) -> TBD | T53: =MONTHDUR(E53,S53) -> 0.46666667
A54: Transference | B54: Xbox | C54: Yes | D54: =IF(E54>TODAY(),"Coming Soon",IF(F54="","Active",IF(F54>TODAY(),"Leaving Soon","Removed"))) -> Active | E54: 45931 | G54: =MONTHDUR(E54,F54) -> 0.46666667 | H54: 43361 | I54: =YEARDUR(H54,E54) -> 7.0361111 | J54: 71 | K54: 2 | L54: Action-Adventure | N54: Ubisoft games joining with price increase | R54: =IF(S54="","TBD",IF(S54>TODAY(),"Coming Soon",IF(F54="","Active",IF(F54>TODAY(),"Leaving Soon","Removed")))) -> TBD | T54: =MONTHDUR(E54,S54) -> 0.46666667
A55: Trials Fusion | B55: Xbox / PC | C55: Yes | D55: =IF(E55>TODAY(),"Coming Soon",IF(F55="","Active",IF(F55>TODAY(),"Leaving Soon","Removed"))) -> Active | E55: 45931 | G55: =MONTHDUR(E55,F55) -> 0.46666667 | H55: 41744 | I55: =YEARDUR(H55,E55) -> 11.461111 | J55: 79 | K55: 7 | L55: Racing | N55: Ubisoft games joining with price increase | R55: =IF(S55="","TBD",IF(S55>TODAY(),"Coming Soon",IF(F55="","Active",IF(F55>TODAY(),"Leaving Soon","Removed")))) -> TBD | T55: =MONTHDUR(E55,S55) -> 0.46666667
A56: Trials of the Blood Dragon | B56: Xbox / PC | C56: Yes | D56: =IF(E56>TODAY(),"Coming Soon",IF(F56="","Active",IF(F56>TODAY(),"Leaving Soon","Removed"))) -> Active | E56: 45931 | G56: =MONTHDUR(E56,F56) -> 0.46666667 | H56: 42534 | I56: =YEARDUR(H56,E56) -> 9.3 | J56: 55 | K56: 3 | L56: Racing | N56: Ubisoft games joining with price increase | R56: =IF(S56="","TBD",IF(S56>TODAY(),"Coming Soon",IF(F56="","Active",IF(F56>TODAY(),"Leaving Soon","Removed")))) -> TBD | T56: =MONTHDUR(E56,S56) -> 0.46666667
A57: Trials Rising | B57: Xbox / PC | C57: Yes | D57: =IF(E57>TODAY(),"Coming Soon",IF(F57="","Active",IF(F57>TODAY(),"Leaving Soon","Removed"))) -> Active | E57: 45931 | G57: =MONTHDUR(E57,F57) -> 0.46666667 | H57: 43522 | I57: =YEARDUR(H57,E57) -> 6.5972222 | J57: 79 | K57: 18 | L57: Racing | N57: Ubisoft games joining with price increase | R57: =IF(S57="","TBD",IF(S57>TODAY(),"Coming Soon",IF(F57="","Active",IF(F57>TODAY(),"Leaving Soon","Removed")))) -> TBD | T57: =MONTHDUR(E57,S57) -> 0.46666667
A58: Uno | B58: Xbox / PC | C58: Yes | D58: =IF(E58>TODAY(),"Coming Soon",IF(F58="","Active",IF(F58>TODAY(),"Leaving Soon","Removed"))) -> Active | E58: 45931 | G58: =MONTHDUR(E58,F58) -> 0.46666667 | H58: 38846 | I58: =YEARDUR(H58,E58) -> 19.394444 | J58: 81 | K58: 3 | L58: Board | N58: Ubisoft games joining with price increase | R58: =IF(S58="","TBD",IF(S58>TODAY(),"Coming Soon",IF(F58="","Active",IF(F58>TODAY(),"Leaving Soon","Removed")))) -> TBD | T58: =MONTHDUR(E58,S58) -> 0.46666667
A59: Valiant Hearts: The Great War | B59: Xbox / PC | C59: Yes | D59: =IF(E59>TODAY(),"Coming Soon",IF(F59="","Active",IF(F59>TODAY(),"Leaving Soon","Removed"))) -> Active | E59: 45931 | G59: =MONTHDUR(E59,F59) -> 0.46666667 | H59: 41814 | I59: =YEARDUR(H59,E59) -> 11.269444 | J59: 77 | K59: 7 | L59: Platformer | N59: Ubisoft games joining with price increase | R59: =IF(S59="","TBD",IF(S59>TODAY(),"Coming Soon",IF(F59="","Active",IF(F59>TODAY(),"Leaving Soon","Removed")))) -> TBD | T59: =MONTHDUR(E59,S59) -> 0.46666667
A60: Watch_Dogs | B60: Xbox / PC | C60: Yes | D60: =IF(E60>TODAY(),"Coming Soon",IF(F60="","Active",IF(F60>TODAY(),"Leaving Soon","Removed"))) -> Active | E60: 45931 | G60: =MONTHDUR(E60,F60) -> 0.46666667 | H60: 41786 | I60: =YEARDUR(H60,E60) -> 11.344444 | J60: 80 | K60: 20 | L60: Action-Adventure | N60: Ubisoft games joining with price increase | R60: =IF(S60="","TBD",IF(S60>TODAY(),"Coming Soon",IF(F60="","Active",IF(F60>TODAY(),"Leaving Soon","Removed")))) -> TBD | T60: =MONTHDUR(E60,S60) -> 0.46666667
A61: Wheel of Fortune | B61: Xbox | C61: Yes | D61: =IF(E61>TODAY(),"Coming Soon",IF(F61="","Active",IF(F61>TODAY(),"Leaving Soon","Removed"))) -> Active | E61: 45931 | G61: =MONTHDUR(E61,F61) -> 0.46666667 | H61: 43046 | I61: =YEARDUR(H61,E61) -> 7.9 | J61: 80 | K61: 2 | L61: Trivia | N61: Ubisoft games joining with price increase | R61: =IF(S61="","TBD",IF(S61>TODAY(),"Coming Soon",IF(F61="","Active",IF(F61>TODAY(),"Leaving Soon","Removed")))) -> TBD | T61: =MONTHDUR(E61,S61) -> 0.46666667
A62: Zombi | B62: Xbox / PC | C62: Yes | D62: =IF(E62>TODAY(),"Coming Soon",IF(F62="","Active",IF(F62>TODAY(),"Leaving Soon","Removed"))) -> Active | E62: 45931 | G62: =MONTHDUR(E62,F62) -> 0.46666667 | H62: 42234 | I62: =YEARDUR(H62,E62) -> 10.119444 | J62: 65 | K62: 12 | L62: Survival | N62: Ubisoft games joining with price increase | R62: =IF(S62="","TBD",IF(S62>TODAY(),"Coming Soon",IF(F62="","Active",IF(F62>TODAY(),"Leaving Soon","Removed")))) -> TBD | T62: =MONTHDUR(E62,S62) -> 0.46666667
A63: Lara Croft and the Guardian of Light | B63: Xbox / PC | C63: Yes | D63: =IF(E63>TODAY(),"Coming Soon",IF(F63="","Active",IF(F63>TODAY(),"Leaving Soon","Removed"))) -> Active | E63: 45930 | G63: =MONTHDUR(E63,F63) -> 0.5 | H63: 42062 | I63: =YEARDUR(H63,E63) -> 10.591667 | J63: 84 | K63: 7 | L63: Action-Adventure | R63: =IF(S63="","TBD",IF(S63>TODAY(),"Coming Soon",IF(F63="","Active",IF(F63>TODAY(),"Leaving Soon","Removed")))) -> Active | S63: =E63 -> 45930 | T63: =MONTHDUR(E63,S63) -> 0
A64: Peppa Pig: World Adventures | B64: Xbox / PC | C64: Yes | D64: =IF(E64>TODAY(),"Coming Soon",IF(F64="","Active",IF(F64>TODAY(),"Leaving Soon","Removed"))) -> Active | E64: 45925 | G64: =MONTHDUR(E64,F64) -> 0.66666667 | H64: 45002 | I64: =YEARDUR(H64,E64) -> 2.5222222 | J64: 72 | K64: 2 | L64: Action-Adventure | M64: Exclusive | R64: =IF(S64="","TBD",IF(S64>TODAY(),"Coming Soon",IF(F64="","Active",IF(F64>TODAY(),"Leaving Soon","Removed")))) -> Active | S64: =E64 -> 45925 | T64: =MONTHDUR(E64,S64) -> 0
A65: Visions of Mana | B65: Xbox / PC | C65: Yes | D65: =IF(E65>TODAY(),"Coming Soon",IF(F65="","Active",IF(F65>TODAY(),"Leaving Soon","Removed"))) -> Active | E65: 45925 | G65: =MONTHDUR(E65,F65) -> 0.66666667 | H65: 45533 | I65: =YEARDUR(H65,E65) -> 1.0722222 | J65: 75 | K65: 29 | L65: RPG | M65: Exclusive | R65: =IF(S65="","TBD",IF(S65>TODAY(),"Coming Soon",IF(F65="","Active",IF(F65>TODAY(),"Leaving Soon","Removed")))) -> Active | S65: =E65 -> 45925 | T65: =MONTHDUR(E65,S65) -> 0
A66: SWORN | B66: Xbox / PC | C66: Yes | D66: =IF(E66>TODAY(),"Coming Soon",IF(F66="","Active",IF(F66>TODAY(),"Leaving Soon","Removed"))) -> Active | E66: 45923 | G66: =MONTHDUR(E66,F66) -> 0.73333333 | H66: 45923 | I66: =YEARDUR(H66,E66) -> 0 | L66: RPG | M66: Exclusive | R66: =IF(S66="","TBD",IF(S66>TODAY(),"Coming Soon",IF(F66="","Active",IF(F66>TODAY(),"Leaving Soon","Removed")))) -> Active | S66: 45931 | T66: =MONTHDUR(E66,S66) -> 0.26666667
A67: ENDLESS Legend 2 (Game Preview) | B67: PC | D67: =IF(E67>TODAY(),"Coming Soon",IF(F67="","Active",IF(F67>TODAY(),"Leaving Soon","Removed"))) -> Active | E67: 45922 | G67: =MONTHDUR(E67,F67) -> 0.76666667 | H67: 45922 | I67: =YEARDUR(H67,E67) -> 0 | L67: Strategy | R67: =IF(S67="","TBD",IF(S67>TODAY(),"Coming Soon",IF(F67="","Active",IF(F67>TODAY(),"Leaving Soon","Removed")))) -> TBD | T67: =MONTHDUR(E67,S67) -> 0.76666667
A68: Hades | B68: Xbox / PC | C68: Touch Controls | D68: =IF(E68>TODAY(),"Coming Soon",IF(F68="","Active",IF(F68>TODAY(),"Leaving Soon","Removed"))) -> Active | E68: 45919 | G68: =MONTHDUR(E68,F68) -> 0.86666667 | H68: 43441 | I68: =YEARDUR(H68,E68) -> 6.7833333 | J68: =(93+94)/2 -> 93.5 | K68: 21 | L68: Action / RPG | M68: Optimized | N68: Game Pass Essential (10/1/25). Returning title: Joined 8/13/21, left 8/31/22 | O68: T | P68: Blood, Suggestive Themes, Alcohol Reference, Mild Language, Violence | R68: =IF(S68="","TBD",IF(S68>TODAY(),"Coming Soon",IF(F68="","Active",IF(F68>TODAY(),"Leaving Soon","Removed")))) -> Active | S68: =E68 -> 45919 | T68: =MONTHDUR(E68,S68) -> 0
A69: Frostpunk 2 | B69: Xbox / PC | D69: =IF(E69>TODAY(),"Coming Soon",IF(F69="","Active",IF(F69>TODAY(),"Leaving Soon","Removed"))) -> Active | E69: 45918 | G69: =MONTHDUR(E69,F69) -> 0.9 | H69: 45552 | I69: =YEARDUR(H69,E69) -> 1.0027778 | J69: 85 | K69: 12 | L69: Management | M69: Exclusive | R69: =IF(S69="","TBD",IF(S69>TODAY(),"Coming Soon",IF(F69="","Active",IF(F69>TODAY(),"Leaving Soon","Removed")))) -> Active | S69: 45931 | T69: =MONTHDUR(E69,S69) -> 0.43333333
A70: Wobbly Life | B70: Xbox / PC | C70: Yes | D70: =IF(E70>TODAY(),"Coming Soon",IF(F70="","Active",IF(F70>TODAY(),"Leaving Soon","Removed"))) -> Active | E70: 45918 | G70: =MONTHDUR(E70,F70) -> 0.9 | H70: 45898 | I70: =YEARDUR(H70,E70) -> 0.052777778 | J70: 80 | K70: 3 | L70: Action-Adventure | M70: Exclusive | R70: =IF(S70="","TBD",IF(S70>TODAY(),"Coming Soon",IF(F70="","Active",IF(F70>TODAY(),"Leaving Soon","Removed")))) -> Active | S70: =E70 -> 45918 | T70: =MONTHDUR(E70,S70) -> 0
A71: Deep Rock Galactic: Survivor | B71: Xbox / PC | C71: Yes | D71: =IF(E71>TODAY(),"Coming Soon",IF(F71="","Active",IF(F71>TODAY(),"Leaving Soon","Removed"))) -> Active | E71: 45917 | G71: =MONTHDUR(E71,F71) -> 0.93333333 | H71: 45917 | I71: =YEARDUR(H71,E71) -> 0 | K71: 15 | L71: Shooter | M71: Exclusive | R71: =IF(S71="","TBD",IF(S71>TODAY(),"Coming Soon",IF(F71="","Active",IF(F71>TODAY(),"Leaving Soon","Removed")))) -> Active | S71: 45931 | T71: =MONTHDUR(E71,S71) -> 0.46666667
A72: PAW Patrol World | B72: Xbox / PC | C72: Yes | D72: =IF(E72>TODAY(),"Coming Soon",IF(F72="","Active",IF(F72>TODAY(),"Leaving Soon","Removed"))) -> Active | E72: 45910 | G72: =MONTHDUR(E72,F72) -> 1.1666667 | H72: 45198 | I72: =YEARDUR(H72,E72) -> 1.9472222 | J72: 79 | K72: 7 | L72: Action-Adventure | N72: Returning title: Joined 3/7/24, left 2/28/25 | O72: E | R72: =IF(S72="","TBD",IF(S72>TODAY(),"Coming Soon",IF(F72="","Active",IF(F72>TODAY(),"Leaving Soon","Removed")))) -> Active | S72: =E72 -> 45910 | T72: =MONTHDUR(E72,S72) -> 0
A73: RoadCraft | B73: Xbox | C73: Yes | D73: =IF(E73>TODAY(),"Coming Soon",IF(F73="","Active",IF(F73>TODAY(),"Leaving Soon","Removed"))) -> Active | E73: 45916 | G73: =MONTHDUR(E73,F73) -> 0.96666667 | H73: 45797 | I73: =YEARDUR(H73,E73) -> 0.32222222 | J73: 77 | K73: 51 | L73: Racing | M73: Exclusive | R73: =IF(S73="","TBD",IF(S73>TODAY(),"Coming Soon",IF(F73="","Active",IF(F73>TODAY(),"Leaving Soon","Removed")))) -> Active | S73: =E73 -> 45916 | T73: =MONTHDUR(E73,S73) -> 0
A74: Hollow Knight: Silksong | B74: Xbox / PC | C74: Yes | D74: =IF(E74>TODAY(),"Coming Soon",IF(F74="","Active",IF(F74>TODAY(),"Leaving Soon","Removed"))) -> Active | E74: 45904 | G74: =MONTHDUR(E74,F74) -> 1.3666667 | H74: 45904 | I74: =YEARDUR(H74,E74) -> 0 | L74: Metroidvania | R74: =IF(S74="","TBD",IF(S74>TODAY(),"Coming Soon",IF(F74="","Active",IF(F74>TODAY(),"Leaving Soon","Removed")))) -> TBD | T74: =MONTHDUR(E74,S74) -> 1.3666667
A75: Cataclismo | B75: PC | D75: =IF(E75>TODAY(),"Coming Soon",IF(F75="","Active",IF(F75>TODAY(),"Leaving Soon","Removed"))) -> Active | E75: 45904 | G75: =MONTHDUR(E75,F75) -> 1.3666667 | H75: 45736 | I75: =YEARDUR(H75,E75) -> 0.45555556 | J75: 82 | K75: 16 | L75: Defense | R75: =IF(S75="","TBD",IF(S75>TODAY(),"Coming Soon",IF(F75="","Active",IF(F75>TODAY(),"Leaving Soon","Removed")))) -> Active | S75: 45931 | T75: =MONTHDUR(E75,S75) -> 0.9
A76: I Am Your Beast | B76: Xbox / PC | C76: Yes | D76: =IF(E76>TODAY(),"Coming Soon",IF(F76="","Active",IF(F76>TODAY(),"Leaving Soon","Removed"))) -> Active | E76: 45901 | G76: =MONTHDUR(E76,F76) -> 1.4666667 | H76: 45545 | I76: =YEARDUR(H76,E76) -> 0.975 | J76: 79 | K76: 3 | L76: Shooter | M76: Exclusive | R76: =IF(S76="","TBD",IF(S76>TODAY(),"Coming Soon",IF(F76="","Active",IF(F76>TODAY(),"Leaving Soon","Removed")))) -> Active | S76: =E76 -> 45901 | T76: =MONTHDUR(E76,S76) -> 0
A77: Dragon Age: The Veilguard | B77: Xbox / PC | C77: Yes | D77: =IF(E77>TODAY(),"Coming Soon",IF(F77="","Active",IF(F77>TODAY(),"Leaving Soon","Removed"))) -> Active | E77: 45897 | G77: =MONTHDUR(E77,F77) -> 1.5666667 | H77: 45596 | I77: =YEARDUR(H77,E77) -> 0.82777778 | J77: 82 | K77: 29 | L77: RPG | M77: Exclusive | R77: =IF(S77="","TBD",IF(S77>TODAY(),"Coming Soon",IF(F77="","Active",IF(F77>TODAY(),"Leaving Soon","Removed")))) -> TBD | T77: =MONTHDUR(E77,S77) -> 1.5666667
A78: Gears of War: Reloaded | B78: Xbox / PC | C78: Yes | D78: =IF(E78>TODAY(),"Coming Soon",IF(F78="","Active",IF(F78>TODAY(),"Leaving Soon","Removed"))) -> Active | E78: 45895 | G78: =MONTHDUR(E78,F78) -> 1.6333333 | H78: 45895 | I78: =YEARDUR(H78,E78) -> 0 | J78: 79 | K78: 7 | L78: Shooter | M78: Exclusive | R78: =IF(S78="","TBD",IF(S78>TODAY(),"Coming Soon",IF(F78="","Active",IF(F78>TODAY(),"Leaving Soon","Removed")))) -> TBD | T78: =MONTHDUR(E78,S78) -> 1.6333333
A79: Herdling | B79: Xbox / PC | C79: Yes | D79: =IF(E79>TODAY(),"Coming Soon",IF(F79="","Active",IF(F79>TODAY(),"Leaving Soon","Removed"))) -> Active | E79: 45890 | G79: =MONTHDUR(E79,F79) -> 1.8 | H79: 45890 | I79: =YEARDUR(H79,E79) -> 0 | J79: 77 | K79: 4 | L79: Action-Adventure | M79: Exclusive | R79: =IF(S79="","TBD",IF(S79>TODAY(),"Coming Soon",IF(F79="","Active",IF(F79>TODAY(),"Leaving Soon","Removed")))) -> TBD | T79: =MONTHDUR(E79,S79) -> 1.8
A80: The Rogue Prince of Persia | B80: Xbox / PC | C80: Yes | D80: =IF(E80>TODAY(),"Coming Soon",IF(F80="","Active",IF(F80>TODAY(),"Leaving Soon","Removed"))) -> Active | E80: 45889 | G80: =MONTHDUR(E80,F80) -> 1.8333333 | H80: 45889 | I80: =YEARDUR(H80,E80) -> 0 | J80: 81 | K80: 8 | L80: Platformer | R80: =IF(S80="","TBD",IF(S80>TODAY(),"Coming Soon",IF(F80="","Active",IF(F80>TODAY(),"Leaving Soon","Removed")))) -> TBD | T80: =MONTHDUR(E80,S80) -> 1.8333333
A81: Persona 4: Golden | B81: Xbox / PC | C81: Yes | D81: =IF(E81>TODAY(),"Coming Soon",IF(F81="","Active",IF(F81>TODAY(),"Leaving Soon","Removed"))) -> Active | E81: 45889 | G81: =MONTHDUR(E81,F81) -> 1.8333333 | H81: 41074 | I81: =YEARDUR(H81,E81) -> 13.183333 | J81: 90 | K81: 68.5 | L81: RPG | N81: Returning title: Joined 1/19/23, left 1/15/24 | O81: M | P81: Alcohol Reference, Animated Blood, Language, Partial Nudity, Sexual Themes, Violence | R81: =IF(S81="","TBD",IF(S81>TODAY(),"Coming Soon",IF(F81="","Active",IF(F81>TODAY(),"Leaving Soon","Removed")))) -> Active | S81: =E81 -> 45889 | T81: =MONTHDUR(E81,S81) -> 0
A82: Blacksmith Master | B82: PC | D82: =IF(E82>TODAY(),"Coming Soon",IF(F82="","Active",IF(F82>TODAY(),"Leaving Soon","Removed"))) -> Active | E82: 45888 | G82: =MONTHDUR(E82,F82) -> 1.8666667 | H82: 45792 | I82: =YEARDUR(H82,E82) -> 0.26111111 | K82: 12 | L82: Tycoon | R82: =IF(S82="","TBD",IF(S82>TODAY(),"Coming Soon",IF(F82="","Active",IF(F82>TODAY(),"Leaving Soon","Removed")))) -> Active | S82: 45931 | T82: =MONTHDUR(E82,S82) -> 1.4
A83: VOID/BREAKER | B83: PC | D83: =IF(E83>TODAY(),"Coming Soon",IF(F83="","Active",IF(F83>TODAY(),"Leaving Soon","Removed"))) -> Active | E83: 45888 | G83: =MONTHDUR(E83,F83) -> 1.8666667 | H83: 45888 | I83: =YEARDUR(H83,E83) -> 0 | L83: Shooter | R83: =IF(S83="","TBD",IF(S83>TODAY(),"Coming Soon",IF(F83="","Active",IF(F83>TODAY(),"Leaving Soon","Removed")))) -> TBD | T83: =MONTHDUR(E83,S83) -> 1.8666667
A84: 9 Kings (Game Preview) | B84: PC | D84: =IF(E84>TODAY(),"Coming Soon",IF(F84="","Active",IF(F84>TODAY(),"Leaving Soon","Removed"))) -> Active | E84: 45883 | G84: =MONTHDUR(E84,F84) -> 2.0333333 | H84: 45883 | I84: =YEARDUR(H84,E84) -> 0 | K84: 3 | L84: Card Battle | R84: =IF(S84="","TBD",IF(S84>TODAY(),"Coming Soon",IF(F84="","Active",IF(F84>TODAY(),"Leaving Soon","Removed")))) -> Active | S84: 45931 | T84: =MONTHDUR(E84,S84) -> 1.5666667
A85: Caesar III | B85: Xbox / PC | C85: Yes | D85: =IF(E85>TODAY(),"Coming Soon",IF(F85="","Active",IF(F85>TODAY(),"Leaving Soon","Removed"))) -> Active | E85: 45883 | G85: =MONTHDUR(E85,F85) -> 2.0333333 | H85: 36068 | I85: =YEARDUR(H85,E85) -> 26.872222 | N85: Retro Classics: Windows 9x | R85: =IF(S85="","TBD",IF(S85>TODAY(),"Coming Soon",IF(F85="","Active",IF(F85>TODAY(),"Leaving Soon","Removed")))) -> Active | S85: =E85 -> 45883 | T85: =MONTHDUR(E85,S85) -> 0
A86: Climber 5 | B86: Xbox / PC | C86: Yes | D86: =IF(E86>TODAY(),"Coming Soon",IF(F86="","Active",IF(F86>TODAY(),"Leaving Soon","Removed"))) -> Active | E86: 45883 | G86: =MONTHDUR(E86,F86) -> 2.0333333 | H86: 31778 | I86: =YEARDUR(H86,E86) -> 38.619444 | N86: Retro Classics: Atari 2600 | R86: =IF(S86="","TBD",IF(S86>TODAY(),"Coming Soon",IF(F86="","Active",IF(F86>TODAY(),"Leaving Soon","Removed")))) -> Active | S86: =E86 -> 45883 | T86: =MONTHDUR(E86,S86) -> 0
A87: The Colonel's Bequest | B87: Xbox / PC | C87: Yes | D87: =IF(E87>TODAY(),"Coming Soon",IF(F87="","Active",IF(F87>TODAY(),"Leaving Soon","Removed"))) -> Active | E87: 45883 | G87: =MONTHDUR(E87,F87) -> 2.0333333 | H87: 32782 | I87: =YEARDUR(H87,E87) -> 35.869444 | N87: Retro Classics: Amiga | R87: =IF(S87="","TBD",IF(S87>TODAY(),"Coming Soon",IF(F87="","Active",IF(F87>TODAY(),"Leaving Soon","Removed")))) -> Active | S87: =E87 -> 45883 | T87: =MONTHDUR(E87,S87) -> 0
A88: Private Eye | B88: Xbox / PC | C88: Yes | D88: =IF(E88>TODAY(),"Coming Soon",IF(F88="","Active",IF(F88>TODAY(),"Leaving Soon","Removed"))) -> Active | E88: 45883 | G88: =MONTHDUR(E88,F88) -> 2.0333333 | H88: 30713 | I88: =YEARDUR(H88,E88) -> 41.536111 | N88: Retro Classics: Atari 2600 | R88: =IF(S88="","TBD",IF(S88>TODAY(),"Coming Soon",IF(F88="","Active",IF(F88>TODAY(),"Leaving Soon","Removed")))) -> Active | S88: =E88 -> 45883 | T88: =MONTHDUR(E88,S88) -> 0
A89: Oystron | B89: Xbox / PC | C89: Yes | D89: =IF(E89>TODAY(),"Coming Soon",IF(F89="","Active",IF(F89>TODAY(),"Leaving Soon","Removed"))) -> Active | E89: 45883 | G89: =MONTHDUR(E89,F89) -> 2.0333333 | H89: 35431 | I89: =YEARDUR(H89,E89) -> 28.619444 | N89: Retro Classics: Atari 2600 | R89: =IF(S89="","TBD",IF(S89>TODAY(),"Coming Soon",IF(F89="","Active",IF(F89>TODAY(),"Leaving Soon","Removed")))) -> Active | S89: =E89 -> 45883 | T89: =MONTHDUR(E89,S89) -> 0
A90: Shootin' Gallery | B90: Xbox / PC | C90: Yes | D90: =IF(E90>TODAY(),"Coming Soon",IF(F90="","Active",IF(F90>TODAY(),"Leaving Soon","Removed"))) -> Active | E90: 45883 | G90: =MONTHDUR(E90,F90) -> 2.0333333 | H90: 29952 | I90: =YEARDUR(H90,E90) -> 43.619444 | N90: Retro Classics: Atari 2600 | R90: =IF(S90="","TBD",IF(S90>TODAY(),"Coming Soon",IF(F90="","Active",IF(F90>TODAY(),"Leaving Soon","Removed")))) -> Active | S90: =E90 -> 45883 | T90: =MONTHDUR(E90,S90) -> 0
A91: Wing War | B91: Xbox / PC | C91: Yes | D91: =IF(E91>TODAY(),"Coming Soon",IF(F91="","Active",IF(F91>TODAY(),"Leaving Soon","Removed"))) -> Active | E91: 45883 | G91: =MONTHDUR(E91,F91) -> 2.0333333 | H91: 30681 | I91: =YEARDUR(H91,E91) -> 41.622222 | N91: Retro Classics: Atari 2600 | R91: =IF(S91="","TBD",IF(S91>TODAY(),"Coming Soon",IF(F91="","Active",IF(F91>TODAY(),"Leaving Soon","Removed")))) -> Active | S91: =E91 -> 45883 | T91: =MONTHDUR(E91,S91) -> 0
A92: Aliens: Fireteam Elite | B92: Xbox / PC | C92: Yes | D92: =IF(E92>TODAY(),"Coming Soon",IF(F92="","Active",IF(F92>TODAY(),"Leaving Soon","Removed"))) -> Active | E92: 45881 | G92: =MONTHDUR(E92,F92) -> 2.1 | H92: 44803 | I92: =YEARDUR(H92,E92) -> 2.95 | J92: 69 | K92: 9 | L92: Shooter | R92: =IF(S92="","TBD",IF(S92>TODAY(),"Coming Soon",IF(F92="","Active",IF(F92>TODAY(),"Leaving Soon","Removed")))) -> Active | S92: =E92 -> 45881 | T92: =MONTHDUR(E92,S92) -> 0
A93: Assassin's Creed Mirage | B93: Xbox / PC | C93: Yes | D93: =IF(E93>TODAY(),"Coming Soon",IF(F93="","Active",IF(F93>TODAY(),"Leaving Soon","Removed"))) -> Active | E93: 45876 | G93: =MONTHDUR(E93,F93) -> 2.2666667 | H93: 45204 | I93: =YEARDUR(H93,E93) -> 1.8388889 | J93: 76 | K93: 16 | L93: RPG | R93: =IF(S93="","TBD",IF(S93>TODAY(),"Coming Soon",IF(F93="","Active",IF(F93>TODAY(),"Leaving Soon","Removed")))) -> TBD | T93: =MONTHDUR(E93,S93) -> 2.2666667
A94: Heretic + Hexen | B94: Xbox / PC | C94: Yes | D94: =IF(E94>TODAY(),"Coming Soon",IF(F94="","Active",IF(F94>TODAY(),"Leaving Soon","Removed"))) -> Active | E94: 45876 | G94: =MONTHDUR(E94,F94) -> 2.2666667 | H94: 45876 | I94: =YEARDUR(H94,E94) -> 0 | J94: 82 | K94: 27 | L94: Compilation | R94: =IF(S94="","TBD",IF(S94>TODAY(),"Coming Soon",IF(F94="","Active",IF(F94>TODAY(),"Leaving Soon","Removed")))) -> TBD | T94: =MONTHDUR(E94,S94) -> 2.2666667
A95: Rain World | B95: Xbox / PC | C95: Yes | D95: =IF(E95>TODAY(),"Coming Soon",IF(F95="","Active",IF(F95>TODAY(),"Leaving Soon","Removed"))) -> Active | E95: 45874 | G95: =MONTHDUR(E95,F95) -> 2.3333333 | H95: 42822 | I95: =YEARDUR(H95,E95) -> 8.3527778 | J95: 59 | K95: 21 | L95: Platformer | R95: =IF(S95="","TBD",IF(S95>TODAY(),"Coming Soon",IF(F95="","Active",IF(F95>TODAY(),"Leaving Soon","Removed")))) -> Active | S95: =E95 -> 45874 | T95: =MONTHDUR(E95,S95) -> 0
A96: Farming Simulator 25 | B96: Xbox / PC | C96: Yes | D96: =IF(E96>TODAY(),"Coming Soon",IF(F96="","Active",IF(F96>TODAY(),"Leaving Soon","Removed"))) -> Active | E96: 45870 | G96: =MONTHDUR(E96,F96) -> 2.4666667 | H96: 45608 | I96: =YEARDUR(H96,E96) -> 0.71944444 | J96: 75 | L96: Simulation | R96: =IF(S96="","TBD",IF(S96>TODAY(),"Coming Soon",IF(F96="","Active",IF(F96>TODAY(),"Leaving Soon","Removed")))) -> Active | S96: =E96 -> 45870 | T96: =MONTHDUR(E96,S96) -> 0
A97: Grounded 2 (Game Preview) | B97: Xbox / PC | C97: Yes | D97: =IF(E97>TODAY(),"Coming Soon",IF(F97="","Active",IF(F97>TODAY(),"Leaving Soon","Removed"))) -> Active | E97: 45867 | G97: =MONTHDUR(E97,F97) -> 2.5333333 | H97: 45867 | I97: =YEARDUR(H97,E97) -> 0 | L97: Sandbox | M97: Exclusive | R97: =IF(S97="","TBD",IF(S97>TODAY(),"Coming Soon",IF(F97="","Active",IF(F97>TODAY(),"Leaving Soon","Removed")))) -> TBD | T97: =MONTHDUR(E97,S97) -> 2.5333333
A98: WUCHANG: Fallen Feathers | B98: Xbox / PC | C98: Yes | D98: =IF(E98>TODAY(),"Coming Soon",IF(F98="","Active",IF(F98>TODAY(),"Leaving Soon","Removed"))) -> Active | E98: 45862 | G98: =MONTHDUR(E98,F98) -> 2.7 | H98: 45862 | I98: =YEARDUR(H98,E98) -> 0 | J98: 74 | K98: 32 | L98: RPG | M98: Exclusive | R98: =IF(S98="","TBD",IF(S98>TODAY(),"Coming Soon",IF(F98="","Active",IF(F98>TODAY(),"Leaving Soon","Removed")))) -> TBD | T98: =MONTHDUR(E98,S98) -> 2.7
A99: Wheel World | B99: Xbox / PC | C99: Yes | D99: =IF(E99>TODAY(),"Coming Soon",IF(F99="","Active",IF(F99>TODAY(),"Leaving Soon","Removed"))) -> Active | E99: 45861 | G99: =MONTHDUR(E99,F99) -> 2.7333333 | H99: 45861 | I99: =YEARDUR(H99,E99) -> 0 | J99: 71 | K99: 5 | L99: Action-Adventure | M99: Exclusive | R99: =IF(S99="","TBD",IF(S99>TODAY(),"Coming Soon",IF(F99="","Active",IF(F99>TODAY(),"Leaving Soon","Removed")))) -> TBD | T99: =MONTHDUR(E99,S99) -> 2.7333333
A100: Abiotic Factor | B100: Xbox / PC | C100: Yes | D100: =IF(E100>TODAY(),"Coming Soon",IF(F100="","Active",IF(F100>TODAY(),"Leaving Soon","Removed"))) -> Active | E100: 45860 | G100: =MONTHDUR(E100,F100) -> 2.7666667 | H100: 45860 | I100: =YEARDUR(H100,E100) -> 0 | J100: 88 | K100: 33 | L100: Survival | M100: Exclusive | R100: =IF(S100="","TBD",IF(S100>TODAY(),"Coming Soon",IF(F100="","Active",IF(F100>TODAY(),"Leaving Soon","Removed")))) -> Active | S100: 45931 | T100: =MONTHDUR(E100,S100) -> 2.3
A101: Descenders Next (Game Preview) | B101: Xbox / PC | C101: Yes | D101: =IF(E101>TODAY(),"Coming Soon",IF(F101="","Active",IF(F101>TODAY(),"Leaving Soon","Removed"))) -> Active | E101: 45859 | G101: =MONTHDUR(E101,F101) -> 2.8 | H101: 45859 | I101: =YEARDUR(H101,E101) -> 0 | L101: Sports | R101: =IF(S101="","TBD",IF(S101>TODAY(),"Coming Soon",IF(F101="","Active",IF(F101>TODAY(),"Leaving Soon","Removed")))) -> TBD | T101: =MONTHDUR(E101,S101) -> 2.8
A102: Caesar | B102: Xbox / PC | C102: Yes | D102: =IF(E102>TODAY(),"Coming Soon",IF(F102="","Active",IF(F102>TODAY(),"Leaving Soon","Removed"))) -> Active | E102: 45859 | G102: =MONTHDUR(E102,F102) -> 2.8 | H102: 33604 | I102: =YEARDUR(H102,E102) -> 33.555556 | N102: Retro Classics: Amiga | R102: =IF(S102="","TBD",IF(S102>TODAY(),"Coming Soon",IF(F102="","Active",IF(F102>TODAY(),"Leaving Soon","Removed")))) -> Active | S102: =E102 -> 45859 | T102: =MONTHDUR(E102,S102) -> 0
...

Sheet Likely Leaving
A1: Complete Game Pass Master List by u/ABattleVet | B1: =COUNTIF(D2:D544,"Active")+COUNTIF(D2:D544,"Leaving Soon") -> 31 | C1: https://www.trueachievements.com/gamer/Bloomy/blog | Q1: l
A2: Game | B2: System | C2: xCloud | D2: Status | E2: Added | F2: Removed | G2: Months | H2: Release | I2: Age | J2: Metacritic | K2: Completion | L2: Genre (Giantbomb) | M2: Xbox Series X|S | N2: Owner Notes | O2: ESRB | P2: ESRB Content Descriptors | Q2: Public Notes
A3: =IFERROR(__xludf.DUMMYFUNCTION("SORT(FILTER('Master List'!A:Q, 'Master List'!D:D=""Active"", ISNA(MATCH('Master List'!A:A, 'Xbox Game Studios'!A:A, 0)), ISNA(MATCH('Master List'!A:A, 'EA Play'!A:A, 0)), map('Master List'!G:G, lambda(a, if(isnumber(a), (a > 1) * ((mod(a, 12) > 10.5) + (m"&"od(a, 12) < 1)), 0)))),7,1)"),"Aliens: Dark Descent") -> Aliens: Dark Descent | B3: =IFERROR(__xludf.DUMMYFUNCTION("""COMPUTED_VALUE"""),"Xbox / PC") -> Xbox / PC | C3: =IFERROR(__xludf.DUMMYFUNCTION("""COMPUTED_VALUE"""),"Yes") -> Yes | D3: =IFERROR(__xludf.DUMMYFUNCTION("""COMPUTED_VALUE"""),"Active") -> Active | E3: =IFERROR(__xludf.DUMMYFUNCTION("""COMPUTED_VALUE"""),45623.0) -> 45623 | G3: =IFERROR(__xludf.DUMMYFUNCTION("""COMPUTED_VALUE"""),10.6) -> 10.6 | H3: =IFERROR(__xludf.DUMMYFUNCTION("""COMPUTED_VALUE"""),45097.0) -> 45097 | I3: =IFERROR(__xludf.DUMMYFUNCTION("""COMPUTED_VALUE"""),1.4361111111111111) -> 1.4361111 | J3: =IFERROR(__xludf.DUMMYFUNCTION("""COMPUTED_VALUE"""),75.0) -> 75 | K3: =IFERROR(__xludf.DUMMYFUNCTION("""COMPUTED_VALUE"""),24.0) -> 24 | L3: =IFERROR(__xludf.DUMMYFUNCTION("""COMPUTED_VALUE"""),"Strategy") -> Strategy
A4: =IFERROR(__xludf.DUMMYFUNCTION("""COMPUTED_VALUE"""),"Nine Sols") -> Nine Sols | B4: =IFERROR(__xludf.DUMMYFUNCTION("""COMPUTED_VALUE"""),"Xbox / PC") -> Xbox / PC | C4: =IFERROR(__xludf.DUMMYFUNCTION("""COMPUTED_VALUE"""),"Yes") -> Yes | D4: =IFERROR(__xludf.DUMMYFUNCTION("""COMPUTED_VALUE"""),"Active") -> Active | E4: =IFERROR(__xludf.DUMMYFUNCTION("""COMPUTED_VALUE"""),45622.0) -> 45622 | G4: =IFERROR(__xludf.DUMMYFUNCTION("""COMPUTED_VALUE"""),10.633333333333333) -> 10.633333 | H4: =IFERROR(__xludf.DUMMYFUNCTION("""COMPUTED_VALUE"""),45440.0) -> 45440 | I4: =IFERROR(__xludf.DUMMYFUNCTION("""COMPUTED_VALUE"""),0.49444444444444446) -> 0.49444444 | J4: =IFERROR(__xludf.DUMMYFUNCTION("""COMPUTED_VALUE"""),83.0) -> 83 | K4: =IFERROR(__xludf.DUMMYFUNCTION("""COMPUTED_VALUE"""),21.0) -> 21 | L4: =IFERROR(__xludf.DUMMYFUNCTION("""COMPUTED_VALUE"""),"Platformer") -> Platformer | M4: =IFERROR(__xludf.DUMMYFUNCTION("""COMPUTED_VALUE"""),"Exclusive") -> Exclusive | N4: =IFERROR(__xludf.DUMMYFUNCTION("""COMPUTED_VALUE"""),"Joins GP in time for day one on console") -> Joins GP in time for day one on console
A5: =IFERROR(__xludf.DUMMYFUNCTION("""COMPUTED_VALUE"""),"S.T.A.L.K.E.R. 2: Heart of Chornobyl") -> S.T.A.L.K.E.R. 2: Heart of Chornobyl | B5: =IFERROR(__xludf.DUMMYFUNCTION("""COMPUTED_VALUE"""),"Xbox / PC") -> Xbox / PC | C5: =IFERROR(__xludf.DUMMYFUNCTION("""COMPUTED_VALUE"""),"Yes") -> Yes | D5: =IFERROR(__xludf.DUMMYFUNCTION("""COMPUTED_VALUE"""),"Active") -> Active | E5: =IFERROR(__xludf.DUMMYFUNCTION("""COMPUTED_VALUE"""),45616.0) -> 45616 | G5: =IFERROR(__xludf.DUMMYFUNCTION("""COMPUTED_VALUE"""),10.833333333333334) -> 10.833333 | H5: =IFERROR(__xludf.DUMMYFUNCTION("""COMPUTED_VALUE"""),45616.0) -> 45616 | I5: =IFERROR(__xludf.DUMMYFUNCTION("""COMPUTED_VALUE"""),0.0) -> 0 | J5: =IFERROR(__xludf.DUMMYFUNCTION("""COMPUTED_VALUE"""),73.0) -> 73 | K5: =IFERROR(__xludf.DUMMYFUNCTION("""COMPUTED_VALUE"""),31.0) -> 31 | L5: =IFERROR(__xludf.DUMMYFUNCTION("""COMPUTED_VALUE"""),"Action-Adventure") -> Action-Adventure | M5: =IFERROR(__xludf.DUMMYFUNCTION("""COMPUTED_VALUE"""),"Exclusive") -> Exclusive
A6: =IFERROR(__xludf.DUMMYFUNCTION("""COMPUTED_VALUE"""),"Goat Simulator: Remastered") -> Goat Simulator: Remastered | B6: =IFERROR(__xludf.DUMMYFUNCTION("""COMPUTED_VALUE"""),"Xbox / PC") -> Xbox / PC | C6: =IFERROR(__xludf.DUMMYFUNCTION("""COMPUTED_VALUE"""),"Yes") -> Yes | D6: =IFERROR(__xludf.DUMMYFUNCTION("""COMPUTED_VALUE"""),"Active") -> Active | E6: =IFERROR(__xludf.DUMMYFUNCTION("""COMPUTED_VALUE"""),45603.0) -> 45603 | G6: =IFERROR(__xludf.DUMMYFUNCTION("""COMPUTED_VALUE"""),11.266666666666666) -> 11.266667 | H6: =IFERROR(__xludf.DUMMYFUNCTION("""COMPUTED_VALUE"""),45603.0) -> 45603 | I6: =IFERROR(__xludf.DUMMYFUNCTION("""COMPUTED_VALUE"""),0.0) -> 0 | J6: =IFERROR(__xludf.DUMMYFUNCTION("""COMPUTED_VALUE"""),65.0) -> 65 | K6: =IFERROR(__xludf.DUMMYFUNCTION("""COMPUTED_VALUE"""),3.0) -> 3 | L6: =IFERROR(__xludf.DUMMYFUNCTION("""COMPUTED_VALUE"""),"Action-Adventure") -> Action-Adventure | M6: =IFERROR(__xludf.DUMMYFUNCTION("""COMPUTED_VALUE"""),"Exclusive") -> Exclusive
A7: =IFERROR(__xludf.DUMMYFUNCTION("""COMPUTED_VALUE"""),"Metal Slug: Tactics") -> Metal Slug: Tactics | B7: =IFERROR(__xludf.DUMMYFUNCTION("""COMPUTED_VALUE"""),"Xbox / PC") -> Xbox / PC | C7: =IFERROR(__xludf.DUMMYFUNCTION("""COMPUTED_VALUE"""),"Yes") -> Yes | D7: =IFERROR(__xludf.DUMMYFUNCTION("""COMPUTED_VALUE"""),"Active") -> Active | E7: =IFERROR(__xludf.DUMMYFUNCTION("""COMPUTED_VALUE"""),45601.0) -> 45601 | G7: =IFERROR(__xludf.DUMMYFUNCTION("""COMPUTED_VALUE"""),11.333333333333332) -> 11.333333 | H7: =IFERROR(__xludf.DUMMYFUNCTION("""COMPUTED_VALUE"""),45601.0) -> 45601 | I7: =IFERROR(__xludf.DUMMYFUNCTION("""COMPUTED_VALUE"""),0.0) -> 0 | J7: =IFERROR(__xludf.DUMMYFUNCTION("""COMPUTED_VALUE"""),79.0) -> 79 | K7: =IFERROR(__xludf.DUMMYFUNCTION("""COMPUTED_VALUE"""),8.0) -> 8 | L7: =IFERROR(__xludf.DUMMYFUNCTION("""COMPUTED_VALUE"""),"Strategy") -> Strategy
A8: =IFERROR(__xludf.DUMMYFUNCTION("""COMPUTED_VALUE"""),"Ashen") -> Ashen | B8: =IFERROR(__xludf.DUMMYFUNCTION("""COMPUTED_VALUE"""),"Xbox / PC") -> Xbox / PC | D8: =IFERROR(__xludf.DUMMYFUNCTION("""COMPUTED_VALUE"""),"Active") -> Active | E8: =IFERROR(__xludf.DUMMYFUNCTION("""COMPUTED_VALUE"""),45594.0) -> 45594 | G8: =IFERROR(__xludf.DUMMYFUNCTION("""COMPUTED_VALUE"""),11.533333333333333) -> 11.533333 | H8: =IFERROR(__xludf.DUMMYFUNCTION("""COMPUTED_VALUE"""),43441.0) -> 43441 | I8: =IFERROR(__xludf.DUMMYFUNCTION("""COMPUTED_VALUE"""),5.894444444444445) -> 5.8944444 | J8: =IFERROR(__xludf.DUMMYFUNCTION("""COMPUTED_VALUE"""),78.0) -> 78 | K8: =IFERROR(__xludf.DUMMYFUNCTION("""COMPUTED_VALUE"""),15.5) -> 15.5 | L8: =IFERROR(__xludf.DUMMYFUNCTION("""COMPUTED_VALUE"""),"Action / RPG / Action-Adventure") -> Action / RPG / Action-Adventure | N8: =IFERROR(__xludf.DUMMYFUNCTION("""COMPUTED_VALUE"""),"Returning title: Originally joined 12/31/18, left 12/1/19") -> Returning title: Originally joined 12/31/18, left 12/1/19
A9: =IFERROR(__xludf.DUMMYFUNCTION("""COMPUTED_VALUE"""),"Call of Duty: Warzone") -> Call of Duty: Warzone | B9: =IFERROR(__xludf.DUMMYFUNCTION("""COMPUTED_VALUE"""),"Xbox / PC") -> Xbox / PC | C9: =IFERROR(__xludf.DUMMYFUNCTION("""COMPUTED_VALUE"""),"Yes") -> Yes | D9: =IFERROR(__xludf.DUMMYFUNCTION("""COMPUTED_VALUE"""),"Active") -> Active | E9: =IFERROR(__xludf.DUMMYFUNCTION("""COMPUTED_VALUE"""),45590.0) -> 45590 | G9: =IFERROR(__xludf.DUMMYFUNCTION("""COMPUTED_VALUE"""),11.666666666666666) -> 11.666667 | H9: =IFERROR(__xludf.DUMMYFUNCTION("""COMPUTED_VALUE"""),44881.0) -> 44881 | I9: =IFERROR(__xludf.DUMMYFUNCTION("""COMPUTED_VALUE"""),1.9416666666666667) -> 1.9416667 | J9: =IFERROR(__xludf.DUMMYFUNCTION("""COMPUTED_VALUE"""),79.0) -> 79 | K9: =IFERROR(__xludf.DUMMYFUNCTION("""COMPUTED_VALUE"""),99.0) -> 99 | L9: =IFERROR(__xludf.DUMMYFUNCTION("""COMPUTED_VALUE"""),"Shooter") -> Shooter | N9: =IFERROR(__xludf.DUMMYFUNCTION("""COMPUTED_VALUE"""),"Joins cloud on 10/25/24 (GPU only), free to play") -> Joins cloud on 10/25/24 (GPU only), free to play
A10: =IFERROR(__xludf.DUMMYFUNCTION("""COMPUTED_VALUE"""),"Donut County") -> Donut County | B10: =IFERROR(__xludf.DUMMYFUNCTION("""COMPUTED_VALUE"""),"Xbox / PC") -> Xbox / PC | C10: =IFERROR(__xludf.DUMMYFUNCTION("""COMPUTED_VALUE"""),"Touch Controls") -> Touch Controls | D10: =IFERROR(__xludf.DUMMYFUNCTION("""COMPUTED_VALUE"""),"Active") -> Active | E10: =IFERROR(__xludf.DUMMYFUNCTION("""COMPUTED_VALUE"""),45582.0) -> 45582 | G10: =IFERROR(__xludf.DUMMYFUNCTION("""COMPUTED_VALUE"""),11.933333333333334) -> 11.933333 | H10: =IFERROR(__xludf.DUMMYFUNCTION("""COMPUTED_VALUE"""),43340.0) -> 43340 | I10: =IFERROR(__xludf.DUMMYFUNCTION("""COMPUTED_VALUE"""),6.136111111111111) -> 6.1361111 | J10: =IFERROR(__xludf.DUMMYFUNCTION("""COMPUTED_VALUE"""),82.0) -> 82 | K10: =IFERROR(__xludf.DUMMYFUNCTION("""COMPUTED_VALUE"""),2.0) -> 2 | L10: =IFERROR(__xludf.DUMMYFUNCTION("""COMPUTED_VALUE"""),"Action") -> Action | N10: =IFERROR(__xludf.DUMMYFUNCTION("""COMPUTED_VALUE"""),"Returning title: Originally joined 1/21/21, left 1/31/23, Official PC Mod Support") -> Returning title: Originally joined 1/21/21, left 1/31/23, Official PC Mod Support | O10: =IFERROR(__xludf.DUMMYFUNCTION("""COMPUTED_VALUE"""),"E") -> E | P10: =IFERROR(__xludf.DUMMYFUNCTION("""COMPUTED_VALUE"""),"Mild Fantasy Violence, Comic Mischief") -> Mild Fantasy Violence, Comic Mischief
A11: =IFERROR(__xludf.DUMMYFUNCTION("""COMPUTED_VALUE"""),"Mechwarrior 5: Clans") -> Mechwarrior 5: Clans | B11: =IFERROR(__xludf.DUMMYFUNCTION("""COMPUTED_VALUE"""),"Xbox / PC") -> Xbox / PC | C11: =IFERROR(__xludf.DUMMYFUNCTION("""COMPUTED_VALUE"""),"Yes") -> Yes | D11: =IFERROR(__xludf.DUMMYFUNCTION("""COMPUTED_VALUE"""),"Active") -> Active | E11: =IFERROR(__xludf.DUMMYFUNCTION("""COMPUTED_VALUE"""),45582.0) -> 45582 | G11: =IFERROR(__xludf.DUMMYFUNCTION("""COMPUTED_VALUE"""),11.933333333333334) -> 11.933333 | H11: =IFERROR(__xludf.DUMMYFUNCTION("""COMPUTED_VALUE"""),45582.0) -> 45582 | I11: =IFERROR(__xludf.DUMMYFUNCTION("""COMPUTED_VALUE"""),0.0) -> 0 | J11: =IFERROR(__xludf.DUMMYFUNCTION("""COMPUTED_VALUE"""),79.0) -> 79 | K11: =IFERROR(__xludf.DUMMYFUNCTION("""COMPUTED_VALUE"""),23.0) -> 23 | L11: =IFERROR(__xludf.DUMMYFUNCTION("""COMPUTED_VALUE"""),"Simulation") -> Simulation | M11: =IFERROR(__xludf.DUMMYFUNCTION("""COMPUTED_VALUE"""),"Exclusive") -> Exclusive
A12: =IFERROR(__xludf.DUMMYFUNCTION("""COMPUTED_VALUE"""),"South Park: The Fractured but Whole") -> South Park: The Fractured but Whole | B12: =IFERROR(__xludf.DUMMYFUNCTION("""COMPUTED_VALUE"""),"Xbox / PC") -> Xbox / PC | C12: =IFERROR(__xludf.DUMMYFUNCTION("""COMPUTED_VALUE"""),"Yes") -> Yes | D12: =IFERROR(__xludf.DUMMYFUNCTION("""COMPUTED_VALUE"""),"Active") -> Active | E12: =IFERROR(__xludf.DUMMYFUNCTION("""COMPUTED_VALUE"""),45581.0) -> 45581 | G12: =IFERROR(__xludf.DUMMYFUNCTION("""COMPUTED_VALUE"""),11.966666666666667) -> 11.966667 | H12: =IFERROR(__xludf.DUMMYFUNCTION("""COMPUTED_VALUE"""),43312.0) -> 43312 | I12: =IFERROR(__xludf.DUMMYFUNCTION("""COMPUTED_VALUE"""),6.211111111111111) -> 6.2111111 | J12: =IFERROR(__xludf.DUMMYFUNCTION("""COMPUTED_VALUE"""),75.0) -> 75 | K12: =IFERROR(__xludf.DUMMYFUNCTION("""COMPUTED_VALUE"""),18.0) -> 18 | L12: =IFERROR(__xludf.DUMMYFUNCTION("""COMPUTED_VALUE"""),"RPG") -> RPG
A13: =IFERROR(__xludf.DUMMYFUNCTION("""COMPUTED_VALUE"""),"Inscryption") -> Inscryption | B13: =IFERROR(__xludf.DUMMYFUNCTION("""COMPUTED_VALUE"""),"Xbox / PC") -> Xbox / PC | C13: =IFERROR(__xludf.DUMMYFUNCTION("""COMPUTED_VALUE"""),"Yes") -> Yes | D13: =IFERROR(__xludf.DUMMYFUNCTION("""COMPUTED_VALUE"""),"Active") -> Active | E13: =IFERROR(__xludf.DUMMYFUNCTION("""COMPUTED_VALUE"""),45575.0) -> 45575 | G13: =IFERROR(__xludf.DUMMYFUNCTION("""COMPUTED_VALUE"""),12.166666666666666) -> 12.166667 | H13: =IFERROR(__xludf.DUMMYFUNCTION("""COMPUTED_VALUE"""),44488.0) -> 44488 | I13: =IFERROR(__xludf.DUMMYFUNCTION("""COMPUTED_VALUE"""),2.975) -> 2.975 | J13: =IFERROR(__xludf.DUMMYFUNCTION("""COMPUTED_VALUE"""),85.0) -> 85 | K13: =IFERROR(__xludf.DUMMYFUNCTION("""COMPUTED_VALUE"""),13.0) -> 13 | L13: =IFERROR(__xludf.DUMMYFUNCTION("""COMPUTED_VALUE"""),"Card Battle") -> Card Battle
A14: =IFERROR(__xludf.DUMMYFUNCTION("""COMPUTED_VALUE"""),"Mad Streets") -> Mad Streets | B14: =IFERROR(__xludf.DUMMYFUNCTION("""COMPUTED_VALUE"""),"Xbox / PC") -> Xbox / PC | C14: =IFERROR(__xludf.DUMMYFUNCTION("""COMPUTED_VALUE"""),"Yes") -> Yes | D14: =IFERROR(__xludf.DUMMYFUNCTION("""COMPUTED_VALUE"""),"Active") -> Active | E14: =IFERROR(__xludf.DUMMYFUNCTION("""COMPUTED_VALUE"""),45572.0) -> 45572 | G14: =IFERROR(__xludf.DUMMYFUNCTION("""COMPUTED_VALUE"""),12.266666666666666) -> 12.266667 | H14: =IFERROR(__xludf.DUMMYFUNCTION("""COMPUTED_VALUE"""),44435.0) -> 44435 | I14: =IFERROR(__xludf.DUMMYFUNCTION("""COMPUTED_VALUE"""),3.111111111111111) -> 3.1111111 | J14: =IFERROR(__xludf.DUMMYFUNCTION("""COMPUTED_VALUE"""),55.0) -> 55 | K14: =IFERROR(__xludf.DUMMYFUNCTION("""COMPUTED_VALUE"""),2.0) -> 2 | L14: =IFERROR(__xludf.DUMMYFUNCTION("""COMPUTED_VALUE"""),"Beat-'Em-Up ") -> Beat-'Em-Up
A15: =IFERROR(__xludf.DUMMYFUNCTION("""COMPUTED_VALUE"""),"SIFU") -> SIFU | B15: =IFERROR(__xludf.DUMMYFUNCTION("""COMPUTED_VALUE"""),"Xbox / PC") -> Xbox / PC | C15: =IFERROR(__xludf.DUMMYFUNCTION("""COMPUTED_VALUE"""),"Yes") -> Yes | D15: =IFERROR(__xludf.DUMMYFUNCTION("""COMPUTED_VALUE"""),"Active") -> Active | E15: =IFERROR(__xludf.DUMMYFUNCTION("""COMPUTED_VALUE"""),45567.0) -> 45567 | G15: =IFERROR(__xludf.DUMMYFUNCTION("""COMPUTED_VALUE"""),12.433333333333334) -> 12.433333 | H15: =IFERROR(__xludf.DUMMYFUNCTION("""COMPUTED_VALUE"""),44600.0) -> 44600 | I15: =IFERROR(__xludf.DUMMYFUNCTION("""COMPUTED_VALUE"""),2.65) -> 2.65 | J15: =IFERROR(__xludf.DUMMYFUNCTION("""COMPUTED_VALUE"""),81.0) -> 81 | K15: =IFERROR(__xludf.DUMMYFUNCTION("""COMPUTED_VALUE"""),9.0) -> 9 | L15: =IFERROR(__xludf.DUMMYFUNCTION("""COMPUTED_VALUE"""),"Xbox / PC") -> Xbox / PC
A16: =IFERROR(__xludf.DUMMYFUNCTION("""COMPUTED_VALUE"""),"Legend of Mana (2021)") -> Legend of Mana (2021) | B16: =IFERROR(__xludf.DUMMYFUNCTION("""COMPUTED_VALUE"""),"Xbox / PC") -> Xbox / PC | C16: =IFERROR(__xludf.DUMMYFUNCTION("""COMPUTED_VALUE"""),"Yes") -> Yes | D16: =IFERROR(__xludf.DUMMYFUNCTION("""COMPUTED_VALUE"""),"Active") -> Active | E16: =IFERROR(__xludf.DUMMYFUNCTION("""COMPUTED_VALUE"""),45561.0) -> 45561 | G16: =IFERROR(__xludf.DUMMYFUNCTION("""COMPUTED_VALUE"""),12.633333333333333) -> 12.633333 | H16: =IFERROR(__xludf.DUMMYFUNCTION("""COMPUTED_VALUE"""),44371.0) -> 44371 | I16: =IFERROR(__xludf.DUMMYFUNCTION("""COMPUTED_VALUE"""),3.2555555555555555) -> 3.2555556 | J16: =IFERROR(__xludf.DUMMYFUNCTION("""COMPUTED_VALUE"""),72.0) -> 72 | K16: =IFERROR(__xludf.DUMMYFUNCTION("""COMPUTED_VALUE"""),18.0) -> 18 | L16: =IFERROR(__xludf.DUMMYFUNCTION("""COMPUTED_VALUE"""),"RPG") -> RPG
A17: =IFERROR(__xludf.DUMMYFUNCTION("""COMPUTED_VALUE"""),"Trials of Mana (2020)") -> Trials of Mana (2020) | B17: =IFERROR(__xludf.DUMMYFUNCTION("""COMPUTED_VALUE"""),"Xbox / PC") -> Xbox / PC | C17: =IFERROR(__xludf.DUMMYFUNCTION("""COMPUTED_VALUE"""),"Yes") -> Yes | D17: =IFERROR(__xludf.DUMMYFUNCTION("""COMPUTED_VALUE"""),"Active") -> Active | E17: =IFERROR(__xludf.DUMMYFUNCTION("""COMPUTED_VALUE"""),45561.0) -> 45561 | G17: =IFERROR(__xludf.DUMMYFUNCTION("""COMPUTED_VALUE"""),12.633333333333333) -> 12.633333 | H17: =IFERROR(__xludf.DUMMYFUNCTION("""COMPUTED_VALUE"""),43945.0) -> 43945 | I17: =IFERROR(__xludf.DUMMYFUNCTION("""COMPUTED_VALUE"""),4.4222222222222225) -> 4.4222222 | J17: =IFERROR(__xludf.DUMMYFUNCTION("""COMPUTED_VALUE"""),76.0) -> 76 | K17: =IFERROR(__xludf.DUMMYFUNCTION("""COMPUTED_VALUE"""),21.0) -> 21 | L17: =IFERROR(__xludf.DUMMYFUNCTION("""COMPUTED_VALUE"""),"RPG") -> RPG
A18: =IFERROR(__xludf.DUMMYFUNCTION("""COMPUTED_VALUE"""),"Ara: History Untold") -> Ara: History Untold | B18: =IFERROR(__xludf.DUMMYFUNCTION("""COMPUTED_VALUE"""),"PC") -> PC | D18: =IFERROR(__xludf.DUMMYFUNCTION("""COMPUTED_VALUE"""),"Active") -> Active | E18: =IFERROR(__xludf.DUMMYFUNCTION("""COMPUTED_VALUE"""),45559.0) -> 45559 | G18: =IFERROR(__xludf.DUMMYFUNCTION("""COMPUTED_VALUE"""),12.7) -> 12.7 | H18: =IFERROR(__xludf.DUMMYFUNCTION("""COMPUTED_VALUE"""),45559.0) -> 45559 | I18: =IFERROR(__xludf.DUMMYFUNCTION("""COMPUTED_VALUE"""),0.0) -> 0 | J18: =IFERROR(__xludf.DUMMYFUNCTION("""COMPUTED_VALUE"""),76.0) -> 76 | K18: =IFERROR(__xludf.DUMMYFUNCTION("""COMPUTED_VALUE"""),13.0) -> 13 | L18: =IFERROR(__xludf.DUMMYFUNCTION("""COMPUTED_VALUE"""),"Strategy") -> Strategy
A19: =IFERROR(__xludf.DUMMYFUNCTION("""COMPUTED_VALUE"""),"Frostpunk 2") -> Frostpunk 2 | B19: =IFERROR(__xludf.DUMMYFUNCTION("""COMPUTED_VALUE"""),"Xbox / PC") -> Xbox / PC | C19: =IFERROR(__xludf.DUMMYFUNCTION("""COMPUTED_VALUE"""),"Yes") -> Yes | D19: =IFERROR(__xludf.DUMMYFUNCTION("""COMPUTED_VALUE"""),"Active") -> Active | E19: =IFERROR(__xludf.DUMMYFUNCTION("""COMPUTED_VALUE"""),45555.0) -> 45555 | G19: =IFERROR(__xludf.DUMMYFUNCTION("""COMPUTED_VALUE"""),12.833333333333332) -> 12.833333 | H19: =IFERROR(__xludf.DUMMYFUNCTION("""COMPUTED_VALUE"""),45555.0) -> 45555 | I19: =IFERROR(__xludf.DUMMYFUNCTION("""COMPUTED_VALUE"""),0.0) -> 0 | J19: =IFERROR(__xludf.DUMMYFUNCTION("""COMPUTED_VALUE"""),86.0) -> 86 | K19: =IFERROR(__xludf.DUMMYFUNCTION("""COMPUTED_VALUE"""),11.0) -> 11 | L19: =IFERROR(__xludf.DUMMYFUNCTION("""COMPUTED_VALUE"""),"Simulation") -> Simulation | M19: =IFERROR(__xludf.DUMMYFUNCTION("""COMPUTED_VALUE"""),"Exclusive") -> Exclusive | N19: =IFERROR(__xludf.DUMMYFUNCTION("""COMPUTED_VALUE"""),"Joins console and cloud 9/18/25") -> Joins console and cloud 9/18/25
A20: =IFERROR(__xludf.DUMMYFUNCTION("""COMPUTED_VALUE"""),"Train Sim World 5") -> Train Sim World 5 | B20: =IFERROR(__xludf.DUMMYFUNCTION("""COMPUTED_VALUE"""),"Xbox / PC") -> Xbox / PC | C20: =IFERROR(__xludf.DUMMYFUNCTION("""COMPUTED_VALUE"""),"Yes") -> Yes | D20: =IFERROR(__xludf.DUMMYFUNCTION("""COMPUTED_VALUE"""),"Active") -> Active | E20: =IFERROR(__xludf.DUMMYFUNCTION("""COMPUTED_VALUE"""),45552.0) -> 45552 | G20: =IFERROR(__xludf.DUMMYFUNCTION("""COMPUTED_VALUE"""),12.933333333333334) -> 12.933333 | H20: =IFERROR(__xludf.DUMMYFUNCTION("""COMPUTED_VALUE"""),45195.0) -> 45195 | I20: =IFERROR(__xludf.DUMMYFUNCTION("""COMPUTED_VALUE"""),0.975) -> 0.975 | J20: =IFERROR(__xludf.DUMMYFUNCTION("""COMPUTED_VALUE"""),77.0) -> 77 | L20: =IFERROR(__xludf.DUMMYFUNCTION("""COMPUTED_VALUE"""),"Simulation") -> Simulation
A21: =IFERROR(__xludf.DUMMYFUNCTION("""COMPUTED_VALUE"""),"Spirittea") -> Spirittea | B21: =IFERROR(__xludf.DUMMYFUNCTION("""COMPUTED_VALUE"""),"Xbox / PC") -> Xbox / PC | C21: =IFERROR(__xludf.DUMMYFUNCTION("""COMPUTED_VALUE"""),"Yes") -> Yes | D21: =IFERROR(__xludf.DUMMYFUNCTION("""COMPUTED_VALUE"""),"Active") -> Active | E21: =IFERROR(__xludf.DUMMYFUNCTION("""COMPUTED_VALUE"""),45243.0) -> 45243 | G21: =IFERROR(__xludf.DUMMYFUNCTION("""COMPUTED_VALUE"""),23.066666666666666) -> 23.066667 | H21: =IFERROR(__xludf.DUMMYFUNCTION("""COMPUTED_VALUE"""),45243.0) -> 45243 | I21: =IFERROR(__xludf.DUMMYFUNCTION("""COMPUTED_VALUE"""),0.0) -> 0 | J21: =IFERROR(__xludf.DUMMYFUNCTION("""COMPUTED_VALUE"""),76.0) -> 76 | K21: =IFERROR(__xludf.DUMMYFUNCTION("""COMPUTED_VALUE"""),33.0) -> 33 | L21: =IFERROR(__xludf.DUMMYFUNCTION("""COMPUTED_VALUE"""),"Strategy / Adventure / RPG / Simulation") -> Strategy / Adventure / RPG / Simulation
A22: =IFERROR(__xludf.DUMMYFUNCTION("""COMPUTED_VALUE"""),"Football Manager 2024") -> Football Manager 2024 | B22: =IFERROR(__xludf.DUMMYFUNCTION("""COMPUTED_VALUE"""),"Xbox / PC") -> Xbox / PC | C22: =IFERROR(__xludf.DUMMYFUNCTION("""COMPUTED_VALUE"""),"Yes") -> Yes | D22: =IFERROR(__xludf.DUMMYFUNCTION("""COMPUTED_VALUE"""),"Active") -> Active | E22: =IFERROR(__xludf.DUMMYFUNCTION("""COMPUTED_VALUE"""),45236.0) -> 45236 | G22: =IFERROR(__xludf.DUMMYFUNCTION("""COMPUTED_VALUE"""),23.3) -> 23.3 | H22: =IFERROR(__xludf.DUMMYFUNCTION("""COMPUTED_VALUE"""),45236.0) -> 45236 | I22: =IFERROR(__xludf.DUMMYFUNCTION("""COMPUTED_VALUE"""),0.0) -> 0 | J22: =IFERROR(__xludf.DUMMYFUNCTION("""COMPUTED_VALUE"""),84.0) -> 84 | K22: =IFERROR(__xludf.DUMMYFUNCTION("""COMPUTED_VALUE"""),11.0) -> 11 | L22: =IFERROR(__xludf.DUMMYFUNCTION("""COMPUTED_VALUE"""),"Simulation / Soccer") -> Simulation / Soccer
A23: =IFERROR(__xludf.DUMMYFUNCTION("""COMPUTED_VALUE"""),"Thirsty Suitors") -> Thirsty Suitors | B23: =IFERROR(__xludf.DUMMYFUNCTION("""COMPUTED_VALUE"""),"Xbox / PC") -> Xbox / PC | C23: =IFERROR(__xludf.DUMMYFUNCTION("""COMPUTED_VALUE"""),"Yes") -> Yes | D23: =IFERROR(__xludf.DUMMYFUNCTION("""COMPUTED_VALUE"""),"Active") -> Active | E23: =IFERROR(__xludf.DUMMYFUNCTION("""COMPUTED_VALUE"""),45232.0) -> 45232 | G23: =IFERROR(__xludf.DUMMYFUNCTION("""COMPUTED_VALUE"""),23.433333333333334) -> 23.433333 | H23: =IFERROR(__xludf.DUMMYFUNCTION("""COMPUTED_VALUE"""),45232.0) -> 45232 | I23: =IFERROR(__xludf.DUMMYFUNCTION("""COMPUTED_VALUE"""),0.0) -> 0 | J23: =IFERROR(__xludf.DUMMYFUNCTION("""COMPUTED_VALUE"""),80.0) -> 80 | K23: =IFERROR(__xludf.DUMMYFUNCTION("""COMPUTED_VALUE"""),8.0) -> 8 | L23: =IFERROR(__xludf.DUMMYFUNCTION("""COMPUTED_VALUE"""),"Adventure / RPG") -> Adventure / RPG | O23: =IFERROR(__xludf.DUMMYFUNCTION("""COMPUTED_VALUE"""),"T") -> T
A24: =IFERROR(__xludf.DUMMYFUNCTION("""COMPUTED_VALUE"""),"Jusant") -> Jusant | B24: =IFERROR(__xludf.DUMMYFUNCTION("""COMPUTED_VALUE"""),"Xbox / PC") -> Xbox / PC | C24: =IFERROR(__xludf.DUMMYFUNCTION("""COMPUTED_VALUE"""),"Yes") -> Yes | D24: =IFERROR(__xludf.DUMMYFUNCTION("""COMPUTED_VALUE"""),"Active") -> Active | E24: =IFERROR(__xludf.DUMMYFUNCTION("""COMPUTED_VALUE"""),45230.0) -> 45230 | G24: =IFERROR(__xludf.DUMMYFUNCTION("""COMPUTED_VALUE"""),23.5) -> 23.5 | H24: =IFERROR(__xludf.DUMMYFUNCTION("""COMPUTED_VALUE"""),45230.0) -> 45230 | I24: =IFERROR(__xludf.DUMMYFUNCTION("""COMPUTED_VALUE"""),0.0) -> 0 | J24: =IFERROR(__xludf.DUMMYFUNCTION("""COMPUTED_VALUE"""),83.0) -> 83 | K24: =IFERROR(__xludf.DUMMYFUNCTION("""COMPUTED_VALUE"""),4.0) -> 4 | L24: =IFERROR(__xludf.DUMMYFUNCTION("""COMPUTED_VALUE"""),"Adventure") -> Adventure | O24: =IFERROR(__xludf.DUMMYFUNCTION("""COMPUTED_VALUE"""),"RP") -> RP
A25: =IFERROR(__xludf.DUMMYFUNCTION("""COMPUTED_VALUE"""),"Wartales") -> Wartales | B25: =IFERROR(__xludf.DUMMYFUNCTION("""COMPUTED_VALUE"""),"Xbox / PC") -> Xbox / PC | C25: =IFERROR(__xludf.DUMMYFUNCTION("""COMPUTED_VALUE"""),"Yes") -> Yes | D25: =IFERROR(__xludf.DUMMYFUNCTION("""COMPUTED_VALUE"""),"Active") -> Active | E25: =IFERROR(__xludf.DUMMYFUNCTION("""COMPUTED_VALUE"""),45230.0) -> 45230 | G25: =IFERROR(__xludf.DUMMYFUNCTION("""COMPUTED_VALUE"""),23.5) -> 23.5 | H25: =IFERROR(__xludf.DUMMYFUNCTION("""COMPUTED_VALUE"""),44531.0) -> 44531 | I25: =IFERROR(__xludf.DUMMYFUNCTION("""COMPUTED_VALUE"""),1.913888888888889) -> 1.9138889 | J25: =IFERROR(__xludf.DUMMYFUNCTION("""COMPUTED_VALUE"""),80.0) -> 80 | K25: =IFERROR(__xludf.DUMMYFUNCTION("""COMPUTED_VALUE"""),38.0) -> 38 | L25: =IFERROR(__xludf.DUMMYFUNCTION("""COMPUTED_VALUE"""),"Strategy / Adventure / RPG") -> Strategy / Adventure / RPG | N25: =IFERROR(__xludf.DUMMYFUNCTION("""COMPUTED_VALUE"""),"Joined xbox one ine June 2024") -> Joined xbox one ine June 2024
A26: =IFERROR(__xludf.DUMMYFUNCTION("""COMPUTED_VALUE"""),"Cities: Skylines II") -> Cities: Skylines II | B26: =IFERROR(__xludf.DUMMYFUNCTION("""COMPUTED_VALUE"""),"PC") -> PC | D26: =IFERROR(__xludf.DUMMYFUNCTION("""COMPUTED_VALUE"""),"Active") -> Active | E26: =IFERROR(__xludf.DUMMYFUNCTION("""COMPUTED_VALUE"""),45223.0) -> 45223 | G26: =IFERROR(__xludf.DUMMYFUNCTION("""COMPUTED_VALUE"""),23.700000000000003) -> 23.7 | H26: =IFERROR(__xludf.DUMMYFUNCTION("""COMPUTED_VALUE"""),45223.0) -> 45223 | I26: =IFERROR(__xludf.DUMMYFUNCTION("""COMPUTED_VALUE"""),0.0) -> 0 | J26: =IFERROR(__xludf.DUMMYFUNCTION("""COMPUTED_VALUE"""),75.0) -> 75 | K26: =IFERROR(__xludf.DUMMYFUNCTION("""COMPUTED_VALUE"""),25.0) -> 25 | L26: =IFERROR(__xludf.DUMMYFUNCTION("""COMPUTED_VALUE"""),"Simulation") -> Simulation | O26: =IFERROR(__xludf.DUMMYFUNCTION("""COMPUTED_VALUE"""),"RP") -> RP
A27: =IFERROR(__xludf.DUMMYFUNCTION("""COMPUTED_VALUE"""),"Return to Monkey Island") -> Return to Monkey Island | B27: =IFERROR(__xludf.DUMMYFUNCTION("""COMPUTED_VALUE"""),"Xbox / PC") -> Xbox / PC | C27: =IFERROR(__xludf.DUMMYFUNCTION("""COMPUTED_VALUE"""),"Yes") -> Yes | D27: =IFERROR(__xludf.DUMMYFUNCTION("""COMPUTED_VALUE"""),"Active") -> Active | E27: =IFERROR(__xludf.DUMMYFUNCTION("""COMPUTED_VALUE"""),44873.0) -> 44873 | G27: =IFERROR(__xludf.DUMMYFUNCTION("""COMPUTED_VALUE"""),35.233333333333334) -> 35.233333 | H27: =IFERROR(__xludf.DUMMYFUNCTION("""COMPUTED_VALUE"""),44823.0) -> 44823 | I27: =IFERROR(__xludf.DUMMYFUNCTION("""COMPUTED_VALUE"""),0.1361111111111111) -> 0.13611111 | J27: =IFERROR(__xludf.DUMMYFUNCTION("""COMPUTED_VALUE"""),87.0) -> 87 | K27: =IFERROR(__xludf.DUMMYFUNCTION("""COMPUTED_VALUE"""),10.5) -> 10.5 | L27: =IFERROR(__xludf.DUMMYFUNCTION("""COMPUTED_VALUE"""),"Adventure") -> Adventure | M27: =IFERROR(__xludf.DUMMYFUNCTION("""COMPUTED_VALUE"""),"Exclusive") -> Exclusive | O27: =IFERROR(__xludf.DUMMYFUNCTION("""COMPUTED_VALUE"""),"E10+") -> E10+ | P27: =IFERROR(__xludf.DUMMYFUNCTION("""COMPUTED_VALUE"""),"Alcohol Reference, Fantasy Violence") -> Alcohol Reference, Fantasy Violence
A28: =IFERROR(__xludf.DUMMYFUNCTION("""COMPUTED_VALUE"""),"A Plague Tale: Requiem") -> A Plague Tale: Requiem | B28: =IFERROR(__xludf.DUMMYFUNCTION("""COMPUTED_VALUE"""),"Xbox / PC") -> Xbox / PC | C28: =IFERROR(__xludf.DUMMYFUNCTION("""COMPUTED_VALUE"""),"Yes") -> Yes | D28: =IFERROR(__xludf.DUMMYFUNCTION("""COMPUTED_VALUE"""),"Active") -> Active | E28: =IFERROR(__xludf.DUMMYFUNCTION("""COMPUTED_VALUE"""),44852.0) -> 44852 | G28: =IFERROR(__xludf.DUMMYFUNCTION("""COMPUTED_VALUE"""),35.9) -> 35.9 | H28: =IFERROR(__xludf.DUMMYFUNCTION("""COMPUTED_VALUE"""),44852.0) -> 44852 | I28: =IFERROR(__xludf.DUMMYFUNCTION("""COMPUTED_VALUE"""),0.0) -> 0 | J28: =IFERROR(__xludf.DUMMYFUNCTION("""COMPUTED_VALUE"""),85.0) -> 85 | K28: =IFERROR(__xludf.DUMMYFUNCTION("""COMPUTED_VALUE"""),15.0) -> 15 | L28: =IFERROR(__xludf.DUMMYFUNCTION("""COMPUTED_VALUE"""),"Action-Adventure") -> Action-Adventure | M28: =IFERROR(__xludf.DUMMYFUNCTION("""COMPUTED_VALUE"""),"Exclusive") -> Exclusive | O28: =IFERROR(__xludf.DUMMYFUNCTION("""COMPUTED_VALUE"""),"M") -> M | P28: =IFERROR(__xludf.DUMMYFUNCTION("""COMPUTED_VALUE"""),"Intense Violence, Blood, Language") -> Intense Violence, Blood, Language
A29: =IFERROR(__xludf.DUMMYFUNCTION("""COMPUTED_VALUE"""),"Chivalry II") -> Chivalry II | B29: =IFERROR(__xludf.DUMMYFUNCTION("""COMPUTED_VALUE"""),"Xbox / PC") -> Xbox / PC | C29: =IFERROR(__xludf.DUMMYFUNCTION("""COMPUTED_VALUE"""),"Yes") -> Yes | D29: =IFERROR(__xludf.DUMMYFUNCTION("""COMPUTED_VALUE"""),"Active") -> Active | E29: =IFERROR(__xludf.DUMMYFUNCTION("""COMPUTED_VALUE"""),44838.0) -> 44838 | G29: =IFERROR(__xludf.DUMMYFUNCTION("""COMPUTED_VALUE"""),36.36666666666667) -> 36.366667 | H29: =IFERROR(__xludf.DUMMYFUNCTION("""COMPUTED_VALUE"""),44355.0) -> 44355 | I29: =IFERROR(__xludf.DUMMYFUNCTION("""COMPUTED_VALUE"""),1.3222222222222222) -> 1.3222222 | J29: =IFERROR(__xludf.DUMMYFUNCTION("""COMPUTED_VALUE"""),82.0) -> 82 | K29: =IFERROR(__xludf.DUMMYFUNCTION("""COMPUTED_VALUE"""),42.5) -> 42.5 | L29: =IFERROR(__xludf.DUMMYFUNCTION("""COMPUTED_VALUE"""),"Action") -> Action | N29: =IFERROR(__xludf.DUMMYFUNCTION("""COMPUTED_VALUE"""),"Game Pass Essential (12/6/23)") -> Game Pass Essential (12/6/23) | O29: =IFERROR(__xludf.DUMMYFUNCTION("""COMPUTED_VALUE"""),"M") -> M | P29: =IFERROR(__xludf.DUMMYFUNCTION("""COMPUTED_VALUE"""),"Use of Alcohol, Blood and Gore, Mild Sexual Themes, Language, Intense Violence") -> Use of Alcohol, Blood and Gore, Mild Sexual Themes, Language, Intense Violence
A30: =IFERROR(__xludf.DUMMYFUNCTION("""COMPUTED_VALUE"""),"Unpacking") -> Unpacking | B30: =IFERROR(__xludf.DUMMYFUNCTION("""COMPUTED_VALUE"""),"Xbox / PC") -> Xbox / PC | C30: =IFERROR(__xludf.DUMMYFUNCTION("""COMPUTED_VALUE"""),"Touch Controls") -> Touch Controls | D30: =IFERROR(__xludf.DUMMYFUNCTION("""COMPUTED_VALUE"""),"Active") -> Active | E30: =IFERROR(__xludf.DUMMYFUNCTION("""COMPUTED_VALUE"""),44502.0) -> 44502 | G30: =IFERROR(__xludf.DUMMYFUNCTION("""COMPUTED_VALUE"""),47.43333333333334) -> 47.433333 | H30: =IFERROR(__xludf.DUMMYFUNCTION("""COMPUTED_VALUE"""),44502.0) -> 44502 | I30: =IFERROR(__xludf.DUMMYFUNCTION("""COMPUTED_VALUE"""),0.0) -> 0 | J30: =IFERROR(__xludf.DUMMYFUNCTION("""COMPUTED_VALUE"""),82.0) -> 82 | K30: =IFERROR(__xludf.DUMMYFUNCTION("""COMPUTED_VALUE"""),3.5) -> 3.5 | L30: =IFERROR(__xludf.DUMMYFUNCTION("""COMPUTED_VALUE"""),"Simulation / Puzzle") -> Simulation / Puzzle | N30: =IFERROR(__xludf.DUMMYFUNCTION("""COMPUTED_VALUE"""),"Game Pass Essential launch title (9/14/23)") -> Game Pass Essential launch title (9/14/23) | O30: =IFERROR(__xludf.DUMMYFUNCTION("""COMPUTED_VALUE"""),"E") -> E
A31: =IFERROR(__xludf.DUMMYFUNCTION("""COMPUTED_VALUE"""),"Superliminal") -> Superliminal | B31: =IFERROR(__xludf.DUMMYFUNCTION("""COMPUTED_VALUE"""),"Xbox / PC") -> Xbox / PC | C31: =IFERROR(__xludf.DUMMYFUNCTION("""COMPUTED_VALUE"""),"Touch Controls") -> Touch Controls | D31: =IFERROR(__xludf.DUMMYFUNCTION("""COMPUTED_VALUE"""),"Active") -> Active | E31: =IFERROR(__xludf.DUMMYFUNCTION("""COMPUTED_VALUE"""),44455.0) -> 44455 | G31: =IFERROR(__xludf.DUMMYFUNCTION("""COMPUTED_VALUE"""),48.96666666666667) -> 48.966667 | H31: =IFERROR(__xludf.DUMMYFUNCTION("""COMPUTED_VALUE"""),43781.0) -> 43781 | I31: =IFERROR(__xludf.DUMMYFUNCTION("""COMPUTED_VALUE"""),1.8444444444444446) -> 1.8444444 | J31: =IFERROR(__xludf.DUMMYFUNCTION("""COMPUTED_VALUE"""),77.0) -> 77 | K31: =IFERROR(__xludf.DUMMYFUNCTION("""COMPUTED_VALUE"""),2.5) -> 2.5 | L31: =IFERROR(__xludf.DUMMYFUNCTION("""COMPUTED_VALUE"""),"Puzzle") -> Puzzle | N31: =IFERROR(__xludf.DUMMYFUNCTION("""COMPUTED_VALUE"""),"Game Pass Essential launch title (9/14/23)") -> Game Pass Essential launch title (9/14/23) | O31: =IFERROR(__xludf.DUMMYFUNCTION("""COMPUTED_VALUE"""),"E") -> E | P31: =IFERROR(__xludf.DUMMYFUNCTION("""COMPUTED_VALUE"""),"Mild Blood") -> Mild Blood
A32: =IFERROR(__xludf.DUMMYFUNCTION("""COMPUTED_VALUE"""),"Deep Rock Galactic") -> Deep Rock Galactic | B32: =IFERROR(__xludf.DUMMYFUNCTION("""COMPUTED_VALUE"""),"Xbox / PC") -> Xbox / PC | C32: =IFERROR(__xludf.DUMMYFUNCTION("""COMPUTED_VALUE"""),"M+KB") -> M+KB | D32: =IFERROR(__xludf.DUMMYFUNCTION("""COMPUTED_VALUE"""),"Active") -> Active | E32: =IFERROR(__xludf.DUMMYFUNCTION("""COMPUTED_VALUE"""),44140.0) -> 44140 | G32: =IFERROR(__xludf.DUMMYFUNCTION("""COMPUTED_VALUE"""),59.333333333333336) -> 59.333333 | H32: =IFERROR(__xludf.DUMMYFUNCTION("""COMPUTED_VALUE"""),43964.0) -> 43964 | I32: =IFERROR(__xludf.DUMMYFUNCTION("""COMPUTED_VALUE"""),0.4777777777777778) -> 0.47777778 | J32: =IFERROR(__xludf.DUMMYFUNCTION("""COMPUTED_VALUE"""),84.0) -> 84 | K32: =IFERROR(__xludf.DUMMYFUNCTION("""COMPUTED_VALUE"""),119.0) -> 119 | L32: =IFERROR(__xludf.DUMMYFUNCTION("""COMPUTED_VALUE"""),"First-Person Shooter") -> First-Person Shooter | N32: =IFERROR(__xludf.DUMMYFUNCTION("""COMPUTED_VALUE"""),"Game Pass Essential (4/23/24)") -> Game Pass Essential (4/23/24) | O32: =IFERROR(__xludf.DUMMYFUNCTION("""COMPUTED_VALUE"""),"T") -> T | P32: =IFERROR(__xludf.DUMMYFUNCTION("""COMPUTED_VALUE"""),"Violence, Blood, Use of Alcohol, Language") -> Violence, Blood, Use of Alcohol, Language
A33: =IFERROR(__xludf.DUMMYFUNCTION("""COMPUTED_VALUE"""),"Tom Clancy's Rainbow Six: Siege - Deluxe Edition") -> Tom Clancy's Rainbow Six: Siege - Deluxe Edition | B33: =IFERROR(__xludf.DUMMYFUNCTION("""COMPUTED_VALUE"""),"Xbox / PC") -> Xbox / PC | C33: =IFERROR(__xludf.DUMMYFUNCTION("""COMPUTED_VALUE"""),"Yes") -> Yes | D33: =IFERROR(__xludf.DUMMYFUNCTION("""COMPUTED_VALUE"""),"Active") -> Active | E33: =IFERROR(__xludf.DUMMYFUNCTION("""COMPUTED_VALUE"""),44126.0) -> 44126 | G33: =IFERROR(__xludf.DUMMYFUNCTION("""COMPUTED_VALUE"""),59.766666666666666) -> 59.766667 | H33: =IFERROR(__xludf.DUMMYFUNCTION("""COMPUTED_VALUE"""),42339.0) -> 42339 | I33: =IFERROR(__xludf.DUMMYFUNCTION("""COMPUTED_VALUE"""),4.891666666666667) -> 4.8916667 | J33: =IFERROR(__xludf.DUMMYFUNCTION("""COMPUTED_VALUE"""),74.0) -> 74 | K33: =IFERROR(__xludf.DUMMYFUNCTION("""COMPUTED_VALUE"""),7.5) -> 7.5 | L33: =IFERROR(__xludf.DUMMYFUNCTION("""COMPUTED_VALUE"""),"First-Person Shooter") -> First-Person Shooter | M33: =IFERROR(__xludf.DUMMYFUNCTION("""COMPUTED_VALUE"""),"Optimized") -> Optimized | N33: =IFERROR(__xludf.DUMMYFUNCTION("""COMPUTED_VALUE"""),"Ubisoft Connect launcher, joined PC 1/20/21") -> Ubisoft Connect launcher, joined PC 1/20/21 | O33: =IFERROR(__xludf.DUMMYFUNCTION("""COMPUTED_VALUE"""),"M") -> M | P33: =IFERROR(__xludf.DUMMYFUNCTION("""COMPUTED_VALUE"""),"Blood, Drug Reference, Strong Language, Violence") -> Blood, Drug Reference, Strong Language, Violence

Sheet Xbox Game Studios
A1: Published or Developed by Subsidiary | B1: Studio | C1: Platform | D1: Added | E1: Publisher | F1: Studio | G1: Date | H1: Closed
A2: The Outer Worlds 2 | B2: Obsidian Entertainment | C2: =VLOOKUP(A2,'Master List'!A:E,2,) -> Xbox / PC | D2: =VLOOKUP(A2,'Master List'!A:E,5,) -> 45959 | F2: Xbox Game Studios Publishing | G2: 2000
A3: Ninja Gaiden 4 | B3: Xbox Game Studios (Publisher) | C3: =VLOOKUP(A3,'Master List'!A:E,2,) -> Xbox / PC | D3: =VLOOKUP(A3,'Master List'!A:E,5,) -> 45951 | F3: Turn 10 Studios | G3: 2001
A4: Gears of War: Reloaded | B4: The Coalition | C4: =VLOOKUP(A4,'Master List'!A:E,2,) -> Xbox / PC | D4: =VLOOKUP(A4,'Master List'!A:E,5,) -> 45895 | F4: Rare | G4: 2002
A5: Caesar III | B5: =VLOOKUP(A5,'Master List'!A:N,14,) -> Retro Classics: Windows 9x | C5: =VLOOKUP(A5,'Master List'!A:E,2,) -> Xbox / PC | D5: =VLOOKUP(A5,'Master List'!A:E,5,) -> 45883 | F5: 343 Industries | G5: 2007
A6: Climber 5 | B6: =VLOOKUP(A6,'Master List'!A:N,14,) -> Retro Classics: Atari 2600 | C6: =VLOOKUP(A6,'Master List'!A:E,2,) -> Xbox / PC | D6: =VLOOKUP(A6,'Master List'!A:E,5,) -> 45883 | F6: The Coalition | G6: 2007
A7: The Colonel's Bequest | B7: =VLOOKUP(A7,'Master List'!A:N,14,) -> Retro Classics: Amiga | C7: =VLOOKUP(A7,'Master List'!A:E,2,) -> Xbox / PC | D7: =VLOOKUP(A7,'Master List'!A:E,5,) -> 45883 | F7: Mojang Studios | G7: 2014
A8: Private Eye | B8: =VLOOKUP(A8,'Master List'!A:N,14,) -> Retro Classics: Atari 2600 | C8: =VLOOKUP(A8,'Master List'!A:E,2,) -> Xbox / PC | D8: =VLOOKUP(A8,'Master List'!A:E,5,) -> 45883 | F8: Compulsion Games | G8: 2018
A9: Oystron | B9: =VLOOKUP(A9,'Master List'!A:N,14,) -> Retro Classics: Atari 2600 | C9: =VLOOKUP(A9,'Master List'!A:E,2,) -> Xbox / PC | D9: =VLOOKUP(A9,'Master List'!A:E,5,) -> 45883 | F9: The Initiative | G9: 2018
A10: Shootin' Gallery | B10: =VLOOKUP(A10,'Master List'!A:N,14,) -> Retro Classics: Atari 2600 | C10: =VLOOKUP(A10,'Master List'!A:E,2,) -> Xbox / PC | D10: =VLOOKUP(A10,'Master List'!A:E,5,) -> 45883 | F10: inXile Entertainment | G10: 2018
A11: Wing War | B11: =VLOOKUP(A11,'Master List'!A:N,14,) -> Retro Classics: Atari 2600 | C11: =VLOOKUP(A11,'Master List'!A:E,2,) -> Xbox / PC | D11: =VLOOKUP(A11,'Master List'!A:E,5,) -> 45883 | F11: Ninja Theory | G11: 2018
A12: Heretic + Hexen | B12: Raven Software (Activision Blizzard King) | C12: =VLOOKUP(A12,'Master List'!A:E,2,) -> Xbox / PC | D12: =VLOOKUP(A12,'Master List'!A:E,5,) -> 45876 | F12: Obsidian Entertainment | G12: 2018
A13: Grounded 2 (Game Preview) | B13: Obsidian Entertainment | C13: =VLOOKUP(A13,'Master List'!A:E,2,) -> Xbox / PC | D13: =VLOOKUP(A13,'Master List'!A:E,5,) -> 45867 | F13: Playground Games | G13: 2018
A14: Caesar | B14: =VLOOKUP(A14,'Master List'!A:N,14,) -> Retro Classics: Amiga | C14: =VLOOKUP(A14,'Master List'!A:E,2,) -> Xbox / PC | D14: =VLOOKUP(A14,'Master List'!A:E,5,) -> 45859 | F14: Undead Labs | G14: 2018
A15: Conquests of Camelot: The Search for the Grail | B15: =VLOOKUP(A15,'Master List'!A:N,14,) -> Retro Classics: Amiga | C15: =VLOOKUP(A15,'Master List'!A:E,2,) -> Xbox / PC | D15: =VLOOKUP(A15,'Master List'!A:E,5,) -> 45859 | F15: Double Fine Productions | G15: 2019
A16: Gabriel Knight: Sins of the Fathers | B16: =VLOOKUP(A16,'Master List'!A:N,14,) -> Retro Classics: DOS | C16: =VLOOKUP(A16,'Master List'!A:E,2,) -> Xbox / PC | D16: =VLOOKUP(A16,'Master List'!A:E,5,) -> 45859 | F16: World's Edge | G16: 2019
A17: Hard Head | B17: =VLOOKUP(A17,'Master List'!A:N,14,) -> Retro Classics: Atari 2600 | C17: =VLOOKUP(A17,'Master List'!A:E,2,) -> Xbox / PC | D17: =VLOOKUP(A17,'Master List'!A:E,5,) -> 45859 | E17: ZeniMax Media/Bethesda Softworks | F17: Bethesda Game Studios | G17: 2021
A18: Okie Dokie | B18: =VLOOKUP(A18,'Master List'!A:N,14,) -> Retro Classics: Atari 2600 | C18: =VLOOKUP(A18,'Master List'!A:E,2,) -> Xbox / PC | D18: =VLOOKUP(A18,'Master List'!A:E,5,) -> 45859 | E18: ZeniMax Media/Bethesda Softworks | F18: ZeniMax Online Studios | G18: 2021
A19: Skate Boardin' | B19: =VLOOKUP(A19,'Master List'!A:N,14,) -> Retro Classics: Atari 2600 | C19: =VLOOKUP(A19,'Master List'!A:E,2,) -> Xbox / PC | D19: =VLOOKUP(A19,'Master List'!A:E,5,) -> 45859 | E19: ZeniMax Media/Bethesda Softworks | F19: Arkane Studios (Austin office closed 2024) | G19: 2021
A20: Skeleton+ | B20: =VLOOKUP(A20,'Master List'!A:N,14,) -> Retro Classics: Atari 2600 | C20: =VLOOKUP(A20,'Master List'!A:E,2,) -> Xbox / PC | D20: =VLOOKUP(A20,'Master List'!A:E,5,) -> 45859 | E20: ZeniMax Media/Bethesda Softworks | F20: id Software | G20: 2021
A21: Cosmic Commuter | B21: =VLOOKUP(A21,'Master List'!A:N,14,) -> Retro Classics: Atari 2600 | C21: =VLOOKUP(A21,'Master List'!A:E,2,) -> Xbox / PC | D21: =VLOOKUP(A21,'Master List'!A:E,5,) -> 45839 | E21: ZeniMax Media/Bethesda Softworks | F21: ZeniMax Media/Bethesda Softworks | G21: MachineGames | H21: 2021
A22: Heart of China | B22: =VLOOKUP(A22,'Master List'!A:N,14,) -> Retro Classics: DOS | C22: =VLOOKUP(A22,'Master List'!A:E,2,) -> Xbox / PC | D22: =VLOOKUP(A22,'Master List'!A:E,5,) -> 45839 | E22: ZeniMax Media/Bethesda Softworks | F22: Tango Gameworks | G22: 2021 | H22: 2024
A23: Skiing | B23: =VLOOKUP(A23,'Master List'!A:N,14,) -> Retro Classics: Atari 2600 | C23: =VLOOKUP(A23,'Master List'!A:E,2,) -> Xbox / PC | D23: =VLOOKUP(A23,'Master List'!A:E,5,) -> 45839 | E23: ZeniMax Media/Bethesda Softworks | F23: Alpha Dog Games | G23: 2021 | H23: 2024
A24: Solar Storm | B24: =VLOOKUP(A24,'Master List'!A:N,14,) -> Retro Classics: Atari 2600 | C24: =VLOOKUP(A24,'Master List'!A:E,2,) -> Xbox / PC | D24: =VLOOKUP(A24,'Master List'!A:E,5,) -> 45839 | E24: ZeniMax Media/Bethesda Softworks | F24: Roundhouse Studios (Absorbed by ZeniMax) | G24: 2021 | H24: 2024
A25: Subterranea | B25: =VLOOKUP(A25,'Master List'!A:N,14,) -> Retro Classics: Atari 2600 | C25: =VLOOKUP(A25,'Master List'!A:E,2,) -> Xbox / PC | D25: =VLOOKUP(A25,'Master List'!A:E,5,) -> 45839 | E25: Activision Blizzard King | F25: Infinity Ward | G25: 2023
A26: Call of Duty: WWII | B26: Sledgehammer Games (Activision Blizzard King) | C26: =VLOOKUP(A26,'Master List'!A:E,2,) -> Xbox / PC | D26: =VLOOKUP(A26,'Master List'!A:E,5,) -> 45838 | E26: Activision Blizzard King | F26: Treyarch | G26: 2023
A27: Warcraft I: Remastered | B27: Blizzard Entertainment | C27: =VLOOKUP(A27,'Master List'!A:E,2,) -> PC | D27: =VLOOKUP(A27,'Master List'!A:E,5,) -> 45834 | E27: Activision Blizzard King | F27: Sledgehammer Games | G27: 2023
A28: Warcraft II: Remastered | B28: Blizzard Entertainment | C28: =VLOOKUP(A28,'Master List'!A:E,2,) -> PC | D28: =VLOOKUP(A28,'Master List'!A:E,5,) -> 45834 | E28: Activision Blizzard King | F28: Raven Software | G28: 2023
A29: Warcraft III: Reforged | B29: Blizzard Entertainment | C29: =VLOOKUP(A29,'Master List'!A:E,2,) -> PC | D29: =VLOOKUP(A29,'Master List'!A:E,5,) -> 45834 | E29: Activision Blizzard King | F29: High Moon Studios | G29: 2023
A30: Tony Hawk's Pro Skater 3 + 4 | B30: Activision (Publisher) | C30: Xbox / PC | D30: 45792 | E30: Activision Blizzard King | F30: Beenox | G30: 2023
A31: Crash Bandicoot 4: It's About Time | B31: Toys For Bob (Activision Blizzard King) | C31: Xbox / PC | D31: 45792 | E31: Activision Blizzard King | F31: Digital Legends Entertainment (Mobile) | G31: 2023
A32: Activision Prototype #1 | B32: =VLOOKUP(A32,'Master List'!A:N,14,) -> Retro Classics: Atari 2600, Publisher | C32: Xbox / PC | D32: 45792 | E32: Activision Blizzard King | F32: Solid State Studios (Mobile) | G32: 2023
A33: Atlantis | B33: =VLOOKUP(A33,'Master List'!A:N,14,) -> Retro Classics: Atari 2600 | C33: Xbox / PC | D33: 45792 | E33: Activision Blizzard King | F33: Radical Entertainment | G33: 2023
A34: Atlantis II | B34: =VLOOKUP(A34,'Master List'!A:N,14,) -> Retro Classics: Atari 2600 | C34: Xbox / PC | D34: 45792 | E34: Activision Blizzard King | F34: Blizzard Entertainment | G34: 2023
A35: Barnstorming | B35: =VLOOKUP(A35,'Master List'!A:N,14,) -> Retro Classics: Atari 2600 | C35: Xbox / PC | D35: 45792 | E35: Activision Blizzard King | F35: King (Mobile) | G35: 2023
A36: Baseball | B36: =VLOOKUP(A36,'Master List'!A:N,14,) -> Retro Classics: Atari 2600 | C36: Xbox / PC | D36: 45792 | E36: Activision Games will not be on xCloud, Ubisoft controls cloud streaming rights as part of the merger
A37: Beamrider | B37: =VLOOKUP(A37,'Master List'!A:N,14,) -> Retro Classics: Atari 2600 | C37: Xbox / PC | D37: 45792
A38: Bloody Human Freeway | B38: =VLOOKUP(A38,'Master List'!A:N,14,) -> Retro Classics: Atari 2600 | C38: Xbox / PC | D38: 45792 | E38: Former
A39: Boxing | B39: =VLOOKUP(A39,'Master List'!A:N,14,) -> Retro Classics: Atari 2600 | C39: Xbox / PC | D39: 45792 | E39: Sold or spun off
A40: Bridge | B40: =VLOOKUP(A40,'Master List'!A:N,14,) -> Retro Classics: Atari 2600 | C40: Xbox / PC | D40: 45792 | E40: Access Software/Salt Lake Games Studio/Indie Games — Links series — Sold to Take-Two Interactive in 2004
A41: Caesar II | B41: =VLOOKUP(A41,'Master List'!A:N,14,) -> Retro Classics: DOS, Sierra Entertainment (defunct) publisher | C41: Xbox / PC | D41: 45792 | E41: Bungie — Halo series — Spun off in 2007[110]
A42: Checkers | B42: =VLOOKUP(A42,'Master List'!A:N,14,) -> Retro Classics: Atari 2600 | C42: Xbox / PC | D42: 45792 | E42: Lift London — Removed from Microsoft's games business in 2019[111]
A43: Chopper Command | B43: =VLOOKUP(A43,'Master List'!A:N,14,) -> Retro Classics: Atari 2600 | C43: Xbox / PC | D43: 45792 | E43: Twisted Pixel Games — The Gunstringer, LocoCycle, The Maw, 'Splosion Man — Spun off in 2015
A44: Commando | B44: =VLOOKUP(A44,'Master List'!A:N,14,) -> Retro Classics: Atari 2600 | C44: Xbox / PC | D44: 45792 | E44: WingNut Interactive — Peter Jackson's joint venture game studio — Sold to WingNut Films[112][113]
A45: Conquests of the Longbow: The Legend of Robin Hood | B45: =VLOOKUP(A45,'Master List'!A:N,14,) -> Retro Classics: DOS, Sierra Entertainment (defunct) publisher | C45: Xbox / PC | D45: 45792 | E45: Closed or consolidated
A46: Cosmic Ark | B46: =VLOOKUP(A46,'Master List'!A:N,14,) -> Retro Classics: Atari 2600 | C46: Xbox / PC | D46: 45792 | E46: Aces Game Studio — Microsoft Flight Simulator series — Closed
A47: Crackpots | B47: =VLOOKUP(A47,'Master List'!A:N,14,) -> Retro Classics: Atari 2600 | C47: Xbox / PC | D47: 45792 | E47: BigPark — Kinect Joy Ride, Kinect Sports: Season Two, Joy Ride Turbo — Consolidated
A48: Decathlon | B48: =VLOOKUP(A48,'Master List'!A:N,14,) -> Retro Classics: Atari 2600 | C48: Xbox / PC | D48: 45792 | E48: Carbonated Games — Closed
A49: Demon Attack | B49: =VLOOKUP(A49,'Master List'!A:N,14,) -> Retro Classics: Atari 2600 | C49: Xbox / PC | D49: 45792 | E49: Digital Anvil — Brute Force, Freelancer — Consolidated[114]
... A60: H.E.R.O. | B60: =VLOOKUP(A60,'Master List'!A:N,14,) -> Retro Classics: Atari 2600 | C60: Xbox / PC | D60: 45792 | E60: Xbox Live Productions — Consolidated
A61: Kaboom! | B61: =VLOOKUP(A61,'Master List'!A:N,14,) -> Retro Classics: Atari 2600 | C61: Xbox / PC | D61: 45792
A62: Laser Blast | B62: =VLOOKUP(A62,'Master List'!A:N,14,) -> Retro Classics: Atari 2600 | C62: Xbox / PC | D62: 45792
A63: MechWarrior | B63: =VLOOKUP(A63,'Master List'!A:N,14,) -> Retro Classics: SNES | C63: Xbox / PC | D63: 45792
A64: MechWarrior 2: 31st Century Combat | B64: =VLOOKUP(A64,'Master List'!A:N,14,) -> Retro Classics: PSX | C64: Xbox / PC | D64: 45792
A65: Megamania | B65: =VLOOKUP(A65,'Master List'!A:N,14,) -> Retro Classics: Atari 2600 | C65: Xbox / PC | D65: 45792
A66: Pitfall II: Lost Caverns | B66: =VLOOKUP(A66,'Master List'!A:N,14,) -> Retro Classics: Atari 2600 | C66: Xbox / PC | D66: 45792
A67: Pitfall! | B67: =VLOOKUP(A67,'Master List'!A:N,14,) -> Retro Classics: Atari 2600 | C67: Xbox / PC | D67: 45792
A68: Police Quest | B68: =VLOOKUP(A68,'Master List'!A:N,14,) -> Retro Classics: Amiga, Sierra Entertainment (defunct) publisher | C68: Xbox / PC | D68: 45792
A69: Pressure Cooker | B69: =VLOOKUP(A69,'Master List'!A:N,14,) -> Retro Classics: Atari 2600 | C69: Xbox / PC | D69: 45792
A70: Quest for Glory: So You Want to Be a Hero | B70: =VLOOKUP(A70,'Master List'!A:N,14,) -> Retro Classics: DOS, Sierra Entertainment (defunct) publisher | C70: Xbox / PC | D70: 45792
A71: Riddle of the Sphinx | B71: =VLOOKUP(A71,'Master List'!A:N,14,) -> Retro Classics: Atari 2600 | C71: Xbox / PC | D71: 45792
A72: River Raid | B72: =VLOOKUP(A72,'Master List'!A:N,14,) -> Retro Classics: Atari 2600 | C72: Xbox / PC | D72: 45792
... A91: Zork Zero: The Revenge of Megaboz | B91: =VLOOKUP(A91,'Master List'!A:N,14,) -> Retro Classics: DOS | C91: Xbox / PC | D91: 45792
A92: DOOM: The Dark Ages | B92: id Software (Bethesda Softworks) | C92: Xbox / PC | D92: 45792
A93: Call of Duty: Modern Warfare II | B93: Infinity Ward (Activision Blizzard King) | C93: =VLOOKUP(A93,'Master List'!A:E,2,) -> Xbox / PC | D93: =VLOOKUP(A93,'Master List'!A:E,5,) -> 45778
A94: The Elder Scrolls IV: Oblivion - Remastered | B94: Bethesda Game Studios | C94: =VLOOKUP(A94,'Master List'!A:E,2,) -> Xbox / PC | D94: =VLOOKUP(A94,'Master List'!A:E,5,) -> 45769
A95: Diablo III: Reaper of Souls - Ultimate Evil Edition | B95: Blizzard Entertainment | C95: =VLOOKUP(A95,'Master List'!A:E,2,) -> Xbox / PC | D95: =VLOOKUP(A95,'Master List'!A:E,5,) -> 45755
A96: South of Midnight | B96: Compulsion Games | C96: =VLOOKUP(A96,'Master List'!A:E,2,) -> Xbox / PC | D96: =VLOOKUP(A96,'Master List'!A:E,5,) -> 45755
A97: Blizzard Arcade Collection | B97: Blizzard Entertainment | C97: =VLOOKUP(A97,'Master List'!A:E,2,) -> Xbox / PC | D97: =VLOOKUP(A97,'Master List'!A:E,5,) -> 45741
A98: Avowed | B98: Obsidian Entertainment | C98: =VLOOKUP(A98,'Master List'!A:E,2,) -> Xbox / PC | D98: =VLOOKUP(A98,'Master List'!A:E,5,) -> 45706
A99: Diablo | B99: Blizzard Entertainment | C99: =VLOOKUP(A99,'Master List'!A:E,2,) -> PC | D99: =VLOOKUP(A99,'Master List'!A:E,5,) -> 45671
A100: Indiana Jones and the Great Circle | B100: MachineGames (Bethesda Softworks) | C100: =VLOOKUP(A100,'Master List'!A:E,2,) -> Xbox / PC | D100: =VLOOKUP(A100,'Master List'!A:E,5,) -> 45635
A101: Crash Team Racing: Nitro-Fueled | B101: Beenox (Activision Blizzard King) | C101: =VLOOKUP(A101,'Master List'!A:E,2,) -> Xbox | D101: =VLOOKUP(A101,'Master List'!A:E,5,) -> 45630
A102: Microsoft Flight Simulator 2024 | B102: Asobo Studio | C102: =VLOOKUP(A102,'Master List'!A:E,2,) -> Xbox / PC | D102: =VLOOKUP(A102,'Master List'!A:E,5,) -> 45615
A103: Spyro Reignited Trilogy | B103: Insomniac Games (Activision Blizzard King) | C103: =VLOOKUP(A103,'Master List'!A:E,2,) -> Xbox / PC | D103: =VLOOKUP(A103,'Master List'!A:E,5,) -> 45608
A104: Starcraft: Remastered | B104: Blizzard Entertainment (Activision Blizzard King) | C104: =VLOOKUP(A104,'Master List'!A:E,2,) -> PC | D104: =VLOOKUP(A104,'Master List'!A:E,5,) -> 45601
... A260: Viva Piñata: Trouble in Paradise | B260: Rare | C260: =VLOOKUP(A260,'Master List'!A:E,2,) -> Xbox | D260: =VLOOKUP(A260,'Master List'!A:E,5,) -> 42887

Sheet PC
A1: PC Games by Metacritic Score | B1: =COUNTA(A3:A975) -> 613
A2: Game | B2: System | C2: xCloud | D2: Status | E2: Added | F2: Removed | G2: Months | H2: Release | I2: Age | J2: Metacritic | K2: Completion | L2: Genre (Giantbomb)
A3: =IFERROR(__xludf.DUMMYFUNCTION("SORT(FILTER('Master List'!A2:L975, REGEXMATCH('Master List'!B2:B975, ""PC""), NOT(REGEXMATCH('Master List'!D2:D975, ""Removed"")) ), 10, false)"),"Grand Theft Auto V") -> Grand Theft Auto V | B3: =IFERROR(__xludf.DUMMYFUNCTION("""COMPUTED_VALUE"""),"Xbox / PC") -> Xbox / PC | C3: =IFERROR(__xludf.DUMMYFUNCTION("""COMPUTED_VALUE"""),"Yes") -> Yes | D3: =IFERROR(__xludf.DUMMYFUNCTION("""COMPUTED_VALUE"""),"Active") -> Active | E3: =IFERROR(__xludf.DUMMYFUNCTION("""COMPUTED_VALUE"""),45762.0) -> 45762 | G3: =IFERROR(__xludf.DUMMYFUNCTION("""COMPUTED_VALUE"""),6.0) -> 6 | H3: =IFERROR(__xludf.DUMMYFUNCTION("""COMPUTED_VALUE"""),41534.0) -> 41534 | I3: =IFERROR(__xludf.DUMMYFUNCTION("""COMPUTED_VALUE"""),11.577777777777778) -> 11.577778 | J3: =IFERROR(__xludf.DUMMYFUNCTION("""COMPUTED_VALUE"""),97.0) -> 97 | K3: =IFERROR(__xludf.DUMMYFUNCTION("""COMPUTED_VALUE"""),31.5) -> 31.5 | L3: =IFERROR(__xludf.DUMMYFUNCTION("""COMPUTED_VALUE"""),"Driving/Racing / Action-Adventure") -> Driving/Racing / Action-Adventure
A4: =IFERROR(__xludf.DUMMYFUNCTION("""COMPUTED_VALUE"""),"Mass Effect 2: Digital Deluxe Edition") -> Mass Effect 2: Digital Deluxe Edition | B4: =IFERROR(__xludf.DUMMYFUNCTION("""COMPUTED_VALUE"""),"Xbox / PC") -> Xbox / PC | D4: =IFERROR(__xludf.DUMMYFUNCTION("""COMPUTED_VALUE"""),"Active") -> Active | E4: =IFERROR(__xludf.DUMMYFUNCTION("""COMPUTED_VALUE"""),44145.0) -> 44145 | G4: =IFERROR(__xludf.DUMMYFUNCTION("""COMPUTED_VALUE"""),59.166666666666664) -> 59.166667 | H4: =IFERROR(__xludf.DUMMYFUNCTION("""COMPUTED_VALUE"""),40204.0) -> 40204 | I4: =IFERROR(__xludf.DUMMYFUNCTION("""COMPUTED_VALUE"""),10.78888888888889) -> 10.788889 | J4: =IFERROR(__xludf.DUMMYFUNCTION("""COMPUTED_VALUE"""),96.0) -> 96 | K4: =IFERROR(__xludf.DUMMYFUNCTION("""COMPUTED_VALUE"""),24.5) -> 24.5 | L4: =IFERROR(__xludf.DUMMYFUNCTION("""COMPUTED_VALUE"""),"RPG / Action-Adventure") -> RPG / Action-Adventure
A5: =IFERROR(__xludf.DUMMYFUNCTION("""COMPUTED_VALUE"""),"Metaphor: ReFantazio") -> Metaphor: ReFantazio | B5: =IFERROR(__xludf.DUMMYFUNCTION("""COMPUTED_VALUE"""),"Xbox / PC") -> Xbox / PC | C5: =IFERROR(__xludf.DUMMYFUNCTION("""COMPUTED_VALUE"""),"Yes") -> Yes | D5: =IFERROR(__xludf.DUMMYFUNCTION("""COMPUTED_VALUE"""),"Active") -> Active | E5: =IFERROR(__xludf.DUMMYFUNCTION("""COMPUTED_VALUE"""),45806.0) -> 45806 | G5: =IFERROR(__xludf.DUMMYFUNCTION("""COMPUTED_VALUE"""),4.533333333333333) -> 4.5333333 | H5: =IFERROR(__xludf.DUMMYFUNCTION("""COMPUTED_VALUE"""),45576.0) -> 45576 | I5: =IFERROR(__xludf.DUMMYFUNCTION("""COMPUTED_VALUE"""),0.6333333333333333) -> 0.63333333 | J5: =IFERROR(__xludf.DUMMYFUNCTION("""COMPUTED_VALUE"""),94.0) -> 94 | K5: =IFERROR(__xludf.DUMMYFUNCTION("""COMPUTED_VALUE"""),66.0) -> 66 | L5: =IFERROR(__xludf.DUMMYFUNCTION("""COMPUTED_VALUE"""),"RPG") -> RPG
A6: =IFERROR(__xludf.DUMMYFUNCTION("""COMPUTED_VALUE"""),"Diablo") -> Diablo | B6: =IFERROR(__xludf.DUMMYFUNCTION("""COMPUTED_VALUE"""),"PC") -> PC | D6: =IFERROR(__xludf.DUMMYFUNCTION("""COMPUTED_VALUE"""),"Active") -> Active | E6: =IFERROR(__xludf.DUMMYFUNCTION("""COMPUTED_VALUE"""),45671.0) -> 45671 | G6: =IFERROR(__xludf.DUMMYFUNCTION("""COMPUTED_VALUE"""),9.033333333333333) -> 9.0333333 | H6: =IFERROR(__xludf.DUMMYFUNCTION("""COMPUTED_VALUE"""),35430.0) -> 35430 | I6: =IFERROR(__xludf.DUMMYFUNCTION("""COMPUTED_VALUE"""),28.038888888888888) -> 28.038889 | J6: =IFERROR(__xludf.DUMMYFUNCTION("""COMPUTED_VALUE"""),94.0) -> 94 | K6: =IFERROR(__xludf.DUMMYFUNCTION("""COMPUTED_VALUE"""),7.0) -> 7 | L6: =IFERROR(__xludf.DUMMYFUNCTION("""COMPUTED_VALUE"""),"RPG") -> RPG
A7: =IFERROR(__xludf.DUMMYFUNCTION("""COMPUTED_VALUE"""),"Quake") -> Quake | B7: =IFERROR(__xludf.DUMMYFUNCTION("""COMPUTED_VALUE"""),"Xbox / PC") -> Xbox / PC | C7: =IFERROR(__xludf.DUMMYFUNCTION("""COMPUTED_VALUE"""),"M+KB") -> M+KB | D7: =IFERROR(__xludf.DUMMYFUNCTION("""COMPUTED_VALUE"""),"Active") -> Active | E7: =IFERROR(__xludf.DUMMYFUNCTION("""COMPUTED_VALUE"""),44427.0) -> 44427 | G7: =IFERROR(__xludf.DUMMYFUNCTION("""COMPUTED_VALUE"""),49.866666666666674) -> 49.866667 | H7: =IFERROR(__xludf.DUMMYFUNCTION("""COMPUTED_VALUE"""),35269.0) -> 35269 | I7: =IFERROR(__xludf.DUMMYFUNCTION("""COMPUTED_VALUE"""),25.072222222222223) -> 25.072222 | J7: =IFERROR(__xludf.DUMMYFUNCTION("""COMPUTED_VALUE"""),94.0) -> 94 | K7: =IFERROR(__xludf.DUMMYFUNCTION("""COMPUTED_VALUE"""),5.5) -> 5.5 | L7: =IFERROR(__xludf.DUMMYFUNCTION("""COMPUTED_VALUE"""),"First-Person Shooter") -> First-Person Shooter
A8: =IFERROR(__xludf.DUMMYFUNCTION("""COMPUTED_VALUE"""),"Ultima Underworld 1") -> Ultima Underworld 1 | B8: =IFERROR(__xludf.DUMMYFUNCTION("""COMPUTED_VALUE"""),"PC") -> PC | D8: =IFERROR(__xludf.DUMMYFUNCTION("""COMPUTED_VALUE"""),"Active") -> Active | E8: =IFERROR(__xludf.DUMMYFUNCTION("""COMPUTED_VALUE"""),44425.0) -> 44425 | G8: =IFERROR(__xludf.DUMMYFUNCTION("""COMPUTED_VALUE"""),49.93333333333334) -> 49.933333 | H8: =IFERROR(__xludf.DUMMYFUNCTION("""COMPUTED_VALUE"""),33690.0) -> 33690 | I8: =IFERROR(__xludf.DUMMYFUNCTION("""COMPUTED_VALUE"""),29.38888888888889) -> 29.388889 | J8: =IFERROR(__xludf.DUMMYFUNCTION("""COMPUTED_VALUE"""),94.0) -> 94 | K8: =IFERROR(__xludf.DUMMYFUNCTION("""COMPUTED_VALUE"""),19.5) -> 19.5 | L8: =IFERROR(__xludf.DUMMYFUNCTION("""COMPUTED_VALUE"""),"Action / RPG") -> Action / RPG
A9: =IFERROR(__xludf.DUMMYFUNCTION("""COMPUTED_VALUE"""),"The Elder Scrolls IV: Oblivion") -> The Elder Scrolls IV: Oblivion | B9: =IFERROR(__xludf.DUMMYFUNCTION("""COMPUTED_VALUE"""),"Xbox / PC") -> Xbox / PC | C9: =IFERROR(__xludf.DUMMYFUNCTION("""COMPUTED_VALUE"""),"Yes") -> Yes | D9: =IFERROR(__xludf.DUMMYFUNCTION("""COMPUTED_VALUE"""),"Active") -> Active | E9: =IFERROR(__xludf.DUMMYFUNCTION("""COMPUTED_VALUE"""),43282.0) -> 43282 | G9: =IFERROR(__xludf.DUMMYFUNCTION("""COMPUTED_VALUE"""),87.46666666666667) -> 87.466667 | H9: =IFERROR(__xludf.DUMMYFUNCTION("""COMPUTED_VALUE"""),38796.0) -> 38796 | I9: =IFERROR(__xludf.DUMMYFUNCTION("""COMPUTED_VALUE"""),12.280555555555555) -> 12.280556 | J9: =IFERROR(__xludf.DUMMYFUNCTION("""COMPUTED_VALUE"""),94.0) -> 94 | K9: =IFERROR(__xludf.DUMMYFUNCTION("""COMPUTED_VALUE"""),27.5) -> 27.5 | L9: =IFERROR(__xludf.DUMMYFUNCTION("""COMPUTED_VALUE"""),"Action / RPG") -> Action / RPG
A10: =IFERROR(__xludf.DUMMYFUNCTION("""COMPUTED_VALUE"""),"Hades") -> Hades | B10: =IFERROR(__xludf.DUMMYFUNCTION("""COMPUTED_VALUE"""),"Xbox / PC") -> Xbox / PC | C10: =IFERROR(__xludf.DUMMYFUNCTION("""COMPUTED_VALUE"""),"Touch Controls") -> Touch Controls | D10: =IFERROR(__xludf.DUMMYFUNCTION("""COMPUTED_VALUE"""),"Active") -> Active | E10: =IFERROR(__xludf.DUMMYFUNCTION("""COMPUTED_VALUE"""),45919.0) -> 45919 | G10: =IFERROR(__xludf.DUMMYFUNCTION("""COMPUTED_VALUE"""),0.8666666666666666) -> 0.86666667 | H10: =IFERROR(__xludf.DUMMYFUNCTION("""COMPUTED_VALUE"""),43441.0) -> 43441 | I10: =IFERROR(__xludf.DUMMYFUNCTION("""COMPUTED_VALUE"""),6.783333333333333) -> 6.7833333 | J10: =IFERROR(__xludf.DUMMYFUNCTION("""COMPUTED_VALUE"""),93.5) -> 93.5 | K10: =IFERROR(__xludf.DUMMYFUNCTION("""COMPUTED_VALUE"""),21.0) -> 21 | L10: =IFERROR(__xludf.DUMMYFUNCTION("""COMPUTED_VALUE"""),"Action / RPG") -> Action / RPG
A11: =IFERROR(__xludf.DUMMYFUNCTION("""COMPUTED_VALUE"""),"Blue Prince") -> Blue Prince | B11: =IFERROR(__xludf.DUMMYFUNCTION("""COMPUTED_VALUE"""),"Xbox / PC") -> Xbox / PC | C11: =IFERROR(__xludf.DUMMYFUNCTION("""COMPUTED_VALUE"""),"Yes") -> Yes | D11: =IFERROR(__xludf.DUMMYFUNCTION("""COMPUTED_VALUE"""),"Active") -> Active | E11: =IFERROR(__xludf.DUMMYFUNCTION("""COMPUTED_VALUE"""),45757.0) -> 45757 | G11: =IFERROR(__xludf.DUMMYFUNCTION("""COMPUTED_VALUE"""),6.166666666666666) -> 6.1666667 | H11: =IFERROR(__xludf.DUMMYFUNCTION("""COMPUTED_VALUE"""),45757.0) -> 45757 | I11: =IFERROR(__xludf.DUMMYFUNCTION("""COMPUTED_VALUE"""),0.0) -> 0 | J11: =IFERROR(__xludf.DUMMYFUNCTION("""COMPUTED_VALUE"""),93.0) -> 93 | K11: =IFERROR(__xludf.DUMMYFUNCTION("""COMPUTED_VALUE"""),14.0) -> 14 | L11: =IFERROR(__xludf.DUMMYFUNCTION("""COMPUTED_VALUE"""),"Action-Adventure") -> Action-Adventure
A12: =IFERROR(__xludf.DUMMYFUNCTION("""COMPUTED_VALUE"""),"Inside") -> Inside | B12: =IFERROR(__xludf.DUMMYFUNCTION("""COMPUTED_VALUE"""),"Xbox / PC") -> Xbox / PC | C12: =IFERROR(__xludf.DUMMYFUNCTION("""COMPUTED_VALUE"""),"Yes") -> Yes | D12: =IFERROR(__xludf.DUMMYFUNCTION("""COMPUTED_VALUE"""),"Active") -> Active | E12: =IFERROR(__xludf.DUMMYFUNCTION("""COMPUTED_VALUE"""),44763.0) -> 44763 | G12: =IFERROR(__xludf.DUMMYFUNCTION("""COMPUTED_VALUE"""),38.8) -> 38.8 | H12: =IFERROR(__xludf.DUMMYFUNCTION("""COMPUTED_VALUE"""),42550.0) -> 42550 | I12: =IFERROR(__xludf.DUMMYFUNCTION("""COMPUTED_VALUE"""),6.061111111111111) -> 6.0611111 | J12: =IFERROR(__xludf.DUMMYFUNCTION("""COMPUTED_VALUE"""),93.0) -> 93 | K12: =IFERROR(__xludf.DUMMYFUNCTION("""COMPUTED_VALUE"""),3.5) -> 3.5 | L12: =IFERROR(__xludf.DUMMYFUNCTION("""COMPUTED_VALUE"""),"Puzzle / Platformer") -> Puzzle / Platformer
A13: =IFERROR(__xludf.DUMMYFUNCTION("""COMPUTED_VALUE"""),"Mass Effect 3: N7 Digital Deluxe Edition") -> Mass Effect 3: N7 Digital Deluxe Edition | B13: =IFERROR(__xludf.DUMMYFUNCTION("""COMPUTED_VALUE"""),"Xbox / PC") -> Xbox / PC | D13: =IFERROR(__xludf.DUMMYFUNCTION("""COMPUTED_VALUE"""),"Active") -> Active | E13: =IFERROR(__xludf.DUMMYFUNCTION("""COMPUTED_VALUE"""),44145.0) -> 44145 | G13: =IFERROR(__xludf.DUMMYFUNCTION("""COMPUTED_VALUE"""),59.166666666666664) -> 59.166667 | H13: =IFERROR(__xludf.DUMMYFUNCTION("""COMPUTED_VALUE"""),40974.0) -> 40974 | I13: =IFERROR(__xludf.DUMMYFUNCTION("""COMPUTED_VALUE"""),8.677777777777777) -> 8.6777778 | J13: =IFERROR(__xludf.DUMMYFUNCTION("""COMPUTED_VALUE"""),93.0) -> 93 | K13: =IFERROR(__xludf.DUMMYFUNCTION("""COMPUTED_VALUE"""),24.0) -> 24 | L13: =IFERROR(__xludf.DUMMYFUNCTION("""COMPUTED_VALUE"""),"RPG / Shooter / Action-Adventure") -> RPG / Shooter / Action-Adventure
A14: =IFERROR(__xludf.DUMMYFUNCTION("""COMPUTED_VALUE"""),"Fallout 3: Game of the Year Edition") -> Fallout 3: Game of the Year Edition | B14: =IFERROR(__xludf.DUMMYFUNCTION("""COMPUTED_VALUE"""),"Xbox / PC") -> Xbox / PC | C14: =IFERROR(__xludf.DUMMYFUNCTION("""COMPUTED_VALUE"""),"Yes") -> Yes | D14: =IFERROR(__xludf.DUMMYFUNCTION("""COMPUTED_VALUE"""),"Active") -> Active | E14: =IFERROR(__xludf.DUMMYFUNCTION("""COMPUTED_VALUE"""),43282.0) -> 43282 | G14: =IFERROR(__xludf.DUMMYFUNCTION("""COMPUTED_VALUE"""),87.46666666666667) -> 87.466667 | H14: =IFERROR(__xludf.DUMMYFUNCTION("""COMPUTED_VALUE"""),39749.0) -> 39749 | I14: =IFERROR(__xludf.DUMMYFUNCTION("""COMPUTED_VALUE"""),9.675) -> 9.675 | J14: =IFERROR(__xludf.DUMMYFUNCTION("""COMPUTED_VALUE"""),93.0) -> 93 | K14: =IFERROR(__xludf.DUMMYFUNCTION("""COMPUTED_VALUE"""),22.5) -> 22.5 | L14: =IFERROR(__xludf.DUMMYFUNCTION("""COMPUTED_VALUE"""),"RPG / First-Person Shooter") -> RPG / First-Person Shooter
A15: =IFERROR(__xludf.DUMMYFUNCTION("""COMPUTED_VALUE"""),"Rayman Legends") -> Rayman Legends | B15: =IFERROR(__xludf.DUMMYFUNCTION("""COMPUTED_VALUE"""),"Xbox / PC") -> Xbox / PC | C15: =IFERROR(__xludf.DUMMYFUNCTION("""COMPUTED_VALUE"""),"Yes") -> Yes | D15: =IFERROR(__xludf.DUMMYFUNCTION("""COMPUTED_VALUE"""),"Active") -> Active | E15: =IFERROR(__xludf.DUMMYFUNCTION("""COMPUTED_VALUE"""),45931.0) -> 45931 | G15: =IFERROR(__xludf.DUMMYFUNCTION("""COMPUTED_VALUE"""),0.4666666666666667) -> 0.46666667 | H15: =IFERROR(__xludf.DUMMYFUNCTION("""COMPUTED_VALUE"""),41520.0) -> 41520 | I15: =IFERROR(__xludf.DUMMYFUNCTION("""COMPUTED_VALUE"""),12.077777777777778) -> 12.077778 | J15: =IFERROR(__xludf.DUMMYFUNCTION("""COMPUTED_VALUE"""),92.0) -> 92 | K15: =IFERROR(__xludf.DUMMYFUNCTION("""COMPUTED_VALUE"""),10.0) -> 10 | L15: =IFERROR(__xludf.DUMMYFUNCTION("""COMPUTED_VALUE"""),"Platformer") -> Platformer
A16: =IFERROR(__xludf.DUMMYFUNCTION("""COMPUTED_VALUE"""),"Clair Obscur: Expedition 33") -> Clair Obscur: Expedition 33 | B16: =IFERROR(__xludf.DUMMYFUNCTION("""COMPUTED_VALUE"""),"Xbox / PC") -> Xbox / PC | C16: =IFERROR(__xludf.DUMMYFUNCTION("""COMPUTED_VALUE"""),"Yes") -> Yes | D16: =IFERROR(__xludf.DUMMYFUNCTION("""COMPUTED_VALUE"""),"Active") -> Active | E16: =IFERROR(__xludf.DUMMYFUNCTION("""COMPUTED_VALUE"""),45771.0) -> 45771 | G16: =IFERROR(__xludf.DUMMYFUNCTION("""COMPUTED_VALUE"""),5.699999999999999) -> 5.7 | H16: =IFERROR(__xludf.DUMMYFUNCTION("""COMPUTED_VALUE"""),45771.0) -> 45771 | I16: =IFERROR(__xludf.DUMMYFUNCTION("""COMPUTED_VALUE"""),0.0) -> 0 | J16: =IFERROR(__xludf.DUMMYFUNCTION("""COMPUTED_VALUE"""),92.0) -> 92 | K16: =IFERROR(__xludf.DUMMYFUNCTION("""COMPUTED_VALUE"""),26.0) -> 26 | L16: =IFERROR(__xludf.DUMMYFUNCTION("""COMPUTED_VALUE"""),"RPG") -> RPG
A17: =IFERROR(__xludf.DUMMYFUNCTION("""COMPUTED_VALUE"""),"Sid Meier's Alpha Centauri") -> Sid Meier's Alpha Centauri | B17: =IFERROR(__xludf.DUMMYFUNCTION("""COMPUTED_VALUE"""),"PC") -> PC | D17: =IFERROR(__xludf.DUMMYFUNCTION("""COMPUTED_VALUE"""),"Active") -> Active | E17: =IFERROR(__xludf.DUMMYFUNCTION("""COMPUTED_VALUE"""),45398.0) -> 45398 | G17: =IFERROR(__xludf.DUMMYFUNCTION("""COMPUTED_VALUE"""),17.96666666666667) -> 17.966667 | H17: =IFERROR(__xludf.DUMMYFUNCTION("""COMPUTED_VALUE"""),36203.0) -> 36203 | I17: =IFERROR(__xludf.DUMMYFUNCTION("""COMPUTED_VALUE"""),25.177777777777777) -> 25.177778 | J17: =IFERROR(__xludf.DUMMYFUNCTION("""COMPUTED_VALUE"""),92.0) -> 92 | K17: =IFERROR(__xludf.DUMMYFUNCTION("""COMPUTED_VALUE"""),25.0) -> 25 | L17: =IFERROR(__xludf.DUMMYFUNCTION("""COMPUTED_VALUE"""),"Strategy") -> Strategy
A18: =IFERROR(__xludf.DUMMYFUNCTION("""COMPUTED_VALUE"""),"Microsoft Flight Simulator (2020): Game of the Year Edition") -> Microsoft Flight Simulator (2020): Game of the Year Edition | B18: =IFERROR(__xludf.DUMMYFUNCTION("""COMPUTED_VALUE"""),"Xbox / PC") -> Xbox / PC | C18: =IFERROR(__xludf.DUMMYFUNCTION("""COMPUTED_VALUE"""),"Yes") -> Yes | D18: =IFERROR(__xludf.DUMMYFUNCTION("""COMPUTED_VALUE"""),"Active") -> Active | E18: =IFERROR(__xludf.DUMMYFUNCTION("""COMPUTED_VALUE"""),44061.0) -> 44061 | G18: =IFERROR(__xludf.DUMMYFUNCTION("""COMPUTED_VALUE"""),61.9) -> 61.9 | H18: =IFERROR(__xludf.DUMMYFUNCTION("""COMPUTED_VALUE"""),44061.0) -> 44061 | I18: =IFERROR(__xludf.DUMMYFUNCTION("""COMPUTED_VALUE"""),0.0) -> 0 | J18: =IFERROR(__xludf.DUMMYFUNCTION("""COMPUTED_VALUE"""),92.0) -> 92 | K18: =IFERROR(__xludf.DUMMYFUNCTION("""COMPUTED_VALUE"""),41.5) -> 41.5 | L18: =IFERROR(__xludf.DUMMYFUNCTION("""COMPUTED_VALUE"""),"Simulation / Flight Simulator") -> Simulation / Flight Simulator
A19: =IFERROR(__xludf.DUMMYFUNCTION("""COMPUTED_VALUE"""),"Forza Horizon 5") -> Forza Horizon 5 | B19: =IFERROR(__xludf.DUMMYFUNCTION("""COMPUTED_VALUE"""),"Xbox / PC") -> Xbox / PC | C19: =IFERROR(__xludf.DUMMYFUNCTION("""COMPUTED_VALUE"""),"Yes") -> Yes | D19: =IFERROR(__xludf.DUMMYFUNCTION("""COMPUTED_VALUE"""),"Active") -> Active | E19: =IFERROR(__xludf.DUMMYFUNCTION("""COMPUTED_VALUE"""),44509.0) -> 44509 | G19: =IFERROR(__xludf.DUMMYFUNCTION("""COMPUTED_VALUE"""),47.199999999999996) -> 47.2 | H19: =IFERROR(__xludf.DUMMYFUNCTION("""COMPUTED_VALUE"""),44509.0) -> 44509 | I19: =IFERROR(__xludf.DUMMYFUNCTION("""COMPUTED_VALUE"""),0.0) -> 0 | J19: =IFERROR(__xludf.DUMMYFUNCTION("""COMPUTED_VALUE"""),91.5) -> 91.5 | K19: =IFERROR(__xludf.DUMMYFUNCTION("""COMPUTED_VALUE"""),17.0) -> 17 | L19: =IFERROR(__xludf.DUMMYFUNCTION("""COMPUTED_VALUE"""),"Driving/Racing") -> Driving/Racing
A20: =IFERROR(__xludf.DUMMYFUNCTION("""COMPUTED_VALUE"""),"Resident Evil 2 (2019)") -> Resident Evil 2 (2019) | B20: =IFERROR(__xludf.DUMMYFUNCTION("""COMPUTED_VALUE"""),"Xbox / PC") -> Xbox / PC | C20: =IFERROR(__xludf.DUMMYFUNCTION("""COMPUTED_VALUE"""),"Yes") -> Yes | D20: =IFERROR(__xludf.DUMMYFUNCTION("""COMPUTED_VALUE"""),"Active") -> Active | E20: =IFERROR(__xludf.DUMMYFUNCTION("""COMPUTED_VALUE"""),45307.0) -> 45307 | G20: =IFERROR(__xludf.DUMMYFUNCTION("""COMPUTED_VALUE"""),20.96666666666667) -> 20.966667 | H20: =IFERROR(__xludf.DUMMYFUNCTION("""COMPUTED_VALUE"""),43480.0) -> 43480 | I20: =IFERROR(__xludf.DUMMYFUNCTION("""COMPUTED_VALUE"""),5.002777777777778) -> 5.0027778 | J20: =IFERROR(__xludf.DUMMYFUNCTION("""COMPUTED_VALUE"""),91.0) -> 91 | K20: =IFERROR(__xludf.DUMMYFUNCTION("""COMPUTED_VALUE"""),9.0) -> 9 | L20: =IFERROR(__xludf.DUMMYFUNCTION("""COMPUTED_VALUE"""),"Shooter / Action-Adventure") -> Shooter / Action-Adventure
A21: =IFERROR(__xludf.DUMMYFUNCTION("""COMPUTED_VALUE"""),"Celeste") -> Celeste | B21: =IFERROR(__xludf.DUMMYFUNCTION("""COMPUTED_VALUE"""),"Xbox / PC") -> Xbox / PC | C21: =IFERROR(__xludf.DUMMYFUNCTION("""COMPUTED_VALUE"""),"Touch Controls") -> Touch Controls | D21: =IFERROR(__xludf.DUMMYFUNCTION("""COMPUTED_VALUE"""),"Active") -> Active | E21: =IFERROR(__xludf.DUMMYFUNCTION("""COMPUTED_VALUE"""),45139.0) -> 45139 | G21: =IFERROR(__xludf.DUMMYFUNCTION("""COMPUTED_VALUE"""),26.46666666666667) -> 26.466667 | H21: =IFERROR(__xludf.DUMMYFUNCTION("""COMPUTED_VALUE"""),43125.0) -> 43125 | I21: =IFERROR(__xludf.DUMMYFUNCTION("""COMPUTED_VALUE"""),5.516666666666667) -> 5.5166667 | J21: =IFERROR(__xludf.DUMMYFUNCTION("""COMPUTED_VALUE"""),91.0) -> 91 | K21: =IFERROR(__xludf.DUMMYFUNCTION("""COMPUTED_VALUE"""),8.0) -> 8 | L21: =IFERROR(__xludf.DUMMYFUNCTION("""COMPUTED_VALUE"""),"Platformer") -> Platformer
A22: =IFERROR(__xludf.DUMMYFUNCTION("""COMPUTED_VALUE"""),"Medal of Honor: Allied Assault - War Chest") -> Medal of Honor: Allied Assault - War Chest | B22: =IFERROR(__xludf.DUMMYFUNCTION("""COMPUTED_VALUE"""),"PC") -> PC | D22: =IFERROR(__xludf.DUMMYFUNCTION("""COMPUTED_VALUE"""),"Active") -> Active | E22: =IFERROR(__xludf.DUMMYFUNCTION("""COMPUTED_VALUE"""),44273.0) -> 44273 | G22: =IFERROR(__xludf.DUMMYFUNCTION("""COMPUTED_VALUE"""),54.900000000000006) -> 54.9 | H22: =IFERROR(__xludf.DUMMYFUNCTION("""COMPUTED_VALUE"""),37276.0) -> 37276 | I22: =IFERROR(__xludf.DUMMYFUNCTION("""COMPUTED_VALUE"""),19.16111111111111) -> 19.161111 | J22: =IFERROR(__xludf.DUMMYFUNCTION("""COMPUTED_VALUE"""),91.0) -> 91 | K22: =IFERROR(__xludf.DUMMYFUNCTION("""COMPUTED_VALUE"""),27.0) -> 27 | L22: =IFERROR(__xludf.DUMMYFUNCTION("""COMPUTED_VALUE"""),"First-Person Shooter") -> First-Person Shooter
A23: =IFERROR(__xludf.DUMMYFUNCTION("""COMPUTED_VALUE"""),"Crusader Kings III") -> Crusader Kings III | B23: =IFERROR(__xludf.DUMMYFUNCTION("""COMPUTED_VALUE"""),"Xbox / PC") -> Xbox / PC | C23: =IFERROR(__xludf.DUMMYFUNCTION("""COMPUTED_VALUE"""),"Yes") -> Yes | D23: =IFERROR(__xludf.DUMMYFUNCTION("""COMPUTED_VALUE"""),"Active") -> Active | E23: =IFERROR(__xludf.DUMMYFUNCTION("""COMPUTED_VALUE"""),44075.0) -> 44075 | G23: =IFERROR(__xludf.DUMMYFUNCTION("""COMPUTED_VALUE"""),61.46666666666666) -> 61.466667 | H23: =IFERROR(__xludf.DUMMYFUNCTION("""COMPUTED_VALUE"""),44075.0) -> 44075 | I23: =IFERROR(__xludf.DUMMYFUNCTION("""COMPUTED_VALUE"""),0.0) -> 0 | J23: =IFERROR(__xludf.DUMMYFUNCTION("""COMPUTED_VALUE"""),91.0) -> 91 | K23: =IFERROR(__xludf.DUMMYFUNCTION("""COMPUTED_VALUE"""),12.5) -> 12.5 | L23: =IFERROR(__xludf.DUMMYFUNCTION("""COMPUTED_VALUE"""),"Strategy") -> Strategy
A24: =IFERROR(__xludf.DUMMYFUNCTION("""COMPUTED_VALUE"""),"Halo: Reach") -> Halo: Reach | B24: =IFERROR(__xludf.DUMMYFUNCTION("""COMPUTED_VALUE"""),"Xbox / PC") -> Xbox / PC | D24: =IFERROR(__xludf.DUMMYFUNCTION("""COMPUTED_VALUE"""),"Active") -> Active | E24: =IFERROR(__xludf.DUMMYFUNCTION("""COMPUTED_VALUE"""),43802.0) -> 43802 | G24: =IFERROR(__xludf.DUMMYFUNCTION("""COMPUTED_VALUE"""),70.39999999999999) -> 70.4 | H24: =IFERROR(__xludf.DUMMYFUNCTION("""COMPUTED_VALUE"""),40435.0) -> 40435 | I24: =IFERROR(__xludf.DUMMYFUNCTION("""COMPUTED_VALUE"""),9.219444444444445) -> 9.2194444 | J24: =IFERROR(__xludf.DUMMYFUNCTION("""COMPUTED_VALUE"""),91.0) -> 91 | K24: =IFERROR(__xludf.DUMMYFUNCTION("""COMPUTED_VALUE"""),8.0) -> 8 | L24: =IFERROR(__xludf.DUMMYFUNCTION("""COMPUTED_VALUE"""),"Action / Shooter / First-Person Shooter") -> Action / Shooter / First-Person Shooter
A25: =IFERROR(__xludf.DUMMYFUNCTION("""COMPUTED_VALUE"""),"Dead Cells") -> Dead Cells | B25: =IFERROR(__xludf.DUMMYFUNCTION("""COMPUTED_VALUE"""),"Xbox / PC") -> Xbox / PC | C25: =IFERROR(__xludf.DUMMYFUNCTION("""COMPUTED_VALUE"""),"Touch Controls") -> Touch Controls | D25: =IFERROR(__xludf.DUMMYFUNCTION("""COMPUTED_VALUE"""),"Active") -> Active | E25: =IFERROR(__xludf.DUMMYFUNCTION("""COMPUTED_VALUE"""),43713.0) -> 43713 | G25: =IFERROR(__xludf.DUMMYFUNCTION("""COMPUTED_VALUE"""),73.33333333333333) -> 73.333333 | H25: =IFERROR(__xludf.DUMMYFUNCTION("""COMPUTED_VALUE"""),42865.0) -> 42865 | I25: =IFERROR(__xludf.DUMMYFUNCTION("""COMPUTED_VALUE"""),2.3194444444444446) -> 2.3194444 | J25: =IFERROR(__xludf.DUMMYFUNCTION("""COMPUTED_VALUE"""),91.0) -> 91 | K25: =IFERROR(__xludf.DUMMYFUNCTION("""COMPUTED_VALUE"""),13.0) -> 13 | L25: =IFERROR(__xludf.DUMMYFUNCTION("""COMPUTED_VALUE"""),"Platformer / Action-Adventure") -> Platformer / Action-Adventure
A26: =IFERROR(__xludf.DUMMYFUNCTION("""COMPUTED_VALUE"""),"Assassin's Creed II") -> Assassin's Creed II | B26: =IFERROR(__xludf.DUMMYFUNCTION("""COMPUTED_VALUE"""),"PC") -> PC | D26: =IFERROR(__xludf.DUMMYFUNCTION("""COMPUTED_VALUE"""),"Active") -> Active | E26: =IFERROR(__xludf.DUMMYFUNCTION("""COMPUTED_VALUE"""),45931.0) -> 45931 | G26: =IFERROR(__xludf.DUMMYFUNCTION("""COMPUTED_VALUE"""),0.4666666666666667) -> 0.46666667 | H26: =IFERROR(__xludf.DUMMYFUNCTION("""COMPUTED_VALUE"""),40134.0) -> 40134 | I26: =IFERROR(__xludf.DUMMYFUNCTION("""COMPUTED_VALUE"""),15.872222222222222) -> 15.872222 | J26: =IFERROR(__xludf.DUMMYFUNCTION("""COMPUTED_VALUE"""),90.0) -> 90 | K26: =IFERROR(__xludf.DUMMYFUNCTION("""COMPUTED_VALUE"""),19.0) -> 19 | L26: =IFERROR(__xludf.DUMMYFUNCTION("""COMPUTED_VALUE"""),"Action-Adventure") -> Action-Adventure
A27: =IFERROR(__xludf.DUMMYFUNCTION("""COMPUTED_VALUE"""),"Persona 4: Golden") -> Persona 4: Golden | B27: =IFERROR(__xludf.DUMMYFUNCTION("""COMPUTED_VALUE"""),"Xbox / PC") -> Xbox / PC | C27: =IFERROR(__xludf.DUMMYFUNCTION("""COMPUTED_VALUE"""),"Yes") -> Yes | D27: =IFERROR(__xludf.DUMMYFUNCTION("""COMPUTED_VALUE"""),"Active") -> Active | E27: =IFERROR(__xludf.DUMMYFUNCTION("""COMPUTED_VALUE"""),45889.0) -> 45889 | G27: =IFERROR(__xludf.DUMMYFUNCTION("""COMPUTED_VALUE"""),1.8333333333333335) -> 1.8333333 | H27: =IFERROR(__xludf.DUMMYFUNCTION("""COMPUTED_VALUE"""),41074.0) -> 41074 | I27: =IFERROR(__xludf.DUMMYFUNCTION("""COMPUTED_VALUE"""),13.183333333333334) -> 13.183333 | J27: =IFERROR(__xludf.DUMMYFUNCTION("""COMPUTED_VALUE"""),90.0) -> 90 | K27: =IFERROR(__xludf.DUMMYFUNCTION("""COMPUTED_VALUE"""),68.5) -> 68.5 | L27: =IFERROR(__xludf.DUMMYFUNCTION("""COMPUTED_VALUE"""),"RPG") -> RPG
A28: =IFERROR(__xludf.DUMMYFUNCTION("""COMPUTED_VALUE"""),"Monster Train 2") -> Monster Train 2 | B28: =IFERROR(__xludf.DUMMYFUNCTION("""COMPUTED_VALUE"""),"Xbox / PC") -> Xbox / PC | C28: =IFERROR(__xludf.DUMMYFUNCTION("""COMPUTED_VALUE"""),"Yes") -> Yes | D28: =IFERROR(__xludf.DUMMYFUNCTION("""COMPUTED_VALUE"""),"Active") -> Active | E28: =IFERROR(__xludf.DUMMYFUNCTION("""COMPUTED_VALUE"""),45798.0) -> 45798 | G28: =IFERROR(__xludf.DUMMYFUNCTION("""COMPUTED_VALUE"""),4.800000000000001) -> 4.8 | H28: =IFERROR(__xludf.DUMMYFUNCTION("""COMPUTED_VALUE"""),45798.0) -> 45798 | I28: =IFERROR(__xludf.DUMMYFUNCTION("""COMPUTED_VALUE"""),0.0) -> 0 | J28: =IFERROR(__xludf.DUMMYFUNCTION("""COMPUTED_VALUE"""),90.0) -> 90 | K28: =IFERROR(__xludf.DUMMYFUNCTION("""COMPUTED_VALUE"""),6.0) -> 6 | L28: =IFERROR(__xludf.DUMMYFUNCTION("""COMPUTED_VALUE"""),"Card Battle") -> Card Battle
A29: =IFERROR(__xludf.DUMMYFUNCTION("""COMPUTED_VALUE"""),"Diablo III: Reaper of Souls - Ultimate Evil Edition") -> Diablo III: Reaper of Souls - Ultimate Evil Edition | B29: =IFERROR(__xludf.DUMMYFUNCTION("""COMPUTED_VALUE"""),"Xbox / PC") -> Xbox / PC | D29: =IFERROR(__xludf.DUMMYFUNCTION("""COMPUTED_VALUE"""),"Active") -> Active | E29: =IFERROR(__xludf.DUMMYFUNCTION("""COMPUTED_VALUE"""),45755.0) -> 45755 | G29: =IFERROR(__xludf.DUMMYFUNCTION("""COMPUTED_VALUE"""),6.233333333333334) -> 6.2333333 | H29: =IFERROR(__xludf.DUMMYFUNCTION("""COMPUTED_VALUE"""),41870.0) -> 41870 | I29: =IFERROR(__xludf.DUMMYFUNCTION("""COMPUTED_VALUE"""),10.636111111111111) -> 10.636111 | J29: =IFERROR(__xludf.DUMMYFUNCTION("""COMPUTED_VALUE"""),90.0) -> 90 | K29: =IFERROR(__xludf.DUMMYFUNCTION("""COMPUTED_VALUE"""),19.0) -> 19 | L29: =IFERROR(__xludf.DUMMYFUNCTION("""COMPUTED_VALUE"""),"RPG") -> RPG
A30: =IFERROR(__xludf.DUMMYFUNCTION("""COMPUTED_VALUE"""),"Balatro") -> Balatro | B30: =IFERROR(__xludf.DUMMYFUNCTION("""COMPUTED_VALUE"""),"Xbox / PC") -> Xbox / PC | C30: =IFERROR(__xludf.DUMMYFUNCTION("""COMPUTED_VALUE"""),"Yes") -> Yes | D30: =IFERROR(__xludf.DUMMYFUNCTION("""COMPUTED_VALUE"""),"Active") -> Active | E30: =IFERROR(__xludf.DUMMYFUNCTION("""COMPUTED_VALUE"""),45712.0) -> 45712 | G30: =IFERROR(__xludf.DUMMYFUNCTION("""COMPUTED_VALUE"""),7.700000000000001) -> 7.7 | H30: =IFERROR(__xludf.DUMMYFUNCTION("""COMPUTED_VALUE"""),45616.0) -> 45616 | I30: =IFERROR(__xludf.DUMMYFUNCTION("""COMPUTED_VALUE"""),0.2611111111111111) -> 0.26111111 | J30: =IFERROR(__xludf.DUMMYFUNCTION("""COMPUTED_VALUE"""),90.0) -> 90 | K30: =IFERROR(__xludf.DUMMYFUNCTION("""COMPUTED_VALUE"""),7.0) -> 7 | L30: =IFERROR(__xludf.DUMMYFUNCTION("""COMPUTED_VALUE"""),"Card Battle") -> Card Battle
A31: =IFERROR(__xludf.DUMMYFUNCTION("""COMPUTED_VALUE"""),"Against the Storm") -> Against the Storm | B31: =IFERROR(__xludf.DUMMYFUNCTION("""COMPUTED_VALUE"""),"Xbox / PC") -> Xbox / PC | D31: =IFERROR(__xludf.DUMMYFUNCTION("""COMPUTED_VALUE"""),"Active") -> Active | E31: =IFERROR(__xludf.DUMMYFUNCTION("""COMPUTED_VALUE"""),45268.0) -> 45268 | G31: =IFERROR(__xludf.DUMMYFUNCTION("""COMPUTED_VALUE"""),22.233333333333334) -> 22.233333 | H31: =IFERROR(__xludf.DUMMYFUNCTION("""COMPUTED_VALUE"""),44487.0) -> 44487 | I31: =IFERROR(__xludf.DUMMYFUNCTION("""COMPUTED_VALUE"""),2.138888888888889) -> 2.1388889 | J31: =IFERROR(__xludf.DUMMYFUNCTION("""COMPUTED_VALUE"""),90.0) -> 90 | K31: =IFERROR(__xludf.DUMMYFUNCTION("""COMPUTED_VALUE"""),93.0) -> 93 | L31: =IFERROR(__xludf.DUMMYFUNCTION("""COMPUTED_VALUE"""),"Strategy") -> Strategy
A32: =IFERROR(__xludf.DUMMYFUNCTION("""COMPUTED_VALUE"""),"Quake III: Arena") -> Quake III: Arena | B32: =IFERROR(__xludf.DUMMYFUNCTION("""COMPUTED_VALUE"""),"PC") -> PC | D32: =IFERROR(__xludf.DUMMYFUNCTION("""COMPUTED_VALUE"""),"Active") -> Active | E32: =IFERROR(__xludf.DUMMYFUNCTION("""COMPUTED_VALUE"""),44427.0) -> 44427 | G32: =IFERROR(__xludf.DUMMYFUNCTION("""COMPUTED_VALUE"""),49.866666666666674) -> 49.866667 | H32: =IFERROR(__xludf.DUMMYFUNCTION("""COMPUTED_VALUE"""),36496.0) -> 36496 | I32: =IFERROR(__xludf.DUMMYFUNCTION("""COMPUTED_VALUE"""),21.71388888888889) -> 21.713889 | J32: =IFERROR(__xludf.DUMMYFUNCTION("""COMPUTED_VALUE"""),90.0) -> 90 | K32: =IFERROR(__xludf.DUMMYFUNCTION("""COMPUTED_VALUE"""),5.5) -> 5.5 | L32: =IFERROR(__xludf.DUMMYFUNCTION("""COMPUTED_VALUE"""),"First-Person Shooter") -> First-Person Shooter
A33: =IFERROR(__xludf.DUMMYFUNCTION("""COMPUTED_VALUE"""),"Ultima Underworld 2") -> Ultima Underworld 2 | B33: =IFERROR(__xludf.DUMMYFUNCTION("""COMPUTED_VALUE"""),"PC") -> PC | D33: =IFERROR(__xludf.DUMMYFUNCTION("""COMPUTED_VALUE"""),"Active") -> Active | E33: =IFERROR(__xludf.DUMMYFUNCTION("""COMPUTED_VALUE"""),44425.0) -> 44425 | G33: =IFERROR(__xludf.DUMMYFUNCTION("""COMPUTED_VALUE"""),49.93333333333334) -> 49.933333 | H33: =IFERROR(__xludf.DUMMYFUNCTION("""COMPUTED_VALUE"""),33970.0) -> 33970 | I33: =IFERROR(__xludf.DUMMYFUNCTION("""COMPUTED_VALUE"""),28.627777777777776) -> 28.627778 | J33: =IFERROR(__xludf.DUMMYFUNCTION("""COMPUTED_VALUE"""),90.0) -> 90 | K33: =IFERROR(__xludf.DUMMYFUNCTION("""COMPUTED_VALUE"""),17.0) -> 17 | L33: =IFERROR(__xludf.DUMMYFUNCTION("""COMPUTED_VALUE"""),"Action / RPG") -> Action / RPG
A34: =IFERROR(__xludf.DUMMYFUNCTION("""COMPUTED_VALUE"""),"Dead Space 2") -> Dead Space 2 | B34: =IFERROR(__xludf.DUMMYFUNCTION("""COMPUTED_VALUE"""),"Xbox / PC") -> Xbox / PC | C34: =IFERROR(__xludf.DUMMYFUNCTION("""COMPUTED_VALUE"""),"Yes") -> Yes | D34: =IFERROR(__xludf.DUMMYFUNCTION("""COMPUTED_VALUE"""),"Active") -> Active | E34: =IFERROR(__xludf.DUMMYFUNCTION("""COMPUTED_VALUE"""),44145.0) -> 44145 | G34: =IFERROR(__xludf.DUMMYFUNCTION("""COMPUTED_VALUE"""),59.166666666666664) -> 59.166667 | H34: =IFERROR(__xludf.DUMMYFUNCTION("""COMPUTED_VALUE"""),40568.0) -> 40568 | I34: =IFERROR(__xludf.DUMMYFUNCTION("""COMPUTED_VALUE"""),9.791666666666666) -> 9.7916667 | J34: =IFERROR(__xludf.DUMMYFUNCTION("""COMPUTED_VALUE"""),90.0) -> 90 | K34: =IFERROR(__xludf.DUMMYFUNCTION("""COMPUTED_VALUE"""),9.0) -> 9 | L34: =IFERROR(__xludf.DUMMYFUNCTION("""COMPUTED_VALUE"""),"Action / Shooter") -> Action / Shooter
A35: =IFERROR(__xludf.DUMMYFUNCTION("""COMPUTED_VALUE"""),"The Bard's Tale ARPG: Remastered and Resnarkled") -> The Bard's Tale ARPG: Remastered and Resnarkled | B35: =IFERROR(__xludf.DUMMYFUNCTION("""COMPUTED_VALUE"""),"Xbox / PC") -> Xbox / PC | C35: =IFERROR(__xludf.DUMMYFUNCTION("""COMPUTED_VALUE"""),"Touch Controls") -> Touch Controls | D35: =IFERROR(__xludf.DUMMYFUNCTION("""COMPUTED_VALUE"""),"Active") -> Active | E35: =IFERROR(__xludf.DUMMYFUNCTION("""COMPUTED_VALUE"""),44000.0) -> 44000 | G35: =IFERROR(__xludf.DUMMYFUNCTION("""COMPUTED_VALUE"""),63.900000000000006) -> 63.9 | H35: =IFERROR(__xludf.DUMMYFUNCTION("""COMPUTED_VALUE"""),44000.0) -> 44000 | I35: =IFERROR(__xludf.DUMMYFUNCTION("""COMPUTED_VALUE"""),0.0) -> 0 | J35: =IFERROR(__xludf.DUMMYFUNCTION("""COMPUTED_VALUE"""),90.0) -> 90 | K35: =IFERROR(__xludf.DUMMYFUNCTION("""COMPUTED_VALUE"""),14.0) -> 14 | L35: =IFERROR(__xludf.DUMMYFUNCTION("""COMPUTED_VALUE"""),"RPG") -> RPG
A36: =IFERROR(__xludf.DUMMYFUNCTION("""COMPUTED_VALUE"""),"Ori and the Will of the Wisps") -> Ori and the Will of the Wisps | B36: =IFERROR(__xludf.DUMMYFUNCTION("""COMPUTED_VALUE"""),"Xbox / PC") -> Xbox / PC | C36: =IFERROR(__xludf.DUMMYFUNCTION("""COMPUTED_VALUE"""),"Yes") -> Yes | D36: =IFERROR(__xludf.DUMMYFUNCTION("""COMPUTED_VALUE"""),"Active") -> Active | E36: =IFERROR(__xludf.DUMMYFUNCTION("""COMPUTED_VALUE"""),43901.0) -> 43901 | G36: =IFERROR(__xludf.DUMMYFUNCTION("""COMPUTED_VALUE"""),67.13333333333333) -> 67.133333 | H36: =IFERROR(__xludf.DUMMYFUNCTION("""COMPUTED_VALUE"""),43901.0) -> 43901 | I36: =IFERROR(__xludf.DUMMYFUNCTION("""COMPUTED_VALUE"""),0.0) -> 0 | J36: =IFERROR(__xludf.DUMMYFUNCTION("""COMPUTED_VALUE"""),90.0) -> 90 | K36: =IFERROR(__xludf.DUMMYFUNCTION("""COMPUTED_VALUE"""),11.0) -> 11 | L36: =IFERROR(__xludf.DUMMYFUNCTION("""COMPUTED_VALUE"""),"Action / Platformer") -> Action / Platformer
A37: =IFERROR(__xludf.DUMMYFUNCTION("""COMPUTED_VALUE"""),"Hollow Knight: Voidheart Edition") -> Hollow Knight: Voidheart Edition | B37: =IFERROR(__xludf.DUMMYFUNCTION("""COMPUTED_VALUE"""),"Xbox / PC") -> Xbox / PC | C37: =IFERROR(__xludf.DUMMYFUNCTION("""COMPUTED_VALUE"""),"Yes") -> Yes | D37: =IFERROR(__xludf.DUMMYFUNCTION("""COMPUTED_VALUE"""),"Active") -> Active | E37: =IFERROR(__xludf.DUMMYFUNCTION("""COMPUTED_VALUE"""),43625.0) -> 43625 | G37: =IFERROR(__xludf.DUMMYFUNCTION("""COMPUTED_VALUE"""),76.19999999999999) -> 76.2 | H37: =IFERROR(__xludf.DUMMYFUNCTION("""COMPUTED_VALUE"""),42790.0) -> 42790 | I37: =IFERROR(__xludf.DUMMYFUNCTION("""COMPUTED_VALUE"""),2.2916666666666665) -> 2.2916667 | J37: =IFERROR(__xludf.DUMMYFUNCTION("""COMPUTED_VALUE"""),90.0) -> 90 | K37: =IFERROR(__xludf.DUMMYFUNCTION("""COMPUTED_VALUE"""),25.0) -> 25 | L37: =IFERROR(__xludf.DUMMYFUNCTION("""COMPUTED_VALUE"""),"Platformer / Action-Adventure") -> Platformer / Action-Adventure
A38: =IFERROR(__xludf.DUMMYFUNCTION("""COMPUTED_VALUE"""),"Mass Effect") -> Mass Effect | B38: =IFERROR(__xludf.DUMMYFUNCTION("""COMPUTED_VALUE"""),"Xbox / PC") -> Xbox / PC | D38: =IFERROR(__xludf.DUMMYFUNCTION("""COMPUTED_VALUE"""),"Active") -> Active | E38: =IFERROR(__xludf.DUMMYFUNCTION("""COMPUTED_VALUE"""),43070.0) -> 43070 | G38: =IFERROR(__xludf.DUMMYFUNCTION("""COMPUTED_VALUE"""),94.46666666666667) -> 94.466667 | H38: =IFERROR(__xludf.DUMMYFUNCTION("""COMPUTED_VALUE"""),39406.0) -> 39406 | I38: =IFERROR(__xludf.DUMMYFUNCTION("""COMPUTED_VALUE"""),10.030555555555555) -> 10.030556 | J38: =IFERROR(__xludf.DUMMYFUNCTION("""COMPUTED_VALUE"""),90.0) -> 90 | K38: =IFERROR(__xludf.DUMMYFUNCTION("""COMPUTED_VALUE"""),17.0) -> 17 | L38: =IFERROR(__xludf.DUMMYFUNCTION("""COMPUTED_VALUE"""),"RPG / Shooter") -> RPG / Shooter
A39: =IFERROR(__xludf.DUMMYFUNCTION("""COMPUTED_VALUE"""),"Assassin's Creed Brotherhood") -> Assassin's Creed Brotherhood | B39: =IFERROR(__xludf.DUMMYFUNCTION("""COMPUTED_VALUE"""),"PC") -> PC | D39: =IFERROR(__xludf.DUMMYFUNCTION("""COMPUTED_VALUE"""),"Active") -> Active | E39: =IFERROR(__xludf.DUMMYFUNCTION("""COMPUTED_VALUE"""),45931.0) -> 45931 | G39: =IFERROR(__xludf.DUMMYFUNCTION("""COMPUTED_VALUE"""),0.4666666666666667) -> 0.46666667 | H39: =IFERROR(__xludf.DUMMYFUNCTION("""COMPUTED_VALUE"""),40498.0) -> 40498 | I39: =IFERROR(__xludf.DUMMYFUNCTION("""COMPUTED_VALUE"""),14.875) -> 14.875 | J39: =IFERROR(__xludf.DUMMYFUNCTION("""COMPUTED_VALUE"""),89.0) -> 89 | K39: =IFERROR(__xludf.DUMMYFUNCTION("""COMPUTED_VALUE"""),15.0) -> 15 | L39: =IFERROR(__xludf.DUMMYFUNCTION("""COMPUTED_VALUE"""),"Action-Adventure") -> Action-Adventure
A40: =IFERROR(__xludf.DUMMYFUNCTION("""COMPUTED_VALUE"""),"Neon White") -> Neon White | B40: =IFERROR(__xludf.DUMMYFUNCTION("""COMPUTED_VALUE"""),"Xbox / PC") -> Xbox / PC | C40: =IFERROR(__xludf.DUMMYFUNCTION("""COMPUTED_VALUE"""),"Yes") -> Yes | D40: =IFERROR(__xludf.DUMMYFUNCTION("""COMPUTED_VALUE"""),"Active") -> Active | E40: =IFERROR(__xludf.DUMMYFUNCTION("""COMPUTED_VALUE"""),45484.0) -> 45484 | G40: =IFERROR(__xludf.DUMMYFUNCTION("""COMPUTED_VALUE"""),15.133333333333333) -> 15.133333 | H40: =IFERROR(__xludf.DUMMYFUNCTION("""COMPUTED_VALUE"""),44728.0) -> 44728 | I40: =IFERROR(__xludf.DUMMYFUNCTION("""COMPUTED_VALUE"""),2.0694444444444446) -> 2.0694444 | J40: =IFERROR(__xludf.DUMMYFUNCTION("""COMPUTED_VALUE"""),89.0) -> 89 | K40: =IFERROR(__xludf.DUMMYFUNCTION("""COMPUTED_VALUE"""),11.0) -> 11 | L40: =IFERROR(__xludf.DUMMYFUNCTION("""COMPUTED_VALUE"""),"First-Person Shooter") -> First-Person Shooter
A41: =IFERROR(__xludf.DUMMYFUNCTION("""COMPUTED_VALUE"""),"Hi-Fi RUSH") -> Hi-Fi RUSH | B41: =IFERROR(__xludf.DUMMYFUNCTION("""COMPUTED_VALUE"""),"Xbox / PC") -> Xbox / PC | C41: =IFERROR(__xludf.DUMMYFUNCTION("""COMPUTED_VALUE"""),"Yes") -> Yes | D41: =IFERROR(__xludf.DUMMYFUNCTION("""COMPUTED_VALUE"""),"Active") -> Active | E41: =IFERROR(__xludf.DUMMYFUNCTION("""COMPUTED_VALUE"""),44951.0) -> 44951 | G41: =IFERROR(__xludf.DUMMYFUNCTION("""COMPUTED_VALUE"""),32.66666666666667) -> 32.666667 | H41: =IFERROR(__xludf.DUMMYFUNCTION("""COMPUTED_VALUE"""),44951.0) -> 44951 | I41: =IFERROR(__xludf.DUMMYFUNCTION("""COMPUTED_VALUE"""),0.0) -> 0 | J41: =IFERROR(__xludf.DUMMYFUNCTION("""COMPUTED_VALUE"""),89.0) -> 89 | K41: =IFERROR(__xludf.DUMMYFUNCTION("""COMPUTED_VALUE"""),10.0) -> 10 | L41: =IFERROR(__xludf.DUMMYFUNCTION("""COMPUTED_VALUE"""),"Action / Music/Rhythm") -> Action / Music/Rhythm
A42: =IFERROR(__xludf.DUMMYFUNCTION("""COMPUTED_VALUE"""),"DEATHLOOP") -> DEATHLOOP | B42: =IFERROR(__xludf.DUMMYFUNCTION("""COMPUTED_VALUE"""),"Xbox / PC") -> Xbox / PC | C42: =IFERROR(__xludf.DUMMYFUNCTION("""COMPUTED_VALUE"""),"Yes") -> Yes | D42: =IFERROR(__xludf.DUMMYFUNCTION("""COMPUTED_VALUE"""),"Active") -> Active | E42: =IFERROR(__xludf.DUMMYFUNCTION("""COMPUTED_VALUE"""),44824.0) -> 44824 | G42: =IFERROR(__xludf.DUMMYFUNCTION("""COMPUTED_VALUE"""),36.833333333333336) -> 36.833333 | H42: =IFERROR(__xludf.DUMMYFUNCTION("""COMPUTED_VALUE"""),44453.0) -> 44453 | I42: =IFERROR(__xludf.DUMMYFUNCTION("""COMPUTED_VALUE"""),1.0166666666666666) -> 1.0166667 | J42: =IFERROR(__xludf.DUMMYFUNCTION("""COMPUTED_VALUE"""),89.0) -> 89 | K42: =IFERROR(__xludf.DUMMYFUNCTION("""COMPUTED_VALUE"""),16.0) -> 16 | L42: =IFERROR(__xludf.DUMMYFUNCTION("""COMPUTED_VALUE"""),"Action / Strategy") -> Action / Strategy
A43: =IFERROR(__xludf.DUMMYFUNCTION("""COMPUTED_VALUE"""),"Stardew Valley") -> Stardew Valley | B43: =IFERROR(__xludf.DUMMYFUNCTION("""COMPUTED_VALUE"""),"Xbox / PC") -> Xbox / PC | C43: =IFERROR(__xludf.DUMMYFUNCTION("""COMPUTED_VALUE"""),"Touch Controls") -> Touch Controls | D43: =IFERROR(__xludf.DUMMYFUNCTION("""COMPUTED_VALUE"""),"Active") -> Active | E43: =IFERROR(__xludf.DUMMYFUNCTION("""COMPUTED_VALUE"""),44532.0) -> 44532 | G43: =IFERROR(__xludf.DUMMYFUNCTION("""COMPUTED_VALUE"""),46.43333333333334) -> 46.433333 | H43: =IFERROR(__xludf.DUMMYFUNCTION("""COMPUTED_VALUE"""),42426.0) -> 42426 | I43: =IFERROR(__xludf.DUMMYFUNCTION("""COMPUTED_VALUE"""),5.766666666666667) -> 5.7666667 | J43: =IFERROR(__xludf.DUMMYFUNCTION("""COMPUTED_VALUE"""),89.0) -> 89 | K43: =IFERROR(__xludf.DUMMYFUNCTION("""COMPUTED_VALUE"""),52.5) -> 52.5 | L43: =IFERROR(__xludf.DUMMYFUNCTION("""COMPUTED_VALUE"""),"RPG / Simulation / Fishing / Action-Adventure") -> RPG / Simulation / Fishing / Action-Adventure
A44: =IFERROR(__xludf.DUMMYFUNCTION("""COMPUTED_VALUE"""),"Psychonauts 2") -> Psychonauts 2 | B44: =IFERROR(__xludf.DUMMYFUNCTION("""COMPUTED_VALUE"""),"Xbox / PC") -> Xbox / PC | C44: =IFERROR(__xludf.DUMMYFUNCTION("""COMPUTED_VALUE"""),"Touch Controls") -> Touch Controls | D44: =IFERROR(__xludf.DUMMYFUNCTION("""COMPUTED_VALUE"""),"Active") -> Active | E44: =IFERROR(__xludf.DUMMYFUNCTION("""COMPUTED_VALUE"""),44433.0) -> 44433 | G44: =IFERROR(__xludf.DUMMYFUNCTION("""COMPUTED_VALUE"""),49.66666666666667) -> 49.666667 | H44: =IFERROR(__xludf.DUMMYFUNCTION("""COMPUTED_VALUE"""),44433.0) -> 44433 | I44: =IFERROR(__xludf.DUMMYFUNCTION("""COMPUTED_VALUE"""),0.0) -> 0 | J44: =IFERROR(__xludf.DUMMYFUNCTION("""COMPUTED_VALUE"""),89.0) -> 89 | K44: =IFERROR(__xludf.DUMMYFUNCTION("""COMPUTED_VALUE"""),14.0) -> 14 | L44: =IFERROR(__xludf.DUMMYFUNCTION("""COMPUTED_VALUE"""),"Platformer / Action-Adventure") -> Platformer / Action-Adventure
A45: =IFERROR(__xludf.DUMMYFUNCTION("""COMPUTED_VALUE"""),"Quake II") -> Quake II | B45: =IFERROR(__xludf.DUMMYFUNCTION("""COMPUTED_VALUE"""),"Xbox / PC") -> Xbox / PC | C45: =IFERROR(__xludf.DUMMYFUNCTION("""COMPUTED_VALUE"""),"M+KB") -> M+KB | D45: =IFERROR(__xludf.DUMMYFUNCTION("""COMPUTED_VALUE"""),"Active") -> Active | E45: =IFERROR(__xludf.DUMMYFUNCTION("""COMPUTED_VALUE"""),44427.0) -> 44427 | G45: =IFERROR(__xludf.DUMMYFUNCTION("""COMPUTED_VALUE"""),49.866666666666674) -> 49.866667 | H45: =IFERROR(__xludf.DUMMYFUNCTION("""COMPUTED_VALUE"""),35773.0) -> 35773 | I45: =IFERROR(__xludf.DUMMYFUNCTION("""COMPUTED_VALUE"""),23.694444444444443) -> 23.694444 | J45: =IFERROR(__xludf.DUMMYFUNCTION("""COMPUTED_VALUE"""),89.0) -> 89 | K45: =IFERROR(__xludf.DUMMYFUNCTION("""COMPUTED_VALUE"""),8.0) -> 8 | L45: =IFERROR(__xludf.DUMMYFUNCTION("""COMPUTED_VALUE"""),"Action / First-Person Shooter") -> Action / First-Person Shooter
A46: =IFERROR(__xludf.DUMMYFUNCTION("""COMPUTED_VALUE"""),"Fallout") -> Fallout | B46: =IFERROR(__xludf.DUMMYFUNCTION("""COMPUTED_VALUE"""),"PC") -> PC | D46: =IFERROR(__xludf.DUMMYFUNCTION("""COMPUTED_VALUE"""),"Active") -> Active | E46: =IFERROR(__xludf.DUMMYFUNCTION("""COMPUTED_VALUE"""),44360.0) -> 44360 | G46: =IFERROR(__xludf.DUMMYFUNCTION("""COMPUTED_VALUE"""),52.06666666666666) -> 52.066667 | H46: =IFERROR(__xludf.DUMMYFUNCTION("""COMPUTED_VALUE"""),35703.0) -> 35703 | I46: =IFERROR(__xludf.DUMMYFUNCTION("""COMPUTED_VALUE"""),23.70277777777778) -> 23.702778 | J46: =IFERROR(__xludf.DUMMYFUNCTION("""COMPUTED_VALUE"""),89.0) -> 89 | K46: =IFERROR(__xludf.DUMMYFUNCTION("""COMPUTED_VALUE"""),16.0) -> 16 | L46: =IFERROR(__xludf.DUMMYFUNCTION("""COMPUTED_VALUE"""),"RPG") -> RPG
A47: =IFERROR(__xludf.DUMMYFUNCTION("""COMPUTED_VALUE"""),"Populous") -> Populous | B47: =IFERROR(__xludf.DUMMYFUNCTION("""COMPUTED_VALUE"""),"PC") -> PC | D47: =IFERROR(__xludf.DUMMYFUNCTION("""COMPUTED_VALUE"""),"Active") -> Active | E47: =IFERROR(__xludf.DUMMYFUNCTION("""COMPUTED_VALUE"""),44273.0) -> 44273 | G47: =IFERROR(__xludf.DUMMYFUNCTION("""COMPUTED_VALUE"""),54.900000000000006) -> 54.9 | H47: =IFERROR(__xludf.DUMMYFUNCTION("""COMPUTED_VALUE"""),32509.0) -> 32509 | I47: =IFERROR(__xludf.DUMMYFUNCTION("""COMPUTED_VALUE"""),32.21388888888889) -> 32.213889 | J47: =IFERROR(__xludf.DUMMYFUNCTION("""COMPUTED_VALUE"""),89.0) -> 89 | K47: =IFERROR(__xludf.DUMMYFUNCTION("""COMPUTED_VALUE"""),13.0) -> 13 | L47: =IFERROR(__xludf.DUMMYFUNCTION("""COMPUTED_VALUE"""),"Strategy") -> Strategy
A48: =IFERROR(__xludf.DUMMYFUNCTION("""COMPUTED_VALUE"""),"Dead Space") -> Dead Space | B48: =IFERROR(__xludf.DUMMYFUNCTION("""COMPUTED_VALUE"""),"Xbox / PC") -> Xbox / PC | C48: =IFERROR(__xludf.DUMMYFUNCTION("""COMPUTED_VALUE"""),"Yes") -> Yes | D48: =IFERROR(__xludf.DUMMYFUNCTION("""COMPUTED_VALUE"""),"Active") -> Active | E48: =IFERROR(__xludf.DUMMYFUNCTION("""COMPUTED_VALUE"""),44145.0) -> 44145 | G48: =IFERROR(__xludf.DUMMYFUNCTION("""COMPUTED_VALUE"""),59.166666666666664) -> 59.166667 | H48: =IFERROR(__xludf.DUMMYFUNCTION("""COMPUTED_VALUE"""),39735.0) -> 39735 | I48: =IFERROR(__xludf.DUMMYFUNCTION("""COMPUTED_VALUE"""),12.072222222222223) -> 12.072222 | J48: =IFERROR(__xludf.DUMMYFUNCTION("""COMPUTED_VALUE"""),89.0) -> 89 | K48: =IFERROR(__xludf.DUMMYFUNCTION("""COMPUTED_VALUE"""),11.0) -> 11 | L48: =IFERROR(__xludf.DUMMYFUNCTION("""COMPUTED_VALUE"""),"Action") -> Action
A49: =IFERROR(__xludf.DUMMYFUNCTION("""COMPUTED_VALUE"""),"Peggle") -> Peggle | B49: =IFERROR(__xludf.DUMMYFUNCTION("""COMPUTED_VALUE"""),"Xbox / PC") -> Xbox / PC | D49: =IFERROR(__xludf.DUMMYFUNCTION("""COMPUTED_VALUE"""),"Active") -> Active | E49: =IFERROR(__xludf.DUMMYFUNCTION("""COMPUTED_VALUE"""),44145.0) -> 44145 | G49: =IFERROR(__xludf.DUMMYFUNCTION("""COMPUTED_VALUE"""),59.166666666666664) -> 59.166667 | H49: =IFERROR(__xludf.DUMMYFUNCTION("""COMPUTED_VALUE"""),39183.0) -> 39183 | I49: =IFERROR(__xludf.DUMMYFUNCTION("""COMPUTED_VALUE"""),13.580555555555556) -> 13.580556 | J49: =IFERROR(__xludf.DUMMYFUNCTION("""COMPUTED_VALUE"""),89.0) -> 89 | K49: =IFERROR(__xludf.DUMMYFUNCTION("""COMPUTED_VALUE"""),4.0) -> 4 | L49: =IFERROR(__xludf.DUMMYFUNCTION("""COMPUTED_VALUE"""),"Puzzle / Block-Breaking") -> Puzzle / Block-Breaking
A50: =IFERROR(__xludf.DUMMYFUNCTION("""COMPUTED_VALUE"""),"Plants vs. Zombies: Game of the Year Edition") -> Plants vs. Zombies: Game of the Year Edition | B50: =IFERROR(__xludf.DUMMYFUNCTION("""COMPUTED_VALUE"""),"Xbox / PC") -> Xbox / PC | D50: =IFERROR(__xludf.DUMMYFUNCTION("""COMPUTED_VALUE"""),"Active") -> Active | E50: =IFERROR(__xludf.DUMMYFUNCTION("""COMPUTED_VALUE"""),44145.0) -> 44145 | G50: =IFERROR(__xludf.DUMMYFUNCTION("""COMPUTED_VALUE"""),59.166666666666664) -> 59.166667 | H50: =IFERROR(__xludf.DUMMYFUNCTION("""COMPUTED_VALUE"""),39938.0) -> 39938 | I50: =IFERROR(__xludf.DUMMYFUNCTION("""COMPUTED_VALUE"""),11.51388888888889) -> 11.513889 | J50: =IFERROR(__xludf.DUMMYFUNCTION("""COMPUTED_VALUE"""),89.0) -> 89 | K50: =IFERROR(__xludf.DUMMYFUNCTION("""COMPUTED_VALUE"""),8.0) -> 8 | L50: =IFERROR(__xludf.DUMMYFUNCTION("""COMPUTED_VALUE"""),"Strategy / Puzzle") -> Strategy / Puzzle
A51: =IFERROR(__xludf.DUMMYFUNCTION("""COMPUTED_VALUE"""),"Rise of Nations: Extended Edition") -> Rise of Nations: Extended Edition | B51: =IFERROR(__xludf.DUMMYFUNCTION("""COMPUTED_VALUE"""),"PC") -> PC | D51: =IFERROR(__xludf.DUMMYFUNCTION("""COMPUTED_VALUE"""),"Active") -> Active | E51: =IFERROR(__xludf.DUMMYFUNCTION("""COMPUTED_VALUE"""),43625.0) -> 43625 | G51: =IFERROR(__xludf.DUMMYFUNCTION("""COMPUTED_VALUE"""),76.19999999999999) -> 76.2 | H51: =IFERROR(__xludf.DUMMYFUNCTION("""COMPUTED_VALUE"""),37761.0) -> 37761 | I51: =IFERROR(__xludf.DUMMYFUNCTION("""COMPUTED_VALUE"""),16.052777777777777) -> 16.052778 | J51: =IFERROR(__xludf.DUMMYFUNCTION("""COMPUTED_VALUE"""),89.0) -> 89 | K51: =IFERROR(__xludf.DUMMYFUNCTION("""COMPUTED_VALUE"""),18.0) -> 18 | L51: =IFERROR(__xludf.DUMMYFUNCTION("""COMPUTED_VALUE"""),"Strategy / Real-Time Strategy / Trivia/Board Game") -> Strategy / Real-Time Strategy / Trivia/Board Game
A52: =IFERROR(__xludf.DUMMYFUNCTION("""COMPUTED_VALUE"""),"The Walking Dead: The Complete First Season") -> The Walking Dead: The Complete First Season | B52: =IFERROR(__xludf.DUMMYFUNCTION("""COMPUTED_VALUE"""),"Xbox / PC") -> Xbox / PC | C52: =IFERROR(__xludf.DUMMYFUNCTION("""COMPUTED_VALUE"""),"Touch Controls") -> Touch Controls | D52: =IFERROR(__xludf.DUMMYFUNCTION("""COMPUTED_VALUE"""),"Active") -> Active | E52: =IFERROR(__xludf.DUMMYFUNCTION("""COMPUTED_VALUE"""),43503.0) -> 43503 | G52: =IFERROR(__xludf.DUMMYFUNCTION("""COMPUTED_VALUE"""),80.26666666666667) -> 80.266667 | H52: =IFERROR(__xludf.DUMMYFUNCTION("""COMPUTED_VALUE"""),43074.0) -> 43074 | I52: =IFERROR(__xludf.DUMMYFUNCTION("""COMPUTED_VALUE"""),1.1722222222222223) -> 1.1722222 | J52: =IFERROR(__xludf.DUMMYFUNCTION("""COMPUTED_VALUE"""),89.0) -> 89 | K52: =IFERROR(__xludf.DUMMYFUNCTION("""COMPUTED_VALUE"""),13.0) -> 13 | L52: =IFERROR(__xludf.DUMMYFUNCTION("""COMPUTED_VALUE"""),"Light-Gun Shooter") -> Light-Gun Shooter
A53: =IFERROR(__xludf.DUMMYFUNCTION("""COMPUTED_VALUE"""),"It Takes Two") -> It Takes Two | B53: =IFERROR(__xludf.DUMMYFUNCTION("""COMPUTED_VALUE"""),"Xbox / PC") -> Xbox / PC | C53: =IFERROR(__xludf.DUMMYFUNCTION("""COMPUTED_VALUE"""),"Yes") -> Yes | D53: =IFERROR(__xludf.DUMMYFUNCTION("""COMPUTED_VALUE"""),"Active") -> Active | E53: =IFERROR(__xludf.DUMMYFUNCTION("""COMPUTED_VALUE"""),44504.0) -> 44504 | G53: =IFERROR(__xludf.DUMMYFUNCTION("""COMPUTED_VALUE"""),47.36666666666667) -> 47.366667 | H53: =IFERROR(__xludf.DUMMYFUNCTION("""COMPUTED_VALUE"""),44281.0) -> 44281 | I53: =IFERROR(__xludf.DUMMYFUNCTION("""COMPUTED_VALUE"""),0.6055555555555555) -> 0.60555556 | J53: =IFERROR(__xludf.DUMMYFUNCTION("""COMPUTED_VALUE"""),88.5) -> 88.5 | K53: =IFERROR(__xludf.DUMMYFUNCTION("""COMPUTED_VALUE"""),12.0) -> 12 | L53: =IFERROR(__xludf.DUMMYFUNCTION("""COMPUTED_VALUE"""),"Platformer / Action-Adventure") -> Platformer / Action-Adventure
A54: =IFERROR(__xludf.DUMMYFUNCTION("""COMPUTED_VALUE"""),"Assassin's Creed IV Black Flag") -> Assassin's Creed IV Black Flag | B54: =IFERROR(__xludf.DUMMYFUNCTION("""COMPUTED_VALUE"""),"Xbox / PC") -> Xbox / PC | C54: =IFERROR(__xludf.DUMMYFUNCTION("""COMPUTED_VALUE"""),"Yes") -> Yes | D54: =IFERROR(__xludf.DUMMYFUNCTION("""COMPUTED_VALUE"""),"Active") -> Active | E54: =IFERROR(__xludf.DUMMYFUNCTION("""COMPUTED_VALUE"""),45931.0) -> 45931 | G54: =IFERROR(__xludf.DUMMYFUNCTION("""COMPUTED_VALUE"""),0.4666666666666667) -> 0.46666667 | H54: =IFERROR(__xludf.DUMMYFUNCTION("""COMPUTED_VALUE"""),41576.0) -> 41576 | I54: =IFERROR(__xludf.DUMMYFUNCTION("""COMPUTED_VALUE"""),11.922222222222222) -> 11.922222 | J54: =IFERROR(__xludf.DUMMYFUNCTION("""COMPUTED_VALUE"""),88.0) -> 88 | K54: =IFERROR(__xludf.DUMMYFUNCTION("""COMPUTED_VALUE"""),24.0) -> 24 | L54: =IFERROR(__xludf.DUMMYFUNCTION("""COMPUTED_VALUE"""),"Action-Adventure") -> Action-Adventure
A55: =IFERROR(__xludf.DUMMYFUNCTION("""COMPUTED_VALUE"""),"Far Cry 3") -> Far Cry 3 | B55: =IFERROR(__xludf.DUMMYFUNCTION("""COMPUTED_VALUE"""),"Xbox / PC") -> Xbox / PC | C55: =IFERROR(__xludf.DUMMYFUNCTION("""COMPUTED_VALUE"""),"Yes") -> Yes | D55: =IFERROR(__xludf.DUMMYFUNCTION("""COMPUTED_VALUE"""),"Active") -> Active | E55: =IFERROR(__xludf.DUMMYFUNCTION("""COMPUTED_VALUE"""),45931.0) -> 45931 | G55: =IFERROR(__xludf.DUMMYFUNCTION("""COMPUTED_VALUE"""),0.4666666666666667) -> 0.46666667 | H55: =IFERROR(__xludf.DUMMYFUNCTION("""COMPUTED_VALUE"""),41247.0) -> 41247 | I55: =IFERROR(__xludf.DUMMYFUNCTION("""COMPUTED_VALUE"""),12.825) -> 12.825 | J55: =IFERROR(__xludf.DUMMYFUNCTION("""COMPUTED_VALUE"""),88.0) -> 88 | K55: =IFERROR(__xludf.DUMMYFUNCTION("""COMPUTED_VALUE"""),16.0) -> 16 | L55: =IFERROR(__xludf.DUMMYFUNCTION("""COMPUTED_VALUE"""),"Action-Adventure") -> Action-Adventure
A56: =IFERROR(__xludf.DUMMYFUNCTION("""COMPUTED_VALUE"""),"Abiotic Factor") -> Abiotic Factor | B56: =IFERROR(__xludf.DUMMYFUNCTION("""COMPUTED_VALUE"""),"Xbox / PC") -> Xbox / PC | C56: =IFERROR(__xludf.DUMMYFUNCTION("""COMPUTED_VALUE"""),"Yes") -> Yes | D56: =IFERROR(__xludf.DUMMYFUNCTION("""COMPUTED_VALUE"""),"Active") -> Active | E56: =IFERROR(__xludf.DUMMYFUNCTION("""COMPUTED_VALUE"""),45860.0) -> 45860 | G56: =IFERROR(__xludf.DUMMYFUNCTION("""COMPUTED_VALUE"""),2.7666666666666666) -> 2.7666667 | H56: =IFERROR(__xludf.DUMMYFUNCTION("""COMPUTED_VALUE"""),45860.0) -> 45860 | I56: =IFERROR(__xludf.DUMMYFUNCTION("""COMPUTED_VALUE"""),0.0) -> 0 | J56: =IFERROR(__xludf.DUMMYFUNCTION("""COMPUTED_VALUE"""),88.0) -> 88 | K56: =IFERROR(__xludf.DUMMYFUNCTION("""COMPUTED_VALUE"""),33.0) -> 33 | L56: =IFERROR(__xludf.DUMMYFUNCTION("""COMPUTED_VALUE"""),"Survival") -> Survival
A57: =IFERROR(__xludf.DUMMYFUNCTION("""COMPUTED_VALUE"""),"Mullet Madjack") -> Mullet Madjack | B57: =IFERROR(__xludf.DUMMYFUNCTION("""COMPUTED_VALUE"""),"Xbox / PC") -> Xbox / PC | C57: =IFERROR(__xludf.DUMMYFUNCTION("""COMPUTED_VALUE"""),"Yes") -> Yes | D57: =IFERROR(__xludf.DUMMYFUNCTION("""COMPUTED_VALUE"""),"Active") -> Active | E57: =IFERROR(__xludf.DUMMYFUNCTION("""COMPUTED_VALUE"""),45729.0) -> 45729 | G57: =IFERROR(__xludf.DUMMYFUNCTION("""COMPUTED_VALUE"""),7.066666666666666) -> 7.0666667 | H57: =IFERROR(__xludf.DUMMYFUNCTION("""COMPUTED_VALUE"""),45427.0) -> 45427 | I57: =IFERROR(__xludf.DUMMYFUNCTION("""COMPUTED_VALUE"""),0.8277777777777777) -> 0.82777778 | J57: =IFERROR(__xludf.DUMMYFUNCTION("""COMPUTED_VALUE"""),88.0) -> 88 | K57: =IFERROR(__xludf.DUMMYFUNCTION("""COMPUTED_VALUE"""),4.0) -> 4 | L57: =IFERROR(__xludf.DUMMYFUNCTION("""COMPUTED_VALUE"""),"Shooter") -> Shooter
A58: =IFERROR(__xludf.DUMMYFUNCTION("""COMPUTED_VALUE"""),"Populous: The Beginning") -> Populous: The Beginning | B58: =IFERROR(__xludf.DUMMYFUNCTION("""COMPUTED_VALUE"""),"PC") -> PC | D58: =IFERROR(__xludf.DUMMYFUNCTION("""COMPUTED_VALUE"""),"Active") -> Active | E58: =IFERROR(__xludf.DUMMYFUNCTION("""COMPUTED_VALUE"""),45398.0) -> 45398 | G58: =IFERROR(__xludf.DUMMYFUNCTION("""COMPUTED_VALUE"""),17.96666666666667) -> 17.966667 | H58: =IFERROR(__xludf.DUMMYFUNCTION("""COMPUTED_VALUE"""),36129.0) -> 36129 | I58: =IFERROR(__xludf.DUMMYFUNCTION("""COMPUTED_VALUE"""),25.377777777777776) -> 25.377778 | J58: =IFERROR(__xludf.DUMMYFUNCTION("""COMPUTED_VALUE"""),88.0) -> 88 | K58: =IFERROR(__xludf.DUMMYFUNCTION("""COMPUTED_VALUE"""),23.0) -> 23 | L58: =IFERROR(__xludf.DUMMYFUNCTION("""COMPUTED_VALUE"""),"Strategy") -> Strategy
A59: =IFERROR(__xludf.DUMMYFUNCTION("""COMPUTED_VALUE"""),"Minecraft: Preview") -> Minecraft: Preview | B59: =IFERROR(__xludf.DUMMYFUNCTION("""COMPUTED_VALUE"""),"Xbox / PC") -> Xbox / PC | D59: =IFERROR(__xludf.DUMMYFUNCTION("""COMPUTED_VALUE"""),"Active") -> Active | E59: =IFERROR(__xludf.DUMMYFUNCTION("""COMPUTED_VALUE"""),45368.0) -> 45368 | G59: =IFERROR(__xludf.DUMMYFUNCTION("""COMPUTED_VALUE"""),18.933333333333334) -> 18.933333 | H59: =IFERROR(__xludf.DUMMYFUNCTION("""COMPUTED_VALUE"""),40865.0) -> 40865 | I59: =IFERROR(__xludf.DUMMYFUNCTION("""COMPUTED_VALUE"""),12.330555555555556) -> 12.330556 | J59: =IFERROR(__xludf.DUMMYFUNCTION("""COMPUTED_VALUE"""),88.0) -> 88 | K59: =IFERROR(__xludf.DUMMYFUNCTION("""COMPUTED_VALUE"""),116.0) -> 116 | L59: =IFERROR(__xludf.DUMMYFUNCTION("""COMPUTED_VALUE"""),"Action-Adventure") -> Action-Adventure
A60: =IFERROR(__xludf.DUMMYFUNCTION("""COMPUTED_VALUE"""),"Dead Space (2023)") -> Dead Space (2023) | B60: =IFERROR(__xludf.DUMMYFUNCTION("""COMPUTED_VALUE"""),"Xbox / PC") -> Xbox / PC | C60: =IFERROR(__xludf.DUMMYFUNCTION("""COMPUTED_VALUE"""),"Yes") -> Yes | D60: =IFERROR(__xludf.DUMMYFUNCTION("""COMPUTED_VALUE"""),"Active") -> Active | E60: =IFERROR(__xludf.DUMMYFUNCTION("""COMPUTED_VALUE"""),45225.0) -> 45225 | G60: =IFERROR(__xludf.DUMMYFUNCTION("""COMPUTED_VALUE"""),23.633333333333333) -> 23.633333 | H60: =IFERROR(__xludf.DUMMYFUNCTION("""COMPUTED_VALUE"""),44953.0) -> 44953 | I60: =IFERROR(__xludf.DUMMYFUNCTION("""COMPUTED_VALUE"""),0.7472222222222222) -> 0.74722222 | J60: =IFERROR(__xludf.DUMMYFUNCTION("""COMPUTED_VALUE"""),88.0) -> 88 | K60: =IFERROR(__xludf.DUMMYFUNCTION("""COMPUTED_VALUE"""),12.0) -> 12 | L60: =IFERROR(__xludf.DUMMYFUNCTION("""COMPUTED_VALUE"""),"Shooter / Action-Adventure") -> Shooter / Action-Adventure
A61: =IFERROR(__xludf.DUMMYFUNCTION("""COMPUTED_VALUE"""),"Return to Castle Wolfenstein") -> Return to Castle Wolfenstein | B61: =IFERROR(__xludf.DUMMYFUNCTION("""COMPUTED_VALUE"""),"PC") -> PC | D61: =IFERROR(__xludf.DUMMYFUNCTION("""COMPUTED_VALUE"""),"Active") -> Active | E61: =IFERROR(__xludf.DUMMYFUNCTION("""COMPUTED_VALUE"""),44791.0) -> 44791 | G61: =IFERROR(__xludf.DUMMYFUNCTION("""COMPUTED_VALUE"""),37.9) -> 37.9 | H61: =IFERROR(__xludf.DUMMYFUNCTION("""COMPUTED_VALUE"""),37214.0) -> 37214 | I61: =IFERROR(__xludf.DUMMYFUNCTION("""COMPUTED_VALUE"""),20.747222222222224) -> 20.747222 | J61: =IFERROR(__xludf.DUMMYFUNCTION("""COMPUTED_VALUE"""),88.0) -> 88 | K61: =IFERROR(__xludf.DUMMYFUNCTION("""COMPUTED_VALUE"""),8.0) -> 8 | L61: =IFERROR(__xludf.DUMMYFUNCTION("""COMPUTED_VALUE"""),"First-Person Shooter") -> First-Person Shooter
A62: =IFERROR(__xludf.DUMMYFUNCTION("""COMPUTED_VALUE"""),"Mass Effect: Legendary Edition") -> Mass Effect: Legendary Edition | B62: =IFERROR(__xludf.DUMMYFUNCTION("""COMPUTED_VALUE"""),"Xbox / PC") -> Xbox / PC | C62: =IFERROR(__xludf.DUMMYFUNCTION("""COMPUTED_VALUE"""),"Yes") -> Yes | D62: =IFERROR(__xludf.DUMMYFUNCTION("""COMPUTED_VALUE"""),"Active") -> Active | E62: =IFERROR(__xludf.DUMMYFUNCTION("""COMPUTED_VALUE"""),44567.0) -> 44567 | G62: =IFERROR(__xludf.DUMMYFUNCTION("""COMPUTED_VALUE"""),45.3) -> 45.3 | H62: =IFERROR(__xludf.DUMMYFUNCTION("""COMPUTED_VALUE"""),44330.0) -> 44330 | I62: =IFERROR(__xludf.DUMMYFUNCTION("""COMPUTED_VALUE"""),0.6444444444444445) -> 0.64444444 | J62: =IFERROR(__xludf.DUMMYFUNCTION("""COMPUTED_VALUE"""),88.0) -> 88 | K62: =IFERROR(__xludf.DUMMYFUNCTION("""COMPUTED_VALUE"""),106.0) -> 106 | L62: =IFERROR(__xludf.DUMMYFUNCTION("""COMPUTED_VALUE"""),"RPG / Shooter / Compilation") -> RPG / Shooter / Compilation
A63: =IFERROR(__xludf.DUMMYFUNCTION("""COMPUTED_VALUE"""),"Dungeon Keeper") -> Dungeon Keeper | B63: =IFERROR(__xludf.DUMMYFUNCTION("""COMPUTED_VALUE"""),"PC") -> PC | D63: =IFERROR(__xludf.DUMMYFUNCTION("""COMPUTED_VALUE"""),"Active") -> Active | E63: =IFERROR(__xludf.DUMMYFUNCTION("""COMPUTED_VALUE"""),44273.0) -> 44273 | G63: =IFERROR(__xludf.DUMMYFUNCTION("""COMPUTED_VALUE"""),54.900000000000006) -> 54.9 | H63: =IFERROR(__xludf.DUMMYFUNCTION("""COMPUTED_VALUE"""),35607.0) -> 35607 | I63: =IFERROR(__xludf.DUMMYFUNCTION("""COMPUTED_VALUE"""),23.727777777777778) -> 23.727778 | J63: =IFERROR(__xludf.DUMMYFUNCTION("""COMPUTED_VALUE"""),88.0) -> 88 | K63: =IFERROR(__xludf.DUMMYFUNCTION("""COMPUTED_VALUE"""),15.0) -> 15 | L63: =IFERROR(__xludf.DUMMYFUNCTION("""COMPUTED_VALUE"""),"Strategy / RPG") -> Strategy / RPG
A64: =IFERROR(__xludf.DUMMYFUNCTION("""COMPUTED_VALUE"""),"Dungeon Keeper 2") -> Dungeon Keeper 2 | B64: =IFERROR(__xludf.DUMMYFUNCTION("""COMPUTED_VALUE"""),"PC") -> PC | D64: =IFERROR(__xludf.DUMMYFUNCTION("""COMPUTED_VALUE"""),"Active") -> Active | E64: =IFERROR(__xludf.DUMMYFUNCTION("""COMPUTED_VALUE"""),44273.0) -> 44273 | G64: =IFERROR(__xludf.DUMMYFUNCTION("""COMPUTED_VALUE"""),54.900000000000006) -> 54.9 | H64: =IFERROR(__xludf.DUMMYFUNCTION("""COMPUTED_VALUE"""),36341.0) -> 36341 | I64: =IFERROR(__xludf.DUMMYFUNCTION("""COMPUTED_VALUE"""),21.716666666666665) -> 21.716667 | J64: =IFERROR(__xludf.DUMMYFUNCTION("""COMPUTED_VALUE"""),88.0) -> 88 | K64: =IFERROR(__xludf.DUMMYFUNCTION("""COMPUTED_VALUE"""),17.5) -> 17.5 | L64: =IFERROR(__xludf.DUMMYFUNCTION("""COMPUTED_VALUE"""),"Action / Real-Time Strategy") -> Action / Real-Time Strategy
A65: =IFERROR(__xludf.DUMMYFUNCTION("""COMPUTED_VALUE"""),"DOOM 3") -> DOOM 3 | B65: =IFERROR(__xludf.DUMMYFUNCTION("""COMPUTED_VALUE"""),"Xbox / PC") -> Xbox / PC | C65: =IFERROR(__xludf.DUMMYFUNCTION("""COMPUTED_VALUE"""),"Yes") -> Yes | D65: =IFERROR(__xludf.DUMMYFUNCTION("""COMPUTED_VALUE"""),"Active") -> Active | E65: =IFERROR(__xludf.DUMMYFUNCTION("""COMPUTED_VALUE"""),44267.0) -> 44267 | G65: =IFERROR(__xludf.DUMMYFUNCTION("""COMPUTED_VALUE"""),55.1) -> 55.1 | H65: =IFERROR(__xludf.DUMMYFUNCTION("""COMPUTED_VALUE"""),38202.0) -> 38202 | I65: =IFERROR(__xludf.DUMMYFUNCTION("""COMPUTED_VALUE"""),16.608333333333334) -> 16.608333 | J65: =IFERROR(__xludf.DUMMYFUNCTION("""COMPUTED_VALUE"""),88.0) -> 88 | K65: =IFERROR(__xludf.DUMMYFUNCTION("""COMPUTED_VALUE"""),11.0) -> 11 | L65: =IFERROR(__xludf.DUMMYFUNCTION("""COMPUTED_VALUE"""),"First-Person Shooter") -> First-Person Shooter
A66: =IFERROR(__xludf.DUMMYFUNCTION("""COMPUTED_VALUE"""),"The Elder Scrolls III: Morrowind") -> The Elder Scrolls III: Morrowind | B66: =IFERROR(__xludf.DUMMYFUNCTION("""COMPUTED_VALUE"""),"Xbox / PC") -> Xbox / PC | C66: =IFERROR(__xludf.DUMMYFUNCTION("""COMPUTED_VALUE"""),"Yes") -> Yes | D66: =IFERROR(__xludf.DUMMYFUNCTION("""COMPUTED_VALUE"""),"Active") -> Active | E66: =IFERROR(__xludf.DUMMYFUNCTION("""COMPUTED_VALUE"""),44267.0) -> 44267 | G66: =IFERROR(__xludf.DUMMYFUNCTION("""COMPUTED_VALUE"""),55.1) -> 55.1 | H66: =IFERROR(__xludf.DUMMYFUNCTION("""COMPUTED_VALUE"""),37377.0) -> 37377 | I66: =IFERROR(__xludf.DUMMYFUNCTION("""COMPUTED_VALUE"""),18.863888888888887) -> 18.863889 | J66: =IFERROR(__xludf.DUMMYFUNCTION("""COMPUTED_VALUE"""),88.0) -> 88 | K66: =IFERROR(__xludf.DUMMYFUNCTION("""COMPUTED_VALUE"""),44.5) -> 44.5 | L66: =IFERROR(__xludf.DUMMYFUNCTION("""COMPUTED_VALUE"""),"RPG") -> RPG
A67: =IFERROR(__xludf.DUMMYFUNCTION("""COMPUTED_VALUE"""),"Pillars of Eternity II: Deadfire - Ultimate Edition") -> Pillars of Eternity II: Deadfire - Ultimate Edition | B67: =IFERROR(__xludf.DUMMYFUNCTION("""COMPUTED_VALUE"""),"Xbox / PC") -> Xbox / PC | C67: =IFERROR(__xludf.DUMMYFUNCTION("""COMPUTED_VALUE"""),"Touch Controls") -> Touch Controls | D67: =IFERROR(__xludf.DUMMYFUNCTION("""COMPUTED_VALUE"""),"Active") -> Active | E67: =IFERROR(__xludf.DUMMYFUNCTION("""COMPUTED_VALUE"""),44245.0) -> 44245 | G67: =IFERROR(__xludf.DUMMYFUNCTION("""COMPUTED_VALUE"""),55.9) -> 55.9 | H67: =IFERROR(__xludf.DUMMYFUNCTION("""COMPUTED_VALUE"""),43228.0) -> 43228 | I67: =IFERROR(__xludf.DUMMYFUNCTION("""COMPUTED_VALUE"""),2.7777777777777777) -> 2.7777778 | J67: =IFERROR(__xludf.DUMMYFUNCTION("""COMPUTED_VALUE"""),88.0) -> 88 | K67: =IFERROR(__xludf.DUMMYFUNCTION("""COMPUTED_VALUE"""),42.0) -> 42 | L67: =IFERROR(__xludf.DUMMYFUNCTION("""COMPUTED_VALUE"""),"RPG") -> RPG
A68: =IFERROR(__xludf.DUMMYFUNCTION("""COMPUTED_VALUE"""),"DOOM Eternal") -> DOOM Eternal | B68: =IFERROR(__xludf.DUMMYFUNCTION("""COMPUTED_VALUE"""),"Xbox / PC") -> Xbox / PC | C68: =IFERROR(__xludf.DUMMYFUNCTION("""COMPUTED_VALUE"""),"Yes") -> Yes | D68: =IFERROR(__xludf.DUMMYFUNCTION("""COMPUTED_VALUE"""),"Active") -> Active | E68: =IFERROR(__xludf.DUMMYFUNCTION("""COMPUTED_VALUE"""),44105.0) -> 44105 | G68: =IFERROR(__xludf.DUMMYFUNCTION("""COMPUTED_VALUE"""),60.46666666666667) -> 60.466667 | H68: =IFERROR(__xludf.DUMMYFUNCTION("""COMPUTED_VALUE"""),43910.0) -> 43910 | I68: =IFERROR(__xludf.DUMMYFUNCTION("""COMPUTED_VALUE"""),0.5305555555555556) -> 0.53055556 | J68: =IFERROR(__xludf.DUMMYFUNCTION("""COMPUTED_VALUE"""),88.0) -> 88 | K68: =IFERROR(__xludf.DUMMYFUNCTION("""COMPUTED_VALUE"""),13.5) -> 13.5 | L68: =IFERROR(__xludf.DUMMYFUNCTION("""COMPUTED_VALUE"""),"First-Person Shooter") -> First-Person Shooter
A69: =IFERROR(__xludf.DUMMYFUNCTION("""COMPUTED_VALUE"""),"Halo 3") -> Halo 3 | B69: =IFERROR(__xludf.DUMMYFUNCTION("""COMPUTED_VALUE"""),"Xbox / PC") -> Xbox / PC | D69: =IFERROR(__xludf.DUMMYFUNCTION("""COMPUTED_VALUE"""),"Active") -> Active | E69: =IFERROR(__xludf.DUMMYFUNCTION("""COMPUTED_VALUE"""),44026.0) -> 44026 | G69: =IFERROR(__xludf.DUMMYFUNCTION("""COMPUTED_VALUE"""),63.03333333333334) -> 63.033333 | H69: =IFERROR(__xludf.DUMMYFUNCTION("""COMPUTED_VALUE"""),39350.0) -> 39350 | I69: =IFERROR(__xludf.DUMMYFUNCTION("""COMPUTED_VALUE"""),12.802777777777777) -> 12.802778 | J69: =IFERROR(__xludf.DUMMYFUNCTION("""COMPUTED_VALUE"""),88.0) -> 88 | K69: =IFERROR(__xludf.DUMMYFUNCTION("""COMPUTED_VALUE"""),9.0) -> 9 | L69: =IFERROR(__xludf.DUMMYFUNCTION("""COMPUTED_VALUE"""),"First-Person Shooter") -> First-Person Shooter
A70: =IFERROR(__xludf.DUMMYFUNCTION("""COMPUTED_VALUE"""),"Dishonored 2") -> Dishonored 2 | B70: =IFERROR(__xludf.DUMMYFUNCTION("""COMPUTED_VALUE"""),"Xbox / PC") -> Xbox / PC | C70: =IFERROR(__xludf.DUMMYFUNCTION("""COMPUTED_VALUE"""),"Yes") -> Yes | D70: =IFERROR(__xludf.DUMMYFUNCTION("""COMPUTED_VALUE"""),"Active") -> Active | E70: =IFERROR(__xludf.DUMMYFUNCTION("""COMPUTED_VALUE"""),43741.0) -> 43741 | G70: =IFERROR(__xludf.DUMMYFUNCTION("""COMPUTED_VALUE"""),72.4) -> 72.4 | H70: =IFERROR(__xludf.DUMMYFUNCTION("""COMPUTED_VALUE"""),42685.0) -> 42685 | I70: =IFERROR(__xludf.DUMMYFUNCTION("""COMPUTED_VALUE"""),2.8944444444444444) -> 2.8944444 | J70: =IFERROR(__xludf.DUMMYFUNCTION("""COMPUTED_VALUE"""),88.0) -> 88 | K70: =IFERROR(__xludf.DUMMYFUNCTION("""COMPUTED_VALUE"""),12.5) -> 12.5 | L70: =IFERROR(__xludf.DUMMYFUNCTION("""COMPUTED_VALUE"""),"Action-Adventure") -> Action-Adventure
A71: =IFERROR(__xludf.DUMMYFUNCTION("""COMPUTED_VALUE"""),"Slay the Spire") -> Slay the Spire | B71: =IFERROR(__xludf.DUMMYFUNCTION("""COMPUTED_VALUE"""),"Xbox / PC") -> Xbox / PC | C71: =IFERROR(__xludf.DUMMYFUNCTION("""COMPUTED_VALUE"""),"Touch Controls") -> Touch Controls | D71: =IFERROR(__xludf.DUMMYFUNCTION("""COMPUTED_VALUE"""),"Active") -> Active | E71: =IFERROR(__xludf.DUMMYFUNCTION("""COMPUTED_VALUE"""),43691.0) -> 43691 | G71: =IFERROR(__xludf.DUMMYFUNCTION("""COMPUTED_VALUE"""),74.03333333333333) -> 74.033333 | H71: =IFERROR(__xludf.DUMMYFUNCTION("""COMPUTED_VALUE"""),43054.0) -> 43054 | I71: =IFERROR(__xludf.DUMMYFUNCTION("""COMPUTED_VALUE"""),1.7472222222222222) -> 1.7472222 | J71: =IFERROR(__xludf.DUMMYFUNCTION("""COMPUTED_VALUE"""),88.0) -> 88 | K71: =IFERROR(__xludf.DUMMYFUNCTION("""COMPUTED_VALUE"""),10.5) -> 10.5 | L71: =IFERROR(__xludf.DUMMYFUNCTION("""COMPUTED_VALUE"""),"Strategy / Card Game") -> Strategy / Card Game
A72: =IFERROR(__xludf.DUMMYFUNCTION("""COMPUTED_VALUE"""),"Wolfenstein II: The New Colossus") -> Wolfenstein II: The New Colossus | B72: =IFERROR(__xludf.DUMMYFUNCTION("""COMPUTED_VALUE"""),"Xbox / PC") -> Xbox / PC | C72: =IFERROR(__xludf.DUMMYFUNCTION("""COMPUTED_VALUE"""),"Yes") -> Yes | D72: =IFERROR(__xludf.DUMMYFUNCTION("""COMPUTED_VALUE"""),"Active") -> Active | E72: =IFERROR(__xludf.DUMMYFUNCTION("""COMPUTED_VALUE"""),43587.0) -> 43587 | G72: =IFERROR(__xludf.DUMMYFUNCTION("""COMPUTED_VALUE"""),77.43333333333334) -> 77.433333 | H72: =IFERROR(__xludf.DUMMYFUNCTION("""COMPUTED_VALUE"""),43035.0) -> 43035 | I72: =IFERROR(__xludf.DUMMYFUNCTION("""COMPUTED_VALUE"""),1.5138888888888888) -> 1.5138889 | J72: =IFERROR(__xludf.DUMMYFUNCTION("""COMPUTED_VALUE"""),88.0) -> 88 | K72: =IFERROR(__xludf.DUMMYFUNCTION("""COMPUTED_VALUE"""),10.5) -> 10.5 | L72: =IFERROR(__xludf.DUMMYFUNCTION("""COMPUTED_VALUE"""),"First-Person Shooter") -> First-Person Shooter
A73: =IFERROR(__xludf.DUMMYFUNCTION("""COMPUTED_VALUE"""),"Minecraft") -> Minecraft | B73: =IFERROR(__xludf.DUMMYFUNCTION("""COMPUTED_VALUE"""),"Xbox / PC") -> Xbox / PC | D73: =IFERROR(__xludf.DUMMYFUNCTION("""COMPUTED_VALUE"""),"Active") -> Active | E73: =IFERROR(__xludf.DUMMYFUNCTION("""COMPUTED_VALUE"""),43559.0) -> 43559 | G73: =IFERROR(__xludf.DUMMYFUNCTION("""COMPUTED_VALUE"""),78.36666666666667) -> 78.366667 | H73: =IFERROR(__xludf.DUMMYFUNCTION("""COMPUTED_VALUE"""),40865.0) -> 40865 | I73: =IFERROR(__xludf.DUMMYFUNCTION("""COMPUTED_VALUE"""),7.377777777777778) -> 7.3777778 | J73: =IFERROR(__xludf.DUMMYFUNCTION("""COMPUTED_VALUE"""),88.0) -> 88 | K73: =IFERROR(__xludf.DUMMYFUNCTION("""COMPUTED_VALUE"""),116.0) -> 116 | L73: =IFERROR(__xludf.DUMMYFUNCTION("""COMPUTED_VALUE"""),"Action-Adventure") -> Action-Adventure
A74: =IFERROR(__xludf.DUMMYFUNCTION("""COMPUTED_VALUE"""),"Fallout 4") -> Fallout 4 | B74: =IFERROR(__xludf.DUMMYFUNCTION("""COMPUTED_VALUE"""),"Xbox / PC") -> Xbox / PC | C74: =IFERROR(__xludf.DUMMYFUNCTION("""COMPUTED_VALUE"""),"Yes") -> Yes | D74: =IFERROR(__xludf.DUMMYFUNCTION("""COMPUTED_VALUE"""),"Active") -> Active | E74: =IFERROR(__xludf.DUMMYFUNCTION("""COMPUTED_VALUE"""),43538.0) -> 43538 | G74: =IFERROR(__xludf.DUMMYFUNCTION("""COMPUTED_VALUE"""),79.03333333333333) -> 79.033333 | H74: =IFERROR(__xludf.DUMMYFUNCTION("""COMPUTED_VALUE"""),42318.0) -> 42318 | I74: =IFERROR(__xludf.DUMMYFUNCTION("""COMPUTED_VALUE"""),3.3444444444444446) -> 3.3444444 | J74: =IFERROR(__xludf.DUMMYFUNCTION("""COMPUTED_VALUE"""),88.0) -> 88 | K74: =IFERROR(__xludf.DUMMYFUNCTION("""COMPUTED_VALUE"""),26.5) -> 26.5 | L74: =IFERROR(__xludf.DUMMYFUNCTION("""COMPUTED_VALUE"""),"RPG / Shooter") -> RPG / Shooter
A75: =IFERROR(__xludf.DUMMYFUNCTION("""COMPUTED_VALUE"""),"Ori and the Blind Forest: Definitive Edition") -> Ori and the Blind Forest: Definitive Edition | B75: =IFERROR(__xludf.DUMMYFUNCTION("""COMPUTED_VALUE"""),"Xbox / PC") -> Xbox / PC | C75: =IFERROR(__xludf.DUMMYFUNCTION("""COMPUTED_VALUE"""),"Yes") -> Yes | D75: =IFERROR(__xludf.DUMMYFUNCTION("""COMPUTED_VALUE"""),"Active") -> Active | E75: =IFERROR(__xludf.DUMMYFUNCTION("""COMPUTED_VALUE"""),43454.0) -> 43454 | G75: =IFERROR(__xludf.DUMMYFUNCTION("""COMPUTED_VALUE"""),81.83333333333334) -> 81.833333 | H75: =IFERROR(__xludf.DUMMYFUNCTION("""COMPUTED_VALUE"""),42074.0) -> 42074 | I75: =IFERROR(__xludf.DUMMYFUNCTION("""COMPUTED_VALUE"""),3.775) -> 3.775 | J75: =IFERROR(__xludf.DUMMYFUNCTION("""COMPUTED_VALUE"""),88.0) -> 88 | K75: =IFERROR(__xludf.DUMMYFUNCTION("""COMPUTED_VALUE"""),8.5) -> 8.5 | L75: =IFERROR(__xludf.DUMMYFUNCTION("""COMPUTED_VALUE"""),"Puzzle / Platformer / Action-Adventure") -> Puzzle / Platformer / Action-Adventure
A76: =IFERROR(__xludf.DUMMYFUNCTION("""COMPUTED_VALUE"""),"Hellblade: Senua's Sacrifice") -> Hellblade: Senua's Sacrifice | B76: =IFERROR(__xludf.DUMMYFUNCTION("""COMPUTED_VALUE"""),"Xbox / PC") -> Xbox / PC | C76: =IFERROR(__xludf.DUMMYFUNCTION("""COMPUTED_VALUE"""),"Touch Controls") -> Touch Controls | D76: =IFERROR(__xludf.DUMMYFUNCTION("""COMPUTED_VALUE"""),"Active") -> Active | E76: =IFERROR(__xludf.DUMMYFUNCTION("""COMPUTED_VALUE"""),43451.0) -> 43451 | G76: =IFERROR(__xludf.DUMMYFUNCTION("""COMPUTED_VALUE"""),81.93333333333334) -> 81.933333 | H76: =IFERROR(__xludf.DUMMYFUNCTION("""COMPUTED_VALUE"""),42955.0) -> 42955 | I76: =IFERROR(__xludf.DUMMYFUNCTION("""COMPUTED_VALUE"""),1.3583333333333334) -> 1.3583333 | J76: =IFERROR(__xludf.DUMMYFUNCTION("""COMPUTED_VALUE"""),88.0) -> 88 | K76: =IFERROR(__xludf.DUMMYFUNCTION("""COMPUTED_VALUE"""),7.5) -> 7.5 | L76: =IFERROR(__xludf.DUMMYFUNCTION("""COMPUTED_VALUE"""),"Action / Action-Adventure") -> Action / Action-Adventure
A77: =IFERROR(__xludf.DUMMYFUNCTION("""COMPUTED_VALUE"""),"Psychonauts") -> Psychonauts | B77: =IFERROR(__xludf.DUMMYFUNCTION("""COMPUTED_VALUE"""),"Xbox / PC") -> Xbox / PC | C77: =IFERROR(__xludf.DUMMYFUNCTION("""COMPUTED_VALUE"""),"Touch Controls") -> Touch Controls | D77: =IFERROR(__xludf.DUMMYFUNCTION("""COMPUTED_VALUE"""),"Active") -> Active | E77: =IFERROR(__xludf.DUMMYFUNCTION("""COMPUTED_VALUE"""),44329.0) -> 44329 | G77: =IFERROR(__xludf.DUMMYFUNCTION("""COMPUTED_VALUE"""),53.06666666666667) -> 53.066667 | H77: =IFERROR(__xludf.DUMMYFUNCTION("""COMPUTED_VALUE"""),38461.0) -> 38461 | I77: =IFERROR(__xludf.DUMMYFUNCTION("""COMPUTED_VALUE"""),16.066666666666666) -> 16.066667 | J77: =IFERROR(__xludf.DUMMYFUNCTION("""COMPUTED_VALUE"""),87.5) -> 87.5 | K77: =IFERROR(__xludf.DUMMYFUNCTION("""COMPUTED_VALUE"""),12.5) -> 12.5 | L77: =IFERROR(__xludf.DUMMYFUNCTION("""COMPUTED_VALUE"""),"Platformer / Action-Adventure") -> Platformer / Action-Adventure
A78: =IFERROR(__xludf.DUMMYFUNCTION("""COMPUTED_VALUE"""),"Injustice 2") -> Injustice 2 | B78: =IFERROR(__xludf.DUMMYFUNCTION("""COMPUTED_VALUE"""),"Xbox / PC") -> Xbox / PC | C78: =IFERROR(__xludf.DUMMYFUNCTION("""COMPUTED_VALUE"""),"Yes") -> Yes | D78: =IFERROR(__xludf.DUMMYFUNCTION("""COMPUTED_VALUE"""),"Active") -> Active | E78: =IFERROR(__xludf.DUMMYFUNCTION("""COMPUTED_VALUE"""),44203.0) -> 44203 | G78: =IFERROR(__xludf.DUMMYFUNCTION("""COMPUTED_VALUE"""),57.266666666666666) -> 57.266667 | H78: =IFERROR(__xludf.DUMMYFUNCTION("""COMPUTED_VALUE"""),42871.0) -> 42871 | I78: =IFERROR(__xludf.DUMMYFUNCTION("""COMPUTED_VALUE"""),3.6416666666666666) -> 3.6416667 | J78: =IFERROR(__xludf.DUMMYFUNCTION("""COMPUTED_VALUE"""),87.5) -> 87.5 | K78: =IFERROR(__xludf.DUMMYFUNCTION("""COMPUTED_VALUE"""),5.5) -> 5.5 | L78: =IFERROR(__xludf.DUMMYFUNCTION("""COMPUTED_VALUE"""),"Fighting") -> Fighting
A79: =IFERROR(__xludf.DUMMYFUNCTION("""COMPUTED_VALUE"""),"Legends of Runeterra") -> Legends of Runeterra | B79: =IFERROR(__xludf.DUMMYFUNCTION("""COMPUTED_VALUE"""),"PC") -> PC | D79: =IFERROR(__xludf.DUMMYFUNCTION("""COMPUTED_VALUE"""),"Active") -> Active | E79: =IFERROR(__xludf.DUMMYFUNCTION("""COMPUTED_VALUE"""),44907.0) -> 44907 | G79: =IFERROR(__xludf.DUMMYFUNCTION("""COMPUTED_VALUE"""),34.1) -> 34.1 | H79: =IFERROR(__xludf.DUMMYFUNCTION("""COMPUTED_VALUE"""),43951.0) -> 43951 | I79: =IFERROR(__xludf.DUMMYFUNCTION("""COMPUTED_VALUE"""),2.6166666666666667) -> 2.6166667 | J79: =IFERROR(__xludf.DUMMYFUNCTION("""COMPUTED_VALUE"""),87.0) -> 87 | K79: =IFERROR(__xludf.DUMMYFUNCTION("""COMPUTED_VALUE"""),44.0) -> 44 | L79: =IFERROR(__xludf.DUMMYFUNCTION("""COMPUTED_VALUE"""),"Card Game") -> Card Game
A80: =IFERROR(__xludf.DUMMYFUNCTION("""COMPUTED_VALUE"""),"Pentiment") -> Pentiment | B80: =IFERROR(__xludf.DUMMYFUNCTION("""COMPUTED_VALUE"""),"Xbox / PC") -> Xbox / PC | C80: =IFERROR(__xludf.DUMMYFUNCTION("""COMPUTED_VALUE"""),"Touch Controls, M+KB") -> Touch Controls, M+KB | D80: =IFERROR(__xludf.DUMMYFUNCTION("""COMPUTED_VALUE"""),"Active") -> Active | E80: =IFERROR(__xludf.DUMMYFUNCTION("""COMPUTED_VALUE"""),44880.0) -> 44880 | G80: =IFERROR(__xludf.DUMMYFUNCTION("""COMPUTED_VALUE"""),35.0) -> 35 | H80: =IFERROR(__xludf.DUMMYFUNCTION("""COMPUTED_VALUE"""),44880.0) -> 44880 | I80: =IFERROR(__xludf.DUMMYFUNCTION("""COMPUTED_VALUE"""),0.0) -> 0 | J80: =IFERROR(__xludf.DUMMYFUNCTION("""COMPUTED_VALUE"""),87.0) -> 87 | K80: =IFERROR(__xludf.DUMMYFUNCTION("""COMPUTED_VALUE"""),18.5) -> 18.5 | L80: =IFERROR(__xludf.DUMMYFUNCTION("""COMPUTED_VALUE"""),"Adventure") -> Adventure
A81: =IFERROR(__xludf.DUMMYFUNCTION("""COMPUTED_VALUE"""),"Return to Monkey Island") -> Return to Monkey Island | B81: =IFERROR(__xludf.DUMMYFUNCTION("""COMPUTED_VALUE"""),"Xbox / PC") -> Xbox / PC | C81: =IFERROR(__xludf.DUMMYFUNCTION("""COMPUTED_VALUE"""),"Yes") -> Yes | D81: =IFERROR(__xludf.DUMMYFUNCTION("""COMPUTED_VALUE"""),"Active") -> Active | E81: =IFERROR(__xludf.DUMMYFUNCTION("""COMPUTED_VALUE"""),44873.0) -> 44873 | G81: =IFERROR(__xludf.DUMMYFUNCTION("""COMPUTED_VALUE"""),35.233333333333334) -> 35.233333 | H81: =IFERROR(__xludf.DUMMYFUNCTION("""COMPUTED_VALUE"""),44823.0) -> 44823 | I81: =IFERROR(__xludf.DUMMYFUNCTION("""COMPUTED_VALUE"""),0.1361111111111111) -> 0.13611111 | J81: =IFERROR(__xludf.DUMMYFUNCTION("""COMPUTED_VALUE"""),87.0) -> 87 | K81: =IFERROR(__xludf.DUMMYFUNCTION("""COMPUTED_VALUE"""),10.5) -> 10.5 | L81: =IFERROR(__xludf.DUMMYFUNCTION("""COMPUTED_VALUE"""),"Adventure") -> Adventure
A82: =IFERROR(__xludf.DUMMYFUNCTION("""COMPUTED_VALUE"""),"Assassin's Creed Odyssey") -> Assassin's Creed Odyssey | B82: =IFERROR(__xludf.DUMMYFUNCTION("""COMPUTED_VALUE"""),"Xbox / PC") -> Xbox / PC | C82: =IFERROR(__xludf.DUMMYFUNCTION("""COMPUTED_VALUE"""),"Touch Controls") -> Touch Controls | D82: =IFERROR(__xludf.DUMMYFUNCTION("""COMPUTED_VALUE"""),"Active") -> Active | E82: =IFERROR(__xludf.DUMMYFUNCTION("""COMPUTED_VALUE"""),44819.0) -> 44819 | G82: =IFERROR(__xludf.DUMMYFUNCTION("""COMPUTED_VALUE"""),37.0) -> 37 | H82: =IFERROR(__xludf.DUMMYFUNCTION("""COMPUTED_VALUE"""),43375.0) -> 43375 | I82: =IFERROR(__xludf.DUMMYFUNCTION("""COMPUTED_VALUE"""),3.952777777777778) -> 3.9527778 | J82: =IFERROR(__xludf.DUMMYFUNCTION("""COMPUTED_VALUE"""),87.0) -> 87 | K82: =IFERROR(__xludf.DUMMYFUNCTION("""COMPUTED_VALUE"""),44.5) -> 44.5 | L82: =IFERROR(__xludf.DUMMYFUNCTION("""COMPUTED_VALUE"""),"RPG / Action-Adventure") -> RPG / Action-Adventure
A83: =IFERROR(__xludf.DUMMYFUNCTION("""COMPUTED_VALUE"""),"Vampire Survivors") -> Vampire Survivors | B83: =IFERROR(__xludf.DUMMYFUNCTION("""COMPUTED_VALUE"""),"Xbox / PC") -> Xbox / PC | C83: =IFERROR(__xludf.DUMMYFUNCTION("""COMPUTED_VALUE"""),"Yes") -> Yes | D83: =IFERROR(__xludf.DUMMYFUNCTION("""COMPUTED_VALUE"""),"Active") -> Active | E83: =IFERROR(__xludf.DUMMYFUNCTION("""COMPUTED_VALUE"""),44700.0) -> 44700 | G83: =IFERROR(__xludf.DUMMYFUNCTION("""COMPUTED_VALUE"""),40.86666666666667) -> 40.866667 | H83: =IFERROR(__xludf.DUMMYFUNCTION("""COMPUTED_VALUE"""),44547.0) -> 44547 | I83: =IFERROR(__xludf.DUMMYFUNCTION("""COMPUTED_VALUE"""),0.4222222222222222) -> 0.42222222 | J83: =IFERROR(__xludf.DUMMYFUNCTION("""COMPUTED_VALUE"""),87.0) -> 87 | K83: =IFERROR(__xludf.DUMMYFUNCTION("""COMPUTED_VALUE"""),4.5) -> 4.5 | L83: =IFERROR(__xludf.DUMMYFUNCTION("""COMPUTED_VALUE"""),"Action") -> Action
A84: =IFERROR(__xludf.DUMMYFUNCTION("""COMPUTED_VALUE"""),"Halo 4") -> Halo 4 | B84: =IFERROR(__xludf.DUMMYFUNCTION("""COMPUTED_VALUE"""),"Xbox / PC") -> Xbox / PC | D84: =IFERROR(__xludf.DUMMYFUNCTION("""COMPUTED_VALUE"""),"Active") -> Active | E84: =IFERROR(__xludf.DUMMYFUNCTION("""COMPUTED_VALUE"""),44152.0) -> 44152 | G84: =IFERROR(__xludf.DUMMYFUNCTION("""COMPUTED_VALUE"""),58.93333333333334) -> 58.933333 | H84: =IFERROR(__xludf.DUMMYFUNCTION("""COMPUTED_VALUE"""),41218.0) -> 41218 | I84: =IFERROR(__xludf.DUMMYFUNCTION("""COMPUTED_VALUE"""),8.033333333333333) -> 8.0333333 | J84: =IFERROR(__xludf.DUMMYFUNCTION("""COMPUTED_VALUE"""),87.0) -> 87 | K84: =IFERROR(__xludf.DUMMYFUNCTION("""COMPUTED_VALUE"""),8.0) -> 8 | L84: =IFERROR(__xludf.DUMMYFUNCTION("""COMPUTED_VALUE"""),"Action / First-Person Shooter") -> Action / First-Person Shooter
A85: =IFERROR(__xludf.DUMMYFUNCTION("""COMPUTED_VALUE"""),"Battlefield 1: Revolution") -> Battlefield 1: Revolution | B85: =IFERROR(__xludf.DUMMYFUNCTION("""COMPUTED_VALUE"""),"Xbox / PC") -> Xbox / PC | C85: =IFERROR(__xludf.DUMMYFUNCTION("""COMPUTED_VALUE"""),"Yes") -> Yes | D85: =IFERROR(__xludf.DUMMYFUNCTION("""COMPUTED_VALUE"""),"Active") -> Active | E85: =IFERROR(__xludf.DUMMYFUNCTION("""COMPUTED_VALUE"""),44145.0) -> 44145 | G85: =IFERROR(__xludf.DUMMYFUNCTION("""COMPUTED_VALUE"""),59.166666666666664) -> 59.166667 | H85: =IFERROR(__xludf.DUMMYFUNCTION("""COMPUTED_VALUE"""),42664.0) -> 42664 | I85: =IFERROR(__xludf.DUMMYFUNCTION("""COMPUTED_VALUE"""),4.052777777777778) -> 4.0527778 | J85: =IFERROR(__xludf.DUMMYFUNCTION("""COMPUTED_VALUE"""),87.0) -> 87 | K85: =IFERROR(__xludf.DUMMYFUNCTION("""COMPUTED_VALUE"""),6.5) -> 6.5 | L85: =IFERROR(__xludf.DUMMYFUNCTION("""COMPUTED_VALUE"""),"First-Person Shooter") -> First-Person Shooter
A86: =IFERROR(__xludf.DUMMYFUNCTION("""COMPUTED_VALUE"""),"Titanfall 2: Ultimate Edition") -> Titanfall 2: Ultimate Edition | B86: =IFERROR(__xludf.DUMMYFUNCTION("""COMPUTED_VALUE"""),"Xbox / PC") -> Xbox / PC | D86: =IFERROR(__xludf.DUMMYFUNCTION("""COMPUTED_VALUE"""),"Active") -> Active | E86: =IFERROR(__xludf.DUMMYFUNCTION("""COMPUTED_VALUE"""),44145.0) -> 44145 | G86: =IFERROR(__xludf.DUMMYFUNCTION("""COMPUTED_VALUE"""),59.166666666666664) -> 59.166667 | H86: =IFERROR(__xludf.DUMMYFUNCTION("""COMPUTED_VALUE"""),42671.0) -> 42671 | I86: =IFERROR(__xludf.DUMMYFUNCTION("""COMPUTED_VALUE"""),4.033333333333333) -> 4.0333333 | J86: =IFERROR(__xludf.DUMMYFUNCTION("""COMPUTED_VALUE"""),87.0) -> 87 | K86: =IFERROR(__xludf.DUMMYFUNCTION("""COMPUTED_VALUE"""),6.0) -> 6 | L86: =IFERROR(__xludf.DUMMYFUNCTION("""COMPUTED_VALUE"""),"First-Person Shooter") -> First-Person Shooter
A87: =IFERROR(__xludf.DUMMYFUNCTION("""COMPUTED_VALUE"""),"Prince of Persia: The Lost Crown") -> Prince of Persia: The Lost Crown | B87: =IFERROR(__xludf.DUMMYFUNCTION("""COMPUTED_VALUE"""),"Xbox / PC") -> Xbox / PC | C87: =IFERROR(__xludf.DUMMYFUNCTION("""COMPUTED_VALUE"""),"Yes") -> Yes | D87: =IFERROR(__xludf.DUMMYFUNCTION("""COMPUTED_VALUE"""),"Active") -> Active | E87: =IFERROR(__xludf.DUMMYFUNCTION("""COMPUTED_VALUE"""),45931.0) -> 45931 | G87: =IFERROR(__xludf.DUMMYFUNCTION("""COMPUTED_VALUE"""),0.4666666666666667) -> 0.46666667 | H87: =IFERROR(__xludf.DUMMYFUNCTION("""COMPUTED_VALUE"""),45309.0) -> 45309 | I87: =IFERROR(__xludf.DUMMYFUNCTION("""COMPUTED_VALUE"""),1.7027777777777777) -> 1.7027778 | J87: =IFERROR(__xludf.DUMMYFUNCTION("""COMPUTED_VALUE"""),86.0) -> 86 | K87: =IFERROR(__xludf.DUMMYFUNCTION("""COMPUTED_VALUE"""),17.0) -> 17 | L87: =IFERROR(__xludf.DUMMYFUNCTION("""COMPUTED_VALUE"""),"Metroidvania") -> Metroidvania
A88: =IFERROR(__xludf.DUMMYFUNCTION("""COMPUTED_VALUE"""),"Rise of the Tomb Raider") -> Rise of the Tomb Raider | B88: =IFERROR(__xludf.DUMMYFUNCTION("""COMPUTED_VALUE"""),"Xbox / PC") -> Xbox / PC | C88: =IFERROR(__xludf.DUMMYFUNCTION("""COMPUTED_VALUE"""),"Yes") -> Yes | D88: =IFERROR(__xludf.DUMMYFUNCTION("""COMPUTED_VALUE"""),"Active") -> Active | E88: =IFERROR(__xludf.DUMMYFUNCTION("""COMPUTED_VALUE"""),45839.0) -> 45839 | G88: =IFERROR(__xludf.DUMMYFUNCTION("""COMPUTED_VALUE"""),3.4666666666666663) -> 3.4666667 | H88: =IFERROR(__xludf.DUMMYFUNCTION("""COMPUTED_VALUE"""),42318.0) -> 42318 | I88: =IFERROR(__xludf.DUMMYFUNCTION("""COMPUTED_VALUE"""),9.641666666666667) -> 9.6416667 | J88: =IFERROR(__xludf.DUMMYFUNCTION("""COMPUTED_VALUE"""),86.0) -> 86 | K88: =IFERROR(__xludf.DUMMYFUNCTION("""COMPUTED_VALUE"""),13.5) -> 13.5 | L88: =IFERROR(__xludf.DUMMYFUNCTION("""COMPUTED_VALUE"""),"Shooter / Action-Adventure") -> Shooter / Action-Adventure
A89: =IFERROR(__xludf.DUMMYFUNCTION("""COMPUTED_VALUE"""),"Warhammer 40,000: Rogue Trader") -> Warhammer 40,000: Rogue Trader | B89: =IFERROR(__xludf.DUMMYFUNCTION("""COMPUTED_VALUE"""),"Xbox / PC") -> Xbox / PC | C89: =IFERROR(__xludf.DUMMYFUNCTION("""COMPUTED_VALUE"""),"Yes") -> Yes | D89: =IFERROR(__xludf.DUMMYFUNCTION("""COMPUTED_VALUE"""),"Active") -> Active | E89: =IFERROR(__xludf.DUMMYFUNCTION("""COMPUTED_VALUE"""),45708.0) -> 45708 | G89: =IFERROR(__xludf.DUMMYFUNCTION("""COMPUTED_VALUE"""),7.833333333333334) -> 7.8333333 | H89: =IFERROR(__xludf.DUMMYFUNCTION("""COMPUTED_VALUE"""),45559.0) -> 45559 | I89: =IFERROR(__xludf.DUMMYFUNCTION("""COMPUTED_VALUE"""),0.40555555555555556) -> 0.40555556 | J89: =IFERROR(__xludf.DUMMYFUNCTION("""COMPUTED_VALUE"""),86.0) -> 86 | K89: =IFERROR(__xludf.DUMMYFUNCTION("""COMPUTED_VALUE"""),65.0) -> 65 | L89: =IFERROR(__xludf.DUMMYFUNCTION("""COMPUTED_VALUE"""),"RPG") -> RPG
A90: =IFERROR(__xludf.DUMMYFUNCTION("""COMPUTED_VALUE"""),"Indiana Jones and the Great Circle") -> Indiana Jones and the Great Circle | B90: =IFERROR(__xludf.DUMMYFUNCTION("""COMPUTED_VALUE"""),"Xbox / PC") -> Xbox / PC | C90: =IFERROR(__xludf.DUMMYFUNCTION("""COMPUTED_VALUE"""),"Yes") -> Yes | D90: =IFERROR(__xludf.DUMMYFUNCTION("""COMPUTED_VALUE"""),"Active") -> Active | E90: =IFERROR(__xludf.DUMMYFUNCTION("""COMPUTED_VALUE"""),45635.0) -> 45635 | G90: =IFERROR(__xludf.DUMMYFUNCTION("""COMPUTED_VALUE"""),10.2) -> 10.2 | H90: =IFERROR(__xludf.DUMMYFUNCTION("""COMPUTED_VALUE"""),45635.0) -> 45635 | I90: =IFERROR(__xludf.DUMMYFUNCTION("""COMPUTED_VALUE"""),0.0) -> 0 | J90: =IFERROR(__xludf.DUMMYFUNCTION("""COMPUTED_VALUE"""),86.0) -> 86 | K90: =IFERROR(__xludf.DUMMYFUNCTION("""COMPUTED_VALUE"""),15.0) -> 15 | L90: =IFERROR(__xludf.DUMMYFUNCTION("""COMPUTED_VALUE"""),"Action-Adventure") -> Action-Adventure
A91: =IFERROR(__xludf.DUMMYFUNCTION("""COMPUTED_VALUE"""),"Frostpunk 2") -> Frostpunk 2 | B91: =IFERROR(__xludf.DUMMYFUNCTION("""COMPUTED_VALUE"""),"Xbox / PC") -> Xbox / PC | C91: =IFERROR(__xludf.DUMMYFUNCTION("""COMPUTED_VALUE"""),"Yes") -> Yes | D91: =IFERROR(__xludf.DUMMYFUNCTION("""COMPUTED_VALUE"""),"Active") -> Active | E91: =IFERROR(__xludf.DUMMYFUNCTION("""COMPUTED_VALUE"""),45555.0) -> 45555 | G91: =IFERROR(__xludf.DUMMYFUNCTION("""COMPUTED_VALUE"""),12.833333333333332) -> 12.833333 | H91: =IFERROR(__xludf.DUMMYFUNCTION("""COMPUTED_VALUE"""),45555.0) -> 45555 | I91: =IFERROR(__xludf.DUMMYFUNCTION("""COMPUTED_VALUE"""),0.0) -> 0 | J91: =IFERROR(__xludf.DUMMYFUNCTION("""COMPUTED_VALUE"""),86.0) -> 86 | K91: =IFERROR(__xludf.DUMMYFUNCTION("""COMPUTED_VALUE"""),11.0) -> 11 | L91: =IFERROR(__xludf.DUMMYFUNCTION("""COMPUTED_VALUE"""),"Simulation") -> Simulation
A92: =IFERROR(__xludf.DUMMYFUNCTION("""COMPUTED_VALUE"""),"Tomb Raider: Definitive Edition") -> Tomb Raider: Definitive Edition | B92: =IFERROR(__xludf.DUMMYFUNCTION("""COMPUTED_VALUE"""),"Xbox / PC") -> Xbox / PC | C92: =IFERROR(__xludf.DUMMYFUNCTION("""COMPUTED_VALUE"""),"Yes") -> Yes | D92: =IFERROR(__xludf.DUMMYFUNCTION("""COMPUTED_VALUE"""),"Active") -> Active | E92: =IFERROR(__xludf.DUMMYFUNCTION("""COMPUTED_VALUE"""),45414.0) -> 45414 | G92: =IFERROR(__xludf.DUMMYFUNCTION("""COMPUTED_VALUE"""),17.433333333333334) -> 17.433333 | H92: =IFERROR(__xludf.DUMMYFUNCTION("""COMPUTED_VALUE"""),41338.0) -> 41338 | I92: =IFERROR(__xludf.DUMMYFUNCTION("""COMPUTED_VALUE"""),11.158333333333333) -> 11.158333 | J92: =IFERROR(__xludf.DUMMYFUNCTION("""COMPUTED_VALUE"""),86.0) -> 86 | K92: =IFERROR(__xludf.DUMMYFUNCTION("""COMPUTED_VALUE"""),11.5) -> 11.5 | L92: =IFERROR(__xludf.DUMMYFUNCTION("""COMPUTED_VALUE"""),"Shooter / Platformer / Action-Adventure") -> Shooter / Platformer / Action-Adventure
A93: =IFERROR(__xludf.DUMMYFUNCTION("""COMPUTED_VALUE"""),"Diablo IV") -> Diablo IV | B93: =IFERROR(__xludf.DUMMYFUNCTION("""COMPUTED_VALUE"""),"Xbox / PC") -> Xbox / PC | D93: =IFERROR(__xludf.DUMMYFUNCTION("""COMPUTED_VALUE"""),"Active") -> Active | E93: =IFERROR(__xludf.DUMMYFUNCTION("""COMPUTED_VALUE"""),45379.0) -> 45379 | G93: =IFERROR(__xludf.DUMMYFUNCTION("""COMPUTED_VALUE"""),18.566666666666666) -> 18.566667 | H93: =IFERROR(__xludf.DUMMYFUNCTION("""COMPUTED_VALUE"""),45078.0) -> 45078 | I93: =IFERROR(__xludf.DUMMYFUNCTION("""COMPUTED_VALUE"""),0.825) -> 0.825 | J93: =IFERROR(__xludf.DUMMYFUNCTION("""COMPUTED_VALUE"""),86.0) -> 86 | K93: =IFERROR(__xludf.DUMMYFUNCTION("""COMPUTED_VALUE"""),27.0) -> 27 | L93: =IFERROR(__xludf.DUMMYFUNCTION("""COMPUTED_VALUE"""),"RPG") -> RPG
A94: =IFERROR(__xludf.DUMMYFUNCTION("""COMPUTED_VALUE"""),"Spiritfarer") -> Spiritfarer | B94: =IFERROR(__xludf.DUMMYFUNCTION("""COMPUTED_VALUE"""),"Xbox / PC") -> Xbox / PC | C94: =IFERROR(__xludf.DUMMYFUNCTION("""COMPUTED_VALUE"""),"Touch Controls") -> Touch Controls | D94: =IFERROR(__xludf.DUMMYFUNCTION("""COMPUTED_VALUE"""),"Active") -> Active | E94: =IFERROR(__xludf.DUMMYFUNCTION("""COMPUTED_VALUE"""),45182.0) -> 45182 | G94: =IFERROR(__xludf.DUMMYFUNCTION("""COMPUTED_VALUE"""),25.06666666666667) -> 25.066667 | H94: =IFERROR(__xludf.DUMMYFUNCTION("""COMPUTED_VALUE"""),44061.0) -> 44061 | I94: =IFERROR(__xludf.DUMMYFUNCTION("""COMPUTED_VALUE"""),3.0694444444444446) -> 3.0694444 | J94: =IFERROR(__xludf.DUMMYFUNCTION("""COMPUTED_VALUE"""),86.0) -> 86 | K94: =IFERROR(__xludf.DUMMYFUNCTION("""COMPUTED_VALUE"""),21.0) -> 21 | L94: =IFERROR(__xludf.DUMMYFUNCTION("""COMPUTED_VALUE"""),"Adventure") -> Adventure
A95: =IFERROR(__xludf.DUMMYFUNCTION("""COMPUTED_VALUE"""),"Teenage Mutant Ninja Turtles: Shredder's Revenge") -> Teenage Mutant Ninja Turtles: Shredder's Revenge | B95: =IFERROR(__xludf.DUMMYFUNCTION("""COMPUTED_VALUE"""),"Xbox / PC") -> Xbox / PC | C95: =IFERROR(__xludf.DUMMYFUNCTION("""COMPUTED_VALUE"""),"Touch Controls") -> Touch Controls | D95: =IFERROR(__xludf.DUMMYFUNCTION("""COMPUTED_VALUE"""),"Active") -> Active | E95: =IFERROR(__xludf.DUMMYFUNCTION("""COMPUTED_VALUE"""),44728.0) -> 44728 | G95: =IFERROR(__xludf.DUMMYFUNCTION("""COMPUTED_VALUE"""),39.96666666666667) -> 39.966667 | H95: =IFERROR(__xludf.DUMMYFUNCTION("""COMPUTED_VALUE"""),44728.0) -> 44728 | I95: =IFERROR(__xludf.DUMMYFUNCTION("""COMPUTED_VALUE"""),0.0) -> 0 | J95: =IFERROR(__xludf.DUMMYFUNCTION("""COMPUTED_VALUE"""),86.0) -> 86 | K95: =IFERROR(__xludf.DUMMYFUNCTION("""COMPUTED_VALUE"""),2.5) -> 2.5 | L95: =IFERROR(__xludf.DUMMYFUNCTION("""COMPUTED_VALUE"""),"Brawler") -> Brawler
A96: =IFERROR(__xludf.DUMMYFUNCTION("""COMPUTED_VALUE"""),"Fallout 2") -> Fallout 2 | B96: =IFERROR(__xludf.DUMMYFUNCTION("""COMPUTED_VALUE"""),"PC") -> PC | D96: =IFERROR(__xludf.DUMMYFUNCTION("""COMPUTED_VALUE"""),"Active") -> Active | E96: =IFERROR(__xludf.DUMMYFUNCTION("""COMPUTED_VALUE"""),44360.0) -> 44360 | G96: =IFERROR(__xludf.DUMMYFUNCTION("""COMPUTED_VALUE"""),52.06666666666666) -> 52.066667 | H96: =IFERROR(__xludf.DUMMYFUNCTION("""COMPUTED_VALUE"""),36068.0) -> 36068 | I96: =IFERROR(__xludf.DUMMYFUNCTION("""COMPUTED_VALUE"""),22.70277777777778) -> 22.702778 | J96: =IFERROR(__xludf.DUMMYFUNCTION("""COMPUTED_VALUE"""),86.0) -> 86 | K96: =IFERROR(__xludf.DUMMYFUNCTION("""COMPUTED_VALUE"""),30.5) -> 30.5 | L96: =IFERROR(__xludf.DUMMYFUNCTION("""COMPUTED_VALUE"""),"RPG") -> RPG
A97: =IFERROR(__xludf.DUMMYFUNCTION("""COMPUTED_VALUE"""),"The Sims 3") -> The Sims 3 | B97: =IFERROR(__xludf.DUMMYFUNCTION("""COMPUTED_VALUE"""),"PC") -> PC | D97: =IFERROR(__xludf.DUMMYFUNCTION("""COMPUTED_VALUE"""),"Active") -> Active | E97: =IFERROR(__xludf.DUMMYFUNCTION("""COMPUTED_VALUE"""),44273.0) -> 44273 | G97: =IFERROR(__xludf.DUMMYFUNCTION("""COMPUTED_VALUE"""),54.900000000000006) -> 54.9 | H97: =IFERROR(__xludf.DUMMYFUNCTION("""COMPUTED_VALUE"""),39966.0) -> 39966 | I97: =IFERROR(__xludf.DUMMYFUNCTION("""COMPUTED_VALUE"""),11.794444444444444) -> 11.794444 | J97: =IFERROR(__xludf.DUMMYFUNCTION("""COMPUTED_VALUE"""),86.0) -> 86 | K97: =IFERROR(__xludf.DUMMYFUNCTION("""COMPUTED_VALUE"""),68.5) -> 68.5 | L97: =IFERROR(__xludf.DUMMYFUNCTION("""COMPUTED_VALUE"""),"Simulation") -> Simulation
A98: =IFERROR(__xludf.DUMMYFUNCTION("""COMPUTED_VALUE"""),"Dragon Age: Inquisition - Game of the Year Edition") -> Dragon Age: Inquisition - Game of the Year Edition | B98: =IFERROR(__xludf.DUMMYFUNCTION("""COMPUTED_VALUE"""),"Xbox / PC") -> Xbox / PC | C98: =IFERROR(__xludf.DUMMYFUNCTION("""COMPUTED_VALUE"""),"Yes") -> Yes | D98: =IFERROR(__xludf.DUMMYFUNCTION("""COMPUTED_VALUE"""),"Active") -> Active | E98: =IFERROR(__xludf.DUMMYFUNCTION("""COMPUTED_VALUE"""),44145.0) -> 44145 | G98: =IFERROR(__xludf.DUMMYFUNCTION("""COMPUTED_VALUE"""),59.166666666666664) -> 59.166667 | H98: =IFERROR(__xludf.DUMMYFUNCTION("""COMPUTED_VALUE"""),41961.0) -> 41961 | I98: =IFERROR(__xludf.DUMMYFUNCTION("""COMPUTED_VALUE"""),5.977777777777778) -> 5.9777778 | J98: =IFERROR(__xludf.DUMMYFUNCTION("""COMPUTED_VALUE"""),86.0) -> 86 | K98: =IFERROR(__xludf.DUMMYFUNCTION("""COMPUTED_VALUE"""),46.5) -> 46.5 | L98: =IFERROR(__xludf.DUMMYFUNCTION("""COMPUTED_VALUE"""),"Action / RPG") -> Action / RPG
A99: =IFERROR(__xludf.DUMMYFUNCTION("""COMPUTED_VALUE"""),"Dragon Age: Origins - Ultimate Edition") -> Dragon Age: Origins - Ultimate Edition | B99: =IFERROR(__xludf.DUMMYFUNCTION("""COMPUTED_VALUE"""),"Xbox / PC") -> Xbox / PC | C99: =IFERROR(__xludf.DUMMYFUNCTION("""COMPUTED_VALUE"""),"Touch Controls") -> Touch Controls | D99: =IFERROR(__xludf.DUMMYFUNCTION("""COMPUTED_VALUE"""),"Active") -> Active | E99: =IFERROR(__xludf.DUMMYFUNCTION("""COMPUTED_VALUE"""),44145.0) -> 44145 | G99: =IFERROR(__xludf.DUMMYFUNCTION("""COMPUTED_VALUE"""),59.166666666666664) -> 59.166667 | H99: =IFERROR(__xludf.DUMMYFUNCTION("""COMPUTED_VALUE"""),40120.0) -> 40120 | I99: =IFERROR(__xludf.DUMMYFUNCTION("""COMPUTED_VALUE"""),11.019444444444444) -> 11.019444 | J99: =IFERROR(__xludf.DUMMYFUNCTION("""COMPUTED_VALUE"""),86.0) -> 86 | K99: =IFERROR(__xludf.DUMMYFUNCTION("""COMPUTED_VALUE"""),40.5) -> 40.5 | L99: =IFERROR(__xludf.DUMMYFUNCTION("""COMPUTED_VALUE"""),"RPG") -> RPG
A100: =IFERROR(__xludf.DUMMYFUNCTION("""COMPUTED_VALUE"""),"Wasteland 3") -> Wasteland 3 | B100: =IFERROR(__xludf.DUMMYFUNCTION("""COMPUTED_VALUE"""),"Xbox / PC") -> Xbox / PC | C100: =IFERROR(__xludf.DUMMYFUNCTION("""COMPUTED_VALUE"""),"Touch Controls") -> Touch Controls | D100: =IFERROR(__xludf.DUMMYFUNCTION("""COMPUTED_VALUE"""),"Active") -> Active | E100: =IFERROR(__xludf.DUMMYFUNCTION("""COMPUTED_VALUE"""),44071.0) -> 44071 | G100: =IFERROR(__xludf.DUMMYFUNCTION("""COMPUTED_VALUE"""),61.56666666666666) -> 61.566667 | H100: =IFERROR(__xludf.DUMMYFUNCTION("""COMPUTED_VALUE"""),44071.0) -> 44071 | I100: =IFERROR(__xludf.DUMMYFUNCTION("""COMPUTED_VALUE"""),0.0) -> 0 | J100: =IFERROR(__xludf.DUMMYFUNCTION("""COMPUTED_VALUE"""),86.0) -> 86 | K100: =IFERROR(__xludf.DUMMYFUNCTION("""COMPUTED_VALUE"""),36.5) -> 36.5 | L100: =IFERROR(__xludf.DUMMYFUNCTION("""COMPUTED_VALUE"""),"RPG") -> RPG
...

Sheet xCloud
A1: xCloud Games by Metacritic Score | B1: =COUNTA(A3:A801) -> 538
A2: =IFERROR(__xludf.DUMMYFUNCTION("SORT(FILTER('Master List'!A2:M801, NOT(ISBLANK('Master List'!C2:C801)), NOT(REGEXMATCH('Master List'!D2:D801, ""Removed"")) ), 10, false)"),"Game") -> Game | B2: =IFERROR(__xludf.DUMMYFUNCTION("""COMPUTED_VALUE"""),"System") -> System | C2: =IFERROR(__xludf.DUMMYFUNCTION("""COMPUTED_VALUE"""),"xCloud") -> xCloud | D2: =IFERROR(__xludf.DUMMYFUNCTION("""COMPUTED_VALUE"""),"Status") -> Status | E2: =IFERROR(__xludf.DUMMYFUNCTION("""COMPUTED_VALUE"""),"Added") -> Added | F2: =IFERROR(__xludf.DUMMYFUNCTION("""COMPUTED_VALUE"""),"Removed") -> Removed | G2: =IFERROR(__xludf.DUMMYFUNCTION("""COMPUTED_VALUE"""),"Months") -> Months | H2: =IFERROR(__xludf.DUMMYFUNCTION("""COMPUTED_VALUE"""),"Release") -> Release | I2: =IFERROR(__xludf.DUMMYFUNCTION("""COMPUTED_VALUE"""),"Age") -> Age | J2: =IFERROR(__xludf.DUMMYFUNCTION("""COMPUTED_VALUE"""),"Metacritic") -> Metacritic | K2: =IFERROR(__xludf.DUMMYFUNCTION("""COMPUTED_VALUE"""),"Completion") -> Completion | L2: =IFERROR(__xludf.DUMMYFUNCTION("""COMPUTED_VALUE"""),"Genre") -> Genre | M2: =IFERROR(__xludf.DUMMYFUNCTION("""COMPUTED_VALUE"""),"Series X|S") -> Series X|S
A3: =IFERROR(__xludf.DUMMYFUNCTION("""COMPUTED_VALUE"""),"Grand Theft Auto V") -> Grand Theft Auto V | B3: =IFERROR(__xludf.DUMMYFUNCTION("""COMPUTED_VALUE"""),"Xbox / PC") -> Xbox / PC | C3: =IFERROR(__xludf.DUMMYFUNCTION("""COMPUTED_VALUE"""),"Yes") -> Yes | D3: =IFERROR(__xludf.DUMMYFUNCTION("""COMPUTED_VALUE"""),"Active") -> Active | E3: =IFERROR(__xludf.DUMMYFUNCTION("""COMPUTED_VALUE"""),45762.0) -> 45762 | G3: =IFERROR(__xludf.DUMMYFUNCTION("""COMPUTED_VALUE"""),6.0) -> 6 | H3: =IFERROR(__xludf.DUMMYFUNCTION("""COMPUTED_VALUE"""),41534.0) -> 41534 | I3: =IFERROR(__xludf.DUMMYFUNCTION("""COMPUTED_VALUE"""),11.577777777777778) -> 11.577778 | J3: =IFERROR(__xludf.DUMMYFUNCTION("""COMPUTED_VALUE"""),97.0) -> 97 | K3: =IFERROR(__xludf.DUMMYFUNCTION("""COMPUTED_VALUE"""),31.5) -> 31.5 | L3: =IFERROR(__xludf.DUMMYFUNCTION("""COMPUTED_VALUE"""),"Driving/Racing / Action-Adventure") -> Driving/Racing / Action-Adventure
A4: =IFERROR(__xludf.DUMMYFUNCTION("""COMPUTED_VALUE"""),"GoldenEye 007 (2023)") -> GoldenEye 007 (2023) | B4: =IFERROR(__xludf.DUMMYFUNCTION("""COMPUTED_VALUE"""),"Xbox") -> Xbox | C4: =IFERROR(__xludf.DUMMYFUNCTION("""COMPUTED_VALUE"""),"Yes") -> Yes | D4: =IFERROR(__xludf.DUMMYFUNCTION("""COMPUTED_VALUE"""),"Active") -> Active | E4: =IFERROR(__xludf.DUMMYFUNCTION("""COMPUTED_VALUE"""),44953.0) -> 44953 | G4: =IFERROR(__xludf.DUMMYFUNCTION("""COMPUTED_VALUE"""),32.6) -> 32.6 | H4: =IFERROR(__xludf.DUMMYFUNCTION("""COMPUTED_VALUE"""),44953.0) -> 44953 | I4: =IFERROR(__xludf.DUMMYFUNCTION("""COMPUTED_VALUE"""),0.0) -> 0 | J4: =IFERROR(__xludf.DUMMYFUNCTION("""COMPUTED_VALUE"""),96.0) -> 96 | K4: =IFERROR(__xludf.DUMMYFUNCTION("""COMPUTED_VALUE"""),10.0) -> 10 | L4: =IFERROR(__xludf.DUMMYFUNCTION("""COMPUTED_VALUE"""),"First-Person Shooter") -> First-Person Shooter
A5: =IFERROR(__xludf.DUMMYFUNCTION("""COMPUTED_VALUE"""),"Metaphor: ReFantazio") -> Metaphor: ReFantazio | B5: =IFERROR(__xludf.DUMMYFUNCTION("""COMPUTED_VALUE"""),"Xbox / PC") -> Xbox / PC | C5: =IFERROR(__xludf.DUMMYFUNCTION("""COMPUTED_VALUE"""),"Yes") -> Yes | D5: =IFERROR(__xludf.DUMMYFUNCTION("""COMPUTED_VALUE"""),"Active") -> Active | E5: =IFERROR(__xludf.DUMMYFUNCTION("""COMPUTED_VALUE"""),45806.0) -> 45806 | G5: =IFERROR(__xludf.DUMMYFUNCTION("""COMPUTED_VALUE"""),4.533333333333333) -> 4.5333333 | H5: =IFERROR(__xludf.DUMMYFUNCTION("""COMPUTED_VALUE"""),45576.0) -> 45576 | I5: =IFERROR(__xludf.DUMMYFUNCTION("""COMPUTED_VALUE"""),0.6333333333333333) -> 0.63333333 | J5: =IFERROR(__xludf.DUMMYFUNCTION("""COMPUTED_VALUE"""),94.0) -> 94 | K5: =IFERROR(__xludf.DUMMYFUNCTION("""COMPUTED_VALUE"""),66.0) -> 66 | L5: =IFERROR(__xludf.DUMMYFUNCTION("""COMPUTED_VALUE"""),"RPG") -> RPG | M5: =IFERROR(__xludf.DUMMYFUNCTION("""COMPUTED_VALUE"""),"Exclusive") -> Exclusive
A6: =IFERROR(__xludf.DUMMYFUNCTION("""COMPUTED_VALUE"""),"Quake") -> Quake | B6: =IFERROR(__xludf.DUMMYFUNCTION("""COMPUTED_VALUE"""),"Xbox / PC") -> Xbox / PC | C6: =IFERROR(__xludf.DUMMYFUNCTION("""COMPUTED_VALUE"""),"M+KB") -> M+KB | D6: =IFERROR(__xludf.DUMMYFUNCTION("""COMPUTED_VALUE"""),"Active") -> Active | E6: =IFERROR(__xludf.DUMMYFUNCTION("""COMPUTED_VALUE"""),44427.0) -> 44427 | G6: =IFERROR(__xludf.DUMMYFUNCTION("""COMPUTED_VALUE"""),49.866666666666674) -> 49.866667 | H6: =IFERROR(__xludf.DUMMYFUNCTION("""COMPUTED_VALUE"""),35269.0) -> 35269 | I6: =IFERROR(__xludf.DUMMYFUNCTION("""COMPUTED_VALUE"""),25.072222222222223) -> 25.072222 | J6: =IFERROR(__xludf.DUMMYFUNCTION("""COMPUTED_VALUE"""),94.0) -> 94 | K6: =IFERROR(__xludf.DUMMYFUNCTION("""COMPUTED_VALUE"""),5.5) -> 5.5 | L6: =IFERROR(__xludf.DUMMYFUNCTION("""COMPUTED_VALUE"""),"First-Person Shooter") -> First-Person Shooter
A7: =IFERROR(__xludf.DUMMYFUNCTION("""COMPUTED_VALUE"""),"The Elder Scrolls IV: Oblivion") -> The Elder Scrolls IV: Oblivion | B7: =IFERROR(__xludf.DUMMYFUNCTION("""COMPUTED_VALUE"""),"Xbox / PC") -> Xbox / PC | C7: =IFERROR(__xludf.DUMMYFUNCTION("""COMPUTED_VALUE"""),"Yes") -> Yes | D7: =IFERROR(__xludf.DUMMYFUNCTION("""COMPUTED_VALUE"""),"Active") -> Active | E7: =IFERROR(__xludf.DUMMYFUNCTION("""COMPUTED_VALUE"""),43282.0) -> 43282 | G7: =IFERROR(__xludf.DUMMYFUNCTION("""COMPUTED_VALUE"""),87.46666666666667) -> 87.466667 | H7: =IFERROR(__xludf.DUMMYFUNCTION("""COMPUTED_VALUE"""),38796.0) -> 38796 | I7: =IFERROR(__xludf.DUMMYFUNCTION("""COMPUTED_VALUE"""),12.280555555555555) -> 12.280556 | J7: =IFERROR(__xludf.DUMMYFUNCTION("""COMPUTED_VALUE"""),94.0) -> 94 | K7: =IFERROR(__xludf.DUMMYFUNCTION("""COMPUTED_VALUE"""),27.5) -> 27.5 | L7: =IFERROR(__xludf.DUMMYFUNCTION("""COMPUTED_VALUE"""),"Action / RPG") -> Action / RPG | M7: =IFERROR(__xludf.DUMMYFUNCTION("""COMPUTED_VALUE"""),"FPS Boost") -> FPS Boost
A8: =IFERROR(__xludf.DUMMYFUNCTION("""COMPUTED_VALUE"""),"Hades") -> Hades | B8: =IFERROR(__xludf.DUMMYFUNCTION("""COMPUTED_VALUE"""),"Xbox / PC") -> Xbox / PC | C8: =IFERROR(__xludf.DUMMYFUNCTION("""COMPUTED_VALUE"""),"Touch Controls") -> Touch Controls | D8: =IFERROR(__xludf.DUMMYFUNCTION("""COMPUTED_VALUE"""),"Active") -> Active | E8: =IFERROR(__xludf.DUMMYFUNCTION("""COMPUTED_VALUE"""),45919.0) -> 45919 | G8: =IFERROR(__xludf.DUMMYFUNCTION("""COMPUTED_VALUE"""),0.8666666666666666) -> 0.86666667 | H8: =IFERROR(__xludf.DUMMYFUNCTION("""COMPUTED_VALUE"""),43441.0) -> 43441 | I8: =IFERROR(__xludf.DUMMYFUNCTION("""COMPUTED_VALUE"""),6.783333333333333) -> 6.7833333 | J8: =IFERROR(__xludf.DUMMYFUNCTION("""COMPUTED_VALUE"""),93.5) -> 93.5 | K8: =IFERROR(__xludf.DUMMYFUNCTION("""COMPUTED_VALUE"""),21.0) -> 21 | L8: =IFERROR(__xludf.DUMMYFUNCTION("""COMPUTED_VALUE"""),"Action / RPG") -> Action / RPG | M8: =IFERROR(__xludf.DUMMYFUNCTION("""COMPUTED_VALUE"""),"Optimized") -> Optimized
A9: =IFERROR(__xludf.DUMMYFUNCTION("""COMPUTED_VALUE"""),"Blue Prince") -> Blue Prince | B9: =IFERROR(__xludf.DUMMYFUNCTION("""COMPUTED_VALUE"""),"Xbox / PC") -> Xbox / PC | C9: =IFERROR(__xludf.DUMMYFUNCTION("""COMPUTED_VALUE"""),"Yes") -> Yes | D9: =IFERROR(__xludf.DUMMYFUNCTION("""COMPUTED_VALUE"""),"Active") -> Active | E9: =IFERROR(__xludf.DUMMYFUNCTION("""COMPUTED_VALUE"""),45757.0) -> 45757 | G9: =IFERROR(__xludf.DUMMYFUNCTION("""COMPUTED_VALUE"""),6.166666666666666) -> 6.1666667 | H9: =IFERROR(__xludf.DUMMYFUNCTION("""COMPUTED_VALUE"""),45757.0) -> 45757 | I9: =IFERROR(__xludf.DUMMYFUNCTION("""COMPUTED_VALUE"""),0.0) -> 0 | J9: =IFERROR(__xludf.DUMMYFUNCTION("""COMPUTED_VALUE"""),93.0) -> 93 | K9: =IFERROR(__xludf.DUMMYFUNCTION("""COMPUTED_VALUE"""),14.0) -> 14 | L9: =IFERROR(__xludf.DUMMYFUNCTION("""COMPUTED_VALUE"""),"Action-Adventure") -> Action-Adventure | M9: =IFERROR(__xludf.DUMMYFUNCTION("""COMPUTED_VALUE"""),"Exclusive") -> Exclusive
A10: =IFERROR(__xludf.DUMMYFUNCTION("""COMPUTED_VALUE"""),"Inside") -> Inside | B10: =IFERROR(__xludf.DUMMYFUNCTION("""COMPUTED_VALUE"""),"Xbox / PC") -> Xbox / PC | C10: =IFERROR(__xludf.DUMMYFUNCTION("""COMPUTED_VALUE"""),"Yes") -> Yes | D10: =IFERROR(__xludf.DUMMYFUNCTION("""COMPUTED_VALUE"""),"Active") -> Active | E10: =IFERROR(__xludf.DUMMYFUNCTION("""COMPUTED_VALUE"""),44763.0) -> 44763 | G10: =IFERROR(__xludf.DUMMYFUNCTION("""COMPUTED_VALUE"""),38.8) -> 38.8 | H10: =IFERROR(__xludf.DUMMYFUNCTION("""COMPUTED_VALUE"""),42550.0) -> 42550 | I10: =IFERROR(__xludf.DUMMYFUNCTION("""COMPUTED_VALUE"""),6.061111111111111) -> 6.0611111 | J10: =IFERROR(__xludf.DUMMYFUNCTION("""COMPUTED_VALUE"""),93.0) -> 93 | K10: =IFERROR(__xludf.DUMMYFUNCTION("""COMPUTED_VALUE"""),3.5) -> 3.5 | L10: =IFERROR(__xludf.DUMMYFUNCTION("""COMPUTED_VALUE"""),"Puzzle / Platformer") -> Puzzle / Platformer
A11: =IFERROR(__xludf.DUMMYFUNCTION("""COMPUTED_VALUE"""),"Fallout 3: Game of the Year Edition") -> Fallout 3: Game of the Year Edition | B11: =IFERROR(__xludf.DUMMYFUNCTION("""COMPUTED_VALUE"""),"Xbox / PC") -> Xbox / PC | C11: =IFERROR(__xludf.DUMMYFUNCTION("""COMPUTED_VALUE"""),"Yes") -> Yes | D11: =IFERROR(__xludf.DUMMYFUNCTION("""COMPUTED_VALUE"""),"Active") -> Active | E11: =IFERROR(__xludf.DUMMYFUNCTION("""COMPUTED_VALUE"""),43282.0) -> 43282 | G11: =IFERROR(__xludf.DUMMYFUNCTION("""COMPUTED_VALUE"""),87.46666666666667) -> 87.466667 | H11: =IFERROR(__xludf.DUMMYFUNCTION("""COMPUTED_VALUE"""),39749.0) -> 39749 | I11: =IFERROR(__xludf.DUMMYFUNCTION("""COMPUTED_VALUE"""),9.675) -> 9.675 | J11: =IFERROR(__xludf.DUMMYFUNCTION("""COMPUTED_VALUE"""),93.0) -> 93 | K11: =IFERROR(__xludf.DUMMYFUNCTION("""COMPUTED_VALUE"""),22.5) -> 22.5 | L11: =IFERROR(__xludf.DUMMYFUNCTION("""COMPUTED_VALUE"""),"RPG / First-Person Shooter") -> RPG / First-Person Shooter | M11: =IFERROR(__xludf.DUMMYFUNCTION("""COMPUTED_VALUE"""),"FPS Boost") -> FPS Boost
A12: =IFERROR(__xludf.DUMMYFUNCTION("""COMPUTED_VALUE"""),"Gears of War 2") -> Gears of War 2 | B12: =IFERROR(__xludf.DUMMYFUNCTION("""COMPUTED_VALUE"""),"Xbox") -> Xbox | C12: =IFERROR(__xludf.DUMMYFUNCTION("""COMPUTED_VALUE"""),"Yes") -> Yes | D12: =IFERROR(__xludf.DUMMYFUNCTION("""COMPUTED_VALUE"""),"Active") -> Active | E12: =IFERROR(__xludf.DUMMYFUNCTION("""COMPUTED_VALUE"""),42887.0) -> 42887 | G12: =IFERROR(__xludf.DUMMYFUNCTION("""COMPUTED_VALUE"""),100.46666666666667) -> 100.46667 | H12: =IFERROR(__xludf.DUMMYFUNCTION("""COMPUTED_VALUE"""),39759.0) -> 39759 | I12: =IFERROR(__xludf.DUMMYFUNCTION("""COMPUTED_VALUE"""),8.566666666666666) -> 8.5666667 | J12: =IFERROR(__xludf.DUMMYFUNCTION("""COMPUTED_VALUE"""),93.0) -> 93 | K12: =IFERROR(__xludf.DUMMYFUNCTION("""COMPUTED_VALUE"""),10.0) -> 10 | L12: =IFERROR(__xludf.DUMMYFUNCTION("""COMPUTED_VALUE"""),"Action / Shooter") -> Action / Shooter | M12: =IFERROR(__xludf.DUMMYFUNCTION("""COMPUTED_VALUE"""),"FPS Boost") -> FPS Boost
A13: =IFERROR(__xludf.DUMMYFUNCTION("""COMPUTED_VALUE"""),"Rayman Legends") -> Rayman Legends | B13: =IFERROR(__xludf.DUMMYFUNCTION("""COMPUTED_VALUE"""),"Xbox / PC") -> Xbox / PC | C13: =IFERROR(__xludf.DUMMYFUNCTION("""COMPUTED_VALUE"""),"Yes") -> Yes | D13: =IFERROR(__xludf.DUMMYFUNCTION("""COMPUTED_VALUE"""),"Active") -> Active | E13: =IFERROR(__xludf.DUMMYFUNCTION("""COMPUTED_VALUE"""),45931.0) -> 45931 | G13: =IFERROR(__xludf.DUMMYFUNCTION("""COMPUTED_VALUE"""),0.4666666666666667) -> 0.46666667 | H13: =IFERROR(__xludf.DUMMYFUNCTION("""COMPUTED_VALUE"""),41520.0) -> 41520 | I13: =IFERROR(__xludf.DUMMYFUNCTION("""COMPUTED_VALUE"""),12.077777777777778) -> 12.077778 | J13: =IFERROR(__xludf.DUMMYFUNCTION("""COMPUTED_VALUE"""),92.0) -> 92 | K13: =IFERROR(__xludf.DUMMYFUNCTION("""COMPUTED_VALUE"""),10.0) -> 10 | L13: =IFERROR(__xludf.DUMMYFUNCTION("""COMPUTED_VALUE"""),"Platformer") -> Platformer
A14: =IFERROR(__xludf.DUMMYFUNCTION("""COMPUTED_VALUE"""),"Clair Obscur: Expedition 33") -> Clair Obscur: Expedition 33 | B14: =IFERROR(__xludf.DUMMYFUNCTION("""COMPUTED_VALUE"""),"Xbox / PC") -> Xbox / PC | C14: =IFERROR(__xludf.DUMMYFUNCTION("""COMPUTED_VALUE"""),"Yes") -> Yes | D14: =IFERROR(__xludf.DUMMYFUNCTION("""COMPUTED_VALUE"""),"Active") -> Active | E14: =IFERROR(__xludf.DUMMYFUNCTION("""COMPUTED_VALUE"""),45771.0) -> 45771 | G14: =IFERROR(__xludf.DUMMYFUNCTION("""COMPUTED_VALUE"""),5.699999999999999) -> 5.7 | H14: =IFERROR(__xludf.DUMMYFUNCTION("""COMPUTED_VALUE"""),45771.0) -> 45771 | I14: =IFERROR(__xludf.DUMMYFUNCTION("""COMPUTED_VALUE"""),0.0) -> 0 | J14: =IFERROR(__xludf.DUMMYFUNCTION("""COMPUTED_VALUE"""),92.0) -> 92 | K14: =IFERROR(__xludf.DUMMYFUNCTION("""COMPUTED_VALUE"""),26.0) -> 26 | L14: =IFERROR(__xludf.DUMMYFUNCTION("""COMPUTED_VALUE"""),"RPG") -> RPG | M14: =IFERROR(__xludf.DUMMYFUNCTION("""COMPUTED_VALUE"""),"Exclusive") -> Exclusive
