Workbook
Name Lake: PC!$B$467
Name b: 'Master List'!$A:$A
Name dragon: 'Master List'!$A$1829
Name assass: 'Master List'!$A$1046
Name banjo: 'Copy of Removed'!$I$110
Name onrush: 'Master List'!$A$1327
Name Tiny: 'Xbox Game Studios'!$A$1
Name civ: PC!$A$1
Name civ: #REF!
Name gris: 'Master List'!$A$1732
Name Lake: #REF!
Name PC: 'Master List'!$A$2
Name hellslinger: xCloud!$K$85
Name persona: 'Copy of Removed'!$H$288:$H$295
Name chain: 'Master List'!$A$1
Name persona: Removed!$H$288:$H$295
Name banjo: Removed!$I$110
Name banjo: 'Master List'!$I$1356
Name YEARDUR: LAMBDA(start, end, lambda(s, e, if(s > e, -1 , 1 ) * yearfrac(s, e, 4))(if(isblank(start),today(),start), if(isblank(end),today(),end)))
Name MONTHDUR: LAMBDA(start, end, YEARDUR(start, end) * 12)

Sheet Master List
A1: Complete Game Pass Master List by u/ABattleVet | B1: =COUNTIFS(D2:D2289,"Active",B2:B2289,"<>")+COUNTIF(D2:D2289,"Leaving Soon") -> 741 | C1: Games with Gold | E1: GPU | H1: Playstation Plus | L1: =Suggestions!A1 -> Coming Soon | N1: The community can add games to cross play/play anywhere | P1: Public Notes | R1: GP Premium (10/1/25 Standard 9/12/24) | U1: GP Essential (10/1/25 Core 9/14/23)
A2: Game | B2: System | C2: xCloud | D2: Status | E2: Added | F2: Removed | G2: Months | H2: Release | I2: Age | J2: Metacritic | K2: Completion | L2: Genre | M2: Series X|S | N2: Owner Notes | O2: ESRB | P2: ESRB Content Descriptors | Q2: Community Notes | R2: Status | S2: Added | T2: Delay | U2: Added | V2: Delay
A3: Gears of War: E-Day | B3: Xbox / PC | C3: Yes | D3: =IF(E3>TODAY(),"Coming Soon",IF(F3="","Active",IF(F3>TODAY(),"Leaving Soon","Removed"))) -> Active | E3: 46301 | G3: =MONTHDUR(E3,F3) -> 0 | H3: 46301 | I3: =YEARDUR(H3,E3) -> 0 | L3: Shooter | M3: Exclusive | N3: Handheld Optimized | R3: =IF(S3="","TBD",IF(S3>TODAY(),"Coming Soon",IF(F3="","Active",IF(F3>TODAY(),"Leaving Soon","Removed")))) -> TBD | T3: =MONTHDUR(E3,S3) -> 0
A4: Minecraft Dungeons II | B4: Xbox / PC | C4: Yes | D4: =IF(E4>TODAY(),"Coming Soon",IF(F4="","Active",IF(F4>TODAY(),"Leaving Soon","Removed"))) -> Active | E4: 46294 | G4: =MONTHDUR(E4,F4) -> 0.23333333 | H4: 46294 | I4: =YEARDUR(H4,E4) -> 0 | L4: Action-Adventure | N4: Handheld Optimized | R4: =IF(S4="","TBD",IF(S4>TODAY(),"Coming Soon",IF(F4="","Active",IF(F4>TODAY(),"Leaving Soon","Removed")))) -> TBD | T4: =MONTHDUR(E4,S4) -> 0.23333333
A5: Mad King Redemption | B5: Xbox / PC | C5: Yes | D5: =IF(E5>TODAY(),"Coming Soon",IF(F5="","Active",IF(F5>TODAY(),"Leaving Soon","Removed"))) -> Active | E5: 46288 | G5: =MONTHDUR(E5,F5) -> 0.43333333 | H5: 46288 | I5: =YEARDUR(H5,E5) -> 0 | L5: Action-Adventure | M5: Exclusive | N5: Handheld Optimized | R5: =IF(S5="","TBD",IF(S5>TODAY(),"Coming Soon",IF(F5="","Active",IF(F5>TODAY(),"Leaving Soon","Removed")))) -> Active | S5: =E5 -> 46288 | T5: =MONTHDUR(E5,S5) -> 0
A6: Dune: Awakening | B6: Xbox / PC | C6: Yes | D6: =IF(E6>TODAY(),"Coming Soon",IF(F6="","Active",IF(F6>TODAY(),"Leaving Soon","Removed"))) -> Active | E6: 46287 | G6: =MONTHDUR(E6,F6) -> 0.46666667 | H6: 45818 | I6: =YEARDUR(H6,E6) -> 1.2833333 | J6: 78 | K6: 114 | L6: Action-Adventure | M6: Exclusive | N6: Handheld Optimized | R6: =IF(S6="","TBD",IF(S6>TODAY(),"Coming Soon",IF(F6="","Active",IF(F6>TODAY(),"Leaving Soon","Removed")))) -> Active | S6: =E6 -> 46287 | T6: =MONTHDUR(E6,S6) -> 0
A7: Well Dweller | B7: Xbox / PC | C7: Yes | D7: =IF(E7>TODAY(),"Coming Soon",IF(F7="","Active",IF(F7>TODAY(),"Leaving Soon","Removed"))) -> Active | E7: 46287 | G7: =MONTHDUR(E7,F7) -> 0.46666667 | H7: 46287 | I7: =YEARDUR(H7,E7) -> 0 | L7: Action-Adventure | N7: Handheld Optimized | R7: =IF(S7="","TBD",IF(S7>TODAY(),"Coming Soon",IF(F7="","Active",IF(F7>TODAY(),"Leaving Soon","Removed")))) -> TBD | T7: =MONTHDUR(E7,S7) -> 0.46666667
A8: Shape of Dreams | B8: Xbox / PC | C8: Yes | D8: =IF(E8>TODAY(),"Coming Soon",IF(F8="","Active",IF(F8>TODAY(),"Leaving Soon","Removed"))) -> Active | E8: 46282 | G8: =MONTHDUR(E8,F8) -> 0.63333333 | H8: 45910 | I8: =YEARDUR(H8,E8) -> 1.0194444 | J8: 84 | K8: 9 | L8: RPG | R8: =IF(S8="","TBD",IF(S8>TODAY(),"Coming Soon",IF(F8="","Active",IF(F8>TODAY(),"Leaving Soon","Removed")))) -> Active | S8: =E8 -> 46282 | T8: =MONTHDUR(E8,S8) -> 0
A9: Kernel Hearts | B9: Xbox / PC | C9: Yes | D9: =IF(E9>TODAY(),"Coming Soon",IF(F9="","Active",IF(F9>TODAY(),"Leaving Soon","Removed"))) -> Active | E9: 46282 | G9: =MONTHDUR(E9,F9) -> 0.63333333 | H9: 46282 | I9: =YEARDUR(H9,E9) -> 0 | L9: RPG | M9: Exclusive | R9: =IF(S9="","TBD",IF(S9>TODAY(),"Coming Soon",IF(F9="","Active",IF(F9>TODAY(),"Leaving Soon","Removed")))) -> TBD | T9: =MONTHDUR(E9,S9) -> 0.63333333
A10: RuneScape: Dragonwilds | B10: Xbox / PC | C10: Yes | D10: =IF(E10>TODAY(),"Coming Soon",IF(F10="","Active",IF(F10>TODAY(),"Leaving Soon","Removed"))) -> Active | E10: 46280 | G10: =MONTHDUR(E10,F10) -> 0.7 | H10: 46280 | I10: =YEARDUR(H10,E10) -> 0 | K10: 23 | L10: Action-Adventure | M10: Exclusive | R10: =IF(S10="","TBD",IF(S10>TODAY(),"Coming Soon",IF(F10="","Active",IF(F10>TODAY(),"Leaving Soon","Removed")))) -> Active | S10: =E10 -> 46280 | T10: =MONTHDUR(E10,S10) -> 0
A11: The Royal Writ | B11: Xbox / PC | C11: Yes | D11: =IF(E11>TODAY(),"Coming Soon",IF(F11="","Active",IF(F11>TODAY(),"Leaving Soon","Removed"))) -> Active | E11: 46275 | G11: =MONTHDUR(E11,F11) -> 0.86666667 | H11: 45876 | I11: =YEARDUR(H11,E11) -> 1.0916667 | J11: 80 | K11: 5 | L11: Card Battle | M11: Exclusive | N11: Handheld Optimized | R11: =IF(S11="","TBD",IF(S11>TODAY(),"Coming Soon",IF(F11="","Active",IF(F11>TODAY(),"Leaving Soon","Removed")))) -> Active | S11: =E11 -> 46275 | T11: =MONTHDUR(E11,S11) -> 0
A12: Virtua Fighter 5 R.E.V.O. World Stage | B12: Xbox / PC | C12: Yes | D12: =IF(E12>TODAY(),"Coming Soon",IF(F12="","Active",IF(F12>TODAY(),"Leaving Soon","Removed"))) -> Active | E12: 46275 | G12: =MONTHDUR(E12,F12) -> 0.86666667 | H12: 45960 | I12: =YEARDUR(H12,E12) -> 0.86111111 | J12: 78 | K12: 1 | L12: Fighting | M12: Exclusive | R12: =IF(S12="","TBD",IF(S12>TODAY(),"Coming Soon",IF(F12="","Active",IF(F12>TODAY(),"Leaving Soon","Removed")))) -> Active | S12: =E12 -> 46275 | T12: =MONTHDUR(E12,S12) -> 0
A13: Call of Duty: Black Ops Cold War | B13: Xbox / PC | C13: Yes | D13: =IF(E13>TODAY(),"Coming Soon",IF(F13="","Active",IF(F13>TODAY(),"Leaving Soon","Removed"))) -> Active | E13: 46273 | G13: =MONTHDUR(E13,F13) -> 0.93333333 | H13: 44148 | I13: =YEARDUR(H13,E13) -> 5.8194444 | J13: 76 | K13: 5.5 | L13: Shooter | R13: =IF(S13="","TBD",IF(S13>TODAY(),"Coming Soon",IF(F13="","Active",IF(F13>TODAY(),"Leaving Soon","Removed")))) -> Active | S13: =E13 -> 46273 | T13: =MONTHDUR(E13,S13) -> 0
A14: Speedrunners 2: King of Speed | B14: Xbox / PC | C14: Yes | D14: =IF(E14>TODAY(),"Coming Soon",IF(F14="","Active",IF(F14>TODAY(),"Leaving Soon","Removed"))) -> Active | E14: 46268 | G14: =MONTHDUR(E14,F14) -> 1.1 | H14: 46268 | I14: =YEARDUR(H14,E14) -> 0 | K14: 3 | L14: Racing | M14: Exclusive | R14: =IF(S14="","TBD",IF(S14>TODAY(),"Coming Soon",IF(F14="","Active",IF(F14>TODAY(),"Leaving Soon","Removed")))) -> TBD | T14: =MONTHDUR(E14,S14) -> 1.1
A15: Shelldiver | B15: Xbox / PC | C15: Yes | D15: =IF(E15>TODAY(),"Coming Soon",IF(F15="","Active",IF(F15>TODAY(),"Leaving Soon","Removed"))) -> Active | E15: 46266 | G15: =MONTHDUR(E15,F15) -> 1.1666667 | H15: 45977 | I15: =YEARDUR(H15,E15) -> 0.79166667 | K15: 4 | L15: Platformer | R15: =IF(S15="","TBD",IF(S15>TODAY(),"Coming Soon",IF(F15="","Active",IF(F15>TODAY(),"Leaving Soon","Removed")))) -> Active | S15: =E15 -> 46266 | T15: =MONTHDUR(E15,S15) -> 0
A16: Resonance: A Plague Tale Legacy | B16: Xbox / PC | C16: Yes | D16: =IF(E16>TODAY(),"Coming Soon",IF(F16="","Active",IF(F16>TODAY(),"Leaving Soon","Removed"))) -> Active | E16: 46261 | G16: =MONTHDUR(E16,F16) -> 1.3 | H16: 46261 | I16: =YEARDUR(H16,E16) -> 0 | J16: 78 | K16: 12 | L16: Action-Adventure | M16: Exclusive | N16: Handheld Optimized | R16: =IF(S16="","TBD",IF(S16>TODAY(),"Coming Soon",IF(F16="","Active",IF(F16>TODAY(),"Leaving Soon","Removed")))) -> TBD | T16: =MONTHDUR(E16,S16) -> 1.3
A17: Blood Dungeon | B17: Xbox / PC | C17: Yes | D17: =IF(E17>TODAY(),"Coming Soon",IF(F17="","Active",IF(F17>TODAY(),"Leaving Soon","Removed"))) -> Active | E17: 46259 | G17: =MONTHDUR(E17,F17) -> 1.3666667 | H17: 46259 | I17: =YEARDUR(H17,E17) -> 0 | J17: 74 | K17: 2 | L17: Action-Adventure | M17: Exclusive | R17: =IF(S17="","TBD",IF(S17>TODAY(),"Coming Soon",IF(F17="","Active",IF(F17>TODAY(),"Leaving Soon","Removed")))) -> TBD | T17: =MONTHDUR(E17,S17) -> 1.3666667
A18: Vapor World: Over the Mind (Game Preview) | B18: Xbox / PC | C18: Yes | D18: =IF(E18>TODAY(),"Coming Soon",IF(F18="","Active",IF(F18>TODAY(),"Leaving Soon","Removed"))) -> Active | E18: 46253 | G18: =MONTHDUR(E18,F18) -> 1.5666667 | H18: 46253 | I18: =YEARDUR(H18,E18) -> 0 | K18: 12 | L18: Action-Adventure | R18: =IF(S18="","TBD",IF(S18>TODAY(),"Coming Soon",IF(F18="","Active",IF(F18>TODAY(),"Leaving Soon","Removed")))) -> TBD | T18: =MONTHDUR(E18,S18) -> 1.5666667
A19: Cricket 26 | B19: Xbox / PC | C19: Yes | D19: =IF(E19>TODAY(),"Coming Soon",IF(F19="","Active",IF(F19>TODAY(),"Leaving Soon","Removed"))) -> Active | E19: 46247 | G19: =MONTHDUR(E19,F19) -> 1.7666667 | H19: 45974 | I19: =YEARDUR(H19,E19) -> 0.75 | J19: 75 | K19: 33 | L19: Sports | R19: =IF(S19="","TBD",IF(S19>TODAY(),"Coming Soon",IF(F19="","Active",IF(F19>TODAY(),"Leaving Soon","Removed")))) -> Active | S19: =E19 -> 46247 | T19: =MONTHDUR(E19,S19) -> 0
A20: Sandustry (Game Preview) | B20: PC | D20: =IF(E20>TODAY(),"Coming Soon",IF(F20="","Active",IF(F20>TODAY(),"Leaving Soon","Removed"))) -> Active | E20: 46247 | G20: =MONTHDUR(E20,F20) -> 1.7666667 | H20: 46247 | I20: =YEARDUR(H20,E20) -> 0 | K20: 8 | L20: Simulation | R20: =IF(S20="","TBD",IF(S20>TODAY(),"Coming Soon",IF(F20="","Active",IF(F20>TODAY(),"Leaving Soon","Removed")))) -> TBD | T20: =MONTHDUR(E20,S20) -> 1.7666667
A21: Date Everything! | B21: Xbox / PC | C21: Yes | D21: =IF(E21>TODAY(),"Coming Soon",IF(F21="","Active",IF(F21>TODAY(),"Leaving Soon","Removed"))) -> Active | E21: 46245 | G21: =MONTHDUR(E21,F21) -> 1.8333333 | H21: 45825 | I21: =YEARDUR(H21,E21) -> 1.15 | J21: 78 | K21: 15 | L21: Simulation | M21: Exclusive | N21: Handheld Optimized | R21: =IF(S21="","TBD",IF(S21>TODAY(),"Coming Soon",IF(F21="","Active",IF(F21>TODAY(),"Leaving Soon","Removed")))) -> Active | S21: =E21 -> 46245 | T21: =MONTHDUR(E21,S21) -> 0
A22: Beast of Reincarnation | B22: Xbox / PC | C22: Yes | D22: =IF(E22>TODAY(),"Coming Soon",IF(F22="","Active",IF(F22>TODAY(),"Leaving Soon","Removed"))) -> Active | E22: 46238 | G22: =MONTHDUR(E22,F22) -> 2.0666667 | H22: 46238 | I22: =YEARDUR(H22,E22) -> 0 | J22: 72 | K22: 23 | L22: RPG | M22: Exclusive | N22: Handheld Optimized | R22: =IF(S22="","TBD",IF(S22>TODAY(),"Coming Soon",IF(F22="","Active",IF(F22>TODAY(),"Leaving Soon","Removed")))) -> TBD | T22: =MONTHDUR(E22,S22) -> 2.0666667
A23: Tears of Metal (Game Preview) | B23: PC | D23: =IF(E23>TODAY(),"Coming Soon",IF(F23="","Active",IF(F23>TODAY(),"Leaving Soon","Removed"))) -> Active | E23: 46225 | G23: =MONTHDUR(E23,F23) -> 2.4666667 | H23: 46225 | I23: =YEARDUR(H23,E23) -> 0 | J23: 75 | K23: 4 | L23: Action-Adventure | R23: =IF(S23="","TBD",IF(S23>TODAY(),"Coming Soon",IF(F23="","Active",IF(F23>TODAY(),"Leaving Soon","Removed")))) -> TBD | T23: =MONTHDUR(E23,S23) -> 2.4666667
A24: Corsair Cove | B24: PC | D24: =IF(E24>TODAY(),"Coming Soon",IF(F24="","Active",IF(F24>TODAY(),"Leaving Soon","Removed"))) -> Active | E24: 46234 | G24: =MONTHDUR(E24,F24) -> 2.2 | H24: 46234 | I24: =YEARDUR(H24,E24) -> 0 | J24: 70 | K24: 29 | L24: Simulation | R24: =IF(S24="","TBD",IF(S24>TODAY(),"Coming Soon",IF(F24="","Active",IF(F24>TODAY(),"Leaving Soon","Removed")))) -> TBD | T24: =MONTHDUR(E24,S24) -> 2.2
A25: Mistfall Hunter | B25: Xbox / PC | C25: Yes | D25: =IF(E25>TODAY(),"Coming Soon",IF(F25="","Active",IF(F25>TODAY(),"Leaving Soon","Removed"))) -> Active | E25: 46233 | G25: =MONTHDUR(E25,F25) -> 2.2 | H25: 46233 | I25: =YEARDUR(H25,E25) -> 0 | J25: 70 | L25: RPG | M25: Exclusive | R25: =IF(S25="","TBD",IF(S25>TODAY(),"Coming Soon",IF(F25="","Active",IF(F25>TODAY(),"Leaving Soon","Removed")))) -> TBD | T25: =MONTHDUR(E25,S25) -> 2.2
A26: Halo: Campaign Evolved | B26: Xbox / PC | C26: Yes | D26: =IF(E26>TODAY(),"Coming Soon",IF(F26="","Active",IF(F26>TODAY(),"Leaving Soon","Removed"))) -> Active | E26: 46231 | G26: =MONTHDUR(E26,F26) -> 2.2666667 | H26: 46231 | I26: =YEARDUR(H26,E26) -> 0 | J26: 80 | K26: 9 | L26: Shooter | N26: Handheld Optimized | R26: =IF(S26="","TBD",IF(S26>TODAY(),"Coming Soon",IF(F26="","Active",IF(F26>TODAY(),"Leaving Soon","Removed")))) -> TBD | T26: =MONTHDUR(E26,S26) -> 2.2666667
A27: Conker: Live & Reloaded | B27: Xbox / PC | C27: Yes | D27: =IF(E27>TODAY(),"Coming Soon",IF(F27="","Active",IF(F27>TODAY(),"Leaving Soon","Removed"))) -> Active | E27: 46225 | G27: =MONTHDUR(E27,F27) -> 2.4666667 | H27: 38673 | I27: =YEARDUR(H27,E27) -> 20.680556 | J27: 82 | K27: 11 | L27: Action-Adventure | M27: Enhanced | N27: XBOX Backward Compatibility on PC (7/22/26) | R27: =IF(S27="","TBD",IF(S27>TODAY(),"Coming Soon",IF(F27="","Active",IF(F27>TODAY(),"Leaving Soon","Removed")))) -> Active | S27: =E27 -> 46225 | T27: =MONTHDUR(E27,S27) -> 0 | U27: 46225 | V27: =MONTHDUR(E27,U27) -> 0
A28: Hell is Us | B28: Xbox / PC | C28: Yes | D28: =IF(E28>TODAY(),"Coming Soon",IF(F28="","Active",IF(F28>TODAY(),"Leaving Soon","Removed"))) -> Active | E28: 46226 | G28: =MONTHDUR(E28,F28) -> 2.4333333 | H28: 45904 | I28: =YEARDUR(H28,E28) -> 0.88611111 | J28: 77 | K28: 18 | L28: Action-Adventure | M28: Exclusive | R28: =IF(S28="","TBD",IF(S28>TODAY(),"Coming Soon",IF(F28="","Active",IF(F28>TODAY(),"Leaving Soon","Removed")))) -> Active | S28: =E28 -> 46226 | T28: =MONTHDUR(E28,S28) -> 0
A29: Shift at Midnight | B29: Xbox / PC | C29: Yes | D29: =IF(E29>TODAY(),"Coming Soon",IF(F29="","Active",IF(F29>TODAY(),"Leaving Soon","Removed"))) -> Active | E29: 46225 | G29: =MONTHDUR(E29,F29) -> 2.4666667 | H29: 46225 | I29: =YEARDUR(H29,E29) -> 0 | J29: 80 | K29: 5 | L29: Horror | M29: Exclusive | R29: =IF(S29="","TBD",IF(S29>TODAY(),"Coming Soon",IF(F29="","Active",IF(F29>TODAY(),"Leaving Soon","Removed")))) -> TBD | T29: =MONTHDUR(E29,S29) -> 2.4666667
A30: The Planet Crafter | B30: Xbox / PC | C30: Yes | D30: =IF(E30>TODAY(),"Coming Soon",IF(F30="","Active",IF(F30>TODAY(),"Leaving Soon","Removed"))) -> Active | E30: 46224 | G30: =MONTHDUR(E30,F30) -> 2.5 | H30: 44644 | I30: =YEARDUR(H30,E30) -> 4.325 | J30: 81 | K30: 35 | L30: Sandbox | M30: Exclusive | R30: =IF(S30="","TBD",IF(S30>TODAY(),"Coming Soon",IF(F30="","Active",IF(F30>TODAY(),"Leaving Soon","Removed")))) -> Active | S30: =E30 -> 46224 | T30: =MONTHDUR(E30,S30) -> 0
A31: FixForce | B31: Xbox / PC | C31: Yes | D31: =IF(E31>TODAY(),"Coming Soon",IF(F31="","Active",IF(F31>TODAY(),"Leaving Soon","Removed"))) -> Active | E31: 46220 | G31: =MONTHDUR(E31,F31) -> 2.6333333 | H31: 46220 | I31: =YEARDUR(H31,E31) -> 0 | J31: 80 | L31: Platformer | M31: Exclusive | R31: =IF(S31="","TBD",IF(S31>TODAY(),"Coming Soon",IF(F31="","Active",IF(F31>TODAY(),"Leaving Soon","Removed")))) -> Active | S31: =E31 -> 46220 | T31: =MONTHDUR(E31,S31) -> 0
A32: Fogpiercer | B32: PC | D32: =IF(E32>TODAY(),"Coming Soon",IF(F32="","Active",IF(F32>TODAY(),"Leaving Soon","Removed"))) -> Active | E32: 46220 | G32: =MONTHDUR(E32,F32) -> 2.6333333 | H32: 46220 | I32: =YEARDUR(H32,E32) -> 0 | J32: 73 | K32: 5 | L32: Strategy | R32: =IF(S32="","TBD",IF(S32>TODAY(),"Coming Soon",IF(F32="","Active",IF(F32>TODAY(),"Leaving Soon","Removed")))) -> TBD | T32: =MONTHDUR(E32,S32) -> 2.6333333
A33: Mavrix by Matt Jones | B33: Xbox / PC | C33: Yes | D33: =IF(E33>TODAY(),"Coming Soon",IF(F33="","Active",IF(F33>TODAY(),"Leaving Soon","Removed"))) -> Active | E33: 46219 | G33: =MONTHDUR(E33,F33) -> 2.6666667 | H33: 46219 | I33: =YEARDUR(H33,E33) -> 0 | J33: 78 | L33: Racing | M33: Exclusive | N33: Handheld Optimized | R33: =IF(S33="","TBD",IF(S33>TODAY(),"Coming Soon",IF(F33="","Active",IF(F33>TODAY(),"Leaving Soon","Removed")))) -> Active | S33: =E33 -> 46219 | T33: =MONTHDUR(E33,S33) -> 0
A34: Denshattack! | B34: Xbox / PC | C34: Yes | D34: =IF(E34>TODAY(),"Coming Soon",IF(F34="","Active",IF(F34>TODAY(),"Leaving Soon","Removed"))) -> Active | E34: 46218 | G34: =MONTHDUR(E34,F34) -> 2.7 | H34: 45853 | I34: =YEARDUR(H34,E34) -> 1 | J34: 88 | K34: 9 | L34: Action-Adventure | M34: Exclusive | R34: =IF(S34="","TBD",IF(S34>TODAY(),"Coming Soon",IF(F34="","Active",IF(F34>TODAY(),"Leaving Soon","Removed")))) -> TBD | T34: =MONTHDUR(E34,S34) -> 2.7
A35: PBA Pro Bowling 2026 | B35: Xbox / PC | C35: Yes | D35: =IF(E35>TODAY(),"Coming Soon",IF(F35="","Active",IF(F35>TODAY(),"Leaving Soon","Removed"))) -> Active | E35: 46217 | G35: =MONTHDUR(E35,F35) -> 2.7333333 | H35: 46217 | I35: =YEARDUR(H35,E35) -> 0 | J35: 70 | K35: 5 | L35: Sports | M35: Exclusive | R35: =IF(S35="","TBD",IF(S35>TODAY(),"Coming Soon",IF(F35="","Active",IF(F35>TODAY(),"Leaving Soon","Removed")))) -> Active | S35: =E35 -> 46217 | T35: =MONTHDUR(E35,S35) -> 0
A36: Ascend to Zero | B36: Xbox / PC | C36: Yes | D36: =IF(E36>TODAY(),"Coming Soon",IF(F36="","Active",IF(F36>TODAY(),"Leaving Soon","Removed"))) -> Active | E36: 46216 | G36: =MONTHDUR(E36,F36) -> 2.7666667 | H36: 46216 | I36: =YEARDUR(H36,E36) -> 0 | J36: 82 | K36: 13 | L36: Action-Adventure | M36: Exclusive | N36: Handheld Optimized | R36: =IF(S36="","TBD",IF(S36>TODAY(),"Coming Soon",IF(F36="","Active",IF(F36>TODAY(),"Leaving Soon","Removed")))) -> TBD | T36: =MONTHDUR(E36,S36) -> 2.7666667
A37: Tamashika | B37: Xbox / PC | C37: Yes | D37: =IF(E37>TODAY(),"Coming Soon",IF(F37="","Active",IF(F37>TODAY(),"Leaving Soon","Removed"))) -> Active | E37: 46212 | G37: =MONTHDUR(E37,F37) -> 2.9 | H37: 46122 | I37: =YEARDUR(H37,E37) -> 0.24722222 | J37: 79 | K37: 2 | L37: Shooter | M37: Exclusive | N37: Handheld Optimized | R37: =IF(S37="","TBD",IF(S37>TODAY(),"Coming Soon",IF(F37="","Active",IF(F37>TODAY(),"Leaving Soon","Removed")))) -> Active | S37: =E37 -> 46212 | T37: =MONTHDUR(E37,S37) -> 0
A38: Buckshot Roulette | B38: Xbox / PC | C38: Yes | D38: =IF(E38>TODAY(),"Coming Soon",IF(F38="","Active",IF(F38>TODAY(),"Leaving Soon","Removed"))) -> Active | E38: 46211 | G38: =MONTHDUR(E38,F38) -> 2.9333333 | H38: 45288 | I38: =YEARDUR(H38,E38) -> 2.5277778 | J38: 85 | K38: 1 | L38: Strategy | R38: =IF(S38="","TBD",IF(S38>TODAY(),"Coming Soon",IF(F38="","Active",IF(F38>TODAY(),"Leaving Soon","Removed")))) -> Active | S38: =E38 -> 46211 | T38: =MONTHDUR(E38,S38) -> 0
A39: Winds of Arcana: Ruination | B39: Xbox / PC | C39: Yes | D39: =IF(E39>TODAY(),"Coming Soon",IF(F39="","Active",IF(F39>TODAY(),"Leaving Soon","Removed"))) -> Active | E39: 46209 | G39: =MONTHDUR(E39,F39) -> 3 | H39: 45975 | I39: =YEARDUR(H39,E39) -> 0.64444444 | J39: 72 | K39: 9 | L39: RPG | N39: Handheld Optimized | R39: =IF(S39="","TBD",IF(S39>TODAY(),"Coming Soon",IF(F39="","Active",IF(F39>TODAY(),"Leaving Soon","Removed")))) -> Active | S39: =E39 -> 46209 | T39: =MONTHDUR(E39,S39) -> 0
A40: RV There Yet? | B40: Xbox / PC | C40: Yes | D40: =IF(E40>TODAY(),"Coming Soon",IF(F40="","Active",IF(F40>TODAY(),"Leaving Soon","Removed"))) -> Active | E40: 46203 | G40: =MONTHDUR(E40,F40) -> 3.2 | H40: 46203 | I40: =YEARDUR(H40,E40) -> 0 | J40: 71 | K40: 4 | L40: Action-Adventure | M40: Exclusive | R40: =IF(S40="","TBD",IF(S40>TODAY(),"Coming Soon",IF(F40="","Active",IF(F40>TODAY(),"Leaving Soon","Removed")))) -> Active | S40: =E40 -> 46203 | T40: =MONTHDUR(E40,S40) -> 0
A41: Abyssus | B41: Xbox / PC | C41: Yes | D41: =IF(E41>TODAY(),"Coming Soon",IF(F41="","Active",IF(F41>TODAY(),"Leaving Soon","Removed"))) -> Active | E41: 46198 | G41: =MONTHDUR(E41,F41) -> 3.3666667 | H41: 46198 | I41: =YEARDUR(H41,E41) -> 0 | J41: 80 | K41: 25 | L41: Shooter | M41: Exclusive | R41: =IF(S41="","TBD",IF(S41>TODAY(),"Coming Soon",IF(F41="","Active",IF(F41>TODAY(),"Leaving Soon","Removed")))) -> Active | S41: =E41 -> 46198 | T41: =MONTHDUR(E41,S41) -> 0
A42: EA Sports FC 26 | B42: Xbox / PC | C42: Yes | D42: =IF(E42>TODAY(),"Coming Soon",IF(F42="","Active",IF(F42>TODAY(),"Leaving Soon","Removed"))) -> Active | E42: 46191 | G42: =MONTHDUR(E42,F42) -> 3.6 | H42: 45926 | I42: =YEARDUR(H42,E42) -> 0.72777778 | J42: 77 | K42: 25 | L42: Sports | R42: =IF(S42="","TBD",IF(S42>TODAY(),"Coming Soon",IF(F42="","Active",IF(F42>TODAY(),"Leaving Soon","Removed")))) -> TBD | T42: =MONTHDUR(E42,S42) -> 3.6
A43: Call of Duty: Vanguard | B43: Xbox / PC | C43: Yes | D43: =IF(E43>TODAY(),"Coming Soon",IF(F43="","Active",IF(F43>TODAY(),"Leaving Soon","Removed"))) -> Active | E43: 46190 | G43: =MONTHDUR(E43,F43) -> 3.6333333 | H43: 44504 | I43: =YEARDUR(H43,E43) -> 4.6194444 | J43: 73 | K43: 6 | L43: Shooter | R43: =IF(S43="","TBD",IF(S43>TODAY(),"Coming Soon",IF(F43="","Active",IF(F43>TODAY(),"Leaving Soon","Removed")))) -> Active | S43: =E43 -> 46190 | T43: =MONTHDUR(E43,S43) -> 0
A44: Junkster | B44: Xbox / PC | C44: Yes | D44: =IF(E44>TODAY(),"Coming Soon",IF(F44="","Active",IF(F44>TODAY(),"Leaving Soon","Removed"))) -> Active | E44: 46189 | G44: =MONTHDUR(E44,F44) -> 3.6666667 | H44: 46189 | I44: =YEARDUR(H44,E44) -> 0 | J44: 78 | K44: 4 | L44: Action-Adventure | M44: Exclusive | N44: Handheld Optimized | R44: =IF(S44="","TBD",IF(S44>TODAY(),"Coming Soon",IF(F44="","Active",IF(F44>TODAY(),"Leaving Soon","Removed")))) -> TBD | T44: =MONTHDUR(E44,S44) -> 3.6666667
A45: Beastro | B45: Xbox / PC | C45: Yes | D45: =IF(E45>TODAY(),"Coming Soon",IF(F45="","Active",IF(F45>TODAY(),"Leaving Soon","Removed"))) -> Active | E45: 46184 | G45: =MONTHDUR(E45,F45) -> 3.8333333 | H45: 46163 | I45: =YEARDUR(H45,E45) -> 0.055555556 | J45: 73 | K45: 9 | L45: Action-Adventure | M45: Exclusive | N45: Handheld Optimized | R45: =IF(S45="","TBD",IF(S45>TODAY(),"Coming Soon",IF(F45="","Active",IF(F45>TODAY(),"Leaving Soon","Removed")))) -> TBD | T45: =MONTHDUR(E45,S45) -> 3.8333333
A46: Frog Sqwad | B46: Xbox / PC | C46: Yes | D46: =IF(E46>TODAY(),"Coming Soon",IF(F46="","Active",IF(F46>TODAY(),"Leaving Soon","Removed"))) -> Active | E46: 46184 | G46: =MONTHDUR(E46,F46) -> 3.8333333 | H46: 46184 | I46: =YEARDUR(H46,E46) -> 0 | J46: 70 | K46: 1 | L46: Puzzle | M46: Exclusive | R46: =IF(S46="","TBD",IF(S46>TODAY(),"Coming Soon",IF(F46="","Active",IF(F46>TODAY(),"Leaving Soon","Removed")))) -> TBD | T46: =MONTHDUR(E46,S46) -> 3.8333333
A47: Starseeker: Astroneer Expeditions (Game Preview) | B47: Xbox / PC | C47: Yes | D47: =IF(E47>TODAY(),"Coming Soon",IF(F47="","Active",IF(F47>TODAY(),"Leaving Soon","Removed"))) -> Active | E47: 46184 | G47: =MONTHDUR(E47,F47) -> 3.8333333 | H47: 46184 | I47: =YEARDUR(H47,E47) -> 0 | K47: 1 | L47: Action-Adventure | R47: =IF(S47="","TBD",IF(S47>TODAY(),"Coming Soon",IF(F47="","Active",IF(F47>TODAY(),"Leaving Soon","Removed")))) -> TBD | T47: =MONTHDUR(E47,S47) -> 3.8333333
A48: Beatdown City Survivors | B48: Xbox / PC | C48: Yes | D48: =IF(E48>TODAY(),"Coming Soon",IF(F48="","Active",IF(F48>TODAY(),"Leaving Soon","Removed"))) -> Active | E48: 46183 | G48: =MONTHDUR(E48,F48) -> 3.8666667 | H48: 45693 | I48: =YEARDUR(H48,E48) -> 1.3472222 | J48: 64 | K48: 10 | L48: Action-Adventure | M48: Exclusive | N48: Handheld Optimized | R48: =IF(S48="","TBD",IF(S48>TODAY(),"Coming Soon",IF(F48="","Active",IF(F48>TODAY(),"Leaving Soon","Removed")))) -> TBD | T48: =MONTHDUR(E48,S48) -> 3.8666667
A49: Persona 5 Royal | B49: Xbox / PC | C49: Touch Controls | D49: =IF(E49>TODAY(),"Coming Soon",IF(F49="","Active",IF(F49>TODAY(),"Leaving Soon","Removed"))) -> Active | E49: 46182 | G49: =MONTHDUR(E49,F49) -> 3.9 | H49: 43921 | I49: =YEARDUR(H49,E49) -> 6.1916667 | J49: 95 | K49: 101 | L49: RPG | N49: Returning title: Added 10/21/22, left 10/31/23 | R49: =IF(S49="","TBD",IF(S49>TODAY(),"Coming Soon",IF(F49="","Active",IF(F49>TODAY(),"Leaving Soon","Removed")))) -> Active | S49: =E49 -> 46182 | T49: =MONTHDUR(E49,S49) -> 0
A50: Solarpunk | B50: Xbox / PC | C50: Yes | D50: =IF(E50>TODAY(),"Coming Soon",IF(F50="","Active",IF(F50>TODAY(),"Leaving Soon","Removed"))) -> Active | E50: 46181 | G50: =MONTHDUR(E50,F50) -> 3.9333333 | H50: 46181 | I50: =YEARDUR(H50,E50) -> 0 | J50: 65 | K50: 17 | L50: Simulation | M50: Exclusive | R50: =IF(S50="","TBD",IF(S50>TODAY(),"Coming Soon",IF(F50="","Active",IF(F50>TODAY(),"Leaving Soon","Removed")))) -> TBD | T50: =MONTHDUR(E50,S50) -> 3.9333333
A51: Undisputed | B51: Xbox / PC | C51: Yes | D51: =IF(E51>TODAY(),"Coming Soon",IF(F51="","Active",IF(F51>TODAY(),"Leaving Soon","Removed"))) -> Active | E51: 46181 | G51: =MONTHDUR(E51,F51) -> 3.9333333 | H51: 45576 | I51: =YEARDUR(H51,E51) -> 1.6583333 | J51: 73 | K51: 15 | L51: Sports | M51: Exclusive | N51: Handheld Optimized | R51: =IF(S51="","TBD",IF(S51>TODAY(),"Coming Soon",IF(F51="","Active",IF(F51>TODAY(),"Leaving Soon","Removed")))) -> Active | S51: =E51 -> 46181 | T51: =MONTHDUR(E51,S51) -> 0
A52: Wo Long: Fallen Dynasty | B52: Xbox / PC | C52: Yes | D52: =IF(E52>TODAY(),"Coming Soon",IF(F52="","Active",IF(F52>TODAY(),"Leaving Soon","Removed"))) -> Active | E52: 46180 | G52: =MONTHDUR(E52,F52) -> 3.9666667 | H52: 44988 | I52: =YEARDUR(H52,E52) -> 3.2611111 | J52: 80 | K52: 29 | L52: Action | N52: Returning title: Added 3/3/23, left 2/28/25 | O52: M | P52: Blood and Gore, Violence | R52: =IF(S52="","TBD",IF(S52>TODAY(),"Coming Soon",IF(F52="","Active",IF(F52>TODAY(),"Leaving Soon","Removed")))) -> Active | S52: =E52 -> 46180 | T52: =MONTHDUR(E52,S52) -> 0
A53: Final Fantasy VI | B53: Xbox / PC | C53: Yes | D53: =IF(E53>TODAY(),"Coming Soon",IF(F53="","Active",IF(F53>TODAY(),"Leaving Soon","Removed"))) -> Active | E53: 46175 | G53: =MONTHDUR(E53,F53) -> 4.1333333 | H53: 45561 | I53: =YEARDUR(H53,E53) -> 1.6833333 | J53: 87 | K53: 36 | L53: RPG | M53: Exclusive | R53: =IF(S53="","TBD",IF(S53>TODAY(),"Coming Soon",IF(F53="","Active",IF(F53>TODAY(),"Leaving Soon","Removed")))) -> Active | S53: =E53 -> 46175 | T53: =MONTHDUR(E53,S53) -> 0
A54: Jurassic World Evolution 3 | B54: Xbox / PC | C54: Yes | D54: =IF(E54>TODAY(),"Coming Soon",IF(F54="","Active",IF(F54>TODAY(),"Leaving Soon","Removed"))) -> Active | E54: 46175 | G54: =MONTHDUR(E54,F54) -> 4.1333333 | H54: 45951 | I54: =YEARDUR(H54,E54) -> 0.61388889 | J54: 81 | K54: 20 | L54: Simulation | M54: Exclusive | R54: =IF(S54="","TBD",IF(S54>TODAY(),"Coming Soon",IF(F54="","Active",IF(F54>TODAY(),"Leaving Soon","Removed")))) -> Active | S54: =E54 -> 46175 | T54: =MONTHDUR(E54,S54) -> 0
A55: Escape the Backrooms | B55: Xbox / PC | C55: Yes | D55: =IF(E55>TODAY(),"Coming Soon",IF(F55="","Active",IF(F55>TODAY(),"Leaving Soon","Removed"))) -> Active | E55: 46170 | G55: =MONTHDUR(E55,F55) -> 4.2666667 | H55: 45953 | I55: =YEARDUR(H55,E55) -> 0.59722222 | J55: 80 | K55: 9 | L55: Survival | M55: Exclusive | R55: =IF(S55="","TBD",IF(S55>TODAY(),"Coming Soon",IF(F55="","Active",IF(F55>TODAY(),"Leaving Soon","Removed")))) -> Active | S55: =E55 -> 46170 | T55: =MONTHDUR(E55,S55) -> 0
A56: Crashout Crew | B56: Xbox / PC | C56: Yes | D56: =IF(E56>TODAY(),"Coming Soon",IF(F56="","Active",IF(F56>TODAY(),"Leaving Soon","Removed"))) -> Active | E56: 46170 | G56: =MONTHDUR(E56,F56) -> 4.2666667 | H56: 46170 | I56: =YEARDUR(H56,E56) -> 0 | J56: 80 | K56: 12 | L56: Action-Adventure | M56: Exclusive | N56: Handheld Optimized | R56: =IF(S56="","TBD",IF(S56>TODAY(),"Coming Soon",IF(F56="","Active",IF(F56>TODAY(),"Leaving Soon","Removed")))) -> TBD | T56: =MONTHDUR(E56,S56) -> 4.2666667
A57: Kabuto Park | B57: Xbox / PC | C57: Yes | D57: =IF(E57>TODAY(),"Coming Soon",IF(F57="","Active",IF(F57>TODAY(),"Leaving Soon","Removed"))) -> Active | E57: 46170 | G57: =MONTHDUR(E57,F57) -> 4.2666667 | H57: 46170 | I57: =YEARDUR(H57,E57) -> 0 | J57: 78 | K57: 2 | L57: Simulation | M57: Exclusive | R57: =IF(S57="","TBD",IF(S57>TODAY(),"Coming Soon",IF(F57="","Active",IF(F57>TODAY(),"Leaving Soon","Removed")))) -> Active | S57: =E57 -> 46170 | T57: =MONTHDUR(E57,S57) -> 0
A58: Echo Generation 2 | B58: Xbox / PC | C58: Yes | D58: =IF(E58>TODAY(),"Coming Soon",IF(F58="","Active",IF(F58>TODAY(),"Leaving Soon","Removed"))) -> Active | E58: 46169 | G58: =MONTHDUR(E58,F58) -> 4.3 | H58: 46169 | I58: =YEARDUR(H58,E58) -> 0 | J58: 70 | K58: 9 | L58: RPG | M58: Exclusive | R58: =IF(S58="","TBD",IF(S58>TODAY(),"Coming Soon",IF(F58="","Active",IF(F58>TODAY(),"Leaving Soon","Removed")))) -> TBD | T58: =MONTHDUR(E58,S58) -> 4.3
A59: The Outer Worlds: Spacer’s Choice Edition | B59: Xbox / PC | C59: Yes | D59: =IF(E59>TODAY(),"Coming Soon",IF(F59="","Active",IF(F59>TODAY(),"Leaving Soon","Removed"))) -> Active | E59: 46169 | G59: =MONTHDUR(E59,F59) -> 4.3 | H59: 44992 | I59: =YEARDUR(H59,E59) -> 3.2222222 | J59: 82 | K59: 13 | L59: RPG | M59: Exclusive | R59: =IF(S59="","TBD",IF(S59>TODAY(),"Coming Soon",IF(F59="","Active",IF(F59>TODAY(),"Leaving Soon","Removed")))) -> Active | S59: =E59 -> 46169 | T59: =MONTHDUR(E59,S59) -> 0
A60: Escape Simulator | B60: Xbox / PC | C60: Yes | D60: =IF(E60>TODAY(),"Coming Soon",IF(F60="","Active",IF(F60>TODAY(),"Leaving Soon","Removed"))) -> Active | E60: 46168 | G60: =MONTHDUR(E60,F60) -> 4.3333333 | H60: 44491 | I60: =YEARDUR(H60,E60) -> 4.5944444 | J60: 81 | K60: 6 | L60: Puzzle | M60: Exclusive | R60: =IF(S60="","TBD",IF(S60>TODAY(),"Coming Soon",IF(F60="","Active",IF(F60>TODAY(),"Leaving Soon","Removed")))) -> Active | S60: =E60 -> 46168 | T60: =MONTHDUR(E60,S60) -> 0
A61: Luna Abyss | B61: Xbox / PC | C61: Yes | D61: =IF(E61>TODAY(),"Coming Soon",IF(F61="","Active",IF(F61>TODAY(),"Leaving Soon","Removed"))) -> Active | E61: 46163 | G61: =MONTHDUR(E61,F61) -> 4.5 | H61: 46163 | I61: =YEARDUR(H61,E61) -> 0 | J61: 81 | K61: 8 | L61: Shooter | M61: Exclusive | R61: =IF(S61="","TBD",IF(S61>TODAY(),"Coming Soon",IF(F61="","Active",IF(F61>TODAY(),"Leaving Soon","Removed")))) -> TBD | T61: =MONTHDUR(E61,S61) -> 4.5
A62: My Friend Peppa Pig | B62: Xbox / PC | C62: Touch Controls | D62: =IF(E62>TODAY(),"Coming Soon",IF(F62="","Active",IF(F62>TODAY(),"Leaving Soon","Removed"))) -> Active | E62: 46162 | G62: =MONTHDUR(E62,F62) -> 4.5333333 | H62: 44491 | I62: =YEARDUR(H62,E62) -> 4.5777778 | J62: 67 | K62: 3 | L62: Action-Adventure | N62: Returning title: joined 7/14/22, left 6/30/25 | R62: =IF(S62="","TBD",IF(S62>TODAY(),"Coming Soon",IF(F62="","Active",IF(F62>TODAY(),"Leaving Soon","Removed")))) -> Active | S62: =E62 -> 46162 | T62: =MONTHDUR(E62,S62) -> 0
A63: Remnant II | B63: Xbox / PC | C63: Yes | D63: =IF(E63>TODAY(),"Coming Soon",IF(F63="","Active",IF(F63>TODAY(),"Leaving Soon","Removed"))) -> Active | E63: 46162 | G63: =MONTHDUR(E63,F63) -> 4.5333333 | H63: 45132 | I63: =YEARDUR(H63,E63) -> 2.8194444 | J63: 84 | K63: 18 | L63: RPG | N63: Returning game: joined 11/29/23, left 5/31/25 | R63: =IF(S63="","TBD",IF(S63>TODAY(),"Coming Soon",IF(F63="","Active",IF(F63>TODAY(),"Leaving Soon","Removed")))) -> Active | S63: =E63 -> 46162 | T63: =MONTHDUR(E63,S63) -> 0
A64: Forza Horizon 6 | B64: Xbox / PC | C64: Yes | D64: =IF(E64>TODAY(),"Coming Soon",IF(F64="","Active",IF(F64>TODAY(),"Leaving Soon","Removed"))) -> Active | E64: 46161 | G64: =MONTHDUR(E64,F64) -> 4.5666667 | H64: 46161 | I64: =YEARDUR(H64,E64) -> 0 | J64: 92 | K64: 17 | L64: Racing | M64: Exclusive | N64: Handheld Optimized | R64: =IF(S64="","TBD",IF(S64>TODAY(),"Coming Soon",IF(F64="","Active",IF(F64>TODAY(),"Leaving Soon","Removed")))) -> TBD | T64: =MONTHDUR(E64,S64) -> 4.5666667
A65: Subnautica 2 (Game Preview) | B65: Xbox / PC | C65: Yes | D65: =IF(E65>TODAY(),"Coming Soon",IF(F65="","Active",IF(F65>TODAY(),"Leaving Soon","Removed"))) -> Active | E65: 46156 | G65: =MONTHDUR(E65,F65) -> 4.7333333 | H65: 46156 | I65: =YEARDUR(H65,E65) -> 0 | K65: 13 | L65: Action-Adventure | N65: Handheld Optimized | R65: =IF(S65="","TBD",IF(S65>TODAY(),"Coming Soon",IF(F65="","Active",IF(F65>TODAY(),"Leaving Soon","Removed")))) -> TBD | T65: =MONTHDUR(E65,S65) -> 4.7333333
A66: Black Jacket | B66: Xbox / PC | C66: Yes | D66: =IF(E66>TODAY(),"Coming Soon",IF(F66="","Active",IF(F66>TODAY(),"Leaving Soon","Removed"))) -> Active | E66: 46154 | G66: =MONTHDUR(E66,F66) -> 4.8 | H66: 46154 | I66: =YEARDUR(H66,E66) -> 0 | J66: 82 | K66: 6 | L66: Roguelike Card Game | M66: Exclusive | N66: Handheld Optimized | R66: =IF(S66="","TBD",IF(S66>TODAY(),"Coming Soon",IF(F66="","Active",IF(F66>TODAY(),"Leaving Soon","Removed")))) -> TBD | T66: =MONTHDUR(E66,S66) -> 4.8
A67: Call of the Elder Gods | B67: Xbox / PC | C67: Yes | D67: =IF(E67>TODAY(),"Coming Soon",IF(F67="","Active",IF(F67>TODAY(),"Leaving Soon","Removed"))) -> Active | E67: 46154 | G67: =MONTHDUR(E67,F67) -> 4.8 | H67: 46154 | I67: =YEARDUR(H67,E67) -> 0 | J67: 76 | K67: 6 | L67: Action-Adventure | M67: Exclusive | N67: Handheld Optimized | R67: =IF(S67="","TBD",IF(S67>TODAY(),"Coming Soon",IF(F67="","Active",IF(F67>TODAY(),"Leaving Soon","Removed")))) -> TBD | T67: =MONTHDUR(E67,S67) -> 4.8
A68: Elite Dangerous | B68: Xbox | C68: Yes | D68: =IF(E68>TODAY(),"Coming Soon",IF(F68="","Active",IF(F68>TODAY(),"Leaving Soon","Removed"))) -> Active | E68: 46154 | G68: =MONTHDUR(E68,F68) -> 4.8 | H68: 41989 | I68: =YEARDUR(H68,E68) -> 11.405556 | J68: 80 | K68: 113 | L68: Space Simulation | N68: Returning title: Joined 2/25/21, left 8/31/22 | R68: =IF(S68="","TBD",IF(S68>TODAY(),"Coming Soon",IF(F68="","Active",IF(F68>TODAY(),"Leaving Soon","Removed")))) -> Active | S68: =E68 -> 46154 | T68: =MONTHDUR(E68,S68) -> 0
A69: Outbound | B69: Xbox / PC | C69: Yes | D69: =IF(E69>TODAY(),"Coming Soon",IF(F69="","Active",IF(F69>TODAY(),"Leaving Soon","Removed"))) -> Active | E69: 46153 | G69: =MONTHDUR(E69,F69) -> 4.8333333 | H69: 46153 | I69: =YEARDUR(H69,E69) -> 0 | J69: 64 | K69: 15 | L69: Survival Crafting | R69: =IF(S69="","TBD",IF(S69>TODAY(),"Coming Soon",IF(F69="","Active",IF(F69>TODAY(),"Leaving Soon","Removed")))) -> TBD | T69: =MONTHDUR(E69,S69) -> 4.8333333
A70: Mixtape | B70: Xbox / PC | C70: Yes | D70: =IF(E70>TODAY(),"Coming Soon",IF(F70="","Active",IF(F70>TODAY(),"Leaving Soon","Removed"))) -> Active | E70: 46149 | G70: =MONTHDUR(E70,F70) -> 4.9666667 | H70: 46148 | I70: =YEARDUR(H70,E70) -> 0.0027777778 | J70: 86 | K70: 3 | L70: Adventure | M70: Exclusive | N70: Handheld Optimized | R70: =IF(S70="","TBD",IF(S70>TODAY(),"Coming Soon",IF(F70="","Active",IF(F70>TODAY(),"Leaving Soon","Removed")))) -> TBD | T70: =MONTHDUR(E70,S70) -> 4.9666667
A71: Ben 10: Power Trip | B71: Xbox / PC | C71: Touch Controls | D71: =IF(E71>TODAY(),"Coming Soon",IF(F71="","Active",IF(F71>TODAY(),"Leaving Soon","Removed"))) -> Active | E71: 46148 | G71: =MONTHDUR(E71,F71) -> 5 | H71: 44113 | I71: =YEARDUR(H71,E71) -> 5.575 | J71: 70 | K71: 5 | L71: Action-Adventure | N71: Returning title: Originally joined 12/16/21, left 8/31/25 | R71: =IF(S71="","TBD",IF(S71>TODAY(),"Coming Soon",IF(F71="","Active",IF(F71>TODAY(),"Leaving Soon","Removed")))) -> Active | S71: =E71 -> 46148 | T71: =MONTHDUR(E71,S71) -> 0
A72: Wildgate | B72: Xbox / PC | C72: Yes | D72: =IF(E72>TODAY(),"Coming Soon",IF(F72="","Active",IF(F72>TODAY(),"Leaving Soon","Removed"))) -> Active | E72: 46148 | G72: =MONTHDUR(E72,F72) -> 5 | H72: 45860 | I72: =YEARDUR(H72,E72) -> 0.78888889 | J72: 72 | K72: 19 | L72: Shooter | M72: Exclusive | R72: =IF(S72="","TBD",IF(S72>TODAY(),"Coming Soon",IF(F72="","Active",IF(F72>TODAY(),"Leaving Soon","Removed")))) -> Active | S72: =E72 -> 46148 | T72: =MONTHDUR(E72,S72) -> 0
A73: Final Fantasy V | B73: Xbox / PC | C73: Yes | D73: =IF(E73>TODAY(),"Coming Soon",IF(F73="","Active",IF(F73>TODAY(),"Leaving Soon","Removed"))) -> Active | E73: 46147 | G73: =MONTHDUR(E73,F73) -> 5.0333333 | H73: 39027 | I73: =YEARDUR(H73,E73) -> 19.497222 | J73: 82 | K73: 31 | L73: RPG | M73: Exclusive | R73: =IF(S73="","TBD",IF(S73>TODAY(),"Coming Soon",IF(F73="","Active",IF(F73>TODAY(),"Leaving Soon","Removed")))) -> Active | S73: =E73 -> 46147 | T73: =MONTHDUR(E73,S73) -> 0
A74: MOTORSLICE | B74: Xbox / PC | C74: Yes | D74: =IF(E74>TODAY(),"Coming Soon",IF(F74="","Active",IF(F74>TODAY(),"Leaving Soon","Removed"))) -> Active | E74: 46147 | G74: =MONTHDUR(E74,F74) -> 5.0333333 | H74: 46147 | I74: =YEARDUR(H74,E74) -> 0 | J74: 79 | K74: 8 | L74: Action-Adventure | R74: =IF(S74="","TBD",IF(S74>TODAY(),"Coming Soon",IF(F74="","Active",IF(F74>TODAY(),"Leaving Soon","Removed")))) -> TBD | T74: =MONTHDUR(E74,S74) -> 5.0333333
A75: Heroes of Might & Magic: Olden Era (Game Preview) | B75: PC | D75: =IF(E75>TODAY(),"Coming Soon",IF(F75="","Active",IF(F75>TODAY(),"Leaving Soon","Removed"))) -> Active | E75: 46142 | G75: =MONTHDUR(E75,F75) -> 5.2 | H75: 46142 | I75: =YEARDUR(H75,E75) -> 0 | J75: 80 | K75: 18 | L75: Strategy | R75: =IF(S75="","TBD",IF(S75>TODAY(),"Coming Soon",IF(F75="","Active",IF(F75>TODAY(),"Leaving Soon","Removed")))) -> TBD | T75: =MONTHDUR(E75,S75) -> 5.2
A76: inKonbini: One Store. Many Stories | B76: Xbox / PC | C76: Yes | D76: =IF(E76>TODAY(),"Coming Soon",IF(F76="","Active",IF(F76>TODAY(),"Leaving Soon","Removed"))) -> Active | E76: 46142 | G76: =MONTHDUR(E76,F76) -> 5.2 | H76: 46142 | I76: =YEARDUR(H76,E76) -> 0 | J76: 82 | K76: 7 | L76: Action-Adventure | N76: Handheld Optimized | R76: =IF(S76="","TBD",IF(S76>TODAY(),"Coming Soon",IF(F76="","Active",IF(F76>TODAY(),"Leaving Soon","Removed")))) -> TBD | T76: =MONTHDUR(E76,S76) -> 5.2
A77: Sledding Game (Game Preview) | B77: Xbox / PC | C77: Yes | D77: =IF(E77>TODAY(),"Coming Soon",IF(F77="","Active",IF(F77>TODAY(),"Leaving Soon","Removed"))) -> Active | E77: 46142 | G77: =MONTHDUR(E77,F77) -> 5.2 | H77: 46142 | I77: =YEARDUR(H77,E77) -> 0 | J77: 60 | K77: 27 | L77: Sports | M77: Exclusive | R77: =IF(S77="","TBD",IF(S77>TODAY(),"Coming Soon",IF(F77="","Active",IF(F77>TODAY(),"Leaving Soon","Removed")))) -> TBD | T77: =MONTHDUR(E77,S77) -> 5.2
A78: TerraTech Legion | B78: Xbox / PC | C78: Yes | D78: =IF(E78>TODAY(),"Coming Soon",IF(F78="","Active",IF(F78>TODAY(),"Leaving Soon","Removed"))) -> Active | E78: 46142 | G78: =MONTHDUR(E78,F78) -> 5.2 | H78: 46142 | I78: =YEARDUR(H78,E78) -> 0 | J78: 85 | K78: 4 | L78: Action-Adventure | M78: Exclusive | R78: =IF(S78="","TBD",IF(S78>TODAY(),"Coming Soon",IF(F78="","Active",IF(F78>TODAY(),"Leaving Soon","Removed")))) -> TBD | T78: =MONTHDUR(E78,S78) -> 5.2
A79: Trepang2 | B79: Xbox / PC | C79: Yes | D79: =IF(E79>TODAY(),"Coming Soon",IF(F79="","Active",IF(F79>TODAY(),"Leaving Soon","Removed"))) -> Active | E79: 46141 | G79: =MONTHDUR(E79,F79) -> 5.2333333 | H79: 45098 | I79: =YEARDUR(H79,E79) -> 2.8555556 | J79: 79 | K79: 5 | L79: Shooter | M79: Exclusive | R79: =IF(S79="","TBD",IF(S79>TODAY(),"Coming Soon",IF(F79="","Active",IF(F79>TODAY(),"Leaving Soon","Removed")))) -> Active | S79: =E79 -> 46141 | T79: =MONTHDUR(E79,S79) -> 0
A80: Aphelion | B80: Xbox / PC | C80: Yes | D80: =IF(E80>TODAY(),"Coming Soon",IF(F80="","Active",IF(F80>TODAY(),"Leaving Soon","Removed"))) -> Active | E80: 46140 | G80: =MONTHDUR(E80,F80) -> 5.2666667 | H80: 46140 | I80: =YEARDUR(H80,E80) -> 0 | J80: 63 | K80: 7 | L80: Action-Adventure | M80: Exclusive | N80: Handheld Optimized | R80: =IF(S80="","TBD",IF(S80>TODAY(),"Coming Soon",IF(F80="","Active",IF(F80>TODAY(),"Leaving Soon","Removed")))) -> TBD | T80: =MONTHDUR(E80,S80) -> 5.2666667
A81: Kiln | B81: Xbox / PC | C81: Yes | D81: =IF(E81>TODAY(),"Coming Soon",IF(F81="","Active",IF(F81>TODAY(),"Leaving Soon","Removed"))) -> Active | E81: 46135 | G81: =MONTHDUR(E81,F81) -> 5.4333333 | H81: 46135 | I81: =YEARDUR(H81,E81) -> 0 | J81: 68 | K81: 6 | L81: Shooter | M81: Exclusive | N81: Handheld Optimized | R81: =IF(S81="","TBD",IF(S81>TODAY(),"Coming Soon",IF(F81="","Active",IF(F81>TODAY(),"Leaving Soon","Removed")))) -> TBD | T81: =MONTHDUR(E81,S81) -> 5.4333333
A82: Vampire Crawlers: The Turbo Wildcard from Vampire Survivors | B82: Xbox / PC | C82: Yes | D82: =IF(E82>TODAY(),"Coming Soon",IF(F82="","Active",IF(F82>TODAY(),"Leaving Soon","Removed"))) -> Active | E82: 46133 | G82: =MONTHDUR(E82,F82) -> 5.5 | H82: 46133 | I82: =YEARDUR(H82,E82) -> 0 | J82: 83 | K82: 14 | L82: Card Battle | M82: Exclusive | N82: Handheld Optimized | R82: =IF(S82="","TBD",IF(S82>TODAY(),"Coming Soon",IF(F82="","Active",IF(F82>TODAY(),"Leaving Soon","Removed")))) -> TBD | T82: =MONTHDUR(E82,S82) -> 5.5
A83: Call of Duty: Modern Warfare (2019) | B83: Xbox / PC | C83: Yes | D83: =IF(E83>TODAY(),"Coming Soon",IF(F83="","Active",IF(F83>TODAY(),"Leaving Soon","Removed"))) -> Active | E83: 46129 | G83: =MONTHDUR(E83,F83) -> 5.6333333 | H83: 43763 | I83: =YEARDUR(H83,E83) -> 6.4777778 | J83: 80 | K83: 6 | L83: Shooter | R83: =IF(S83="","TBD",IF(S83>TODAY(),"Coming Soon",IF(F83="","Active",IF(F83>TODAY(),"Leaving Soon","Removed")))) -> Active | S83: =E83 -> 46129 | T83: =MONTHDUR(E83,S83) -> 0
A84: NHL 26 | B84: Xbox | C84: Yes | D84: =IF(E84>TODAY(),"Coming Soon",IF(F84="","Active",IF(F84>TODAY(),"Leaving Soon","Removed"))) -> Active | E84: 46128 | G84: =MONTHDUR(E84,F84) -> 5.6666667 | H84: 45912 | I84: =YEARDUR(H84,E84) -> 0.59444444 | J84: 73 | K84: 20 | L84: Sports | M84: Exclusive | R84: =IF(S84="","TBD",IF(S84>TODAY(),"Coming Soon",IF(F84="","Active",IF(F84>TODAY(),"Leaving Soon","Removed")))) -> TBD | T84: =MONTHDUR(E84,S84) -> 5.6666667
A85: Hades II | B85: Xbox / PC | C85: Yes | D85: =IF(E85>TODAY(),"Coming Soon",IF(F85="","Active",IF(F85>TODAY(),"Leaving Soon","Removed"))) -> Active | E85: 46126 | G85: =MONTHDUR(E85,F85) -> 5.7333333 | H85: 45925 | I85: =YEARDUR(H85,E85) -> 0.55277778 | J85: 95 | K85: 22 | L85: RPG | M85: Exclusive | N85: Handheld Optimized | R85: =IF(S85="","TBD",IF(S85>TODAY(),"Coming Soon",IF(F85="","Active",IF(F85>TODAY(),"Leaving Soon","Removed")))) -> Active | S85: =E85 -> 46126 | T85: =MONTHDUR(E85,S85) -> 0
A86: REPLACED | B86: Xbox / PC | C86: Yes | D86: =IF(E86>TODAY(),"Coming Soon",IF(F86="","Active",IF(F86>TODAY(),"Leaving Soon","Removed"))) -> Active | E86: 46126 | G86: =MONTHDUR(E86,F86) -> 5.7333333 | H86: 46126 | I86: =YEARDUR(H86,E86) -> 0 | J86: 76 | K86: 11 | L86: Action-Adventure | M86: Exclusive | R86: =IF(S86="","TBD",IF(S86>TODAY(),"Coming Soon",IF(F86="","Active",IF(F86>TODAY(),"Leaving Soon","Removed")))) -> TBD | T86: =MONTHDUR(E86,S86) -> 5.7333333
A87: The Thaumaturge | B87: Xbox / PC | C87: Yes | D87: =IF(E87>TODAY(),"Coming Soon",IF(F87="","Active",IF(F87>TODAY(),"Leaving Soon","Removed"))) -> Active | E87: 46126 | G87: =MONTHDUR(E87,F87) -> 5.7333333 | H87: 45355 | I87: =YEARDUR(H87,E87) -> 2.1111111 | J87: 74 | K87: 16 | L87: RPG | M87: Exclusive | R87: =IF(S87="","TBD",IF(S87>TODAY(),"Coming Soon",IF(F87="","Active",IF(F87>TODAY(),"Leaving Soon","Removed")))) -> Active | S87: =E87 -> 46126 | T87: =MONTHDUR(E87,S87) -> 0
A88: Tiny Bookshop | B88: Xbox / PC | C88: Yes | D88: =IF(E88>TODAY(),"Coming Soon",IF(F88="","Active",IF(F88>TODAY(),"Leaving Soon","Removed"))) -> Active | E88: 46122 | G88: =MONTHDUR(E88,F88) -> 5.8666667 | H88: 45876 | I88: =YEARDUR(H88,E88) -> 0.675 | J88: 81 | K88: 16 | L88: Tycoon | M88: Exclusive | N88: Handheld Optimized | R88: =IF(S88="","TBD",IF(S88>TODAY(),"Coming Soon",IF(F88="","Active",IF(F88>TODAY(),"Leaving Soon","Removed")))) -> Active | S88: =E88 -> 46122 | T88: =MONTHDUR(E88,S88) -> 0
A89: Planet Coaster 2 | B89: Xbox / PC | C89: Yes | D89: =IF(E89>TODAY(),"Coming Soon",IF(F89="","Active",IF(F89>TODAY(),"Leaving Soon","Removed"))) -> Active | E89: 46121 | G89: =MONTHDUR(E89,F89) -> 5.9 | H89: 45602 | I89: =YEARDUR(H89,E89) -> 1.425 | J89: 76 | K89: 32 | L89: Simulation | M89: Exclusive | R89: =IF(S89="","TBD",IF(S89>TODAY(),"Coming Soon",IF(F89="","Active",IF(F89>TODAY(),"Leaving Soon","Removed")))) -> Active | S89: =E89 -> 46121 | T89: =MONTHDUR(E89,S89) -> 0
A90: Final Fantasy IV | B90: Xbox / PC | C90: Yes | D90: =IF(E90>TODAY(),"Coming Soon",IF(F90="","Active",IF(F90>TODAY(),"Leaving Soon","Removed"))) -> Active | E90: 46119 | G90: =MONTHDUR(E90,F90) -> 5.9666667 | H90: 41899 | I90: =YEARDUR(H90,E90) -> 11.555556 | J90: 67 | K90: 23 | L90: RPG | M90: Exclusive | R90: =IF(S90="","TBD",IF(S90>TODAY(),"Coming Soon",IF(F90="","Active",IF(F90>TODAY(),"Leaving Soon","Removed")))) -> Active | S90: =E90 -> 46119 | T90: =MONTHDUR(E90,S90) -> 0
A91: Barbie Horse Trails | B91: Xbox / PC | C91: Yes | D91: =IF(E91>TODAY(),"Coming Soon",IF(F91="","Active",IF(F91>TODAY(),"Leaving Soon","Removed"))) -> Active | E91: 46114 | G91: =MONTHDUR(E91,F91) -> 6.1333333 | H91: 39734 | I91: =YEARDUR(H91,E91) -> 17.469444 | J91: 80 | K91: 6 | L91: Action-Adventure | N91: Handheld Optimized | R91: =IF(S91="","TBD",IF(S91>TODAY(),"Coming Soon",IF(F91="","Active",IF(F91>TODAY(),"Leaving Soon","Removed")))) -> Active | S91: =E91 -> 46114 | T91: =MONTHDUR(E91,S91) -> 0
A92: Resident Evil 7: Biohazard | B92: Xbox / PC | C92: Yes | D92: =IF(E92>TODAY(),"Coming Soon",IF(F92="","Active",IF(F92>TODAY(),"Leaving Soon","Removed"))) -> Active | E92: 46112 | G92: =MONTHDUR(E92,F92) -> 6.2 | H92: 42759 | I92: =YEARDUR(H92,E92) -> 9.1833333 | J92: 86 | K92: 9 | L92: Action-Adventure | N92: Returning title: Joined 9/3/20, left 5/31/22 | R92: =IF(S92="","TBD",IF(S92>TODAY(),"Coming Soon",IF(F92="","Active",IF(F92>TODAY(),"Leaving Soon","Removed")))) -> Active | S92: =E92 -> 46112 | T92: =MONTHDUR(E92,S92) -> 0
A93: Super Meat Boy 3D | B93: Xbox / PC | C93: Yes | D93: =IF(E93>TODAY(),"Coming Soon",IF(F93="","Active",IF(F93>TODAY(),"Leaving Soon","Removed"))) -> Active | E93: 46112 | G93: =MONTHDUR(E93,F93) -> 6.2 | H93: 46112 | I93: =YEARDUR(H93,E93) -> 0 | J93: 75 | K93: 6 | L93: Platformer | M93: Exclusive | N93: Handheld Optimized | R93: =IF(S93="","TBD",IF(S93>TODAY(),"Coming Soon",IF(F93="","Active",IF(F93>TODAY(),"Leaving Soon","Removed")))) -> TBD | T93: =MONTHDUR(E93,S93) -> 6.2
A94: The Long Dark | B94: Xbox / PC | C94: Yes | D94: =IF(E94>TODAY(),"Coming Soon",IF(F94="","Active",IF(F94>TODAY(),"Leaving Soon","Removed"))) -> Active | E94: 46111 | G94: =MONTHDUR(E94,F94) -> 6.2 | H94: 42948 | I94: =YEARDUR(H94,E94) -> 8.6638889 | J94: 77 | K94: 20 | L94: Action-Adventure | N94: Returning title: Joined 4/16/20, left 4/15/23 | R94: =IF(S94="","TBD",IF(S94>TODAY(),"Coming Soon",IF(F94="","Active",IF(F94>TODAY(),"Leaving Soon","Removed")))) -> Active | S94: =E94 -> 46111 | T94: =MONTHDUR(E94,S94) -> 0
A95: Easy Delivery Co. | B95: Xbox / PC | C95: Yes | D95: =IF(E95>TODAY(),"Coming Soon",IF(F95="","Active",IF(F95>TODAY(),"Leaving Soon","Removed"))) -> Active | E95: 46107 | G95: =MONTHDUR(E95,F95) -> 6.3333333 | H95: 45918 | I95: =YEARDUR(H95,E95) -> 0.52222222 | J95: 73 | K95: 5 | L95: Action-Adventure | N95: Handheld Optimized | R95: =IF(S95="","TBD",IF(S95>TODAY(),"Coming Soon",IF(F95="","Active",IF(F95>TODAY(),"Leaving Soon","Removed")))) -> Active | S95: =E95 -> 46107 | T95: =MONTHDUR(E95,S95) -> 0
A96: Absolum | B96: Xbox / PC | C96: Yes | D96: =IF(E96>TODAY(),"Coming Soon",IF(F96="","Active",IF(F96>TODAY(),"Leaving Soon","Removed"))) -> Active | E96: 46106 | G96: =MONTHDUR(E96,F96) -> 6.3666667 | H96: 45939 | I96: =YEARDUR(H96,E96) -> 0.46111111 | J96: 87 | K96: 9 | L96: Beat-’Em-Up | M96: Exclusive | R96: =IF(S96="","TBD",IF(S96>TODAY(),"Coming Soon",IF(F96="","Active",IF(F96>TODAY(),"Leaving Soon","Removed")))) -> Active | S96: =E96 -> 46106 | T96: =MONTHDUR(E96,S96) -> 0
A97: Like a Dragon: Infinite Wealth | B97: Xbox / PC | C97: Yes | D97: =IF(E97>TODAY(),"Coming Soon",IF(F97="","Active",IF(F97>TODAY(),"Leaving Soon","Removed"))) -> Active | E97: 46105 | G97: =MONTHDUR(E97,F97) -> 6.4 | H97: 45317 | I97: =YEARDUR(H97,E97) -> 2.1611111 | J97: 89 | K97: 45 | L97: RPG | N97: Handheld Optimized | R97: =IF(S97="","TBD",IF(S97>TODAY(),"Coming Soon",IF(F97="","Active",IF(F97>TODAY(),"Leaving Soon","Removed")))) -> Active | S97: =E97 -> 46105 | T97: =MONTHDUR(E97,S97) -> 0
A98: Disco Elysium | B98: Xbox / PC | C98: Yes | D98: =IF(E98>TODAY(),"Coming Soon",IF(F98="","Active",IF(F98>TODAY(),"Leaving Soon","Removed"))) -> Active | E98: 46100 | G98: =MONTHDUR(E98,F98) -> 6.5666667 | H98: 43753 | I98: =YEARDUR(H98,E98) -> 6.4277778 | J98: 91 | K98: 23 | L98: RPG | M98: Exclusive | R98: =IF(S98="","TBD",IF(S98>TODAY(),"Coming Soon",IF(F98="","Active",IF(F98>TODAY(),"Leaving Soon","Removed")))) -> Active | S98: =E98 -> 46100 | T98: =MONTHDUR(E98,S98) -> 0
A99: DreamWorks Gabby's Dollhouse: Ready to Party | B99: Xbox / PC | C99: Yes | D99: =IF(E99>TODAY(),"Coming Soon",IF(F99="","Active",IF(F99>TODAY(),"Leaving Soon","Removed"))) -> Active | E99: 46098 | G99: =MONTHDUR(E99,F99) -> 6.6333333 | H99: 45919 | I99: =YEARDUR(H99,E99) -> 0.49444444 | J99: 80 | K99: 3 | L99: Action-Adventure | M99: Exclusive | R99: =IF(S99="","TBD",IF(S99>TODAY(),"Coming Soon",IF(F99="","Active",IF(F99>TODAY(),"Leaving Soon","Removed")))) -> Active | S99: =E99 -> 46098 | T99: =MONTHDUR(E99,S99) -> 0
A100: Construction Simulator | B100: Xbox / PC | C100: Yes | D100: =IF(E100>TODAY(),"Coming Soon",IF(F100="","Active",IF(F100>TODAY(),"Leaving Soon","Removed"))) -> Active | E100: 46091 | G100: =MONTHDUR(E100,F100) -> 6.8666667 | H100: 43775 | I100: =YEARDUR(H100,E100) -> 6.3444444 | J100: 72 | K100: 43 | L100: Simulation | R100: =IF(S100="","TBD",IF(S100>TODAY(),"Coming Soon",IF(F100="","Active",IF(F100>TODAY(),"Leaving Soon","Removed")))) -> Active | S100: =E100 -> 46091 | T100: =MONTHDUR(E100,S100) -> 0
...

Sheet Likely Leaving
A1: Complete Game Pass Master List by u/ABattleVet | B1: =COUNTIF(D2:D544,"Active")+COUNTIF(D2:D544,"Leaving Soon") -> 89 | C1: https://www.trueachievements.com/gamer/Bloomy/blog | Q1: l
A2: Game | B2: System | C2: xCloud | D2: Status | E2: Added | F2: Removed | G2: Months | H2: Release | I2: Age | J2: Metacritic | K2: Completion | L2: Genre (Giantbomb) | M2: Xbox Series X|S | N2: Owner Notes | O2: ESRB | P2: ESRB Content Descriptors | Q2: Public Notes
A3: =IFERROR(__xludf.DUMMYFUNCTION("SORT(FILTER('Master List'!A:Q, 'Master List'!D:D=""Active"", ISNA(MATCH('Master List'!A:A, 'Xbox Game Studios'!A:A, 0)), ISNA(MATCH('Master List'!A:A, 'EA Play'!A:A, 0)), map('Master List'!G:G, lambda(a, if(isnumber(a), (a > 1) * ((mod(a, 12) > 10.5) + (m"&"od(a, 12) < 1)), 0)))),7,1)"),"Clover Pit") -> Clover Pit | B3: =IFERROR(__xludf.DUMMYFUNCTION("""COMPUTED_VALUE"""),"Xbox / PC") -> Xbox / PC | C3: =IFERROR(__xludf.DUMMYFUNCTION("""COMPUTED_VALUE"""),"Yes") -> Yes | D3: =IFERROR(__xludf.DUMMYFUNCTION("""COMPUTED_VALUE"""),"Active") -> Active | E3: =IFERROR(__xludf.DUMMYFUNCTION("""COMPUTED_VALUE"""),45981.0) -> 45981 | G3: =IFERROR(__xludf.DUMMYFUNCTION("""COMPUTED_VALUE"""),10.533333333333333) -> 10.533333 | H3: =IFERROR(__xludf.DUMMYFUNCTION("""COMPUTED_VALUE"""),45926.0) -> 45926 | I3: =IFERROR(__xludf.DUMMYFUNCTION("""COMPUTED_VALUE"""),0.15) -> 0.15 | J3: =IFERROR(__xludf.DUMMYFUNCTION("""COMPUTED_VALUE"""),77.0) -> 77 | K3: =IFERROR(__xludf.DUMMYFUNCTION("""COMPUTED_VALUE"""),8.0) -> 8 | L3: =IFERROR(__xludf.DUMMYFUNCTION("""COMPUTED_VALUE"""),"Action-Adventure") -> Action-Adventure | N3: =IFERROR(__xludf.DUMMYFUNCTION("""COMPUTED_VALUE"""),"Handheld Optimized") -> Handheld Optimized
A4: =IFERROR(__xludf.DUMMYFUNCTION("""COMPUTED_VALUE"""),"Monsters are Coming! Rock & Road") -> Monsters are Coming! Rock & Road | B4: =IFERROR(__xludf.DUMMYFUNCTION("""COMPUTED_VALUE"""),"PC") -> PC | D4: =IFERROR(__xludf.DUMMYFUNCTION("""COMPUTED_VALUE"""),"Active") -> Active | E4: =IFERROR(__xludf.DUMMYFUNCTION("""COMPUTED_VALUE"""),45981.0) -> 45981 | G4: =IFERROR(__xludf.DUMMYFUNCTION("""COMPUTED_VALUE"""),10.533333333333333) -> 10.533333 | H4: =IFERROR(__xludf.DUMMYFUNCTION("""COMPUTED_VALUE"""),45981.0) -> 45981 | I4: =IFERROR(__xludf.DUMMYFUNCTION("""COMPUTED_VALUE"""),0.0) -> 0 | J4: =IFERROR(__xludf.DUMMYFUNCTION("""COMPUTED_VALUE"""),79.0) -> 79 | K4: =IFERROR(__xludf.DUMMYFUNCTION("""COMPUTED_VALUE"""),3.0) -> 3 | L4: =IFERROR(__xludf.DUMMYFUNCTION("""COMPUTED_VALUE"""),"Action-Adventure") -> Action-Adventure
A5: =IFERROR(__xludf.DUMMYFUNCTION("""COMPUTED_VALUE"""),"The Crew Motorfest") -> The Crew Motorfest | B5: =IFERROR(__xludf.DUMMYFUNCTION("""COMPUTED_VALUE"""),"Xbox / PC") -> Xbox / PC | C5: =IFERROR(__xludf.DUMMYFUNCTION("""COMPUTED_VALUE"""),"Yes") -> Yes | D5: =IFERROR(__xludf.DUMMYFUNCTION("""COMPUTED_VALUE"""),"Active") -> Active | E5: =IFERROR(__xludf.DUMMYFUNCTION("""COMPUTED_VALUE"""),45981.0) -> 45981 | G5: =IFERROR(__xludf.DUMMYFUNCTION("""COMPUTED_VALUE"""),10.533333333333333) -> 10.533333 | H5: =IFERROR(__xludf.DUMMYFUNCTION("""COMPUTED_VALUE"""),45183.0) -> 45183 | I5: =IFERROR(__xludf.DUMMYFUNCTION("""COMPUTED_VALUE"""),2.183333333333333) -> 2.1833333 | J5: =IFERROR(__xludf.DUMMYFUNCTION("""COMPUTED_VALUE"""),76.0) -> 76 | K5: =IFERROR(__xludf.DUMMYFUNCTION("""COMPUTED_VALUE"""),21.0) -> 21 | L5: =IFERROR(__xludf.DUMMYFUNCTION("""COMPUTED_VALUE"""),"Racing") -> Racing
A6: =IFERROR(__xludf.DUMMYFUNCTION("""COMPUTED_VALUE"""),"Total Chaos (2025)") -> Total Chaos (2025) | B6: =IFERROR(__xludf.DUMMYFUNCTION("""COMPUTED_VALUE"""),"Xbox / PC") -> Xbox / PC | C6: =IFERROR(__xludf.DUMMYFUNCTION("""COMPUTED_VALUE"""),"Yes") -> Yes | D6: =IFERROR(__xludf.DUMMYFUNCTION("""COMPUTED_VALUE"""),"Active") -> Active | E6: =IFERROR(__xludf.DUMMYFUNCTION("""COMPUTED_VALUE"""),45981.0) -> 45981 | G6: =IFERROR(__xludf.DUMMYFUNCTION("""COMPUTED_VALUE"""),10.533333333333333) -> 10.533333 | H6: =IFERROR(__xludf.DUMMYFUNCTION("""COMPUTED_VALUE"""),45981.0) -> 45981 | I6: =IFERROR(__xludf.DUMMYFUNCTION("""COMPUTED_VALUE"""),0.0) -> 0 | J6: =IFERROR(__xludf.DUMMYFUNCTION("""COMPUTED_VALUE"""),80.0) -> 80 | K6: =IFERROR(__xludf.DUMMYFUNCTION("""COMPUTED_VALUE"""),11.0) -> 11 | L6: =IFERROR(__xludf.DUMMYFUNCTION("""COMPUTED_VALUE"""),"Action-Adventure") -> Action-Adventure | M6: =IFERROR(__xludf.DUMMYFUNCTION("""COMPUTED_VALUE"""),"Exclusive") -> Exclusive
A7: =IFERROR(__xludf.DUMMYFUNCTION("""COMPUTED_VALUE"""),"Moonlighter 2: The Endless Vault (Game Preview)") -> Moonlighter 2: The Endless Vault (Game Preview) | B7: =IFERROR(__xludf.DUMMYFUNCTION("""COMPUTED_VALUE"""),"PC") -> PC | D7: =IFERROR(__xludf.DUMMYFUNCTION("""COMPUTED_VALUE"""),"Active") -> Active | E7: =IFERROR(__xludf.DUMMYFUNCTION("""COMPUTED_VALUE"""),45980.0) -> 45980 | G7: =IFERROR(__xludf.DUMMYFUNCTION("""COMPUTED_VALUE"""),10.566666666666666) -> 10.566667 | H7: =IFERROR(__xludf.DUMMYFUNCTION("""COMPUTED_VALUE"""),45980.0) -> 45980 | I7: =IFERROR(__xludf.DUMMYFUNCTION("""COMPUTED_VALUE"""),0.0) -> 0 | K7: =IFERROR(__xludf.DUMMYFUNCTION("""COMPUTED_VALUE"""),13.0) -> 13 | L7: =IFERROR(__xludf.DUMMYFUNCTION("""COMPUTED_VALUE"""),"Action-Adventure") -> Action-Adventure
A8: =IFERROR(__xludf.DUMMYFUNCTION("""COMPUTED_VALUE"""),"Relic Hunters Legend") -> Relic Hunters Legend | B8: =IFERROR(__xludf.DUMMYFUNCTION("""COMPUTED_VALUE"""),"Xbox / PC") -> Xbox / PC | C8: =IFERROR(__xludf.DUMMYFUNCTION("""COMPUTED_VALUE"""),"Yes") -> Yes | D8: =IFERROR(__xludf.DUMMYFUNCTION("""COMPUTED_VALUE"""),"Active") -> Active | E8: =IFERROR(__xludf.DUMMYFUNCTION("""COMPUTED_VALUE"""),45973.0) -> 45973 | G8: =IFERROR(__xludf.DUMMYFUNCTION("""COMPUTED_VALUE"""),10.8) -> 10.8 | H8: =IFERROR(__xludf.DUMMYFUNCTION("""COMPUTED_VALUE"""),45883.0) -> 45883 | I8: =IFERROR(__xludf.DUMMYFUNCTION("""COMPUTED_VALUE"""),0.24444444444444444) -> 0.24444444 | K8: =IFERROR(__xludf.DUMMYFUNCTION("""COMPUTED_VALUE"""),29.0) -> 29 | L8: =IFERROR(__xludf.DUMMYFUNCTION("""COMPUTED_VALUE"""),"Shoot-’Em-Up") -> Shoot-’Em-Up
A9: =IFERROR(__xludf.DUMMYFUNCTION("""COMPUTED_VALUE"""),"Winter Burrow") -> Winter Burrow | B9: =IFERROR(__xludf.DUMMYFUNCTION("""COMPUTED_VALUE"""),"Xbox / PC") -> Xbox / PC | C9: =IFERROR(__xludf.DUMMYFUNCTION("""COMPUTED_VALUE"""),"Yes") -> Yes | D9: =IFERROR(__xludf.DUMMYFUNCTION("""COMPUTED_VALUE"""),"Active") -> Active | E9: =IFERROR(__xludf.DUMMYFUNCTION("""COMPUTED_VALUE"""),45973.0) -> 45973 | G9: =IFERROR(__xludf.DUMMYFUNCTION("""COMPUTED_VALUE"""),10.8) -> 10.8 | H9: =IFERROR(__xludf.DUMMYFUNCTION("""COMPUTED_VALUE"""),45973.0) -> 45973 | I9: =IFERROR(__xludf.DUMMYFUNCTION("""COMPUTED_VALUE"""),0.0) -> 0 | J9: =IFERROR(__xludf.DUMMYFUNCTION("""COMPUTED_VALUE"""),68.0) -> 68 | K9: =IFERROR(__xludf.DUMMYFUNCTION("""COMPUTED_VALUE"""),8.0) -> 8 | L9: =IFERROR(__xludf.DUMMYFUNCTION("""COMPUTED_VALUE"""),"Action-Adventure") -> Action-Adventure
A10: =IFERROR(__xludf.DUMMYFUNCTION("""COMPUTED_VALUE"""),"Great God Grove") -> Great God Grove | B10: =IFERROR(__xludf.DUMMYFUNCTION("""COMPUTED_VALUE"""),"Xbox / PC") -> Xbox / PC | C10: =IFERROR(__xludf.DUMMYFUNCTION("""COMPUTED_VALUE"""),"Yes") -> Yes | D10: =IFERROR(__xludf.DUMMYFUNCTION("""COMPUTED_VALUE"""),"Active") -> Active | E10: =IFERROR(__xludf.DUMMYFUNCTION("""COMPUTED_VALUE"""),45972.0) -> 45972 | G10: =IFERROR(__xludf.DUMMYFUNCTION("""COMPUTED_VALUE"""),10.833333333333334) -> 10.833333 | H10: =IFERROR(__xludf.DUMMYFUNCTION("""COMPUTED_VALUE"""),45611.0) -> 45611 | I10: =IFERROR(__xludf.DUMMYFUNCTION("""COMPUTED_VALUE"""),0.9888888888888889) -> 0.98888889 | J10: =IFERROR(__xludf.DUMMYFUNCTION("""COMPUTED_VALUE"""),81.0) -> 81 | K10: =IFERROR(__xludf.DUMMYFUNCTION("""COMPUTED_VALUE"""),6.0) -> 6 | L10: =IFERROR(__xludf.DUMMYFUNCTION("""COMPUTED_VALUE"""),"Action-Adventure") -> Action-Adventure | M10: =IFERROR(__xludf.DUMMYFUNCTION("""COMPUTED_VALUE"""),"Exclusive") -> Exclusive
A11: =IFERROR(__xludf.DUMMYFUNCTION("""COMPUTED_VALUE"""),"Lara Croft and the Temple of Osiris") -> Lara Croft and the Temple of Osiris | B11: =IFERROR(__xludf.DUMMYFUNCTION("""COMPUTED_VALUE"""),"Xbox / PC") -> Xbox / PC | C11: =IFERROR(__xludf.DUMMYFUNCTION("""COMPUTED_VALUE"""),"Yes") -> Yes | D11: =IFERROR(__xludf.DUMMYFUNCTION("""COMPUTED_VALUE"""),"Active") -> Active | E11: =IFERROR(__xludf.DUMMYFUNCTION("""COMPUTED_VALUE"""),45972.0) -> 45972 | G11: =IFERROR(__xludf.DUMMYFUNCTION("""COMPUTED_VALUE"""),10.833333333333334) -> 10.833333 | H11: =IFERROR(__xludf.DUMMYFUNCTION("""COMPUTED_VALUE"""),41982.0) -> 41982 | I11: =IFERROR(__xludf.DUMMYFUNCTION("""COMPUTED_VALUE"""),10.922222222222222) -> 10.922222 | J11: =IFERROR(__xludf.DUMMYFUNCTION("""COMPUTED_VALUE"""),74.0) -> 74 | K11: =IFERROR(__xludf.DUMMYFUNCTION("""COMPUTED_VALUE"""),5.0) -> 5 | L11: =IFERROR(__xludf.DUMMYFUNCTION("""COMPUTED_VALUE"""),"Action-Adventure") -> Action-Adventure
A12: =IFERROR(__xludf.DUMMYFUNCTION("""COMPUTED_VALUE"""),"Pigeon Simulator") -> Pigeon Simulator | B12: =IFERROR(__xludf.DUMMYFUNCTION("""COMPUTED_VALUE"""),"Xbox / PC") -> Xbox / PC | C12: =IFERROR(__xludf.DUMMYFUNCTION("""COMPUTED_VALUE"""),"Yes") -> Yes | D12: =IFERROR(__xludf.DUMMYFUNCTION("""COMPUTED_VALUE"""),"Active") -> Active | E12: =IFERROR(__xludf.DUMMYFUNCTION("""COMPUTED_VALUE"""),45972.0) -> 45972 | G12: =IFERROR(__xludf.DUMMYFUNCTION("""COMPUTED_VALUE"""),10.833333333333334) -> 10.833333 | H12: =IFERROR(__xludf.DUMMYFUNCTION("""COMPUTED_VALUE"""),45972.0) -> 45972 | I12: =IFERROR(__xludf.DUMMYFUNCTION("""COMPUTED_VALUE"""),0.0) -> 0 | J12: =IFERROR(__xludf.DUMMYFUNCTION("""COMPUTED_VALUE"""),64.0) -> 64 | K12: =IFERROR(__xludf.DUMMYFUNCTION("""COMPUTED_VALUE"""),7.0) -> 7 | L12: =IFERROR(__xludf.DUMMYFUNCTION("""COMPUTED_VALUE"""),"Sandbox") -> Sandbox | M12: =IFERROR(__xludf.DUMMYFUNCTION("""COMPUTED_VALUE"""),"Exclusive") -> Exclusive
A13: =IFERROR(__xludf.DUMMYFUNCTION("""COMPUTED_VALUE"""),"Voidtrain") -> Voidtrain | B13: =IFERROR(__xludf.DUMMYFUNCTION("""COMPUTED_VALUE"""),"Xbox / PC") -> Xbox / PC | C13: =IFERROR(__xludf.DUMMYFUNCTION("""COMPUTED_VALUE"""),"Yes") -> Yes | D13: =IFERROR(__xludf.DUMMYFUNCTION("""COMPUTED_VALUE"""),"Active") -> Active | E13: =IFERROR(__xludf.DUMMYFUNCTION("""COMPUTED_VALUE"""),45968.0) -> 45968 | G13: =IFERROR(__xludf.DUMMYFUNCTION("""COMPUTED_VALUE"""),10.966666666666667) -> 10.966667 | H13: =IFERROR(__xludf.DUMMYFUNCTION("""COMPUTED_VALUE"""),45968.0) -> 45968 | I13: =IFERROR(__xludf.DUMMYFUNCTION("""COMPUTED_VALUE"""),0.0) -> 0 | J13: =IFERROR(__xludf.DUMMYFUNCTION("""COMPUTED_VALUE"""),82.0) -> 82 | K13: =IFERROR(__xludf.DUMMYFUNCTION("""COMPUTED_VALUE"""),19.0) -> 19 | L13: =IFERROR(__xludf.DUMMYFUNCTION("""COMPUTED_VALUE"""),"Shooter") -> Shooter | M13: =IFERROR(__xludf.DUMMYFUNCTION("""COMPUTED_VALUE"""),"Exclusive") -> Exclusive
A14: =IFERROR(__xludf.DUMMYFUNCTION("""COMPUTED_VALUE"""),"Egging On") -> Egging On | B14: =IFERROR(__xludf.DUMMYFUNCTION("""COMPUTED_VALUE"""),"Xbox / PC") -> Xbox / PC | C14: =IFERROR(__xludf.DUMMYFUNCTION("""COMPUTED_VALUE"""),"Yes") -> Yes | D14: =IFERROR(__xludf.DUMMYFUNCTION("""COMPUTED_VALUE"""),"Active") -> Active | E14: =IFERROR(__xludf.DUMMYFUNCTION("""COMPUTED_VALUE"""),45967.0) -> 45967 | G14: =IFERROR(__xludf.DUMMYFUNCTION("""COMPUTED_VALUE"""),11.0) -> 11 | H14: =IFERROR(__xludf.DUMMYFUNCTION("""COMPUTED_VALUE"""),45967.0) -> 45967 | I14: =IFERROR(__xludf.DUMMYFUNCTION("""COMPUTED_VALUE"""),0.0) -> 0 | J14: =IFERROR(__xludf.DUMMYFUNCTION("""COMPUTED_VALUE"""),80.0) -> 80 | K14: =IFERROR(__xludf.DUMMYFUNCTION("""COMPUTED_VALUE"""),8.0) -> 8 | L14: =IFERROR(__xludf.DUMMYFUNCTION("""COMPUTED_VALUE"""),"Platformer") -> Platformer | M14: =IFERROR(__xludf.DUMMYFUNCTION("""COMPUTED_VALUE"""),"Exclusive") -> Exclusive
A15: =IFERROR(__xludf.DUMMYFUNCTION("""COMPUTED_VALUE"""),"Dead Static Drive") -> Dead Static Drive | B15: =IFERROR(__xludf.DUMMYFUNCTION("""COMPUTED_VALUE"""),"Xbox / PC") -> Xbox / PC | C15: =IFERROR(__xludf.DUMMYFUNCTION("""COMPUTED_VALUE"""),"Yes") -> Yes | D15: =IFERROR(__xludf.DUMMYFUNCTION("""COMPUTED_VALUE"""),"Active") -> Active | E15: =IFERROR(__xludf.DUMMYFUNCTION("""COMPUTED_VALUE"""),45966.0) -> 45966 | G15: =IFERROR(__xludf.DUMMYFUNCTION("""COMPUTED_VALUE"""),11.033333333333333) -> 11.033333 | H15: =IFERROR(__xludf.DUMMYFUNCTION("""COMPUTED_VALUE"""),45966.0) -> 45966 | I15: =IFERROR(__xludf.DUMMYFUNCTION("""COMPUTED_VALUE"""),0.0) -> 0 | J15: =IFERROR(__xludf.DUMMYFUNCTION("""COMPUTED_VALUE"""),35.0) -> 35 | K15: =IFERROR(__xludf.DUMMYFUNCTION("""COMPUTED_VALUE"""),4.0) -> 4 | L15: =IFERROR(__xludf.DUMMYFUNCTION("""COMPUTED_VALUE"""),"Survival") -> Survival
A16: =IFERROR(__xludf.DUMMYFUNCTION("""COMPUTED_VALUE"""),"1000xResist") -> 1000xResist | B16: =IFERROR(__xludf.DUMMYFUNCTION("""COMPUTED_VALUE"""),"Xbox / PC") -> Xbox / PC | C16: =IFERROR(__xludf.DUMMYFUNCTION("""COMPUTED_VALUE"""),"Yes") -> Yes | D16: =IFERROR(__xludf.DUMMYFUNCTION("""COMPUTED_VALUE"""),"Active") -> Active | E16: =IFERROR(__xludf.DUMMYFUNCTION("""COMPUTED_VALUE"""),45965.0) -> 45965 | G16: =IFERROR(__xludf.DUMMYFUNCTION("""COMPUTED_VALUE"""),11.066666666666666) -> 11.066667 | H16: =IFERROR(__xludf.DUMMYFUNCTION("""COMPUTED_VALUE"""),45786.0) -> 45786 | I16: =IFERROR(__xludf.DUMMYFUNCTION("""COMPUTED_VALUE"""),0.4861111111111111) -> 0.48611111 | J16: =IFERROR(__xludf.DUMMYFUNCTION("""COMPUTED_VALUE"""),86.0) -> 86 | K16: =IFERROR(__xludf.DUMMYFUNCTION("""COMPUTED_VALUE"""),11.0) -> 11 | L16: =IFERROR(__xludf.DUMMYFUNCTION("""COMPUTED_VALUE"""),"Action-Adventure") -> Action-Adventure | M16: =IFERROR(__xludf.DUMMYFUNCTION("""COMPUTED_VALUE"""),"Exclusive") -> Exclusive
A17: =IFERROR(__xludf.DUMMYFUNCTION("""COMPUTED_VALUE"""),"Football Manager 26") -> Football Manager 26 | B17: =IFERROR(__xludf.DUMMYFUNCTION("""COMPUTED_VALUE"""),"PC") -> PC | D17: =IFERROR(__xludf.DUMMYFUNCTION("""COMPUTED_VALUE"""),"Active") -> Active | E17: =IFERROR(__xludf.DUMMYFUNCTION("""COMPUTED_VALUE"""),45965.0) -> 45965 | G17: =IFERROR(__xludf.DUMMYFUNCTION("""COMPUTED_VALUE"""),11.066666666666666) -> 11.066667 | H17: =IFERROR(__xludf.DUMMYFUNCTION("""COMPUTED_VALUE"""),45965.0) -> 45965 | I17: =IFERROR(__xludf.DUMMYFUNCTION("""COMPUTED_VALUE"""),0.0) -> 0 | J17: =IFERROR(__xludf.DUMMYFUNCTION("""COMPUTED_VALUE"""),68.0) -> 68 | K17: =IFERROR(__xludf.DUMMYFUNCTION("""COMPUTED_VALUE"""),64.0) -> 64 | L17: =IFERROR(__xludf.DUMMYFUNCTION("""COMPUTED_VALUE"""),"Management") -> Management
A18: =IFERROR(__xludf.DUMMYFUNCTION("""COMPUTED_VALUE"""),"Halls of Torment") -> Halls of Torment | B18: =IFERROR(__xludf.DUMMYFUNCTION("""COMPUTED_VALUE"""),"Xbox / PC") -> Xbox / PC | C18: =IFERROR(__xludf.DUMMYFUNCTION("""COMPUTED_VALUE"""),"Yes") -> Yes | D18: =IFERROR(__xludf.DUMMYFUNCTION("""COMPUTED_VALUE"""),"Active") -> Active | E18: =IFERROR(__xludf.DUMMYFUNCTION("""COMPUTED_VALUE"""),45958.0) -> 45958 | G18: =IFERROR(__xludf.DUMMYFUNCTION("""COMPUTED_VALUE"""),11.266666666666666) -> 11.266667 | H18: =IFERROR(__xludf.DUMMYFUNCTION("""COMPUTED_VALUE"""),45559.0) -> 45559 | I18: =IFERROR(__xludf.DUMMYFUNCTION("""COMPUTED_VALUE"""),1.0944444444444446) -> 1.0944444 | J18: =IFERROR(__xludf.DUMMYFUNCTION("""COMPUTED_VALUE"""),88.0) -> 88 | K18: =IFERROR(__xludf.DUMMYFUNCTION("""COMPUTED_VALUE"""),12.0) -> 12 | L18: =IFERROR(__xludf.DUMMYFUNCTION("""COMPUTED_VALUE"""),"Shoot-'Em-Up") -> Shoot-'Em-Up | M18: =IFERROR(__xludf.DUMMYFUNCTION("""COMPUTED_VALUE"""),"Exclusive") -> Exclusive
A19: =IFERROR(__xludf.DUMMYFUNCTION("""COMPUTED_VALUE"""),"PowerWash Simulator 2") -> PowerWash Simulator 2 | B19: =IFERROR(__xludf.DUMMYFUNCTION("""COMPUTED_VALUE"""),"Xbox / PC") -> Xbox / PC | C19: =IFERROR(__xludf.DUMMYFUNCTION("""COMPUTED_VALUE"""),"Yes") -> Yes | D19: =IFERROR(__xludf.DUMMYFUNCTION("""COMPUTED_VALUE"""),"Active") -> Active | E19: =IFERROR(__xludf.DUMMYFUNCTION("""COMPUTED_VALUE"""),45953.0) -> 45953 | G19: =IFERROR(__xludf.DUMMYFUNCTION("""COMPUTED_VALUE"""),11.433333333333334) -> 11.433333 | H19: =IFERROR(__xludf.DUMMYFUNCTION("""COMPUTED_VALUE"""),45953.0) -> 45953 | I19: =IFERROR(__xludf.DUMMYFUNCTION("""COMPUTED_VALUE"""),0.0) -> 0 | J19: =IFERROR(__xludf.DUMMYFUNCTION("""COMPUTED_VALUE"""),82.0) -> 82 | K19: =IFERROR(__xludf.DUMMYFUNCTION("""COMPUTED_VALUE"""),37.0) -> 37 | L19: =IFERROR(__xludf.DUMMYFUNCTION("""COMPUTED_VALUE"""),"Simulation") -> Simulation | M19: =IFERROR(__xludf.DUMMYFUNCTION("""COMPUTED_VALUE"""),"Exclusive") -> Exclusive
A20: =IFERROR(__xludf.DUMMYFUNCTION("""COMPUTED_VALUE"""),"Bounty Star: The Morose Tale of Graveyard Clem") -> Bounty Star: The Morose Tale of Graveyard Clem | B20: =IFERROR(__xludf.DUMMYFUNCTION("""COMPUTED_VALUE"""),"Xbox / PC") -> Xbox / PC | C20: =IFERROR(__xludf.DUMMYFUNCTION("""COMPUTED_VALUE"""),"Yes") -> Yes | D20: =IFERROR(__xludf.DUMMYFUNCTION("""COMPUTED_VALUE"""),"Active") -> Active | E20: =IFERROR(__xludf.DUMMYFUNCTION("""COMPUTED_VALUE"""),45953.0) -> 45953 | G20: =IFERROR(__xludf.DUMMYFUNCTION("""COMPUTED_VALUE"""),11.433333333333334) -> 11.433333 | H20: =IFERROR(__xludf.DUMMYFUNCTION("""COMPUTED_VALUE"""),45953.0) -> 45953 | I20: =IFERROR(__xludf.DUMMYFUNCTION("""COMPUTED_VALUE"""),0.0) -> 0 | J20: =IFERROR(__xludf.DUMMYFUNCTION("""COMPUTED_VALUE"""),74.0) -> 74 | K20: =IFERROR(__xludf.DUMMYFUNCTION("""COMPUTED_VALUE"""),13.0) -> 13 | L20: =IFERROR(__xludf.DUMMYFUNCTION("""COMPUTED_VALUE"""),"Shooter") -> Shooter | M20: =IFERROR(__xludf.DUMMYFUNCTION("""COMPUTED_VALUE"""),"Exclusive") -> Exclusive
A21: =IFERROR(__xludf.DUMMYFUNCTION("""COMPUTED_VALUE"""),"Keeper (2025)") -> Keeper (2025) | B21: =IFERROR(__xludf.DUMMYFUNCTION("""COMPUTED_VALUE"""),"Xbox / PC") -> Xbox / PC | C21: =IFERROR(__xludf.DUMMYFUNCTION("""COMPUTED_VALUE"""),"Yes") -> Yes | D21: =IFERROR(__xludf.DUMMYFUNCTION("""COMPUTED_VALUE"""),"Active") -> Active | E21: =IFERROR(__xludf.DUMMYFUNCTION("""COMPUTED_VALUE"""),45947.0) -> 45947 | G21: =IFERROR(__xludf.DUMMYFUNCTION("""COMPUTED_VALUE"""),11.633333333333333) -> 11.633333 | H21: =IFERROR(__xludf.DUMMYFUNCTION("""COMPUTED_VALUE"""),45947.0) -> 45947 | I21: =IFERROR(__xludf.DUMMYFUNCTION("""COMPUTED_VALUE"""),0.0) -> 0 | J21: =IFERROR(__xludf.DUMMYFUNCTION("""COMPUTED_VALUE"""),80.0) -> 80 | K21: =IFERROR(__xludf.DUMMYFUNCTION("""COMPUTED_VALUE"""),5.0) -> 5 | L21: =IFERROR(__xludf.DUMMYFUNCTION("""COMPUTED_VALUE"""),"Action-Adventure") -> Action-Adventure | M21: =IFERROR(__xludf.DUMMYFUNCTION("""COMPUTED_VALUE"""),"Exclusive") -> Exclusive
A22: =IFERROR(__xludf.DUMMYFUNCTION("""COMPUTED_VALUE"""),"Pax Dei") -> Pax Dei | B22: =IFERROR(__xludf.DUMMYFUNCTION("""COMPUTED_VALUE"""),"PC") -> PC | D22: =IFERROR(__xludf.DUMMYFUNCTION("""COMPUTED_VALUE"""),"Active") -> Active | E22: =IFERROR(__xludf.DUMMYFUNCTION("""COMPUTED_VALUE"""),45946.0) -> 45946 | G22: =IFERROR(__xludf.DUMMYFUNCTION("""COMPUTED_VALUE"""),11.666666666666666) -> 11.666667 | H22: =IFERROR(__xludf.DUMMYFUNCTION("""COMPUTED_VALUE"""),45946.0) -> 45946 | I22: =IFERROR(__xludf.DUMMYFUNCTION("""COMPUTED_VALUE"""),0.0) -> 0 | J22: =IFERROR(__xludf.DUMMYFUNCTION("""COMPUTED_VALUE"""),70.0) -> 70 | L22: =IFERROR(__xludf.DUMMYFUNCTION("""COMPUTED_VALUE"""),"RPG") -> RPG
A23: =IFERROR(__xludf.DUMMYFUNCTION("""COMPUTED_VALUE"""),"Ball x Pit") -> Ball x Pit | B23: =IFERROR(__xludf.DUMMYFUNCTION("""COMPUTED_VALUE"""),"Xbox / PC") -> Xbox / PC | C23: =IFERROR(__xludf.DUMMYFUNCTION("""COMPUTED_VALUE"""),"Yes") -> Yes | D23: =IFERROR(__xludf.DUMMYFUNCTION("""COMPUTED_VALUE"""),"Active") -> Active | E23: =IFERROR(__xludf.DUMMYFUNCTION("""COMPUTED_VALUE"""),45945.0) -> 45945 | G23: =IFERROR(__xludf.DUMMYFUNCTION("""COMPUTED_VALUE"""),11.7) -> 11.7 | H23: =IFERROR(__xludf.DUMMYFUNCTION("""COMPUTED_VALUE"""),45945.0) -> 45945 | I23: =IFERROR(__xludf.DUMMYFUNCTION("""COMPUTED_VALUE"""),0.0) -> 0 | J23: =IFERROR(__xludf.DUMMYFUNCTION("""COMPUTED_VALUE"""),84.0) -> 84 | K23: =IFERROR(__xludf.DUMMYFUNCTION("""COMPUTED_VALUE"""),19.0) -> 19 | L23: =IFERROR(__xludf.DUMMYFUNCTION("""COMPUTED_VALUE"""),"Shoot-'Em-Up") -> Shoot-'Em-Up
A24: =IFERROR(__xludf.DUMMYFUNCTION("""COMPUTED_VALUE"""),"Heroes of Might and Magic II: Gold Edition") -> Heroes of Might and Magic II: Gold Edition | B24: =IFERROR(__xludf.DUMMYFUNCTION("""COMPUTED_VALUE"""),"PC") -> PC | D24: =IFERROR(__xludf.DUMMYFUNCTION("""COMPUTED_VALUE"""),"Active") -> Active | E24: =IFERROR(__xludf.DUMMYFUNCTION("""COMPUTED_VALUE"""),45940.0) -> 45940 | G24: =IFERROR(__xludf.DUMMYFUNCTION("""COMPUTED_VALUE"""),11.866666666666667) -> 11.866667 | H24: =IFERROR(__xludf.DUMMYFUNCTION("""COMPUTED_VALUE"""),35338.0) -> 35338 | I24: =IFERROR(__xludf.DUMMYFUNCTION("""COMPUTED_VALUE"""),29.02777777777778) -> 29.027778 | J24: =IFERROR(__xludf.DUMMYFUNCTION("""COMPUTED_VALUE"""),84.0) -> 84 | K24: =IFERROR(__xludf.DUMMYFUNCTION("""COMPUTED_VALUE"""),80.0) -> 80 | L24: =IFERROR(__xludf.DUMMYFUNCTION("""COMPUTED_VALUE"""),"Strategy") -> Strategy | N24: =IFERROR(__xludf.DUMMYFUNCTION("""COMPUTED_VALUE"""),"Ubisoft games joining with price increase") -> Ubisoft games joining with price increase
A25: =IFERROR(__xludf.DUMMYFUNCTION("""COMPUTED_VALUE"""),"Heroes of Might and Magic III: Complete Edition") -> Heroes of Might and Magic III: Complete Edition | B25: =IFERROR(__xludf.DUMMYFUNCTION("""COMPUTED_VALUE"""),"PC") -> PC | D25: =IFERROR(__xludf.DUMMYFUNCTION("""COMPUTED_VALUE"""),"Active") -> Active | E25: =IFERROR(__xludf.DUMMYFUNCTION("""COMPUTED_VALUE"""),45940.0) -> 45940 | G25: =IFERROR(__xludf.DUMMYFUNCTION("""COMPUTED_VALUE"""),11.866666666666667) -> 11.866667 | H25: =IFERROR(__xludf.DUMMYFUNCTION("""COMPUTED_VALUE"""),36219.0) -> 36219 | I25: =IFERROR(__xludf.DUMMYFUNCTION("""COMPUTED_VALUE"""),26.616666666666667) -> 26.616667 | J25: =IFERROR(__xludf.DUMMYFUNCTION("""COMPUTED_VALUE"""),65.0) -> 65 | K25: =IFERROR(__xludf.DUMMYFUNCTION("""COMPUTED_VALUE"""),153.0) -> 153 | L25: =IFERROR(__xludf.DUMMYFUNCTION("""COMPUTED_VALUE"""),"Strategy") -> Strategy | N25: =IFERROR(__xludf.DUMMYFUNCTION("""COMPUTED_VALUE"""),"Ubisoft games joining with price increase") -> Ubisoft games joining with price increase
A26: =IFERROR(__xludf.DUMMYFUNCTION("""COMPUTED_VALUE"""),"Supermarket Simulator") -> Supermarket Simulator | B26: =IFERROR(__xludf.DUMMYFUNCTION("""COMPUTED_VALUE"""),"Xbox / PC") -> Xbox / PC | C26: =IFERROR(__xludf.DUMMYFUNCTION("""COMPUTED_VALUE"""),"Yes") -> Yes | D26: =IFERROR(__xludf.DUMMYFUNCTION("""COMPUTED_VALUE"""),"Active") -> Active | E26: =IFERROR(__xludf.DUMMYFUNCTION("""COMPUTED_VALUE"""),45938.0) -> 45938 | G26: =IFERROR(__xludf.DUMMYFUNCTION("""COMPUTED_VALUE"""),11.933333333333334) -> 11.933333 | H26: =IFERROR(__xludf.DUMMYFUNCTION("""COMPUTED_VALUE"""),45827.0) -> 45827 | I26: =IFERROR(__xludf.DUMMYFUNCTION("""COMPUTED_VALUE"""),0.30277777777777776) -> 0.30277778 | J26: =IFERROR(__xludf.DUMMYFUNCTION("""COMPUTED_VALUE"""),76.66666666666667) -> 76.666667 | K26: =IFERROR(__xludf.DUMMYFUNCTION("""COMPUTED_VALUE"""),22.0) -> 22 | L26: =IFERROR(__xludf.DUMMYFUNCTION("""COMPUTED_VALUE"""),"Simulation") -> Simulation
A27: =IFERROR(__xludf.DUMMYFUNCTION("""COMPUTED_VALUE"""),"Hogwarts Legacy") -> Hogwarts Legacy | B27: =IFERROR(__xludf.DUMMYFUNCTION("""COMPUTED_VALUE"""),"Xbox / PC") -> Xbox / PC | C27: =IFERROR(__xludf.DUMMYFUNCTION("""COMPUTED_VALUE"""),"Yes") -> Yes | D27: =IFERROR(__xludf.DUMMYFUNCTION("""COMPUTED_VALUE"""),"Active") -> Active | E27: =IFERROR(__xludf.DUMMYFUNCTION("""COMPUTED_VALUE"""),45931.0) -> 45931 | G27: =IFERROR(__xludf.DUMMYFUNCTION("""COMPUTED_VALUE"""),12.166666666666666) -> 12.166667 | H27: =IFERROR(__xludf.DUMMYFUNCTION("""COMPUTED_VALUE"""),44964.0) -> 44964 | I27: =IFERROR(__xludf.DUMMYFUNCTION("""COMPUTED_VALUE"""),2.65) -> 2.65 | J27: =IFERROR(__xludf.DUMMYFUNCTION("""COMPUTED_VALUE"""),84.0) -> 84 | K27: =IFERROR(__xludf.DUMMYFUNCTION("""COMPUTED_VALUE"""),27.0) -> 27 | L27: =IFERROR(__xludf.DUMMYFUNCTION("""COMPUTED_VALUE"""),"Action-Adventure") -> Action-Adventure | N27: =IFERROR(__xludf.DUMMYFUNCTION("""COMPUTED_VALUE"""),"Ubisoft games joining with price increase") -> Ubisoft games joining with price increase
A28: =IFERROR(__xludf.DUMMYFUNCTION("""COMPUTED_VALUE"""),"Assassin's Creed II") -> Assassin's Creed II | B28: =IFERROR(__xludf.DUMMYFUNCTION("""COMPUTED_VALUE"""),"Xbox / PC") -> Xbox / PC | D28: =IFERROR(__xludf.DUMMYFUNCTION("""COMPUTED_VALUE"""),"Active") -> Active | E28: =IFERROR(__xludf.DUMMYFUNCTION("""COMPUTED_VALUE"""),45931.0) -> 45931 | G28: =IFERROR(__xludf.DUMMYFUNCTION("""COMPUTED_VALUE"""),12.166666666666666) -> 12.166667 | H28: =IFERROR(__xludf.DUMMYFUNCTION("""COMPUTED_VALUE"""),40134.0) -> 40134 | I28: =IFERROR(__xludf.DUMMYFUNCTION("""COMPUTED_VALUE"""),15.872222222222222) -> 15.872222 | J28: =IFERROR(__xludf.DUMMYFUNCTION("""COMPUTED_VALUE"""),90.0) -> 90 | K28: =IFERROR(__xludf.DUMMYFUNCTION("""COMPUTED_VALUE"""),19.0) -> 19 | L28: =IFERROR(__xludf.DUMMYFUNCTION("""COMPUTED_VALUE"""),"Action-Adventure") -> Action-Adventure | N28: =IFERROR(__xludf.DUMMYFUNCTION("""COMPUTED_VALUE"""),"Ubisoft games joining with price increase") -> Ubisoft games joining with price increase
A29: =IFERROR(__xludf.DUMMYFUNCTION("""COMPUTED_VALUE"""),"Assassin's Creed III: Remastered") -> Assassin's Creed III: Remastered | B29: =IFERROR(__xludf.DUMMYFUNCTION("""COMPUTED_VALUE"""),"Xbox / PC") -> Xbox / PC | C29: =IFERROR(__xludf.DUMMYFUNCTION("""COMPUTED_VALUE"""),"Yes") -> Yes | D29: =IFERROR(__xludf.DUMMYFUNCTION("""COMPUTED_VALUE"""),"Active") -> Active | E29: =IFERROR(__xludf.DUMMYFUNCTION("""COMPUTED_VALUE"""),45931.0) -> 45931 | G29: =IFERROR(__xludf.DUMMYFUNCTION("""COMPUTED_VALUE"""),12.166666666666666) -> 12.166667 | H29: =IFERROR(__xludf.DUMMYFUNCTION("""COMPUTED_VALUE"""),43553.0) -> 43553 | I29: =IFERROR(__xludf.DUMMYFUNCTION("""COMPUTED_VALUE"""),6.5055555555555555) -> 6.5055556 | J29: =IFERROR(__xludf.DUMMYFUNCTION("""COMPUTED_VALUE"""),72.0) -> 72 | K29: =IFERROR(__xludf.DUMMYFUNCTION("""COMPUTED_VALUE"""),15.0) -> 15 | L29: =IFERROR(__xludf.DUMMYFUNCTION("""COMPUTED_VALUE"""),"Action-Adventure") -> Action-Adventure | N29: =IFERROR(__xludf.DUMMYFUNCTION("""COMPUTED_VALUE"""),"Ubisoft games joining with price increase") -> Ubisoft games joining with price increase
A30: =IFERROR(__xludf.DUMMYFUNCTION("""COMPUTED_VALUE"""),"Assassin's Creed IV Black Flag") -> Assassin's Creed IV Black Flag | B30: =IFERROR(__xludf.DUMMYFUNCTION("""COMPUTED_VALUE"""),"Xbox / PC") -> Xbox / PC | C30: =IFERROR(__xludf.DUMMYFUNCTION("""COMPUTED_VALUE"""),"Yes") -> Yes | D30: =IFERROR(__xludf.DUMMYFUNCTION("""COMPUTED_VALUE"""),"Active") -> Active | E30: =IFERROR(__xludf.DUMMYFUNCTION("""COMPUTED_VALUE"""),45931.0) -> 45931 | G30: =IFERROR(__xludf.DUMMYFUNCTION("""COMPUTED_VALUE"""),12.166666666666666) -> 12.166667 | H30: =IFERROR(__xludf.DUMMYFUNCTION("""COMPUTED_VALUE"""),41576.0) -> 41576 | I30: =IFERROR(__xludf.DUMMYFUNCTION("""COMPUTED_VALUE"""),11.922222222222222) -> 11.922222 | J30: =IFERROR(__xludf.DUMMYFUNCTION("""COMPUTED_VALUE"""),88.0) -> 88 | K30: =IFERROR(__xludf.DUMMYFUNCTION("""COMPUTED_VALUE"""),24.0) -> 24 | L30: =IFERROR(__xludf.DUMMYFUNCTION("""COMPUTED_VALUE"""),"Action-Adventure") -> Action-Adventure | N30: =IFERROR(__xludf.DUMMYFUNCTION("""COMPUTED_VALUE"""),"Ubisoft games joining with price increase") -> Ubisoft games joining with price increase
A31: =IFERROR(__xludf.DUMMYFUNCTION("""COMPUTED_VALUE"""),"Assassin's Creed IV Black Flag: Freedom Cry") -> Assassin's Creed IV Black Flag: Freedom Cry | B31: =IFERROR(__xludf.DUMMYFUNCTION("""COMPUTED_VALUE"""),"Xbox / PC") -> Xbox / PC | D31: =IFERROR(__xludf.DUMMYFUNCTION("""COMPUTED_VALUE"""),"Active") -> Active | E31: =IFERROR(__xludf.DUMMYFUNCTION("""COMPUTED_VALUE"""),45931.0) -> 45931 | G31: =IFERROR(__xludf.DUMMYFUNCTION("""COMPUTED_VALUE"""),12.166666666666666) -> 12.166667 | H31: =IFERROR(__xludf.DUMMYFUNCTION("""COMPUTED_VALUE"""),41626.0) -> 41626 | I31: =IFERROR(__xludf.DUMMYFUNCTION("""COMPUTED_VALUE"""),11.786111111111111) -> 11.786111 | J31: =IFERROR(__xludf.DUMMYFUNCTION("""COMPUTED_VALUE"""),71.0) -> 71 | K31: =IFERROR(__xludf.DUMMYFUNCTION("""COMPUTED_VALUE"""),4.0) -> 4 | L31: =IFERROR(__xludf.DUMMYFUNCTION("""COMPUTED_VALUE"""),"Action-Adventure") -> Action-Adventure | N31: =IFERROR(__xludf.DUMMYFUNCTION("""COMPUTED_VALUE"""),"Ubisoft games joining with price increase") -> Ubisoft games joining with price increase
A32: =IFERROR(__xludf.DUMMYFUNCTION("""COMPUTED_VALUE"""),"Assassin's Creed Brotherhood") -> Assassin's Creed Brotherhood | B32: =IFERROR(__xludf.DUMMYFUNCTION("""COMPUTED_VALUE"""),"Xbox / PC") -> Xbox / PC | D32: =IFERROR(__xludf.DUMMYFUNCTION("""COMPUTED_VALUE"""),"Active") -> Active | E32: =IFERROR(__xludf.DUMMYFUNCTION("""COMPUTED_VALUE"""),45931.0) -> 45931 | G32: =IFERROR(__xludf.DUMMYFUNCTION("""COMPUTED_VALUE"""),12.166666666666666) -> 12.166667 | H32: =IFERROR(__xludf.DUMMYFUNCTION("""COMPUTED_VALUE"""),40498.0) -> 40498 | I32: =IFERROR(__xludf.DUMMYFUNCTION("""COMPUTED_VALUE"""),14.875) -> 14.875 | J32: =IFERROR(__xludf.DUMMYFUNCTION("""COMPUTED_VALUE"""),89.0) -> 89 | K32: =IFERROR(__xludf.DUMMYFUNCTION("""COMPUTED_VALUE"""),15.0) -> 15 | L32: =IFERROR(__xludf.DUMMYFUNCTION("""COMPUTED_VALUE"""),"Action-Adventure") -> Action-Adventure | N32: =IFERROR(__xludf.DUMMYFUNCTION("""COMPUTED_VALUE"""),"Ubisoft games joining with price increase") -> Ubisoft games joining with price increase
A33: =IFERROR(__xludf.DUMMYFUNCTION("""COMPUTED_VALUE"""),"Assassin's Creed Chronicles: China") -> Assassin's Creed Chronicles: China | B33: =IFERROR(__xludf.DUMMYFUNCTION("""COMPUTED_VALUE"""),"Xbox / PC") -> Xbox / PC | C33: =IFERROR(__xludf.DUMMYFUNCTION("""COMPUTED_VALUE"""),"Yes") -> Yes | D33: =IFERROR(__xludf.DUMMYFUNCTION("""COMPUTED_VALUE"""),"Active") -> Active | E33: =IFERROR(__xludf.DUMMYFUNCTION("""COMPUTED_VALUE"""),45931.0) -> 45931 | G33: =IFERROR(__xludf.DUMMYFUNCTION("""COMPUTED_VALUE"""),12.166666666666666) -> 12.166667 | H33: =IFERROR(__xludf.DUMMYFUNCTION("""COMPUTED_VALUE"""),42115.0) -> 42115 | I33: =IFERROR(__xludf.DUMMYFUNCTION("""COMPUTED_VALUE"""),10.444444444444445) -> 10.444444 | J33: =IFERROR(__xludf.DUMMYFUNCTION("""COMPUTED_VALUE"""),69.0) -> 69 | K33: =IFERROR(__xludf.DUMMYFUNCTION("""COMPUTED_VALUE"""),6.0) -> 6 | L33: =IFERROR(__xludf.DUMMYFUNCTION("""COMPUTED_VALUE"""),"Action-Adventure") -> Action-Adventure | N33: =IFERROR(__xludf.DUMMYFUNCTION("""COMPUTED_VALUE"""),"Ubisoft games joining with price increase") -> Ubisoft games joining with price increase
A34: =IFERROR(__xludf.DUMMYFUNCTION("""COMPUTED_VALUE"""),"Assassin's Creed Chronicles: India") -> Assassin's Creed Chronicles: India | B34: =IFERROR(__xludf.DUMMYFUNCTION("""COMPUTED_VALUE"""),"Xbox / PC") -> Xbox / PC | C34: =IFERROR(__xludf.DUMMYFUNCTION("""COMPUTED_VALUE"""),"Yes") -> Yes | D34: =IFERROR(__xludf.DUMMYFUNCTION("""COMPUTED_VALUE"""),"Active") -> Active | E34: =IFERROR(__xludf.DUMMYFUNCTION("""COMPUTED_VALUE"""),45931.0) -> 45931 | G34: =IFERROR(__xludf.DUMMYFUNCTION("""COMPUTED_VALUE"""),12.166666666666666) -> 12.166667 | H34: =IFERROR(__xludf.DUMMYFUNCTION("""COMPUTED_VALUE"""),42382.0) -> 42382 | I34: =IFERROR(__xludf.DUMMYFUNCTION("""COMPUTED_VALUE"""),9.716666666666667) -> 9.7166667 | J34: =IFERROR(__xludf.DUMMYFUNCTION("""COMPUTED_VALUE"""),63.0) -> 63 | K34: =IFERROR(__xludf.DUMMYFUNCTION("""COMPUTED_VALUE"""),6.0) -> 6 | L34: =IFERROR(__xludf.DUMMYFUNCTION("""COMPUTED_VALUE"""),"Action-Adventure") -> Action-Adventure | N34: =IFERROR(__xludf.DUMMYFUNCTION("""COMPUTED_VALUE"""),"Ubisoft games joining with price increase") -> Ubisoft games joining with price increase
A35: =IFERROR(__xludf.DUMMYFUNCTION("""COMPUTED_VALUE"""),"Assassin's Creed Chronicles: Russia") -> Assassin's Creed Chronicles: Russia | B35: =IFERROR(__xludf.DUMMYFUNCTION("""COMPUTED_VALUE"""),"Xbox / PC") -> Xbox / PC | C35: =IFERROR(__xludf.DUMMYFUNCTION("""COMPUTED_VALUE"""),"Yes") -> Yes | D35: =IFERROR(__xludf.DUMMYFUNCTION("""COMPUTED_VALUE"""),"Active") -> Active | E35: =IFERROR(__xludf.DUMMYFUNCTION("""COMPUTED_VALUE"""),45931.0) -> 45931 | G35: =IFERROR(__xludf.DUMMYFUNCTION("""COMPUTED_VALUE"""),12.166666666666666) -> 12.166667 | H35: =IFERROR(__xludf.DUMMYFUNCTION("""COMPUTED_VALUE"""),42409.0) -> 42409 | I35: =IFERROR(__xludf.DUMMYFUNCTION("""COMPUTED_VALUE"""),9.644444444444444) -> 9.6444444 | J35: =IFERROR(__xludf.DUMMYFUNCTION("""COMPUTED_VALUE"""),62.0) -> 62 | K35: =IFERROR(__xludf.DUMMYFUNCTION("""COMPUTED_VALUE"""),7.0) -> 7 | L35: =IFERROR(__xludf.DUMMYFUNCTION("""COMPUTED_VALUE"""),"Action-Adventure") -> Action-Adventure | N35: =IFERROR(__xludf.DUMMYFUNCTION("""COMPUTED_VALUE"""),"Ubisoft games joining with price increase") -> Ubisoft games joining with price increase
A36: =IFERROR(__xludf.DUMMYFUNCTION("""COMPUTED_VALUE"""),"Assassin's Creed Liberation HD") -> Assassin's Creed Liberation HD | B36: =IFERROR(__xludf.DUMMYFUNCTION("""COMPUTED_VALUE"""),"Xbox / PC") -> Xbox / PC | D36: =IFERROR(__xludf.DUMMYFUNCTION("""COMPUTED_VALUE"""),"Active") -> Active | E36: =IFERROR(__xludf.DUMMYFUNCTION("""COMPUTED_VALUE"""),45931.0) -> 45931 | G36: =IFERROR(__xludf.DUMMYFUNCTION("""COMPUTED_VALUE"""),12.166666666666666) -> 12.166667 | H36: =IFERROR(__xludf.DUMMYFUNCTION("""COMPUTED_VALUE"""),41654.0) -> 41654 | I36: =IFERROR(__xludf.DUMMYFUNCTION("""COMPUTED_VALUE"""),11.71111111111111) -> 11.711111 | J36: =IFERROR(__xludf.DUMMYFUNCTION("""COMPUTED_VALUE"""),62.0) -> 62 | K36: =IFERROR(__xludf.DUMMYFUNCTION("""COMPUTED_VALUE"""),8.0) -> 8 | L36: =IFERROR(__xludf.DUMMYFUNCTION("""COMPUTED_VALUE"""),"Action-Adventure") -> Action-Adventure | N36: =IFERROR(__xludf.DUMMYFUNCTION("""COMPUTED_VALUE"""),"Ubisoft games joining with price increase") -> Ubisoft games joining with price increase
A37: =IFERROR(__xludf.DUMMYFUNCTION("""COMPUTED_VALUE"""),"Assassin's Creed Revelations") -> Assassin's Creed Revelations | B37: =IFERROR(__xludf.DUMMYFUNCTION("""COMPUTED_VALUE"""),"Xbox / PC") -> Xbox / PC | D37: =IFERROR(__xludf.DUMMYFUNCTION("""COMPUTED_VALUE"""),"Active") -> Active | E37: =IFERROR(__xludf.DUMMYFUNCTION("""COMPUTED_VALUE"""),45931.0) -> 45931 | G37: =IFERROR(__xludf.DUMMYFUNCTION("""COMPUTED_VALUE"""),12.166666666666666) -> 12.166667 | H37: =IFERROR(__xludf.DUMMYFUNCTION("""COMPUTED_VALUE"""),40862.0) -> 40862 | I37: =IFERROR(__xludf.DUMMYFUNCTION("""COMPUTED_VALUE"""),13.877777777777778) -> 13.877778 | J37: =IFERROR(__xludf.DUMMYFUNCTION("""COMPUTED_VALUE"""),80.0) -> 80 | K37: =IFERROR(__xludf.DUMMYFUNCTION("""COMPUTED_VALUE"""),13.0) -> 13 | L37: =IFERROR(__xludf.DUMMYFUNCTION("""COMPUTED_VALUE"""),"Action-Adventure") -> Action-Adventure | N37: =IFERROR(__xludf.DUMMYFUNCTION("""COMPUTED_VALUE"""),"Ubisoft games joining with price increase") -> Ubisoft games joining with price increase
A38: =IFERROR(__xludf.DUMMYFUNCTION("""COMPUTED_VALUE"""),"Assassin's Creed Rogue: Remastered") -> Assassin's Creed Rogue: Remastered | B38: =IFERROR(__xludf.DUMMYFUNCTION("""COMPUTED_VALUE"""),"Xbox / PC") -> Xbox / PC | C38: =IFERROR(__xludf.DUMMYFUNCTION("""COMPUTED_VALUE"""),"Yes") -> Yes | D38: =IFERROR(__xludf.DUMMYFUNCTION("""COMPUTED_VALUE"""),"Active") -> Active | E38: =IFERROR(__xludf.DUMMYFUNCTION("""COMPUTED_VALUE"""),45931.0) -> 45931 | G38: =IFERROR(__xludf.DUMMYFUNCTION("""COMPUTED_VALUE"""),12.166666666666666) -> 12.166667 | H38: =IFERROR(__xludf.DUMMYFUNCTION("""COMPUTED_VALUE"""),43179.0) -> 43179 | I38: =IFERROR(__xludf.DUMMYFUNCTION("""COMPUTED_VALUE"""),7.530555555555556) -> 7.5305556 | J38: =IFERROR(__xludf.DUMMYFUNCTION("""COMPUTED_VALUE"""),71.0) -> 71 | K38: =IFERROR(__xludf.DUMMYFUNCTION("""COMPUTED_VALUE"""),11.0) -> 11 | L38: =IFERROR(__xludf.DUMMYFUNCTION("""COMPUTED_VALUE"""),"Action-Adventure") -> Action-Adventure | N38: =IFERROR(__xludf.DUMMYFUNCTION("""COMPUTED_VALUE"""),"Ubisoft games joining with price increase") -> Ubisoft games joining with price increase
A39: =IFERROR(__xludf.DUMMYFUNCTION("""COMPUTED_VALUE"""),"Assassin's Creed Syndicate") -> Assassin's Creed Syndicate | B39: =IFERROR(__xludf.DUMMYFUNCTION("""COMPUTED_VALUE"""),"Xbox / PC") -> Xbox / PC | C39: =IFERROR(__xludf.DUMMYFUNCTION("""COMPUTED_VALUE"""),"Yes") -> Yes | D39: =IFERROR(__xludf.DUMMYFUNCTION("""COMPUTED_VALUE"""),"Active") -> Active | E39: =IFERROR(__xludf.DUMMYFUNCTION("""COMPUTED_VALUE"""),45931.0) -> 45931 | G39: =IFERROR(__xludf.DUMMYFUNCTION("""COMPUTED_VALUE"""),12.166666666666666) -> 12.166667 | H39: =IFERROR(__xludf.DUMMYFUNCTION("""COMPUTED_VALUE"""),42300.0) -> 42300 | I39: =IFERROR(__xludf.DUMMYFUNCTION("""COMPUTED_VALUE"""),9.938888888888888) -> 9.9388889 | J39: =IFERROR(__xludf.DUMMYFUNCTION("""COMPUTED_VALUE"""),76.0) -> 76 | K39: =IFERROR(__xludf.DUMMYFUNCTION("""COMPUTED_VALUE"""),19.0) -> 19 | L39: =IFERROR(__xludf.DUMMYFUNCTION("""COMPUTED_VALUE"""),"Action-Adventure") -> Action-Adventure | N39: =IFERROR(__xludf.DUMMYFUNCTION("""COMPUTED_VALUE"""),"Ubisoft games joining with price increase") -> Ubisoft games joining with price increase
A40: =IFERROR(__xludf.DUMMYFUNCTION("""COMPUTED_VALUE"""),"Assassin's Creed: The Ezio Collection") -> Assassin's Creed: The Ezio Collection | B40: =IFERROR(__xludf.DUMMYFUNCTION("""COMPUTED_VALUE"""),"Xbox / PC") -> Xbox / PC | C40: =IFERROR(__xludf.DUMMYFUNCTION("""COMPUTED_VALUE"""),"Yes") -> Yes | D40: =IFERROR(__xludf.DUMMYFUNCTION("""COMPUTED_VALUE"""),"Active") -> Active | E40: =IFERROR(__xludf.DUMMYFUNCTION("""COMPUTED_VALUE"""),45931.0) -> 45931 | G40: =IFERROR(__xludf.DUMMYFUNCTION("""COMPUTED_VALUE"""),12.166666666666666) -> 12.166667 | H40: =IFERROR(__xludf.DUMMYFUNCTION("""COMPUTED_VALUE"""),42689.0) -> 42689 | I40: =IFERROR(__xludf.DUMMYFUNCTION("""COMPUTED_VALUE"""),8.877777777777778) -> 8.8777778 | J40: =IFERROR(__xludf.DUMMYFUNCTION("""COMPUTED_VALUE"""),72.0) -> 72 | K40: =IFERROR(__xludf.DUMMYFUNCTION("""COMPUTED_VALUE"""),72.0) -> 72 | L40: =IFERROR(__xludf.DUMMYFUNCTION("""COMPUTED_VALUE"""),"Action-Adventure") -> Action-Adventure | N40: =IFERROR(__xludf.DUMMYFUNCTION("""COMPUTED_VALUE"""),"Ubisoft games joining with price increase") -> Ubisoft games joining with price increase
A41: =IFERROR(__xludf.DUMMYFUNCTION("""COMPUTED_VALUE"""),"Assassin's Creed Unity") -> Assassin's Creed Unity | B41: =IFERROR(__xludf.DUMMYFUNCTION("""COMPUTED_VALUE"""),"Xbox / PC") -> Xbox / PC | C41: =IFERROR(__xludf.DUMMYFUNCTION("""COMPUTED_VALUE"""),"Yes") -> Yes | D41: =IFERROR(__xludf.DUMMYFUNCTION("""COMPUTED_VALUE"""),"Active") -> Active | E41: =IFERROR(__xludf.DUMMYFUNCTION("""COMPUTED_VALUE"""),45931.0) -> 45931 | G41: =IFERROR(__xludf.DUMMYFUNCTION("""COMPUTED_VALUE"""),12.166666666666666) -> 12.166667 | H41: =IFERROR(__xludf.DUMMYFUNCTION("""COMPUTED_VALUE"""),41954.0) -> 41954 | I41: =IFERROR(__xludf.DUMMYFUNCTION("""COMPUTED_VALUE"""),10.88888888888889) -> 10.888889 | J41: =IFERROR(__xludf.DUMMYFUNCTION("""COMPUTED_VALUE"""),72.0) -> 72 | K41: =IFERROR(__xludf.DUMMYFUNCTION("""COMPUTED_VALUE"""),17.0) -> 17 | L41: =IFERROR(__xludf.DUMMYFUNCTION("""COMPUTED_VALUE"""),"Action-Adventure") -> Action-Adventure | N41: =IFERROR(__xludf.DUMMYFUNCTION("""COMPUTED_VALUE"""),"Ubisoft games joining with price increase") -> Ubisoft games joining with price increase
A42: =IFERROR(__xludf.DUMMYFUNCTION("""COMPUTED_VALUE"""),"Child of Light") -> Child of Light | B42: =IFERROR(__xludf.DUMMYFUNCTION("""COMPUTED_VALUE"""),"Xbox / PC") -> Xbox / PC | C42: =IFERROR(__xludf.DUMMYFUNCTION("""COMPUTED_VALUE"""),"Yes") -> Yes | D42: =IFERROR(__xludf.DUMMYFUNCTION("""COMPUTED_VALUE"""),"Active") -> Active | E42: =IFERROR(__xludf.DUMMYFUNCTION("""COMPUTED_VALUE"""),45931.0) -> 45931 | G42: =IFERROR(__xludf.DUMMYFUNCTION("""COMPUTED_VALUE"""),12.166666666666666) -> 12.166667 | H42: =IFERROR(__xludf.DUMMYFUNCTION("""COMPUTED_VALUE"""),41758.0) -> 41758 | I42: =IFERROR(__xludf.DUMMYFUNCTION("""COMPUTED_VALUE"""),11.422222222222222) -> 11.422222 | J42: =IFERROR(__xludf.DUMMYFUNCTION("""COMPUTED_VALUE"""),82.0) -> 82 | K42: =IFERROR(__xludf.DUMMYFUNCTION("""COMPUTED_VALUE"""),11.0) -> 11 | L42: =IFERROR(__xludf.DUMMYFUNCTION("""COMPUTED_VALUE"""),"RPG") -> RPG | N42: =IFERROR(__xludf.DUMMYFUNCTION("""COMPUTED_VALUE"""),"Ubisoft games joining with price increase") -> Ubisoft games joining with price increase
A43: =IFERROR(__xludf.DUMMYFUNCTION("""COMPUTED_VALUE"""),"Far Cry 3") -> Far Cry 3 | B43: =IFERROR(__xludf.DUMMYFUNCTION("""COMPUTED_VALUE"""),"Xbox / PC") -> Xbox / PC | C43: =IFERROR(__xludf.DUMMYFUNCTION("""COMPUTED_VALUE"""),"Yes") -> Yes | D43: =IFERROR(__xludf.DUMMYFUNCTION("""COMPUTED_VALUE"""),"Active") -> Active | E43: =IFERROR(__xludf.DUMMYFUNCTION("""COMPUTED_VALUE"""),45931.0) -> 45931 | G43: =IFERROR(__xludf.DUMMYFUNCTION("""COMPUTED_VALUE"""),12.166666666666666) -> 12.166667 | H43: =IFERROR(__xludf.DUMMYFUNCTION("""COMPUTED_VALUE"""),41247.0) -> 41247 | I43: =IFERROR(__xludf.DUMMYFUNCTION("""COMPUTED_VALUE"""),12.825) -> 12.825 | J43: =IFERROR(__xludf.DUMMYFUNCTION("""COMPUTED_VALUE"""),88.0) -> 88 | K43: =IFERROR(__xludf.DUMMYFUNCTION("""COMPUTED_VALUE"""),16.0) -> 16 | L43: =IFERROR(__xludf.DUMMYFUNCTION("""COMPUTED_VALUE"""),"Action-Adventure") -> Action-Adventure | N43: =IFERROR(__xludf.DUMMYFUNCTION("""COMPUTED_VALUE"""),"Ubisoft games joining with price increase") -> Ubisoft games joining with price increase
A44: =IFERROR(__xludf.DUMMYFUNCTION("""COMPUTED_VALUE"""),"Far Cry 3: Blood Dragon") -> Far Cry 3: Blood Dragon | B44: =IFERROR(__xludf.DUMMYFUNCTION("""COMPUTED_VALUE"""),"Xbox / PC") -> Xbox / PC | C44: =IFERROR(__xludf.DUMMYFUNCTION("""COMPUTED_VALUE"""),"Yes") -> Yes | D44: =IFERROR(__xludf.DUMMYFUNCTION("""COMPUTED_VALUE"""),"Active") -> Active | E44: =IFERROR(__xludf.DUMMYFUNCTION("""COMPUTED_VALUE"""),45931.0) -> 45931 | G44: =IFERROR(__xludf.DUMMYFUNCTION("""COMPUTED_VALUE"""),12.166666666666666) -> 12.166667 | H44: =IFERROR(__xludf.DUMMYFUNCTION("""COMPUTED_VALUE"""),41395.0) -> 41395 | I44: =IFERROR(__xludf.DUMMYFUNCTION("""COMPUTED_VALUE"""),12.416666666666666) -> 12.416667 | J44: =IFERROR(__xludf.DUMMYFUNCTION("""COMPUTED_VALUE"""),80.0) -> 80 | K44: =IFERROR(__xludf.DUMMYFUNCTION("""COMPUTED_VALUE"""),5.0) -> 5 | L44: =IFERROR(__xludf.DUMMYFUNCTION("""COMPUTED_VALUE"""),"Action-Adventure") -> Action-Adventure | N44: =IFERROR(__xludf.DUMMYFUNCTION("""COMPUTED_VALUE"""),"Ubisoft games joining with price increase") -> Ubisoft games joining with price increase
A45: =IFERROR(__xludf.DUMMYFUNCTION("""COMPUTED_VALUE"""),"Far Cry Primal") -> Far Cry Primal | B45: =IFERROR(__xludf.DUMMYFUNCTION("""COMPUTED_VALUE"""),"Xbox / PC") -> Xbox / PC | C45: =IFERROR(__xludf.DUMMYFUNCTION("""COMPUTED_VALUE"""),"Yes") -> Yes | D45: =IFERROR(__xludf.DUMMYFUNCTION("""COMPUTED_VALUE"""),"Active") -> Active | E45: =IFERROR(__xludf.DUMMYFUNCTION("""COMPUTED_VALUE"""),45931.0) -> 45931 | G45: =IFERROR(__xludf.DUMMYFUNCTION("""COMPUTED_VALUE"""),12.166666666666666) -> 12.166667 | H45: =IFERROR(__xludf.DUMMYFUNCTION("""COMPUTED_VALUE"""),42423.0) -> 42423 | I45: =IFERROR(__xludf.DUMMYFUNCTION("""COMPUTED_VALUE"""),9.605555555555556) -> 9.6055556 | J45: =IFERROR(__xludf.DUMMYFUNCTION("""COMPUTED_VALUE"""),76.0) -> 76 | K45: =IFERROR(__xludf.DUMMYFUNCTION("""COMPUTED_VALUE"""),15.0) -> 15 | L45: =IFERROR(__xludf.DUMMYFUNCTION("""COMPUTED_VALUE"""),"Action-Adventure") -> Action-Adventure | N45: =IFERROR(__xludf.DUMMYFUNCTION("""COMPUTED_VALUE"""),"Ubisoft games joining with price increase") -> Ubisoft games joining with price increase
A46: =IFERROR(__xludf.DUMMYFUNCTION("""COMPUTED_VALUE"""),"Hungry Shark World") -> Hungry Shark World | B46: =IFERROR(__xludf.DUMMYFUNCTION("""COMPUTED_VALUE"""),"Xbox / PC") -> Xbox / PC | C46: =IFERROR(__xludf.DUMMYFUNCTION("""COMPUTED_VALUE"""),"Yes") -> Yes | D46: =IFERROR(__xludf.DUMMYFUNCTION("""COMPUTED_VALUE"""),"Active") -> Active | E46: =IFERROR(__xludf.DUMMYFUNCTION("""COMPUTED_VALUE"""),45931.0) -> 45931 | G46: =IFERROR(__xludf.DUMMYFUNCTION("""COMPUTED_VALUE"""),12.166666666666666) -> 12.166667 | H46: =IFERROR(__xludf.DUMMYFUNCTION("""COMPUTED_VALUE"""),43298.0) -> 43298 | I46: =IFERROR(__xludf.DUMMYFUNCTION("""COMPUTED_VALUE"""),7.205555555555556) -> 7.2055556 | J46: =IFERROR(__xludf.DUMMYFUNCTION("""COMPUTED_VALUE"""),58.0) -> 58 | K46: =IFERROR(__xludf.DUMMYFUNCTION("""COMPUTED_VALUE"""),8.0) -> 8 | L46: =IFERROR(__xludf.DUMMYFUNCTION("""COMPUTED_VALUE"""),"Action-Adventure") -> Action-Adventure | N46: =IFERROR(__xludf.DUMMYFUNCTION("""COMPUTED_VALUE"""),"Ubisoft games joining with price increase") -> Ubisoft games joining with price increase
A47: =IFERROR(__xludf.DUMMYFUNCTION("""COMPUTED_VALUE"""),"Monopoly Madness") -> Monopoly Madness | B47: =IFERROR(__xludf.DUMMYFUNCTION("""COMPUTED_VALUE"""),"Xbox / PC") -> Xbox / PC | C47: =IFERROR(__xludf.DUMMYFUNCTION("""COMPUTED_VALUE"""),"Yes") -> Yes | D47: =IFERROR(__xludf.DUMMYFUNCTION("""COMPUTED_VALUE"""),"Active") -> Active | E47: =IFERROR(__xludf.DUMMYFUNCTION("""COMPUTED_VALUE"""),45931.0) -> 45931 | G47: =IFERROR(__xludf.DUMMYFUNCTION("""COMPUTED_VALUE"""),12.166666666666666) -> 12.166667 | H47: =IFERROR(__xludf.DUMMYFUNCTION("""COMPUTED_VALUE"""),44914.0) -> 44914 | I47: =IFERROR(__xludf.DUMMYFUNCTION("""COMPUTED_VALUE"""),2.783333333333333) -> 2.7833333 | J47: =IFERROR(__xludf.DUMMYFUNCTION("""COMPUTED_VALUE"""),71.0) -> 71 | K47: =IFERROR(__xludf.DUMMYFUNCTION("""COMPUTED_VALUE"""),6.0) -> 6 | L47: =IFERROR(__xludf.DUMMYFUNCTION("""COMPUTED_VALUE"""),"Party") -> Party | N47: =IFERROR(__xludf.DUMMYFUNCTION("""COMPUTED_VALUE"""),"Ubisoft games joining with price increase") -> Ubisoft games joining with price increase
A48: =IFERROR(__xludf.DUMMYFUNCTION("""COMPUTED_VALUE"""),"Monopoly (2024)") -> Monopoly (2024) | B48: =IFERROR(__xludf.DUMMYFUNCTION("""COMPUTED_VALUE"""),"Xbox / PC") -> Xbox / PC | C48: =IFERROR(__xludf.DUMMYFUNCTION("""COMPUTED_VALUE"""),"Yes") -> Yes | D48: =IFERROR(__xludf.DUMMYFUNCTION("""COMPUTED_VALUE"""),"Active") -> Active | E48: =IFERROR(__xludf.DUMMYFUNCTION("""COMPUTED_VALUE"""),45931.0) -> 45931 | G48: =IFERROR(__xludf.DUMMYFUNCTION("""COMPUTED_VALUE"""),12.166666666666666) -> 12.166667 | H48: =IFERROR(__xludf.DUMMYFUNCTION("""COMPUTED_VALUE"""),45561.0) -> 45561 | I48: =IFERROR(__xludf.DUMMYFUNCTION("""COMPUTED_VALUE"""),1.0138888888888888) -> 1.0138889 | J48: =IFERROR(__xludf.DUMMYFUNCTION("""COMPUTED_VALUE"""),74.0) -> 74 | K48: =IFERROR(__xludf.DUMMYFUNCTION("""COMPUTED_VALUE"""),14.0) -> 14 | L48: =IFERROR(__xludf.DUMMYFUNCTION("""COMPUTED_VALUE"""),"Board") -> Board | N48: =IFERROR(__xludf.DUMMYFUNCTION("""COMPUTED_VALUE"""),"Ubisoft games joining with price increase") -> Ubisoft games joining with price increase
A49: =IFERROR(__xludf.DUMMYFUNCTION("""COMPUTED_VALUE"""),"OddBallers") -> OddBallers | B49: =IFERROR(__xludf.DUMMYFUNCTION("""COMPUTED_VALUE"""),"Xbox / PC") -> Xbox / PC | C49: =IFERROR(__xludf.DUMMYFUNCTION("""COMPUTED_VALUE"""),"Yes") -> Yes | D49: =IFERROR(__xludf.DUMMYFUNCTION("""COMPUTED_VALUE"""),"Active") -> Active | E49: =IFERROR(__xludf.DUMMYFUNCTION("""COMPUTED_VALUE"""),45931.0) -> 45931 | G49: =IFERROR(__xludf.DUMMYFUNCTION("""COMPUTED_VALUE"""),12.166666666666666) -> 12.166667 | H49: =IFERROR(__xludf.DUMMYFUNCTION("""COMPUTED_VALUE"""),44952.0) -> 44952 | I49: =IFERROR(__xludf.DUMMYFUNCTION("""COMPUTED_VALUE"""),2.6805555555555554) -> 2.6805556 | J49: =IFERROR(__xludf.DUMMYFUNCTION("""COMPUTED_VALUE"""),71.0) -> 71 | K49: =IFERROR(__xludf.DUMMYFUNCTION("""COMPUTED_VALUE"""),8.0) -> 8 | L49: =IFERROR(__xludf.DUMMYFUNCTION("""COMPUTED_VALUE"""),"Party") -> Party | N49: =IFERROR(__xludf.DUMMYFUNCTION("""COMPUTED_VALUE"""),"Ubisoft games joining with price increase") -> Ubisoft games joining with price increase
A50: =IFERROR(__xludf.DUMMYFUNCTION("""COMPUTED_VALUE"""),"Prince of Persia: The Lost Crown") -> Prince of Persia: The Lost Crown | B50: =IFERROR(__xludf.DUMMYFUNCTION("""COMPUTED_VALUE"""),"Xbox / PC") -> Xbox / PC | C50: =IFERROR(__xludf.DUMMYFUNCTION("""COMPUTED_VALUE"""),"Yes") -> Yes | D50: =IFERROR(__xludf.DUMMYFUNCTION("""COMPUTED_VALUE"""),"Active") -> Active | E50: =IFERROR(__xludf.DUMMYFUNCTION("""COMPUTED_VALUE"""),45931.0) -> 45931 | G50: =IFERROR(__xludf.DUMMYFUNCTION("""COMPUTED_VALUE"""),12.166666666666666) -> 12.166667 | H50: =IFERROR(__xludf.DUMMYFUNCTION("""COMPUTED_VALUE"""),45309.0) -> 45309 | I50: =IFERROR(__xludf.DUMMYFUNCTION("""COMPUTED_VALUE"""),1.7027777777777777) -> 1.7027778 | J50: =IFERROR(__xludf.DUMMYFUNCTION("""COMPUTED_VALUE"""),86.0) -> 86 | K50: =IFERROR(__xludf.DUMMYFUNCTION("""COMPUTED_VALUE"""),17.0) -> 17 | L50: =IFERROR(__xludf.DUMMYFUNCTION("""COMPUTED_VALUE"""),"Metroidvania") -> Metroidvania | N50: =IFERROR(__xludf.DUMMYFUNCTION("""COMPUTED_VALUE"""),"Ubisoft games joining with price increase") -> Ubisoft games joining with price increase
A51: =IFERROR(__xludf.DUMMYFUNCTION("""COMPUTED_VALUE"""),"Rabbids Invasion: The Interactive TV Show") -> Rabbids Invasion: The Interactive TV Show | B51: =IFERROR(__xludf.DUMMYFUNCTION("""COMPUTED_VALUE"""),"Xbox") -> Xbox | C51: =IFERROR(__xludf.DUMMYFUNCTION("""COMPUTED_VALUE"""),"Yes") -> Yes | D51: =IFERROR(__xludf.DUMMYFUNCTION("""COMPUTED_VALUE"""),"Active") -> Active | E51: =IFERROR(__xludf.DUMMYFUNCTION("""COMPUTED_VALUE"""),45931.0) -> 45931 | G51: =IFERROR(__xludf.DUMMYFUNCTION("""COMPUTED_VALUE"""),12.166666666666666) -> 12.166667 | H51: =IFERROR(__xludf.DUMMYFUNCTION("""COMPUTED_VALUE"""),41951.0) -> 41951 | I51: =IFERROR(__xludf.DUMMYFUNCTION("""COMPUTED_VALUE"""),10.897222222222222) -> 10.897222 | J51: =IFERROR(__xludf.DUMMYFUNCTION("""COMPUTED_VALUE"""),53.0) -> 53 | K51: =IFERROR(__xludf.DUMMYFUNCTION("""COMPUTED_VALUE"""),10.0) -> 10 | L51: =IFERROR(__xludf.DUMMYFUNCTION("""COMPUTED_VALUE"""),"Party") -> Party | N51: =IFERROR(__xludf.DUMMYFUNCTION("""COMPUTED_VALUE"""),"Ubisoft games joining with price increase") -> Ubisoft games joining with price increase
A52: =IFERROR(__xludf.DUMMYFUNCTION("""COMPUTED_VALUE"""),"Rabbids: Party of Legends") -> Rabbids: Party of Legends | B52: =IFERROR(__xludf.DUMMYFUNCTION("""COMPUTED_VALUE"""),"Xbox / PC") -> Xbox / PC | C52: =IFERROR(__xludf.DUMMYFUNCTION("""COMPUTED_VALUE"""),"Yes") -> Yes | D52: =IFERROR(__xludf.DUMMYFUNCTION("""COMPUTED_VALUE"""),"Active") -> Active | E52: =IFERROR(__xludf.DUMMYFUNCTION("""COMPUTED_VALUE"""),45931.0) -> 45931 | G52: =IFERROR(__xludf.DUMMYFUNCTION("""COMPUTED_VALUE"""),12.166666666666666) -> 12.166667 | H52: =IFERROR(__xludf.DUMMYFUNCTION("""COMPUTED_VALUE"""),44742.0) -> 44742 | I52: =IFERROR(__xludf.DUMMYFUNCTION("""COMPUTED_VALUE"""),3.2527777777777778) -> 3.2527778 | J52: =IFERROR(__xludf.DUMMYFUNCTION("""COMPUTED_VALUE"""),69.0) -> 69 | K52: =IFERROR(__xludf.DUMMYFUNCTION("""COMPUTED_VALUE"""),3.0) -> 3 | L52: =IFERROR(__xludf.DUMMYFUNCTION("""COMPUTED_VALUE"""),"Party") -> Party | N52: =IFERROR(__xludf.DUMMYFUNCTION("""COMPUTED_VALUE"""),"Ubisoft games joining with price increase") -> Ubisoft games joining with price increase
A53: =IFERROR(__xludf.DUMMYFUNCTION("""COMPUTED_VALUE"""),"Rayman Legends") -> Rayman Legends | B53: =IFERROR(__xludf.DUMMYFUNCTION("""COMPUTED_VALUE"""),"Xbox / PC") -> Xbox / PC | C53: =IFERROR(__xludf.DUMMYFUNCTION("""COMPUTED_VALUE"""),"Yes") -> Yes | D53: =IFERROR(__xludf.DUMMYFUNCTION("""COMPUTED_VALUE"""),"Active") -> Active | E53: =IFERROR(__xludf.DUMMYFUNCTION("""COMPUTED_VALUE"""),45931.0) -> 45931 | G53: =IFERROR(__xludf.DUMMYFUNCTION("""COMPUTED_VALUE"""),12.166666666666666) -> 12.166667 | H53: =IFERROR(__xludf.DUMMYFUNCTION("""COMPUTED_VALUE"""),41520.0) -> 41520 | I53: =IFERROR(__xludf.DUMMYFUNCTION("""COMPUTED_VALUE"""),12.077777777777778) -> 12.077778 | J53: =IFERROR(__xludf.DUMMYFUNCTION("""COMPUTED_VALUE"""),92.0) -> 92 | K53: =IFERROR(__xludf.DUMMYFUNCTION("""COMPUTED_VALUE"""),10.0) -> 10 | L53: =IFERROR(__xludf.DUMMYFUNCTION("""COMPUTED_VALUE"""),"Platformer") -> Platformer | N53: =IFERROR(__xludf.DUMMYFUNCTION("""COMPUTED_VALUE"""),"Ubisoft games joining with price increase") -> Ubisoft games joining with price increase
A54: =IFERROR(__xludf.DUMMYFUNCTION("""COMPUTED_VALUE"""),"Risk: Urban Assault") -> Risk: Urban Assault | B54: =IFERROR(__xludf.DUMMYFUNCTION("""COMPUTED_VALUE"""),"Xbox") -> Xbox | C54: =IFERROR(__xludf.DUMMYFUNCTION("""COMPUTED_VALUE"""),"Yes") -> Yes | D54: =IFERROR(__xludf.DUMMYFUNCTION("""COMPUTED_VALUE"""),"Active") -> Active | E54: =IFERROR(__xludf.DUMMYFUNCTION("""COMPUTED_VALUE"""),45931.0) -> 45931 | G54: =IFERROR(__xludf.DUMMYFUNCTION("""COMPUTED_VALUE"""),12.166666666666666) -> 12.166667 | H54: =IFERROR(__xludf.DUMMYFUNCTION("""COMPUTED_VALUE"""),42584.0) -> 42584 | I54: =IFERROR(__xludf.DUMMYFUNCTION("""COMPUTED_VALUE"""),9.16388888888889) -> 9.1638889 | J54: =IFERROR(__xludf.DUMMYFUNCTION("""COMPUTED_VALUE"""),61.0) -> 61 | K54: =IFERROR(__xludf.DUMMYFUNCTION("""COMPUTED_VALUE"""),4.0) -> 4 | L54: =IFERROR(__xludf.DUMMYFUNCTION("""COMPUTED_VALUE"""),"Board") -> Board | N54: =IFERROR(__xludf.DUMMYFUNCTION("""COMPUTED_VALUE"""),"Ubisoft games joining with price increase") -> Ubisoft games joining with price increase
A55: =IFERROR(__xludf.DUMMYFUNCTION("""COMPUTED_VALUE"""),"Skull and Bones") -> Skull and Bones | B55: =IFERROR(__xludf.DUMMYFUNCTION("""COMPUTED_VALUE"""),"Xbox / PC") -> Xbox / PC | C55: =IFERROR(__xludf.DUMMYFUNCTION("""COMPUTED_VALUE"""),"Yes") -> Yes | D55: =IFERROR(__xludf.DUMMYFUNCTION("""COMPUTED_VALUE"""),"Active") -> Active | E55: =IFERROR(__xludf.DUMMYFUNCTION("""COMPUTED_VALUE"""),45931.0) -> 45931 | G55: =IFERROR(__xludf.DUMMYFUNCTION("""COMPUTED_VALUE"""),12.166666666666666) -> 12.166667 | H55: =IFERROR(__xludf.DUMMYFUNCTION("""COMPUTED_VALUE"""),45338.0) -> 45338 | I55: =IFERROR(__xludf.DUMMYFUNCTION("""COMPUTED_VALUE"""),1.625) -> 1.625 | J55: =IFERROR(__xludf.DUMMYFUNCTION("""COMPUTED_VALUE"""),59.0) -> 59 | K55: =IFERROR(__xludf.DUMMYFUNCTION("""COMPUTED_VALUE"""),32.0) -> 32 | L55: =IFERROR(__xludf.DUMMYFUNCTION("""COMPUTED_VALUE"""),"Action-Adventure") -> Action-Adventure | N55: =IFERROR(__xludf.DUMMYFUNCTION("""COMPUTED_VALUE"""),"Ubisoft games joining with price increase") -> Ubisoft games joining with price increase
A56: =IFERROR(__xludf.DUMMYFUNCTION("""COMPUTED_VALUE"""),"South Park: The Stick of Truth") -> South Park: The Stick of Truth | B56: =IFERROR(__xludf.DUMMYFUNCTION("""COMPUTED_VALUE"""),"Xbox / PC") -> Xbox / PC | C56: =IFERROR(__xludf.DUMMYFUNCTION("""COMPUTED_VALUE"""),"Yes") -> Yes | D56: =IFERROR(__xludf.DUMMYFUNCTION("""COMPUTED_VALUE"""),"Active") -> Active | E56: =IFERROR(__xludf.DUMMYFUNCTION("""COMPUTED_VALUE"""),45931.0) -> 45931 | G56: =IFERROR(__xludf.DUMMYFUNCTION("""COMPUTED_VALUE"""),12.166666666666666) -> 12.166667 | H56: =IFERROR(__xludf.DUMMYFUNCTION("""COMPUTED_VALUE"""),41702.0) -> 41702 | I56: =IFERROR(__xludf.DUMMYFUNCTION("""COMPUTED_VALUE"""),11.575) -> 11.575 | J56: =IFERROR(__xludf.DUMMYFUNCTION("""COMPUTED_VALUE"""),85.0) -> 85 | K56: =IFERROR(__xludf.DUMMYFUNCTION("""COMPUTED_VALUE"""),12.0) -> 12 | L56: =IFERROR(__xludf.DUMMYFUNCTION("""COMPUTED_VALUE"""),"RPG") -> RPG | N56: =IFERROR(__xludf.DUMMYFUNCTION("""COMPUTED_VALUE"""),"Ubisoft games joining with price increase") -> Ubisoft games joining with price increase
A57: =IFERROR(__xludf.DUMMYFUNCTION("""COMPUTED_VALUE"""),"Starlink: Battle for Atlas") -> Starlink: Battle for Atlas | B57: =IFERROR(__xludf.DUMMYFUNCTION("""COMPUTED_VALUE"""),"Xbox / PC") -> Xbox / PC | C57: =IFERROR(__xludf.DUMMYFUNCTION("""COMPUTED_VALUE"""),"Yes") -> Yes | D57: =IFERROR(__xludf.DUMMYFUNCTION("""COMPUTED_VALUE"""),"Active") -> Active | E57: =IFERROR(__xludf.DUMMYFUNCTION("""COMPUTED_VALUE"""),45931.0) -> 45931 | G57: =IFERROR(__xludf.DUMMYFUNCTION("""COMPUTED_VALUE"""),12.166666666666666) -> 12.166667 | H57: =IFERROR(__xludf.DUMMYFUNCTION("""COMPUTED_VALUE"""),43389.0) -> 43389 | I57: =IFERROR(__xludf.DUMMYFUNCTION("""COMPUTED_VALUE"""),6.958333333333333) -> 6.9583333 | J57: =IFERROR(__xludf.DUMMYFUNCTION("""COMPUTED_VALUE"""),74.0) -> 74 | K57: =IFERROR(__xludf.DUMMYFUNCTION("""COMPUTED_VALUE"""),15.0) -> 15 | L57: =IFERROR(__xludf.DUMMYFUNCTION("""COMPUTED_VALUE"""),"Simulation") -> Simulation | N57: =IFERROR(__xludf.DUMMYFUNCTION("""COMPUTED_VALUE"""),"Ubisoft games joining with price increase") -> Ubisoft games joining with price increase
A58: =IFERROR(__xludf.DUMMYFUNCTION("""COMPUTED_VALUE"""),"Steep") -> Steep | B58: =IFERROR(__xludf.DUMMYFUNCTION("""COMPUTED_VALUE"""),"Xbox / PC") -> Xbox / PC | C58: =IFERROR(__xludf.DUMMYFUNCTION("""COMPUTED_VALUE"""),"Touch Controls") -> Touch Controls | D58: =IFERROR(__xludf.DUMMYFUNCTION("""COMPUTED_VALUE"""),"Active") -> Active | E58: =IFERROR(__xludf.DUMMYFUNCTION("""COMPUTED_VALUE"""),45931.0) -> 45931 | G58: =IFERROR(__xludf.DUMMYFUNCTION("""COMPUTED_VALUE"""),12.166666666666666) -> 12.166667 | H58: =IFERROR(__xludf.DUMMYFUNCTION("""COMPUTED_VALUE"""),42703.0) -> 42703 | I58: =IFERROR(__xludf.DUMMYFUNCTION("""COMPUTED_VALUE"""),8.838888888888889) -> 8.8388889 | J58: =IFERROR(__xludf.DUMMYFUNCTION("""COMPUTED_VALUE"""),71.0) -> 71 | K58: =IFERROR(__xludf.DUMMYFUNCTION("""COMPUTED_VALUE"""),12.0) -> 12 | L58: =IFERROR(__xludf.DUMMYFUNCTION("""COMPUTED_VALUE"""),"Sports") -> Sports | M58: =IFERROR(__xludf.DUMMYFUNCTION("""COMPUTED_VALUE"""),"FPS Boost S Only") -> FPS Boost S Only | N58: =IFERROR(__xludf.DUMMYFUNCTION("""COMPUTED_VALUE"""),"Returning title: Joined 5/6/21, left 5/15/22. Ubisoft games joining with price increase") -> Returning title: Joined 5/6/21, left 5/15/22. Ubisoft games joining with price increase
A59: =IFERROR(__xludf.DUMMYFUNCTION("""COMPUTED_VALUE"""),"The Crew 2") -> The Crew 2 | B59: =IFERROR(__xludf.DUMMYFUNCTION("""COMPUTED_VALUE"""),"Xbox / PC") -> Xbox / PC | C59: =IFERROR(__xludf.DUMMYFUNCTION("""COMPUTED_VALUE"""),"Yes") -> Yes | D59: =IFERROR(__xludf.DUMMYFUNCTION("""COMPUTED_VALUE"""),"Active") -> Active | E59: =IFERROR(__xludf.DUMMYFUNCTION("""COMPUTED_VALUE"""),45931.0) -> 45931 | G59: =IFERROR(__xludf.DUMMYFUNCTION("""COMPUTED_VALUE"""),12.166666666666666) -> 12.166667 | H59: =IFERROR(__xludf.DUMMYFUNCTION("""COMPUTED_VALUE"""),43277.0) -> 43277 | I59: =IFERROR(__xludf.DUMMYFUNCTION("""COMPUTED_VALUE"""),7.263888888888889) -> 7.2638889 | J59: =IFERROR(__xludf.DUMMYFUNCTION("""COMPUTED_VALUE"""),64.0) -> 64 | K59: =IFERROR(__xludf.DUMMYFUNCTION("""COMPUTED_VALUE"""),21.0) -> 21 | L59: =IFERROR(__xludf.DUMMYFUNCTION("""COMPUTED_VALUE"""),"Racing") -> Racing | N59: =IFERROR(__xludf.DUMMYFUNCTION("""COMPUTED_VALUE"""),"Ubisoft games joining with price increase") -> Ubisoft games joining with price increase
A60: =IFERROR(__xludf.DUMMYFUNCTION("""COMPUTED_VALUE"""),"The Settlers: New Allies") -> The Settlers: New Allies | B60: =IFERROR(__xludf.DUMMYFUNCTION("""COMPUTED_VALUE"""),"Xbox / PC") -> Xbox / PC | C60: =IFERROR(__xludf.DUMMYFUNCTION("""COMPUTED_VALUE"""),"Yes") -> Yes | D60: =IFERROR(__xludf.DUMMYFUNCTION("""COMPUTED_VALUE"""),"Active") -> Active | E60: =IFERROR(__xludf.DUMMYFUNCTION("""COMPUTED_VALUE"""),45931.0) -> 45931 | G60: =IFERROR(__xludf.DUMMYFUNCTION("""COMPUTED_VALUE"""),12.166666666666666) -> 12.166667 | H60: =IFERROR(__xludf.DUMMYFUNCTION("""COMPUTED_VALUE"""),44974.0) -> 44974 | I60: =IFERROR(__xludf.DUMMYFUNCTION("""COMPUTED_VALUE"""),2.6222222222222222) -> 2.6222222 | J60: =IFERROR(__xludf.DUMMYFUNCTION("""COMPUTED_VALUE"""),54.0) -> 54 | K60: =IFERROR(__xludf.DUMMYFUNCTION("""COMPUTED_VALUE"""),35.0) -> 35 | L60: =IFERROR(__xludf.DUMMYFUNCTION("""COMPUTED_VALUE"""),"Management") -> Management | N60: =IFERROR(__xludf.DUMMYFUNCTION("""COMPUTED_VALUE"""),"Ubisoft games joining with price increase") -> Ubisoft games joining with price increase
A61: =IFERROR(__xludf.DUMMYFUNCTION("""COMPUTED_VALUE"""),"Tom Clancy's Ghost Recon Breakpoint") -> Tom Clancy's Ghost Recon Breakpoint | B61: =IFERROR(__xludf.DUMMYFUNCTION("""COMPUTED_VALUE"""),"Xbox / PC") -> Xbox / PC | C61: =IFERROR(__xludf.DUMMYFUNCTION("""COMPUTED_VALUE"""),"Yes") -> Yes | D61: =IFERROR(__xludf.DUMMYFUNCTION("""COMPUTED_VALUE"""),"Active") -> Active | E61: =IFERROR(__xludf.DUMMYFUNCTION("""COMPUTED_VALUE"""),45931.0) -> 45931 | G61: =IFERROR(__xludf.DUMMYFUNCTION("""COMPUTED_VALUE"""),12.166666666666666) -> 12.166667 | H61: =IFERROR(__xludf.DUMMYFUNCTION("""COMPUTED_VALUE"""),43739.0) -> 43739 | I61: =IFERROR(__xludf.DUMMYFUNCTION("""COMPUTED_VALUE"""),6.0) -> 6 | J61: =IFERROR(__xludf.DUMMYFUNCTION("""COMPUTED_VALUE"""),56.0) -> 56 | K61: =IFERROR(__xludf.DUMMYFUNCTION("""COMPUTED_VALUE"""),23.0) -> 23 | L61: =IFERROR(__xludf.DUMMYFUNCTION("""COMPUTED_VALUE"""),"Shooter") -> Shooter | N61: =IFERROR(__xludf.DUMMYFUNCTION("""COMPUTED_VALUE"""),"Ubisoft games joining with price increase") -> Ubisoft games joining with price increase
A62: =IFERROR(__xludf.DUMMYFUNCTION("""COMPUTED_VALUE"""),"Tom Clancy's Rainbow Six: Extraction") -> Tom Clancy's Rainbow Six: Extraction | B62: =IFERROR(__xludf.DUMMYFUNCTION("""COMPUTED_VALUE"""),"Xbox / PC") -> Xbox / PC | C62: =IFERROR(__xludf.DUMMYFUNCTION("""COMPUTED_VALUE"""),"Yes") -> Yes | D62: =IFERROR(__xludf.DUMMYFUNCTION("""COMPUTED_VALUE"""),"Active") -> Active | E62: =IFERROR(__xludf.DUMMYFUNCTION("""COMPUTED_VALUE"""),45931.0) -> 45931 | G62: =IFERROR(__xludf.DUMMYFUNCTION("""COMPUTED_VALUE"""),12.166666666666666) -> 12.166667 | H62: =IFERROR(__xludf.DUMMYFUNCTION("""COMPUTED_VALUE"""),44581.0) -> 44581 | I62: =IFERROR(__xludf.DUMMYFUNCTION("""COMPUTED_VALUE"""),3.6972222222222224) -> 3.6972222 | J62: =IFERROR(__xludf.DUMMYFUNCTION("""COMPUTED_VALUE"""),71.5) -> 71.5 | K62: =IFERROR(__xludf.DUMMYFUNCTION("""COMPUTED_VALUE"""),8.0) -> 8 | L62: =IFERROR(__xludf.DUMMYFUNCTION("""COMPUTED_VALUE"""),"Shooter") -> Shooter | N62: =IFERROR(__xludf.DUMMYFUNCTION("""COMPUTED_VALUE"""),"Returning game: added 1/20/22, left 4/15/23. Ubisoft Connect launcher. Ubisoft games joining with price increase") -> Returning game: added 1/20/22, left 4/15/23. Ubisoft Connect launcher. Ubisoft games joining with price increase | O62: =IFERROR(__xludf.DUMMYFUNCTION("""COMPUTED_VALUE"""),"M") -> M | P62: =IFERROR(__xludf.DUMMYFUNCTION("""COMPUTED_VALUE"""),"Blood, Drug Reference, Strong Language, Violence") -> Blood, Drug Reference, Strong Language, Violence
A63: =IFERROR(__xludf.DUMMYFUNCTION("""COMPUTED_VALUE"""),"Tom Clancy's The Division") -> Tom Clancy's The Division | B63: =IFERROR(__xludf.DUMMYFUNCTION("""COMPUTED_VALUE"""),"Xbox / PC") -> Xbox / PC | C63: =IFERROR(__xludf.DUMMYFUNCTION("""COMPUTED_VALUE"""),"Yes") -> Yes | D63: =IFERROR(__xludf.DUMMYFUNCTION("""COMPUTED_VALUE"""),"Active") -> Active | E63: =IFERROR(__xludf.DUMMYFUNCTION("""COMPUTED_VALUE"""),45931.0) -> 45931 | G63: =IFERROR(__xludf.DUMMYFUNCTION("""COMPUTED_VALUE"""),12.166666666666666) -> 12.166667 | H63: =IFERROR(__xludf.DUMMYFUNCTION("""COMPUTED_VALUE"""),42437.0) -> 42437 | I63: =IFERROR(__xludf.DUMMYFUNCTION("""COMPUTED_VALUE"""),9.563888888888888) -> 9.5638889 | J63: =IFERROR(__xludf.DUMMYFUNCTION("""COMPUTED_VALUE"""),80.0) -> 80 | K63: =IFERROR(__xludf.DUMMYFUNCTION("""COMPUTED_VALUE"""),24.0) -> 24 | L63: =IFERROR(__xludf.DUMMYFUNCTION("""COMPUTED_VALUE"""),"Shooter") -> Shooter | N63: =IFERROR(__xludf.DUMMYFUNCTION("""COMPUTED_VALUE"""),"Returning title: Joined 12/1/19, left 6/10/18. Ubisoft games joining with price increase") -> Returning title: Joined 12/1/19, left 6/10/18. Ubisoft games joining with price increase
A64: =IFERROR(__xludf.DUMMYFUNCTION("""COMPUTED_VALUE"""),"Trackmania Turbo") -> Trackmania Turbo | B64: =IFERROR(__xludf.DUMMYFUNCTION("""COMPUTED_VALUE"""),"Xbox / PC") -> Xbox / PC | C64: =IFERROR(__xludf.DUMMYFUNCTION("""COMPUTED_VALUE"""),"Yes") -> Yes | D64: =IFERROR(__xludf.DUMMYFUNCTION("""COMPUTED_VALUE"""),"Active") -> Active | E64: =IFERROR(__xludf.DUMMYFUNCTION("""COMPUTED_VALUE"""),45931.0) -> 45931 | G64: =IFERROR(__xludf.DUMMYFUNCTION("""COMPUTED_VALUE"""),12.166666666666666) -> 12.166667 | H64: =IFERROR(__xludf.DUMMYFUNCTION("""COMPUTED_VALUE"""),42451.0) -> 42451 | I64: =IFERROR(__xludf.DUMMYFUNCTION("""COMPUTED_VALUE"""),9.525) -> 9.525 | J64: =IFERROR(__xludf.DUMMYFUNCTION("""COMPUTED_VALUE"""),81.0) -> 81 | K64: =IFERROR(__xludf.DUMMYFUNCTION("""COMPUTED_VALUE"""),13.0) -> 13 | L64: =IFERROR(__xludf.DUMMYFUNCTION("""COMPUTED_VALUE"""),"Racing") -> Racing | N64: =IFERROR(__xludf.DUMMYFUNCTION("""COMPUTED_VALUE"""),"Ubisoft games joining with price increase") -> Ubisoft games joining with price increase
A65: =IFERROR(__xludf.DUMMYFUNCTION("""COMPUTED_VALUE"""),"Transference") -> Transference | B65: =IFERROR(__xludf.DUMMYFUNCTION("""COMPUTED_VALUE"""),"Xbox") -> Xbox | C65: =IFERROR(__xludf.DUMMYFUNCTION("""COMPUTED_VALUE"""),"Yes") -> Yes | D65: =IFERROR(__xludf.DUMMYFUNCTION("""COMPUTED_VALUE"""),"Active") -> Active | E65: =IFERROR(__xludf.DUMMYFUNCTION("""COMPUTED_VALUE"""),45931.0) -> 45931 | G65: =IFERROR(__xludf.DUMMYFUNCTION("""COMPUTED_VALUE"""),12.166666666666666) -> 12.166667 | H65: =IFERROR(__xludf.DUMMYFUNCTION("""COMPUTED_VALUE"""),43361.0) -> 43361 | I65: =IFERROR(__xludf.DUMMYFUNCTION("""COMPUTED_VALUE"""),7.036111111111111) -> 7.0361111 | J65: =IFERROR(__xludf.DUMMYFUNCTION("""COMPUTED_VALUE"""),71.0) -> 71 | K65: =IFERROR(__xludf.DUMMYFUNCTION("""COMPUTED_VALUE"""),2.0) -> 2 | L65: =IFERROR(__xludf.DUMMYFUNCTION("""COMPUTED_VALUE"""),"Action-Adventure") -> Action-Adventure | N65: =IFERROR(__xludf.DUMMYFUNCTION("""COMPUTED_VALUE"""),"Ubisoft games joining with price increase") -> Ubisoft games joining with price increase
A66: =IFERROR(__xludf.DUMMYFUNCTION("""COMPUTED_VALUE"""),"Trials Fusion") -> Trials Fusion | B66: =IFERROR(__xludf.DUMMYFUNCTION("""COMPUTED_VALUE"""),"Xbox / PC") -> Xbox / PC | C66: =IFERROR(__xludf.DUMMYFUNCTION("""COMPUTED_VALUE"""),"Yes") -> Yes | D66: =IFERROR(__xludf.DUMMYFUNCTION("""COMPUTED_VALUE"""),"Active") -> Active | E66: =IFERROR(__xludf.DUMMYFUNCTION("""COMPUTED_VALUE"""),45931.0) -> 45931 | G66: =IFERROR(__xludf.DUMMYFUNCTION("""COMPUTED_VALUE"""),12.166666666666666) -> 12.166667 | H66: =IFERROR(__xludf.DUMMYFUNCTION("""COMPUTED_VALUE"""),41744.0) -> 41744 | I66: =IFERROR(__xludf.DUMMYFUNCTION("""COMPUTED_VALUE"""),11.46111111111111) -> 11.461111 | J66: =IFERROR(__xludf.DUMMYFUNCTION("""COMPUTED_VALUE"""),79.0) -> 79 | K66: =IFERROR(__xludf.DUMMYFUNCTION("""COMPUTED_VALUE"""),7.0) -> 7 | L66: =IFERROR(__xludf.DUMMYFUNCTION("""COMPUTED_VALUE"""),"Racing") -> Racing | N66: =IFERROR(__xludf.DUMMYFUNCTION("""COMPUTED_VALUE"""),"Ubisoft games joining with price increase") -> Ubisoft games joining with price increase
A67: =IFERROR(__xludf.DUMMYFUNCTION("""COMPUTED_VALUE"""),"Trials of the Blood Dragon") -> Trials of the Blood Dragon | B67: =IFERROR(__xludf.DUMMYFUNCTION("""COMPUTED_VALUE"""),"Xbox / PC") -> Xbox / PC | C67: =IFERROR(__xludf.DUMMYFUNCTION("""COMPUTED_VALUE"""),"Yes") -> Yes | D67: =IFERROR(__xludf.DUMMYFUNCTION("""COMPUTED_VALUE"""),"Active") -> Active | E67: =IFERROR(__xludf.DUMMYFUNCTION("""COMPUTED_VALUE"""),45931.0) -> 45931 | G67: =IFERROR(__xludf.DUMMYFUNCTION("""COMPUTED_VALUE"""),12.166666666666666) -> 12.166667 | H67: =IFERROR(__xludf.DUMMYFUNCTION("""COMPUTED_VALUE"""),42534.0) -> 42534 | I67: =IFERROR(__xludf.DUMMYFUNCTION("""COMPUTED_VALUE"""),9.3) -> 9.3 | J67: =IFERROR(__xludf.DUMMYFUNCTION("""COMPUTED_VALUE"""),55.0) -> 55 | K67: =IFERROR(__xludf.DUMMYFUNCTION("""COMPUTED_VALUE"""),3.0) -> 3 | L67: =IFERROR(__xludf.DUMMYFUNCTION("""COMPUTED_VALUE"""),"Racing") -> Racing | N67: =IFERROR(__xludf.DUMMYFUNCTION("""COMPUTED_VALUE"""),"Ubisoft games joining with price increase") -> Ubisoft games joining with price increase
A68: =IFERROR(__xludf.DUMMYFUNCTION("""COMPUTED_VALUE"""),"Trials Rising") -> Trials Rising | B68: =IFERROR(__xludf.DUMMYFUNCTION("""COMPUTED_VALUE"""),"Xbox / PC") -> Xbox / PC | C68: =IFERROR(__xludf.DUMMYFUNCTION("""COMPUTED_VALUE"""),"Yes") -> Yes | D68: =IFERROR(__xludf.DUMMYFUNCTION("""COMPUTED_VALUE"""),"Active") -> Active | E68: =IFERROR(__xludf.DUMMYFUNCTION("""COMPUTED_VALUE"""),45931.0) -> 45931 | G68: =IFERROR(__xludf.DUMMYFUNCTION("""COMPUTED_VALUE"""),12.166666666666666) -> 12.166667 | H68: =IFERROR(__xludf.DUMMYFUNCTION("""COMPUTED_VALUE"""),43522.0) -> 43522 | I68: =IFERROR(__xludf.DUMMYFUNCTION("""COMPUTED_VALUE"""),6.597222222222222) -> 6.5972222 | J68: =IFERROR(__xludf.DUMMYFUNCTION("""COMPUTED_VALUE"""),79.0) -> 79 | K68: =IFERROR(__xludf.DUMMYFUNCTION("""COMPUTED_VALUE"""),18.0) -> 18 | L68: =IFERROR(__xludf.DUMMYFUNCTION("""COMPUTED_VALUE"""),"Racing") -> Racing | N68: =IFERROR(__xludf.DUMMYFUNCTION("""COMPUTED_VALUE"""),"Ubisoft games joining with price increase") -> Ubisoft games joining with price increase
A69: =IFERROR(__xludf.DUMMYFUNCTION("""COMPUTED_VALUE"""),"Uno") -> Uno | B69: =IFERROR(__xludf.DUMMYFUNCTION("""COMPUTED_VALUE"""),"Xbox / PC") -> Xbox / PC | C69: =IFERROR(__xludf.DUMMYFUNCTION("""COMPUTED_VALUE"""),"Yes") -> Yes | D69: =IFERROR(__xludf.DUMMYFUNCTION("""COMPUTED_VALUE"""),"Active") -> Active | E69: =IFERROR(__xludf.DUMMYFUNCTION("""COMPUTED_VALUE"""),45931.0) -> 45931 | G69: =IFERROR(__xludf.DUMMYFUNCTION("""COMPUTED_VALUE"""),12.166666666666666) -> 12.166667 | H69: =IFERROR(__xludf.DUMMYFUNCTION("""COMPUTED_VALUE"""),38846.0) -> 38846 | I69: =IFERROR(__xludf.DUMMYFUNCTION("""COMPUTED_VALUE"""),19.394444444444446) -> 19.394444 | J69: =IFERROR(__xludf.DUMMYFUNCTION("""COMPUTED_VALUE"""),81.0) -> 81 | K69: =IFERROR(__xludf.DUMMYFUNCTION("""COMPUTED_VALUE"""),3.0) -> 3 | L69: =IFERROR(__xludf.DUMMYFUNCTION("""COMPUTED_VALUE"""),"Board") -> Board | N69: =IFERROR(__xludf.DUMMYFUNCTION("""COMPUTED_VALUE"""),"Ubisoft games joining with price increase") -> Ubisoft games joining with price increase
A70: =IFERROR(__xludf.DUMMYFUNCTION("""COMPUTED_VALUE"""),"Valiant Hearts: The Great War") -> Valiant Hearts: The Great War | B70: =IFERROR(__xludf.DUMMYFUNCTION("""COMPUTED_VALUE"""),"Xbox / PC") -> Xbox / PC | C70: =IFERROR(__xludf.DUMMYFUNCTION("""COMPUTED_VALUE"""),"Yes") -> Yes | D70: =IFERROR(__xludf.DUMMYFUNCTION("""COMPUTED_VALUE"""),"Active") -> Active | E70: =IFERROR(__xludf.DUMMYFUNCTION("""COMPUTED_VALUE"""),45931.0) -> 45931 | G70: =IFERROR(__xludf.DUMMYFUNCTION("""COMPUTED_VALUE"""),12.166666666666666) -> 12.166667 | H70: =IFERROR(__xludf.DUMMYFUNCTION("""COMPUTED_VALUE"""),41814.0) -> 41814 | I70: =IFERROR(__xludf.DUMMYFUNCTION("""COMPUTED_VALUE"""),11.269444444444444) -> 11.269444 | J70: =IFERROR(__xludf.DUMMYFUNCTION("""COMPUTED_VALUE"""),77.0) -> 77 | K70: =IFERROR(__xludf.DUMMYFUNCTION("""COMPUTED_VALUE"""),7.0) -> 7 | L70: =IFERROR(__xludf.DUMMYFUNCTION("""COMPUTED_VALUE"""),"Platformer") -> Platformer | N70: =IFERROR(__xludf.DUMMYFUNCTION("""COMPUTED_VALUE"""),"Ubisoft games joining with price increase") -> Ubisoft games joining with price increase
A71: =IFERROR(__xludf.DUMMYFUNCTION("""COMPUTED_VALUE"""),"Watch_Dogs") -> Watch_Dogs | B71: =IFERROR(__xludf.DUMMYFUNCTION("""COMPUTED_VALUE"""),"Xbox / PC") -> Xbox / PC | C71: =IFERROR(__xludf.DUMMYFUNCTION("""COMPUTED_VALUE"""),"Yes") -> Yes | D71: =IFERROR(__xludf.DUMMYFUNCTION("""COMPUTED_VALUE"""),"Active") -> Active | E71: =IFERROR(__xludf.DUMMYFUNCTION("""COMPUTED_VALUE"""),45931.0) -> 45931 | G71: =IFERROR(__xludf.DUMMYFUNCTION("""COMPUTED_VALUE"""),12.166666666666666) -> 12.166667 | H71: =IFERROR(__xludf.DUMMYFUNCTION("""COMPUTED_VALUE"""),41786.0) -> 41786 | I71: =IFERROR(__xludf.DUMMYFUNCTION("""COMPUTED_VALUE"""),11.344444444444445) -> 11.344444 | J71: =IFERROR(__xludf.DUMMYFUNCTION("""COMPUTED_VALUE"""),80.0) -> 80 | K71: =IFERROR(__xludf.DUMMYFUNCTION("""COMPUTED_VALUE"""),20.0) -> 20 | L71: =IFERROR(__xludf.DUMMYFUNCTION("""COMPUTED_VALUE"""),"Action-Adventure") -> Action-Adventure | N71: =IFERROR(__xludf.DUMMYFUNCTION("""COMPUTED_VALUE"""),"Ubisoft games joining with price increase") -> Ubisoft games joining with price increase
A72: =IFERROR(__xludf.DUMMYFUNCTION("""COMPUTED_VALUE"""),"Wheel of Fortune") -> Wheel of Fortune | B72: =IFERROR(__xludf.DUMMYFUNCTION("""COMPUTED_VALUE"""),"Xbox") -> Xbox | C72: =IFERROR(__xludf.DUMMYFUNCTION("""COMPUTED_VALUE"""),"Yes") -> Yes | D72: =IFERROR(__xludf.DUMMYFUNCTION("""COMPUTED_VALUE"""),"Active") -> Active | E72: =IFERROR(__xludf.DUMMYFUNCTION("""COMPUTED_VALUE"""),45931.0) -> 45931 | G72: =IFERROR(__xludf.DUMMYFUNCTION("""COMPUTED_VALUE"""),12.166666666666666) -> 12.166667 | H72: =IFERROR(__xludf.DUMMYFUNCTION("""COMPUTED_VALUE"""),43046.0) -> 43046 | I72: =IFERROR(__xludf.DUMMYFUNCTION("""COMPUTED_VALUE"""),7.9) -> 7.9 | J72: =IFERROR(__xludf.DUMMYFUNCTION("""COMPUTED_VALUE"""),80.0) -> 80 | K72: =IFERROR(__xludf.DUMMYFUNCTION("""COMPUTED_VALUE"""),2.0) -> 2 | L72: =IFERROR(__xludf.DUMMYFUNCTION("""COMPUTED_VALUE"""),"Trivia") -> Trivia | N72: =IFERROR(__xludf.DUMMYFUNCTION("""COMPUTED_VALUE"""),"Ubisoft games joining with price increase") -> Ubisoft games joining with price increase
A73: =IFERROR(__xludf.DUMMYFUNCTION("""COMPUTED_VALUE"""),"Zombi") -> Zombi | B73: =IFERROR(__xludf.DUMMYFUNCTION("""COMPUTED_VALUE"""),"Xbox / PC") -> Xbox / PC | C73: =IFERROR(__xludf.DUMMYFUNCTION("""COMPUTED_VALUE"""),"Yes") -> Yes | D73: =IFERROR(__xludf.DUMMYFUNCTION("""COMPUTED_VALUE"""),"Active") -> Active | E73: =IFERROR(__xludf.DUMMYFUNCTION("""COMPUTED_VALUE"""),45931.0) -> 45931 | G73: =IFERROR(__xludf.DUMMYFUNCTION("""COMPUTED_VALUE"""),12.166666666666666) -> 12.166667 | H73: =IFERROR(__xludf.DUMMYFUNCTION("""COMPUTED_VALUE"""),42234.0) -> 42234 | I73: =IFERROR(__xludf.DUMMYFUNCTION("""COMPUTED_VALUE"""),10.119444444444444) -> 10.119444 | J73: =IFERROR(__xludf.DUMMYFUNCTION("""COMPUTED_VALUE"""),65.0) -> 65 | K73: =IFERROR(__xludf.DUMMYFUNCTION("""COMPUTED_VALUE"""),12.0) -> 12 | L73: =IFERROR(__xludf.DUMMYFUNCTION("""COMPUTED_VALUE"""),"Survival") -> Survival | N73: =IFERROR(__xludf.DUMMYFUNCTION("""COMPUTED_VALUE"""),"Ubisoft games joining with price increase") -> Ubisoft games joining with price increase
A74: =IFERROR(__xludf.DUMMYFUNCTION("""COMPUTED_VALUE"""),"Visions of Mana") -> Visions of Mana | B74: =IFERROR(__xludf.DUMMYFUNCTION("""COMPUTED_VALUE"""),"Xbox / PC") -> Xbox / PC | C74: =IFERROR(__xludf.DUMMYFUNCTION("""COMPUTED_VALUE"""),"Yes") -> Yes | D74: =IFERROR(__xludf.DUMMYFUNCTION("""COMPUTED_VALUE"""),"Active") -> Active | E74: =IFERROR(__xludf.DUMMYFUNCTION("""COMPUTED_VALUE"""),45925.0) -> 45925 | G74: =IFERROR(__xludf.DUMMYFUNCTION("""COMPUTED_VALUE"""),12.366666666666665) -> 12.366667 | H74: =IFERROR(__xludf.DUMMYFUNCTION("""COMPUTED_VALUE"""),45533.0) -> 45533 | I74: =IFERROR(__xludf.DUMMYFUNCTION("""COMPUTED_VALUE"""),1.0722222222222222) -> 1.0722222 | J74: =IFERROR(__xludf.DUMMYFUNCTION("""COMPUTED_VALUE"""),75.0) -> 75 | K74: =IFERROR(__xludf.DUMMYFUNCTION("""COMPUTED_VALUE"""),29.0) -> 29 | L74: =IFERROR(__xludf.DUMMYFUNCTION("""COMPUTED_VALUE"""),"RPG") -> RPG | M74: =IFERROR(__xludf.DUMMYFUNCTION("""COMPUTED_VALUE"""),"Exclusive") -> Exclusive
A75: =IFERROR(__xludf.DUMMYFUNCTION("""COMPUTED_VALUE"""),"Hades") -> Hades | B75: =IFERROR(__xludf.DUMMYFUNCTION("""COMPUTED_VALUE"""),"Xbox / PC") -> Xbox / PC | C75: =IFERROR(__xludf.DUMMYFUNCTION("""COMPUTED_VALUE"""),"Touch Controls") -> Touch Controls | D75: =IFERROR(__xludf.DUMMYFUNCTION("""COMPUTED_VALUE"""),"Active") -> Active | E75: =IFERROR(__xludf.DUMMYFUNCTION("""COMPUTED_VALUE"""),45919.0) -> 45919 | G75: =IFERROR(__xludf.DUMMYFUNCTION("""COMPUTED_VALUE"""),12.566666666666666) -> 12.566667 | H75: =IFERROR(__xludf.DUMMYFUNCTION("""COMPUTED_VALUE"""),43441.0) -> 43441 | I75: =IFERROR(__xludf.DUMMYFUNCTION("""COMPUTED_VALUE"""),6.783333333333333) -> 6.7833333 | J75: =IFERROR(__xludf.DUMMYFUNCTION("""COMPUTED_VALUE"""),93.5) -> 93.5 | K75: =IFERROR(__xludf.DUMMYFUNCTION("""COMPUTED_VALUE"""),21.0) -> 21 | L75: =IFERROR(__xludf.DUMMYFUNCTION("""COMPUTED_VALUE"""),"RPG") -> RPG | M75: =IFERROR(__xludf.DUMMYFUNCTION("""COMPUTED_VALUE"""),"Optimized") -> Optimized | N75: =IFERROR(__xludf.DUMMYFUNCTION("""COMPUTED_VALUE"""),"Game Pass Essential (10/1/25). Returning title: Joined 8/13/21, left 8/31/22") -> Game Pass Essential (10/1/25). Returning title: Joined 8/13/21, left 8/31/22 | O75: =IFERROR(__xludf.DUMMYFUNCTION("""COMPUTED_VALUE"""),"T") -> T | P75: =IFERROR(__xludf.DUMMYFUNCTION("""COMPUTED_VALUE"""),"Blood, Suggestive Themes, Alcohol Reference, Mild Language, Violence") -> Blood, Suggestive Themes, Alcohol Reference, Mild Language, Violence
A76: =IFERROR(__xludf.DUMMYFUNCTION("""COMPUTED_VALUE"""),"Wobbly Life") -> Wobbly Life | B76: =IFERROR(__xludf.DUMMYFUNCTION("""COMPUTED_VALUE"""),"Xbox / PC") -> Xbox / PC | C76: =IFERROR(__xludf.DUMMYFUNCTION("""COMPUTED_VALUE"""),"Yes") -> Yes | D76: =IFERROR(__xludf.DUMMYFUNCTION("""COMPUTED_VALUE"""),"Active") -> Active | E76: =IFERROR(__xludf.DUMMYFUNCTION("""COMPUTED_VALUE"""),45918.0) -> 45918 | G76: =IFERROR(__xludf.DUMMYFUNCTION("""COMPUTED_VALUE"""),12.600000000000001) -> 12.6 | H76: =IFERROR(__xludf.DUMMYFUNCTION("""COMPUTED_VALUE"""),45898.0) -> 45898 | I76: =IFERROR(__xludf.DUMMYFUNCTION("""COMPUTED_VALUE"""),0.05277777777777778) -> 0.052777778 | J76: =IFERROR(__xludf.DUMMYFUNCTION("""COMPUTED_VALUE"""),80.0) -> 80 | K76: =IFERROR(__xludf.DUMMYFUNCTION("""COMPUTED_VALUE"""),3.0) -> 3 | L76: =IFERROR(__xludf.DUMMYFUNCTION("""COMPUTED_VALUE"""),"Action-Adventure") -> Action-Adventure | M76: =IFERROR(__xludf.DUMMYFUNCTION("""COMPUTED_VALUE"""),"Exclusive") -> Exclusive
A77: =IFERROR(__xludf.DUMMYFUNCTION("""COMPUTED_VALUE"""),"RoadCraft") -> RoadCraft | B77: =IFERROR(__xludf.DUMMYFUNCTION("""COMPUTED_VALUE"""),"Xbox / PC") -> Xbox / PC | C77: =IFERROR(__xludf.DUMMYFUNCTION("""COMPUTED_VALUE"""),"Yes") -> Yes | D77: =IFERROR(__xludf.DUMMYFUNCTION("""COMPUTED_VALUE"""),"Active") -> Active | E77: =IFERROR(__xludf.DUMMYFUNCTION("""COMPUTED_VALUE"""),45916.0) -> 45916 | G77: =IFERROR(__xludf.DUMMYFUNCTION("""COMPUTED_VALUE"""),12.666666666666668) -> 12.666667 | H77: =IFERROR(__xludf.DUMMYFUNCTION("""COMPUTED_VALUE"""),45797.0) -> 45797 | I77: =IFERROR(__xludf.DUMMYFUNCTION("""COMPUTED_VALUE"""),0.32222222222222224) -> 0.32222222 | J77: =IFERROR(__xludf.DUMMYFUNCTION("""COMPUTED_VALUE"""),77.0) -> 77 | K77: =IFERROR(__xludf.DUMMYFUNCTION("""COMPUTED_VALUE"""),51.0) -> 51 | L77: =IFERROR(__xludf.DUMMYFUNCTION("""COMPUTED_VALUE"""),"Racing") -> Racing | M77: =IFERROR(__xludf.DUMMYFUNCTION("""COMPUTED_VALUE"""),"Exclusive") -> Exclusive | N77: =IFERROR(__xludf.DUMMYFUNCTION("""COMPUTED_VALUE"""),"Joined PC 1/21/26") -> Joined PC 1/21/26
A78: =IFERROR(__xludf.DUMMYFUNCTION("""COMPUTED_VALUE"""),"Mechwarrior 5: Clans") -> Mechwarrior 5: Clans | B78: =IFERROR(__xludf.DUMMYFUNCTION("""COMPUTED_VALUE"""),"Xbox / PC") -> Xbox / PC | C78: =IFERROR(__xludf.DUMMYFUNCTION("""COMPUTED_VALUE"""),"Yes") -> Yes | D78: =IFERROR(__xludf.DUMMYFUNCTION("""COMPUTED_VALUE"""),"Active") -> Active | E78: =IFERROR(__xludf.DUMMYFUNCTION("""COMPUTED_VALUE"""),45582.0) -> 45582 | G78: =IFERROR(__xludf.DUMMYFUNCTION("""COMPUTED_VALUE"""),23.633333333333333) -> 23.633333 | H78: =IFERROR(__xludf.DUMMYFUNCTION("""COMPUTED_VALUE"""),45582.0) -> 45582 | I78: =IFERROR(__xludf.DUMMYFUNCTION("""COMPUTED_VALUE"""),0.0) -> 0 | J78: =IFERROR(__xludf.DUMMYFUNCTION("""COMPUTED_VALUE"""),79.0) -> 79 | K78: =IFERROR(__xludf.DUMMYFUNCTION("""COMPUTED_VALUE"""),23.0) -> 23 | L78: =IFERROR(__xludf.DUMMYFUNCTION("""COMPUTED_VALUE"""),"Simulation") -> Simulation | M78: =IFERROR(__xludf.DUMMYFUNCTION("""COMPUTED_VALUE"""),"Exclusive") -> Exclusive
A79: =IFERROR(__xludf.DUMMYFUNCTION("""COMPUTED_VALUE"""),"South Park: The Fractured but Whole") -> South Park: The Fractured but Whole | B79: =IFERROR(__xludf.DUMMYFUNCTION("""COMPUTED_VALUE"""),"Xbox / PC") -> Xbox / PC | C79: =IFERROR(__xludf.DUMMYFUNCTION("""COMPUTED_VALUE"""),"Yes") -> Yes | D79: =IFERROR(__xludf.DUMMYFUNCTION("""COMPUTED_VALUE"""),"Active") -> Active | E79: =IFERROR(__xludf.DUMMYFUNCTION("""COMPUTED_VALUE"""),45581.0) -> 45581 | G79: =IFERROR(__xludf.DUMMYFUNCTION("""COMPUTED_VALUE"""),23.666666666666668) -> 23.666667 | H79: =IFERROR(__xludf.DUMMYFUNCTION("""COMPUTED_VALUE"""),43312.0) -> 43312 | I79: =IFERROR(__xludf.DUMMYFUNCTION("""COMPUTED_VALUE"""),6.211111111111111) -> 6.2111111 | J79: =IFERROR(__xludf.DUMMYFUNCTION("""COMPUTED_VALUE"""),75.0) -> 75 | K79: =IFERROR(__xludf.DUMMYFUNCTION("""COMPUTED_VALUE"""),18.0) -> 18 | L79: =IFERROR(__xludf.DUMMYFUNCTION("""COMPUTED_VALUE"""),"RPG") -> RPG
A80: =IFERROR(__xludf.DUMMYFUNCTION("""COMPUTED_VALUE"""),"Inscryption") -> Inscryption | B80: =IFERROR(__xludf.DUMMYFUNCTION("""COMPUTED_VALUE"""),"Xbox / PC") -> Xbox / PC | C80: =IFERROR(__xludf.DUMMYFUNCTION("""COMPUTED_VALUE"""),"Yes") -> Yes | D80: =IFERROR(__xludf.DUMMYFUNCTION("""COMPUTED_VALUE"""),"Active") -> Active | E80: =IFERROR(__xludf.DUMMYFUNCTION("""COMPUTED_VALUE"""),45575.0) -> 45575 | G80: =IFERROR(__xludf.DUMMYFUNCTION("""COMPUTED_VALUE"""),23.866666666666667) -> 23.866667 | H80: =IFERROR(__xludf.DUMMYFUNCTION("""COMPUTED_VALUE"""),44488.0) -> 44488 | I80: =IFERROR(__xludf.DUMMYFUNCTION("""COMPUTED_VALUE"""),2.975) -> 2.975 | J80: =IFERROR(__xludf.DUMMYFUNCTION("""COMPUTED_VALUE"""),85.0) -> 85 | K80: =IFERROR(__xludf.DUMMYFUNCTION("""COMPUTED_VALUE"""),13.0) -> 13 | L80: =IFERROR(__xludf.DUMMYFUNCTION("""COMPUTED_VALUE"""),"Card Battle") -> Card Battle
A81: =IFERROR(__xludf.DUMMYFUNCTION("""COMPUTED_VALUE"""),"Legend of Mana (2021)") -> Legend of Mana (2021) | B81: =IFERROR(__xludf.DUMMYFUNCTION("""COMPUTED_VALUE"""),"Xbox / PC") -> Xbox / PC | C81: =IFERROR(__xludf.DUMMYFUNCTION("""COMPUTED_VALUE"""),"Yes") -> Yes | D81: =IFERROR(__xludf.DUMMYFUNCTION("""COMPUTED_VALUE"""),"Active") -> Active | E81: =IFERROR(__xludf.DUMMYFUNCTION("""COMPUTED_VALUE"""),45561.0) -> 45561 | G81: =IFERROR(__xludf.DUMMYFUNCTION("""COMPUTED_VALUE"""),24.333333333333332) -> 24.333333 | H81: =IFERROR(__xludf.DUMMYFUNCTION("""COMPUTED_VALUE"""),44371.0) -> 44371 | I81: =IFERROR(__xludf.DUMMYFUNCTION("""COMPUTED_VALUE"""),3.2555555555555555) -> 3.2555556 | J81: =IFERROR(__xludf.DUMMYFUNCTION("""COMPUTED_VALUE"""),72.0) -> 72 | K81: =IFERROR(__xludf.DUMMYFUNCTION("""COMPUTED_VALUE"""),18.0) -> 18 | L81: =IFERROR(__xludf.DUMMYFUNCTION("""COMPUTED_VALUE"""),"RPG") -> RPG
A82: =IFERROR(__xludf.DUMMYFUNCTION("""COMPUTED_VALUE"""),"Trials of Mana (2020)") -> Trials of Mana (2020) | B82: =IFERROR(__xludf.DUMMYFUNCTION("""COMPUTED_VALUE"""),"Xbox / PC") -> Xbox / PC | C82: =IFERROR(__xludf.DUMMYFUNCTION("""COMPUTED_VALUE"""),"Yes") -> Yes | D82: =IFERROR(__xludf.DUMMYFUNCTION("""COMPUTED_VALUE"""),"Active") -> Active | E82: =IFERROR(__xludf.DUMMYFUNCTION("""COMPUTED_VALUE"""),45561.0) -> 45561 | G82: =IFERROR(__xludf.DUMMYFUNCTION("""COMPUTED_VALUE"""),24.333333333333332) -> 24.333333 | H82: =IFERROR(__xludf.DUMMYFUNCTION("""COMPUTED_VALUE"""),43945.0) -> 43945 | I82: =IFERROR(__xludf.DUMMYFUNCTION("""COMPUTED_VALUE"""),4.4222222222222225) -> 4.4222222 | J82: =IFERROR(__xludf.DUMMYFUNCTION("""COMPUTED_VALUE"""),76.0) -> 76 | K82: =IFERROR(__xludf.DUMMYFUNCTION("""COMPUTED_VALUE"""),21.0) -> 21 | L82: =IFERROR(__xludf.DUMMYFUNCTION("""COMPUTED_VALUE"""),"RPG") -> RPG
A83: =IFERROR(__xludf.DUMMYFUNCTION("""COMPUTED_VALUE"""),"Ara: History Untold") -> Ara: History Untold | B83: =IFERROR(__xludf.DUMMYFUNCTION("""COMPUTED_VALUE"""),"PC") -> PC | D83: =IFERROR(__xludf.DUMMYFUNCTION("""COMPUTED_VALUE"""),"Active") -> Active | E83: =IFERROR(__xludf.DUMMYFUNCTION("""COMPUTED_VALUE"""),45559.0) -> 45559 | G83: =IFERROR(__xludf.DUMMYFUNCTION("""COMPUTED_VALUE"""),24.4) -> 24.4 | H83: =IFERROR(__xludf.DUMMYFUNCTION("""COMPUTED_VALUE"""),45559.0) -> 45559 | I83: =IFERROR(__xludf.DUMMYFUNCTION("""COMPUTED_VALUE"""),0.0) -> 0 | J83: =IFERROR(__xludf.DUMMYFUNCTION("""COMPUTED_VALUE"""),76.0) -> 76 | K83: =IFERROR(__xludf.DUMMYFUNCTION("""COMPUTED_VALUE"""),13.0) -> 13 | L83: =IFERROR(__xludf.DUMMYFUNCTION("""COMPUTED_VALUE"""),"Strategy") -> Strategy
A84: =IFERROR(__xludf.DUMMYFUNCTION("""COMPUTED_VALUE"""),"Riders Republic") -> Riders Republic | B84: =IFERROR(__xludf.DUMMYFUNCTION("""COMPUTED_VALUE"""),"Xbox / PC") -> Xbox / PC | C84: =IFERROR(__xludf.DUMMYFUNCTION("""COMPUTED_VALUE"""),"Yes") -> Yes | D84: =IFERROR(__xludf.DUMMYFUNCTION("""COMPUTED_VALUE"""),"Active") -> Active | E84: =IFERROR(__xludf.DUMMYFUNCTION("""COMPUTED_VALUE"""),45546.0) -> 45546 | G84: =IFERROR(__xludf.DUMMYFUNCTION("""COMPUTED_VALUE"""),24.833333333333336) -> 24.833333 | H84: =IFERROR(__xludf.DUMMYFUNCTION("""COMPUTED_VALUE"""),44497.0) -> 44497 | I84: =IFERROR(__xludf.DUMMYFUNCTION("""COMPUTED_VALUE"""),2.8694444444444445) -> 2.8694444 | J84: =IFERROR(__xludf.DUMMYFUNCTION("""COMPUTED_VALUE"""),77.0) -> 77 | K84: =IFERROR(__xludf.DUMMYFUNCTION("""COMPUTED_VALUE"""),18.0) -> 18 | L84: =IFERROR(__xludf.DUMMYFUNCTION("""COMPUTED_VALUE"""),"Sports") -> Sports
A85: =IFERROR(__xludf.DUMMYFUNCTION("""COMPUTED_VALUE"""),"Wartales") -> Wartales | B85: =IFERROR(__xludf.DUMMYFUNCTION("""COMPUTED_VALUE"""),"Xbox / PC") -> Xbox / PC | C85: =IFERROR(__xludf.DUMMYFUNCTION("""COMPUTED_VALUE"""),"Yes") -> Yes | D85: =IFERROR(__xludf.DUMMYFUNCTION("""COMPUTED_VALUE"""),"Active") -> Active | E85: =IFERROR(__xludf.DUMMYFUNCTION("""COMPUTED_VALUE"""),45230.0) -> 45230 | G85: =IFERROR(__xludf.DUMMYFUNCTION("""COMPUTED_VALUE"""),35.199999999999996) -> 35.2 | H85: =IFERROR(__xludf.DUMMYFUNCTION("""COMPUTED_VALUE"""),44531.0) -> 44531 | I85: =IFERROR(__xludf.DUMMYFUNCTION("""COMPUTED_VALUE"""),1.913888888888889) -> 1.9138889 | J85: =IFERROR(__xludf.DUMMYFUNCTION("""COMPUTED_VALUE"""),80.0) -> 80 | K85: =IFERROR(__xludf.DUMMYFUNCTION("""COMPUTED_VALUE"""),38.0) -> 38 | L85: =IFERROR(__xludf.DUMMYFUNCTION("""COMPUTED_VALUE"""),"RPG") -> RPG | N85: =IFERROR(__xludf.DUMMYFUNCTION("""COMPUTED_VALUE"""),"Joined xbox one ine June 2024") -> Joined xbox one ine June 2024
A86: =IFERROR(__xludf.DUMMYFUNCTION("""COMPUTED_VALUE"""),"Cities: Skylines II") -> Cities: Skylines II | B86: =IFERROR(__xludf.DUMMYFUNCTION("""COMPUTED_VALUE"""),"PC") -> PC | D86: =IFERROR(__xludf.DUMMYFUNCTION("""COMPUTED_VALUE"""),"Active") -> Active | E86: =IFERROR(__xludf.DUMMYFUNCTION("""COMPUTED_VALUE"""),45223.0) -> 45223 | G86: =IFERROR(__xludf.DUMMYFUNCTION("""COMPUTED_VALUE"""),35.400000000000006) -> 35.4 | H86: =IFERROR(__xludf.DUMMYFUNCTION("""COMPUTED_VALUE"""),45223.0) -> 45223 | I86: =IFERROR(__xludf.DUMMYFUNCTION("""COMPUTED_VALUE"""),0.0) -> 0 | J86: =IFERROR(__xludf.DUMMYFUNCTION("""COMPUTED_VALUE"""),75.0) -> 75 | K86: =IFERROR(__xludf.DUMMYFUNCTION("""COMPUTED_VALUE"""),25.0) -> 25 | L86: =IFERROR(__xludf.DUMMYFUNCTION("""COMPUTED_VALUE"""),"Simulation") -> Simulation | O86: =IFERROR(__xludf.DUMMYFUNCTION("""COMPUTED_VALUE"""),"RP") -> RP
A87: =IFERROR(__xludf.DUMMYFUNCTION("""COMPUTED_VALUE"""),"Chivalry II") -> Chivalry II | B87: =IFERROR(__xludf.DUMMYFUNCTION("""COMPUTED_VALUE"""),"Xbox / PC") -> Xbox / PC | C87: =IFERROR(__xludf.DUMMYFUNCTION("""COMPUTED_VALUE"""),"Yes") -> Yes | D87: =IFERROR(__xludf.DUMMYFUNCTION("""COMPUTED_VALUE"""),"Active") -> Active | E87: =IFERROR(__xludf.DUMMYFUNCTION("""COMPUTED_VALUE"""),44838.0) -> 44838 | G87: =IFERROR(__xludf.DUMMYFUNCTION("""COMPUTED_VALUE"""),48.06666666666666) -> 48.066667 | H87: =IFERROR(__xludf.DUMMYFUNCTION("""COMPUTED_VALUE"""),44355.0) -> 44355 | I87: =IFERROR(__xludf.DUMMYFUNCTION("""COMPUTED_VALUE"""),1.3222222222222222) -> 1.3222222 | J87: =IFERROR(__xludf.DUMMYFUNCTION("""COMPUTED_VALUE"""),82.0) -> 82 | K87: =IFERROR(__xludf.DUMMYFUNCTION("""COMPUTED_VALUE"""),42.5) -> 42.5 | L87: =IFERROR(__xludf.DUMMYFUNCTION("""COMPUTED_VALUE"""),"Action") -> Action | N87: =IFERROR(__xludf.DUMMYFUNCTION("""COMPUTED_VALUE"""),"Game Pass Essential (12/6/23)") -> Game Pass Essential (12/6/23) | O87: =IFERROR(__xludf.DUMMYFUNCTION("""COMPUTED_VALUE"""),"M") -> M | P87: =IFERROR(__xludf.DUMMYFUNCTION("""COMPUTED_VALUE"""),"Use of Alcohol, Blood and Gore, Mild Sexual Themes, Language, Intense Violence") -> Use of Alcohol, Blood and Gore, Mild Sexual Themes, Language, Intense Violence
A88: =IFERROR(__xludf.DUMMYFUNCTION("""COMPUTED_VALUE"""),"Assassin's Creed Odyssey") -> Assassin's Creed Odyssey | B88: =IFERROR(__xludf.DUMMYFUNCTION("""COMPUTED_VALUE"""),"Xbox / PC") -> Xbox / PC | C88: =IFERROR(__xludf.DUMMYFUNCTION("""COMPUTED_VALUE"""),"Touch Controls") -> Touch Controls | D88: =IFERROR(__xludf.DUMMYFUNCTION("""COMPUTED_VALUE"""),"Active") -> Active | E88: =IFERROR(__xludf.DUMMYFUNCTION("""COMPUTED_VALUE"""),44819.0) -> 44819 | G88: =IFERROR(__xludf.DUMMYFUNCTION("""COMPUTED_VALUE"""),48.7) -> 48.7 | H88: =IFERROR(__xludf.DUMMYFUNCTION("""COMPUTED_VALUE"""),43375.0) -> 43375 | I88: =IFERROR(__xludf.DUMMYFUNCTION("""COMPUTED_VALUE"""),3.952777777777778) -> 3.9527778 | J88: =IFERROR(__xludf.DUMMYFUNCTION("""COMPUTED_VALUE"""),87.0) -> 87 | K88: =IFERROR(__xludf.DUMMYFUNCTION("""COMPUTED_VALUE"""),44.5) -> 44.5 | L88: =IFERROR(__xludf.DUMMYFUNCTION("""COMPUTED_VALUE"""),"RPG") -> RPG | N88: =IFERROR(__xludf.DUMMYFUNCTION("""COMPUTED_VALUE"""),"Ubisoft Connect launcher") -> Ubisoft Connect launcher | O88: =IFERROR(__xludf.DUMMYFUNCTION("""COMPUTED_VALUE"""),"M") -> M | P88: =IFERROR(__xludf.DUMMYFUNCTION("""COMPUTED_VALUE"""),"Blood and Gore, Sexual Themes, Strong Language, Intense Violence") -> Blood and Gore, Sexual Themes, Strong Language, Intense Violence
A89: =IFERROR(__xludf.DUMMYFUNCTION("""COMPUTED_VALUE"""),"Ni no Kuni: Wrath of the White Witch - Remastered") -> Ni no Kuni: Wrath of the White Witch - Remastered | B89: =IFERROR(__xludf.DUMMYFUNCTION("""COMPUTED_VALUE"""),"Xbox / PC") -> Xbox / PC | C89: =IFERROR(__xludf.DUMMYFUNCTION("""COMPUTED_VALUE"""),"Touch Controls") -> Touch Controls | D89: =IFERROR(__xludf.DUMMYFUNCTION("""COMPUTED_VALUE"""),"Active") -> Active | E89: =IFERROR(__xludf.DUMMYFUNCTION("""COMPUTED_VALUE"""),44819.0) -> 44819 | G89: =IFERROR(__xludf.DUMMYFUNCTION("""COMPUTED_VALUE"""),48.7) -> 48.7 | H89: =IFERROR(__xludf.DUMMYFUNCTION("""COMPUTED_VALUE"""),43728.0) -> 43728 | I89: =IFERROR(__xludf.DUMMYFUNCTION("""COMPUTED_VALUE"""),2.986111111111111) -> 2.9861111 | J89: =IFERROR(__xludf.DUMMYFUNCTION("""COMPUTED_VALUE"""),82.0) -> 82 | K89: =IFERROR(__xludf.DUMMYFUNCTION("""COMPUTED_VALUE"""),44.5) -> 44.5 | L89: =IFERROR(__xludf.DUMMYFUNCTION("""COMPUTED_VALUE"""),"RPG") -> RPG | O89: =IFERROR(__xludf.DUMMYFUNCTION("""COMPUTED_VALUE"""),"E10+") -> E10+ | P89: =IFERROR(__xludf.DUMMYFUNCTION("""COMPUTED_VALUE"""),"Fantasy Violence, Mild Language, Simulated Gambling, Alcohol and Tobacco Reference") -> Fantasy Violence, Mild Language, Simulated Gambling, Alcohol and Tobacco Reference
A90: =IFERROR(__xludf.DUMMYFUNCTION("""COMPUTED_VALUE"""),"Deep Rock Galactic") -> Deep Rock Galactic | B90: =IFERROR(__xludf.DUMMYFUNCTION("""COMPUTED_VALUE"""),"Xbox / PC") -> Xbox / PC | C90: =IFERROR(__xludf.DUMMYFUNCTION("""COMPUTED_VALUE"""),"M+KB") -> M+KB | D90: =IFERROR(__xludf.DUMMYFUNCTION("""COMPUTED_VALUE"""),"Active") -> Active | E90: =IFERROR(__xludf.DUMMYFUNCTION("""COMPUTED_VALUE"""),44140.0) -> 44140 | G90: =IFERROR(__xludf.DUMMYFUNCTION("""COMPUTED_VALUE"""),71.03333333333333) -> 71.033333 | H90: =IFERROR(__xludf.DUMMYFUNCTION("""COMPUTED_VALUE"""),43964.0) -> 43964 | I90: =IFERROR(__xludf.DUMMYFUNCTION("""COMPUTED_VALUE"""),0.4777777777777778) -> 0.47777778 | J90: =IFERROR(__xludf.DUMMYFUNCTION("""COMPUTED_VALUE"""),84.0) -> 84 | K90: =IFERROR(__xludf.DUMMYFUNCTION("""COMPUTED_VALUE"""),119.0) -> 119 | L90: =IFERROR(__xludf.DUMMYFUNCTION("""COMPUTED_VALUE"""),"Shooter") -> Shooter | N90: =IFERROR(__xludf.DUMMYFUNCTION("""COMPUTED_VALUE"""),"Game Pass Essential (4/23/24)") -> Game Pass Essential (4/23/24) | O90: =IFERROR(__xludf.DUMMYFUNCTION("""COMPUTED_VALUE"""),"T") -> T
A91: =IFERROR(__xludf.DUMMYFUNCTION("""COMPUTED_VALUE"""),"Tom Clancy's Rainbow Six: Siege - Deluxe Edition") -> Tom Clancy's Rainbow Six: Siege - Deluxe Edition | B91: =IFERROR(__xludf.DUMMYFUNCTION("""COMPUTED_VALUE"""),"Xbox / PC") -> Xbox / PC | C91: =IFERROR(__xludf.DUMMYFUNCTION("""COMPUTED_VALUE"""),"Yes") -> Yes | D91: =IFERROR(__xludf.DUMMYFUNCTION("""COMPUTED_VALUE"""),"Active") -> Active | E91: =IFERROR(__xludf.DUMMYFUNCTION("""COMPUTED_VALUE"""),44126.0) -> 44126 | G91: =IFERROR(__xludf.DUMMYFUNCTION("""COMPUTED_VALUE"""),71.46666666666667) -> 71.466667 | H91: =IFERROR(__xludf.DUMMYFUNCTION("""COMPUTED_VALUE"""),42339.0) -> 42339 | I91: =IFERROR(__xludf.DUMMYFUNCTION("""COMPUTED_VALUE"""),4.891666666666667) -> 4.8916667 | J91: =IFERROR(__xludf.DUMMYFUNCTION("""COMPUTED_VALUE"""),74.0) -> 74 | K91: =IFERROR(__xludf.DUMMYFUNCTION("""COMPUTED_VALUE"""),7.5) -> 7.5 | L91: =IFERROR(__xludf.DUMMYFUNCTION("""COMPUTED_VALUE"""),"Shooter") -> Shooter | M91: =IFERROR(__xludf.DUMMYFUNCTION("""COMPUTED_VALUE"""),"Optimized") -> Optimized | N91: =IFERROR(__xludf.DUMMYFUNCTION("""COMPUTED_VALUE"""),"Ubisoft Connect launcher, joined PC 1/20/21") -> Ubisoft Connect launcher, joined PC 1/20/21 | O91: =IFERROR(__xludf.DUMMYFUNCTION("""COMPUTED_VALUE"""),"M") -> M | P91: =IFERROR(__xludf.DUMMYFUNCTION("""COMPUTED_VALUE"""),"Blood, Drug Reference, Strong Language, Violence") -> Blood, Drug Reference, Strong Language, Violence

Sheet Tiers
A1: Game | B1: System | C1: xCloud | D1: Status | E1: Added | F1: Removed | G1: Months | H1: Release | I1: Age | J1: Metacritic | K1: Completion | L1: Genre (Giantbomb) | M1: PC | N1: Premium | O1: Essential
A2: =IFERROR(__xludf.DUMMYFUNCTION("SORT(FILTER('Master List'!A2:L1071, REGEXMATCH('Master List'!B2:B1071, ""Xbox""), NOT(REGEXMATCH('Master List'!D2:D1071, ""Removed"")) ), 10, false)"),"NHL 94 Rewind") -> NHL 94 Rewind | B2: =IFERROR(__xludf.DUMMYFUNCTION("""COMPUTED_VALUE"""),"Xbox") -> Xbox | D2: =IFERROR(__xludf.DUMMYFUNCTION("""COMPUTED_VALUE"""),"Active") -> Active | E2: =IFERROR(__xludf.DUMMYFUNCTION("""COMPUTED_VALUE"""),44168.0) -> 44168 | G2: =IFERROR(__xludf.DUMMYFUNCTION("""COMPUTED_VALUE"""),70.1) -> 70.1 | H2: =IFERROR(__xludf.DUMMYFUNCTION("""COMPUTED_VALUE"""),44134.0) -> 44134 | I2: =IFERROR(__xludf.DUMMYFUNCTION("""COMPUTED_VALUE"""),0.09166666666666666) -> 0.091666667 | J2: =IFERROR(__xludf.DUMMYFUNCTION("""COMPUTED_VALUE"""),100.0) -> 100 | K2: =IFERROR(__xludf.DUMMYFUNCTION("""COMPUTED_VALUE"""),14.5) -> 14.5 | L2: =IFERROR(__xludf.DUMMYFUNCTION("""COMPUTED_VALUE"""),"Sports") -> Sports | M2: =NOT(ISNA(VLOOKUP(A2,PC!A:A,1,FALSE))) -> FALSE | N2: =NOT(ISNA(VLOOKUP(A2,'Game Pass Premium'!A:A,1,FALSE))) -> TRUE | O2: =NOT(ISNA(VLOOKUP(A2,'Game Pass Essential'!A:A,1,FALSE))) -> FALSE
A3: =IFERROR(__xludf.DUMMYFUNCTION("""COMPUTED_VALUE"""),"GoldenEye 007 (2023)") -> GoldenEye 007 (2023) | B3: =IFERROR(__xludf.DUMMYFUNCTION("""COMPUTED_VALUE"""),"Xbox") -> Xbox | C3: =IFERROR(__xludf.DUMMYFUNCTION("""COMPUTED_VALUE"""),"Yes") -> Yes | D3: =IFERROR(__xludf.DUMMYFUNCTION("""COMPUTED_VALUE"""),"Active") -> Active | E3: =IFERROR(__xludf.DUMMYFUNCTION("""COMPUTED_VALUE"""),44953.0) -> 44953 | G3: =IFERROR(__xludf.DUMMYFUNCTION("""COMPUTED_VALUE"""),44.300000000000004) -> 44.3 | H3: =IFERROR(__xludf.DUMMYFUNCTION("""COMPUTED_VALUE"""),44953.0) -> 44953 | I3: =IFERROR(__xludf.DUMMYFUNCTION("""COMPUTED_VALUE"""),0.0) -> 0 | J3: =IFERROR(__xludf.DUMMYFUNCTION("""COMPUTED_VALUE"""),96.0) -> 96 | K3: =IFERROR(__xludf.DUMMYFUNCTION("""COMPUTED_VALUE"""),10.0) -> 10 | L3: =IFERROR(__xludf.DUMMYFUNCTION("""COMPUTED_VALUE"""),"Shooter") -> Shooter | M3: =NOT(ISNA(VLOOKUP(A3,PC!A:A,1,FALSE))) -> FALSE | N3: =NOT(ISNA(VLOOKUP(A3,'Game Pass Premium'!A:A,1,FALSE))) -> TRUE | O3: =NOT(ISNA(VLOOKUP(A3,'Game Pass Essential'!A:A,1,FALSE))) -> FALSE
A4: =IFERROR(__xludf.DUMMYFUNCTION("""COMPUTED_VALUE"""),"Mass Effect 2: Digital Deluxe Edition") -> Mass Effect 2: Digital Deluxe Edition | B4: =IFERROR(__xludf.DUMMYFUNCTION("""COMPUTED_VALUE"""),"Xbox / PC") -> Xbox / PC | D4: =IFERROR(__xludf.DUMMYFUNCTION("""COMPUTED_VALUE"""),"Active") -> Active | E4: =IFERROR(__xludf.DUMMYFUNCTION("""COMPUTED_VALUE"""),44145.0) -> 44145 | G4: =IFERROR(__xludf.DUMMYFUNCTION("""COMPUTED_VALUE"""),70.86666666666667) -> 70.866667 | H4: =IFERROR(__xludf.DUMMYFUNCTION("""COMPUTED_VALUE"""),40204.0) -> 40204 | I4: =IFERROR(__xludf.DUMMYFUNCTION("""COMPUTED_VALUE"""),10.78888888888889) -> 10.788889 | J4: =IFERROR(__xludf.DUMMYFUNCTION("""COMPUTED_VALUE"""),96.0) -> 96 | K4: =IFERROR(__xludf.DUMMYFUNCTION("""COMPUTED_VALUE"""),24.5) -> 24.5 | L4: =IFERROR(__xludf.DUMMYFUNCTION("""COMPUTED_VALUE"""),"RPG") -> RPG | M4: =NOT(ISNA(VLOOKUP(A4,PC!A:A,1,FALSE))) -> TRUE | N4: =NOT(ISNA(VLOOKUP(A4,'Game Pass Premium'!A:A,1,FALSE))) -> TRUE | O4: =NOT(ISNA(VLOOKUP(A4,'Game Pass Essential'!A:A,1,FALSE))) -> FALSE
A5: =IFERROR(__xludf.DUMMYFUNCTION("""COMPUTED_VALUE"""),"Persona 5 Royal") -> Persona 5 Royal | B5: =IFERROR(__xludf.DUMMYFUNCTION("""COMPUTED_VALUE"""),"Xbox / PC") -> Xbox / PC | C5: =IFERROR(__xludf.DUMMYFUNCTION("""COMPUTED_VALUE"""),"Touch Controls") -> Touch Controls | D5: =IFERROR(__xludf.DUMMYFUNCTION("""COMPUTED_VALUE"""),"Active") -> Active | E5: =IFERROR(__xludf.DUMMYFUNCTION("""COMPUTED_VALUE"""),46182.0) -> 46182 | G5: =IFERROR(__xludf.DUMMYFUNCTION("""COMPUTED_VALUE"""),3.9000000000000004) -> 3.9 | H5: =IFERROR(__xludf.DUMMYFUNCTION("""COMPUTED_VALUE"""),43921.0) -> 43921 | I5: =IFERROR(__xludf.DUMMYFUNCTION("""COMPUTED_VALUE"""),6.191666666666666) -> 6.1916667 | J5: =IFERROR(__xludf.DUMMYFUNCTION("""COMPUTED_VALUE"""),95.0) -> 95 | K5: =IFERROR(__xludf.DUMMYFUNCTION("""COMPUTED_VALUE"""),101.0) -> 101 | L5: =IFERROR(__xludf.DUMMYFUNCTION("""COMPUTED_VALUE"""),"RPG") -> RPG | M5: =NOT(ISNA(VLOOKUP(A5,PC!A:A,1,FALSE))) -> TRUE | N5: =NOT(ISNA(VLOOKUP(A5,'Game Pass Premium'!A:A,1,FALSE))) -> TRUE | O5: =NOT(ISNA(VLOOKUP(A5,'Game Pass Essential'!A:A,1,FALSE))) -> FALSE
A6: =IFERROR(__xludf.DUMMYFUNCTION("""COMPUTED_VALUE"""),"Hades II") -> Hades II | B6: =IFERROR(__xludf.DUMMYFUNCTION("""COMPUTED_VALUE"""),"Xbox / PC") -> Xbox / PC | C6: =IFERROR(__xludf.DUMMYFUNCTION("""COMPUTED_VALUE"""),"Yes") -> Yes | D6: =IFERROR(__xludf.DUMMYFUNCTION("""COMPUTED_VALUE"""),"Active") -> Active | E6: =IFERROR(__xludf.DUMMYFUNCTION("""COMPUTED_VALUE"""),46126.0) -> 46126 | G6: =IFERROR(__xludf.DUMMYFUNCTION("""COMPUTED_VALUE"""),5.733333333333333) -> 5.7333333 | H6: =IFERROR(__xludf.DUMMYFUNCTION("""COMPUTED_VALUE"""),45925.0) -> 45925 | I6: =IFERROR(__xludf.DUMMYFUNCTION("""COMPUTED_VALUE"""),0.5527777777777778) -> 0.55277778 | J6: =IFERROR(__xludf.DUMMYFUNCTION("""COMPUTED_VALUE"""),95.0) -> 95 | K6: =IFERROR(__xludf.DUMMYFUNCTION("""COMPUTED_VALUE"""),22.0) -> 22 | L6: =IFERROR(__xludf.DUMMYFUNCTION("""COMPUTED_VALUE"""),"RPG") -> RPG | M6: =NOT(ISNA(VLOOKUP(A6,PC!A:A,1,FALSE))) -> TRUE | N6: =NOT(ISNA(VLOOKUP(A6,'Game Pass Premium'!A:A,1,FALSE))) -> TRUE | O6: =NOT(ISNA(VLOOKUP(A6,'Game Pass Essential'!A:A,1,FALSE))) -> FALSE
A7: =IFERROR(__xludf.DUMMYFUNCTION("""COMPUTED_VALUE"""),"Portal 2") -> Portal 2 | B7: =IFERROR(__xludf.DUMMYFUNCTION("""COMPUTED_VALUE"""),"XB360/OG Xbox") -> XB360/OG Xbox | D7: =IFERROR(__xludf.DUMMYFUNCTION("""COMPUTED_VALUE"""),"GwG Permanent") -> GwG Permanent | E7: =IFERROR(__xludf.DUMMYFUNCTION("""COMPUTED_VALUE"""),44819.0) -> 44819 | F7: =IFERROR(__xludf.DUMMYFUNCTION("""COMPUTED_VALUE"""),44834.0) -> 44834 | G7: =IFERROR(__xludf.DUMMYFUNCTION("""COMPUTED_VALUE"""),0.5) -> 0.5 | H7: =IFERROR(__xludf.DUMMYFUNCTION("""COMPUTED_VALUE"""),40652.0) -> 40652 | I7: =IFERROR(__xludf.DUMMYFUNCTION("""COMPUTED_VALUE"""),11.405555555555555) -> 11.405556 | J7: =IFERROR(__xludf.DUMMYFUNCTION("""COMPUTED_VALUE"""),95.0) -> 95 | K7: =IFERROR(__xludf.DUMMYFUNCTION("""COMPUTED_VALUE"""),9.0) -> 9 | L7: =IFERROR(__xludf.DUMMYFUNCTION("""COMPUTED_VALUE"""),"Puzzle") -> Puzzle | M7: =NOT(ISNA(VLOOKUP(A7,PC!A:A,1,FALSE))) -> FALSE | N7: =NOT(ISNA(VLOOKUP(A7,'Game Pass Premium'!A:A,1,FALSE))) -> FALSE | O7: =NOT(ISNA(VLOOKUP(A7,'Game Pass Essential'!A:A,1,FALSE))) -> FALSE
A8: =IFERROR(__xludf.DUMMYFUNCTION("""COMPUTED_VALUE"""),"Quake") -> Quake | B8: =IFERROR(__xludf.DUMMYFUNCTION("""COMPUTED_VALUE"""),"Xbox / PC") -> Xbox / PC | C8: =IFERROR(__xludf.DUMMYFUNCTION("""COMPUTED_VALUE"""),"M+KB") -> M+KB | D8: =IFERROR(__xludf.DUMMYFUNCTION("""COMPUTED_VALUE"""),"Active") -> Active | E8: =IFERROR(__xludf.DUMMYFUNCTION("""COMPUTED_VALUE"""),44427.0) -> 44427 | G8: =IFERROR(__xludf.DUMMYFUNCTION("""COMPUTED_VALUE"""),61.56666666666666) -> 61.566667 | H8: =IFERROR(__xludf.DUMMYFUNCTION("""COMPUTED_VALUE"""),35269.0) -> 35269 | I8: =IFERROR(__xludf.DUMMYFUNCTION("""COMPUTED_VALUE"""),25.072222222222223) -> 25.072222 | J8: =IFERROR(__xludf.DUMMYFUNCTION("""COMPUTED_VALUE"""),94.0) -> 94 | K8: =IFERROR(__xludf.DUMMYFUNCTION("""COMPUTED_VALUE"""),5.5) -> 5.5 | L8: =IFERROR(__xludf.DUMMYFUNCTION("""COMPUTED_VALUE"""),"Shooter") -> Shooter | M8: =NOT(ISNA(VLOOKUP(A8,PC!A:A,1,FALSE))) -> TRUE | N8: =NOT(ISNA(VLOOKUP(A8,'Game Pass Premium'!A:A,1,FALSE))) -> TRUE | O8: =NOT(ISNA(VLOOKUP(A8,'Game Pass Essential'!A:A,1,FALSE))) -> FALSE
A9: =IFERROR(__xludf.DUMMYFUNCTION("""COMPUTED_VALUE"""),"The Elder Scrolls IV: Oblivion") -> The Elder Scrolls IV: Oblivion | B9: =IFERROR(__xludf.DUMMYFUNCTION("""COMPUTED_VALUE"""),"Xbox / PC") -> Xbox / PC | C9: =IFERROR(__xludf.DUMMYFUNCTION("""COMPUTED_VALUE"""),"Yes") -> Yes | D9: =IFERROR(__xludf.DUMMYFUNCTION("""COMPUTED_VALUE"""),"Active") -> Active | E9: =IFERROR(__xludf.DUMMYFUNCTION("""COMPUTED_VALUE"""),43282.0) -> 43282 | G9: =IFERROR(__xludf.DUMMYFUNCTION("""COMPUTED_VALUE"""),99.16666666666667) -> 99.166667 | H9: =IFERROR(__xludf.DUMMYFUNCTION("""COMPUTED_VALUE"""),38796.0) -> 38796 | I9: =IFERROR(__xludf.DUMMYFUNCTION("""COMPUTED_VALUE"""),12.280555555555555) -> 12.280556 | J9: =IFERROR(__xludf.DUMMYFUNCTION("""COMPUTED_VALUE"""),94.0) -> 94 | K9: =IFERROR(__xludf.DUMMYFUNCTION("""COMPUTED_VALUE"""),27.5) -> 27.5 | L9: =IFERROR(__xludf.DUMMYFUNCTION("""COMPUTED_VALUE"""),"RPG") -> RPG | M9: =NOT(ISNA(VLOOKUP(A9,PC!A:A,1,FALSE))) -> TRUE | N9: =NOT(ISNA(VLOOKUP(A9,'Game Pass Premium'!A:A,1,FALSE))) -> TRUE | O9: =NOT(ISNA(VLOOKUP(A9,'Game Pass Essential'!A:A,1,FALSE))) -> FALSE
A10: =IFERROR(__xludf.DUMMYFUNCTION("""COMPUTED_VALUE"""),"Gears of War") -> Gears of War | B10: =IFERROR(__xludf.DUMMYFUNCTION("""COMPUTED_VALUE"""),"Xbox") -> Xbox | D10: =IFERROR(__xludf.DUMMYFUNCTION("""COMPUTED_VALUE"""),"Active") -> Active | E10: =IFERROR(__xludf.DUMMYFUNCTION("""COMPUTED_VALUE"""),42887.0) -> 42887 | G10: =IFERROR(__xludf.DUMMYFUNCTION("""COMPUTED_VALUE"""),112.16666666666666) -> 112.16667 | H10: =IFERROR(__xludf.DUMMYFUNCTION("""COMPUTED_VALUE"""),39028.0) -> 39028 | I10: =IFERROR(__xludf.DUMMYFUNCTION("""COMPUTED_VALUE"""),10.566666666666666) -> 10.566667 | J10: =IFERROR(__xludf.DUMMYFUNCTION("""COMPUTED_VALUE"""),94.0) -> 94 | K10: =IFERROR(__xludf.DUMMYFUNCTION("""COMPUTED_VALUE"""),9.0) -> 9 | L10: =IFERROR(__xludf.DUMMYFUNCTION("""COMPUTED_VALUE"""),"Shooter") -> Shooter | M10: =NOT(ISNA(VLOOKUP(A10,PC!A:A,1,FALSE))) -> FALSE | N10: =NOT(ISNA(VLOOKUP(A10,'Game Pass Premium'!A:A,1,FALSE))) -> TRUE | O10: =NOT(ISNA(VLOOKUP(A10,'Game Pass Essential'!A:A,1,FALSE))) -> FALSE
A11: =IFERROR(__xludf.DUMMYFUNCTION("""COMPUTED_VALUE"""),"Battlefield 3") -> Battlefield 3 | B11: =IFERROR(__xludf.DUMMYFUNCTION("""COMPUTED_VALUE"""),"XB360/OG Xbox") -> XB360/OG Xbox | D11: =IFERROR(__xludf.DUMMYFUNCTION("""COMPUTED_VALUE"""),"GwG Permanent") -> GwG Permanent | E11: =IFERROR(__xludf.DUMMYFUNCTION("""COMPUTED_VALUE"""),42994.0) -> 42994 | F11: =IFERROR(__xludf.DUMMYFUNCTION("""COMPUTED_VALUE"""),43008.0) -> 43008 | G11: =IFERROR(__xludf.DUMMYFUNCTION("""COMPUTED_VALUE"""),0.4666666666666667) -> 0.46666667 | H11: =IFERROR(__xludf.DUMMYFUNCTION("""COMPUTED_VALUE"""),40841.0) -> 40841 | I11: =IFERROR(__xludf.DUMMYFUNCTION("""COMPUTED_VALUE"""),5.891666666666667) -> 5.8916667 | J11: =IFERROR(__xludf.DUMMYFUNCTION("""COMPUTED_VALUE"""),94.0) -> 94 | K11: =IFERROR(__xludf.DUMMYFUNCTION("""COMPUTED_VALUE"""),7.0) -> 7 | L11: =IFERROR(__xludf.DUMMYFUNCTION("""COMPUTED_VALUE"""),"Shooter") -> Shooter | M11: =NOT(ISNA(VLOOKUP(A11,PC!A:A,1,FALSE))) -> FALSE | N11: =NOT(ISNA(VLOOKUP(A11,'Game Pass Premium'!A:A,1,FALSE))) -> FALSE | O11: =NOT(ISNA(VLOOKUP(A11,'Game Pass Essential'!A:A,1,FALSE))) -> FALSE
A12: =IFERROR(__xludf.DUMMYFUNCTION("""COMPUTED_VALUE"""),"BioShock Infinite") -> BioShock Infinite | B12: =IFERROR(__xludf.DUMMYFUNCTION("""COMPUTED_VALUE"""),"XB360/OG Xbox") -> XB360/OG Xbox | D12: =IFERROR(__xludf.DUMMYFUNCTION("""COMPUTED_VALUE"""),"GwG Permanent") -> GwG Permanent | E12: =IFERROR(__xludf.DUMMYFUNCTION("""COMPUTED_VALUE"""),42079.0) -> 42079 | F12: =IFERROR(__xludf.DUMMYFUNCTION("""COMPUTED_VALUE"""),42094.0) -> 42094 | G12: =IFERROR(__xludf.DUMMYFUNCTION("""COMPUTED_VALUE"""),0.4666666666666667) -> 0.46666667 | H12: =IFERROR(__xludf.DUMMYFUNCTION("""COMPUTED_VALUE"""),41359.0) -> 41359 | I12: =IFERROR(__xludf.DUMMYFUNCTION("""COMPUTED_VALUE"""),1.9722222222222223) -> 1.9722222 | J12: =IFERROR(__xludf.DUMMYFUNCTION("""COMPUTED_VALUE"""),94.0) -> 94 | K12: =IFERROR(__xludf.DUMMYFUNCTION("""COMPUTED_VALUE"""),11.0) -> 11 | L12: =IFERROR(__xludf.DUMMYFUNCTION("""COMPUTED_VALUE"""),"Action-Adventure") -> Action-Adventure | M12: =NOT(ISNA(VLOOKUP(A12,PC!A:A,1,FALSE))) -> FALSE | N12: =NOT(ISNA(VLOOKUP(A12,'Game Pass Premium'!A:A,1,FALSE))) -> FALSE | O12: =NOT(ISNA(VLOOKUP(A12,'Game Pass Essential'!A:A,1,FALSE))) -> FALSE
A13: =IFERROR(__xludf.DUMMYFUNCTION("""COMPUTED_VALUE"""),"Halo 3") -> Halo 3 | B13: =IFERROR(__xludf.DUMMYFUNCTION("""COMPUTED_VALUE"""),"XB360/OG Xbox") -> XB360/OG Xbox | D13: =IFERROR(__xludf.DUMMYFUNCTION("""COMPUTED_VALUE"""),"GwG Permanent") -> GwG Permanent | E13: =IFERROR(__xludf.DUMMYFUNCTION("""COMPUTED_VALUE"""),41563.0) -> 41563 | F13: =IFERROR(__xludf.DUMMYFUNCTION("""COMPUTED_VALUE"""),41578.0) -> 41578 | G13: =IFERROR(__xludf.DUMMYFUNCTION("""COMPUTED_VALUE"""),0.4666666666666667) -> 0.46666667 | H13: =IFERROR(__xludf.DUMMYFUNCTION("""COMPUTED_VALUE"""),39350.0) -> 39350 | I13: =IFERROR(__xludf.DUMMYFUNCTION("""COMPUTED_VALUE"""),6.058333333333334) -> 6.0583333 | J13: =IFERROR(__xludf.DUMMYFUNCTION("""COMPUTED_VALUE"""),94.0) -> 94 | K13: =IFERROR(__xludf.DUMMYFUNCTION("""COMPUTED_VALUE"""),12.0) -> 12 | L13: =IFERROR(__xludf.DUMMYFUNCTION("""COMPUTED_VALUE"""),"Shooter") -> Shooter | M13: =NOT(ISNA(VLOOKUP(A13,PC!A:A,1,FALSE))) -> TRUE | N13: =NOT(ISNA(VLOOKUP(A13,'Game Pass Premium'!A:A,1,FALSE))) -> TRUE | O13: =NOT(ISNA(VLOOKUP(A13,'Game Pass Essential'!A:A,1,FALSE))) -> FALSE
A14: =IFERROR(__xludf.DUMMYFUNCTION("""COMPUTED_VALUE"""),"Hades") -> Hades | B14: =IFERROR(__xludf.DUMMYFUNCTION("""COMPUTED_VALUE"""),"Xbox / PC") -> Xbox / PC | C14: =IFERROR(__xludf.DUMMYFUNCTION("""COMPUTED_VALUE"""),"Touch Controls") -> Touch Controls | D14: =IFERROR(__xludf.DUMMYFUNCTION("""COMPUTED_VALUE"""),"Active") -> Active | E14: =IFERROR(__xludf.DUMMYFUNCTION("""COMPUTED_VALUE"""),45919.0) -> 45919 | G14: =IFERROR(__xludf.DUMMYFUNCTION("""COMPUTED_VALUE"""),12.566666666666666) -> 12.566667 | H14: =IFERROR(__xludf.DUMMYFUNCTION("""COMPUTED_VALUE"""),43441.0) -> 43441 | I14: =IFERROR(__xludf.DUMMYFUNCTION("""COMPUTED_VALUE"""),6.783333333333333) -> 6.7833333 | J14: =IFERROR(__xludf.DUMMYFUNCTION("""COMPUTED_VALUE"""),93.5) -> 93.5 | K14: =IFERROR(__xludf.DUMMYFUNCTION("""COMPUTED_VALUE"""),21.0) -> 21 | L14: =IFERROR(__xludf.DUMMYFUNCTION("""COMPUTED_VALUE"""),"RPG") -> RPG | M14: =NOT(ISNA(VLOOKUP(A14,PC!A:A,1,FALSE))) -> TRUE | N14: =NOT(ISNA(VLOOKUP(A14,'Game Pass Premium'!A:A,1,FALSE))) -> TRUE | O14: =NOT(ISNA(VLOOKUP(A14,'Game Pass Essential'!A:A,1,FALSE))) -> TRUE
A15: =IFERROR(__xludf.DUMMYFUNCTION("""COMPUTED_VALUE"""),"Blue Prince") -> Blue Prince | B15: =IFERROR(__xludf.DUMMYFUNCTION("""COMPUTED_VALUE"""),"Xbox / PC") -> Xbox / PC | C15: =IFERROR(__xludf.DUMMYFUNCTION("""COMPUTED_VALUE"""),"Yes") -> Yes | D15: =IFERROR(__xludf.DUMMYFUNCTION("""COMPUTED_VALUE"""),"Active") -> Active | E15: =IFERROR(__xludf.DUMMYFUNCTION("""COMPUTED_VALUE"""),45757.0) -> 45757 | G15: =IFERROR(__xludf.DUMMYFUNCTION("""COMPUTED_VALUE"""),17.866666666666667) -> 17.866667 | H15: =IFERROR(__xludf.DUMMYFUNCTION("""COMPUTED_VALUE"""),45757.0) -> 45757 | I15: =IFERROR(__xludf.DUMMYFUNCTION("""COMPUTED_VALUE"""),0.0) -> 0 | J15: =IFERROR(__xludf.DUMMYFUNCTION("""COMPUTED_VALUE"""),93.0) -> 93 | K15: =IFERROR(__xludf.DUMMYFUNCTION("""COMPUTED_VALUE"""),14.0) -> 14 | L15: =IFERROR(__xludf.DUMMYFUNCTION("""COMPUTED_VALUE"""),"Action-Adventure") -> Action-Adventure | M15: =NOT(ISNA(VLOOKUP(A15,PC!A:A,1,FALSE))) -> TRUE | N15: =NOT(ISNA(VLOOKUP(A15,'Game Pass Premium'!A:A,1,FALSE))) -> FALSE | O15: =NOT(ISNA(VLOOKUP(A15,'Game Pass Essential'!A:A,1,FALSE))) -> FALSE
A16: =IFERROR(__xludf.DUMMYFUNCTION("""COMPUTED_VALUE"""),"Inside") -> Inside | B16: =IFERROR(__xludf.DUMMYFUNCTION("""COMPUTED_VALUE"""),"Xbox / PC") -> Xbox / PC | C16: =IFERROR(__xludf.DUMMYFUNCTION("""COMPUTED_VALUE"""),"Yes") -> Yes | D16: =IFERROR(__xludf.DUMMYFUNCTION("""COMPUTED_VALUE"""),"Active") -> Active | E16: =IFERROR(__xludf.DUMMYFUNCTION("""COMPUTED_VALUE"""),44763.0) -> 44763 | G16: =IFERROR(__xludf.DUMMYFUNCTION("""COMPUTED_VALUE"""),50.5) -> 50.5 | H16: =IFERROR(__xludf.DUMMYFUNCTION("""COMPUTED_VALUE"""),42550.0) -> 42550 | I16: =IFERROR(__xludf.DUMMYFUNCTION("""COMPUTED_VALUE"""),6.061111111111111) -> 6.0611111 | J16: =IFERROR(__xludf.DUMMYFUNCTION("""COMPUTED_VALUE"""),93.0) -> 93 | K16: =IFERROR(__xludf.DUMMYFUNCTION("""COMPUTED_VALUE"""),3.5) -> 3.5 | L16: =IFERROR(__xludf.DUMMYFUNCTION("""COMPUTED_VALUE"""),"Platformer") -> Platformer | M16: =NOT(ISNA(VLOOKUP(A16,PC!A:A,1,FALSE))) -> TRUE | N16: =NOT(ISNA(VLOOKUP(A16,'Game Pass Premium'!A:A,1,FALSE))) -> TRUE | O16: =NOT(ISNA(VLOOKUP(A16,'Game Pass Essential'!A:A,1,FALSE))) -> TRUE
A17: =IFERROR(__xludf.DUMMYFUNCTION("""COMPUTED_VALUE"""),"Mass Effect 3: N7 Digital Deluxe Edition") -> Mass Effect 3: N7 Digital Deluxe Edition | B17: =IFERROR(__xludf.DUMMYFUNCTION("""COMPUTED_VALUE"""),"Xbox / PC") -> Xbox / PC | D17: =IFERROR(__xludf.DUMMYFUNCTION("""COMPUTED_VALUE"""),"Active") -> Active | E17: =IFERROR(__xludf.DUMMYFUNCTION("""COMPUTED_VALUE"""),44145.0) -> 44145 | G17: =IFERROR(__xludf.DUMMYFUNCTION("""COMPUTED_VALUE"""),70.86666666666667) -> 70.866667 | H17: =IFERROR(__xludf.DUMMYFUNCTION("""COMPUTED_VALUE"""),40974.0) -> 40974 | I17: =IFERROR(__xludf.DUMMYFUNCTION("""COMPUTED_VALUE"""),8.677777777777777) -> 8.6777778 | J17: =IFERROR(__xludf.DUMMYFUNCTION("""COMPUTED_VALUE"""),93.0) -> 93 | K17: =IFERROR(__xludf.DUMMYFUNCTION("""COMPUTED_VALUE"""),24.0) -> 24 | L17: =IFERROR(__xludf.DUMMYFUNCTION("""COMPUTED_VALUE"""),"Shooter") -> Shooter | M17: =NOT(ISNA(VLOOKUP(A17,PC!A:A,1,FALSE))) -> TRUE | N17: =NOT(ISNA(VLOOKUP(A17,'Game Pass Premium'!A:A,1,FALSE))) -> TRUE | O17: =NOT(ISNA(VLOOKUP(A17,'Game Pass Essential'!A:A,1,FALSE))) -> FALSE
A18: =IFERROR(__xludf.DUMMYFUNCTION("""COMPUTED_VALUE"""),"Fallout 3: Game of the Year Edition") -> Fallout 3: Game of the Year Edition | B18: =IFERROR(__xludf.DUMMYFUNCTION("""COMPUTED_VALUE"""),"Xbox / PC") -> Xbox / PC | C18: =IFERROR(__xludf.DUMMYFUNCTION("""COMPUTED_VALUE"""),"Yes") -> Yes | D18: =IFERROR(__xludf.DUMMYFUNCTION("""COMPUTED_VALUE"""),"Active") -> Active | E18: =IFERROR(__xludf.DUMMYFUNCTION("""COMPUTED_VALUE"""),43282.0) -> 43282 | G18: =IFERROR(__xludf.DUMMYFUNCTION("""COMPUTED_VALUE"""),99.16666666666667) -> 99.166667 | H18: =IFERROR(__xludf.DUMMYFUNCTION("""COMPUTED_VALUE"""),39749.0) -> 39749 | I18: =IFERROR(__xludf.DUMMYFUNCTION("""COMPUTED_VALUE"""),9.675) -> 9.675 | J18: =IFERROR(__xludf.DUMMYFUNCTION("""COMPUTED_VALUE"""),93.0) -> 93 | K18: =IFERROR(__xludf.DUMMYFUNCTION("""COMPUTED_VALUE"""),22.5) -> 22.5 | L18: =IFERROR(__xludf.DUMMYFUNCTION("""COMPUTED_VALUE"""),"Shooter") -> Shooter | M18: =NOT(ISNA(VLOOKUP(A18,PC!A:A,1,FALSE))) -> TRUE | N18: =NOT(ISNA(VLOOKUP(A18,'Game Pass Premium'!A:A,1,FALSE))) -> TRUE | O18: =NOT(ISNA(VLOOKUP(A18,'Game Pass Essential'!A:A,1,FALSE))) -> FALSE
A19: =IFERROR(__xludf.DUMMYFUNCTION("""COMPUTED_VALUE"""),"Gears of War 2") -> Gears of War 2 | B19: =IFERROR(__xludf.DUMMYFUNCTION("""COMPUTED_VALUE"""),"Xbox") -> Xbox | C19: =IFERROR(__xludf.DUMMYFUNCTION("""COMPUTED_VALUE"""),"Yes") -> Yes | D19: =IFERROR(__xludf.DUMMYFUNCTION("""COMPUTED_VALUE"""),"Active") -> Active | E19: =IFERROR(__xludf.DUMMYFUNCTION("""COMPUTED_VALUE"""),42887.0) -> 42887 | G19: =IFERROR(__xludf.DUMMYFUNCTION("""COMPUTED_VALUE"""),112.16666666666666) -> 112.16667 | H19: =IFERROR(__xludf.DUMMYFUNCTION("""COMPUTED_VALUE"""),39759.0) -> 39759 | I19: =IFERROR(__xludf.DUMMYFUNCTION("""COMPUTED_VALUE"""),8.566666666666666) -> 8.5666667 | J19: =IFERROR(__xludf.DUMMYFUNCTION("""COMPUTED_VALUE"""),93.0) -> 93 | K19: =IFERROR(__xludf.DUMMYFUNCTION("""COMPUTED_VALUE"""),10.0) -> 10 | L19: =IFERROR(__xludf.DUMMYFUNCTION("""COMPUTED_VALUE"""),"Shooter") -> Shooter | M19: =NOT(ISNA(VLOOKUP(A19,PC!A:A,1,FALSE))) -> FALSE | N19: =NOT(ISNA(VLOOKUP(A19,'Game Pass Premium'!A:A,1,FALSE))) -> TRUE | O19: =NOT(ISNA(VLOOKUP(A19,'Game Pass Essential'!A:A,1,FALSE))) -> FALSE
A20: =IFERROR(__xludf.DUMMYFUNCTION("""COMPUTED_VALUE"""),"Forza Horizon 6") -> Forza Horizon 6 | B20: =IFERROR(__xludf.DUMMYFUNCTION("""COMPUTED_VALUE"""),"Xbox / PC") -> Xbox / PC | C20: =IFERROR(__xludf.DUMMYFUNCTION("""COMPUTED_VALUE"""),"Yes") -> Yes | D20: =IFERROR(__xludf.DUMMYFUNCTION("""COMPUTED_VALUE"""),"Active") -> Active | E20: =IFERROR(__xludf.DUMMYFUNCTION("""COMPUTED_VALUE"""),46161.0) -> 46161 | G20: =IFERROR(__xludf.DUMMYFUNCTION("""COMPUTED_VALUE"""),4.566666666666666) -> 4.5666667 | H20: =IFERROR(__xludf.DUMMYFUNCTION("""COMPUTED_VALUE"""),46161.0) -> 46161 | I20: =IFERROR(__xludf.DUMMYFUNCTION("""COMPUTED_VALUE"""),0.0) -> 0 | J20: =IFERROR(__xludf.DUMMYFUNCTION("""COMPUTED_VALUE"""),92.0) -> 92 | K20: =IFERROR(__xludf.DUMMYFUNCTION("""COMPUTED_VALUE"""),17.0) -> 17 | L20: =IFERROR(__xludf.DUMMYFUNCTION("""COMPUTED_VALUE"""),"Racing") -> Racing | M20: =NOT(ISNA(VLOOKUP(A20,PC!A:A,1,FALSE))) -> TRUE | N20: =NOT(ISNA(VLOOKUP(A20,'Game Pass Premium'!A:A,1,FALSE))) -> FALSE | O20: =NOT(ISNA(VLOOKUP(A20,'Game Pass Essential'!A:A,1,FALSE))) -> FALSE
A21: =IFERROR(__xludf.DUMMYFUNCTION("""COMPUTED_VALUE"""),"Rayman Legends") -> Rayman Legends | B21: =IFERROR(__xludf.DUMMYFUNCTION("""COMPUTED_VALUE"""),"Xbox / PC") -> Xbox / PC | C21: =IFERROR(__xludf.DUMMYFUNCTION("""COMPUTED_VALUE"""),"Yes") -> Yes | D21: =IFERROR(__xludf.DUMMYFUNCTION("""COMPUTED_VALUE"""),"Active") -> Active | E21: =IFERROR(__xludf.DUMMYFUNCTION("""COMPUTED_VALUE"""),45931.0) -> 45931 | G21: =IFERROR(__xludf.DUMMYFUNCTION("""COMPUTED_VALUE"""),12.166666666666666) -> 12.166667 | H21: =IFERROR(__xludf.DUMMYFUNCTION("""COMPUTED_VALUE"""),41520.0) -> 41520 | I21: =IFERROR(__xludf.DUMMYFUNCTION("""COMPUTED_VALUE"""),12.077777777777778) -> 12.077778 | J21: =IFERROR(__xludf.DUMMYFUNCTION("""COMPUTED_VALUE"""),92.0) -> 92 | K21: =IFERROR(__xludf.DUMMYFUNCTION("""COMPUTED_VALUE"""),10.0) -> 10 | L21: =IFERROR(__xludf.DUMMYFUNCTION("""COMPUTED_VALUE"""),"Platformer") -> Platformer | M21: =NOT(ISNA(VLOOKUP(A21,PC!A:A,1,FALSE))) -> TRUE | N21: =NOT(ISNA(VLOOKUP(A21,'Game Pass Premium'!A:A,1,FALSE))) -> FALSE | O21: =NOT(ISNA(VLOOKUP(A21,'Game Pass Essential'!A:A,1,FALSE))) -> FALSE
A22: =IFERROR(__xludf.DUMMYFUNCTION("""COMPUTED_VALUE"""),"Oystron") -> Oystron | B22: =IFERROR(__xludf.DUMMYFUNCTION("""COMPUTED_VALUE"""),"Xbox / PC") -> Xbox / PC | C22: =IFERROR(__xludf.DUMMYFUNCTION("""COMPUTED_VALUE"""),"Yes") -> Yes | D22: =IFERROR(__xludf.DUMMYFUNCTION("""COMPUTED_VALUE"""),"Active") -> Active | E22: =IFERROR(__xludf.DUMMYFUNCTION("""COMPUTED_VALUE"""),45883.0) -> 45883 | G22: =IFERROR(__xludf.DUMMYFUNCTION("""COMPUTED_VALUE"""),13.733333333333333) -> 13.733333 | H22: =IFERROR(__xludf.DUMMYFUNCTION("""COMPUTED_VALUE"""),35431.0) -> 35431 | I22: =IFERROR(__xludf.DUMMYFUNCTION("""COMPUTED_VALUE"""),28.619444444444444) -> 28.619444 | J22: =IFERROR(__xludf.DUMMYFUNCTION("""COMPUTED_VALUE"""),92.0) -> 92 | L22: =IFERROR(__xludf.DUMMYFUNCTION("""COMPUTED_VALUE"""),"Action") -> Action | M22: =NOT(ISNA(VLOOKUP(A22,PC!A:A,1,FALSE))) -> TRUE | N22: =NOT(ISNA(VLOOKUP(A22,'Game Pass Premium'!A:A,1,FALSE))) -> TRUE | O22: =NOT(ISNA(VLOOKUP(A22,'Game Pass Essential'!A:A,1,FALSE))) -> FALSE
A23: =IFERROR(__xludf.DUMMYFUNCTION("""COMPUTED_VALUE"""),"Microsoft Flight Simulator (2020): Game of the Year Edition") -> Microsoft Flight Simulator (2020): Game of the Year Edition | B23: =IFERROR(__xludf.DUMMYFUNCTION("""COMPUTED_VALUE"""),"Xbox / PC") -> Xbox / PC | C23: =IFERROR(__xludf.DUMMYFUNCTION("""COMPUTED_VALUE"""),"Yes") -> Yes | D23: =IFERROR(__xludf.DUMMYFUNCTION("""COMPUTED_VALUE"""),"Active") -> Active | E23: =IFERROR(__xludf.DUMMYFUNCTION("""COMPUTED_VALUE"""),44061.0) -> 44061 | G23: =IFERROR(__xludf.DUMMYFUNCTION("""COMPUTED_VALUE"""),73.60000000000001) -> 73.6 | H23: =IFERROR(__xludf.DUMMYFUNCTION("""COMPUTED_VALUE"""),44061.0) -> 44061 | I23: =IFERROR(__xludf.DUMMYFUNCTION("""COMPUTED_VALUE"""),0.0) -> 0 | J23: =IFERROR(__xludf.DUMMYFUNCTION("""COMPUTED_VALUE"""),92.0) -> 92 | K23: =IFERROR(__xludf.DUMMYFUNCTION("""COMPUTED_VALUE"""),41.5) -> 41.5 | L23: =IFERROR(__xludf.DUMMYFUNCTION("""COMPUTED_VALUE"""),"Flight") -> Flight | M23: =NOT(ISNA(VLOOKUP(A23,PC!A:A,1,FALSE))) -> TRUE | N23: =NOT(ISNA(VLOOKUP(A23,'Game Pass Premium'!A:A,1,FALSE))) -> TRUE | O23: =NOT(ISNA(VLOOKUP(A23,'Game Pass Essential'!A:A,1,FALSE))) -> FALSE
A24: =IFERROR(__xludf.DUMMYFUNCTION("""COMPUTED_VALUE"""),"Clair Obscur: Expedition 33") -> Clair Obscur: Expedition 33 | B24: =IFERROR(__xludf.DUMMYFUNCTION("""COMPUTED_VALUE"""),"Xbox / PC") -> Xbox / PC | C24: =IFERROR(__xludf.DUMMYFUNCTION("""COMPUTED_VALUE"""),"Yes") -> Yes | D24: =IFERROR(__xludf.DUMMYFUNCTION("""COMPUTED_VALUE"""),"Leaving Soon") -> Leaving Soon | E24: =IFERROR(__xludf.DUMMYFUNCTION("""COMPUTED_VALUE"""),45771.0) -> 45771 | F24: =IFERROR(__xludf.DUMMYFUNCTION("""COMPUTED_VALUE"""),46310.0) -> 46310 | G24: =IFERROR(__xludf.DUMMYFUNCTION("""COMPUTED_VALUE"""),17.700000000000003) -> 17.7 | H24: =IFERROR(__xludf.DUMMYFUNCTION("""COMPUTED_VALUE"""),45771.0) -> 45771 | I24: =IFERROR(__xludf.DUMMYFUNCTION("""COMPUTED_VALUE"""),0.0) -> 0 | J24: =IFERROR(__xludf.DUMMYFUNCTION("""COMPUTED_VALUE"""),92.0) -> 92 | K24: =IFERROR(__xludf.DUMMYFUNCTION("""COMPUTED_VALUE"""),26.0) -> 26 | L24: =IFERROR(__xludf.DUMMYFUNCTION("""COMPUTED_VALUE"""),"RPG") -> RPG | M24: =NOT(ISNA(VLOOKUP(A24,PC!A:A,1,FALSE))) -> TRUE | N24: =NOT(ISNA(VLOOKUP(A24,'Game Pass Premium'!A:A,1,FALSE))) -> TRUE | O24: =NOT(ISNA(VLOOKUP(A24,'Game Pass Essential'!A:A,1,FALSE))) -> FALSE
A25: =IFERROR(__xludf.DUMMYFUNCTION("""COMPUTED_VALUE"""),"Castlevania: Symphony of the Night") -> Castlevania: Symphony of the Night | B25: =IFERROR(__xludf.DUMMYFUNCTION("""COMPUTED_VALUE"""),"XB360/OG Xbox") -> XB360/OG Xbox | D25: =IFERROR(__xludf.DUMMYFUNCTION("""COMPUTED_VALUE"""),"GwG Permanent") -> GwG Permanent | E25: =IFERROR(__xludf.DUMMYFUNCTION("""COMPUTED_VALUE"""),43647.0) -> 43647 | F25: =IFERROR(__xludf.DUMMYFUNCTION("""COMPUTED_VALUE"""),43661.0) -> 43661 | G25: =IFERROR(__xludf.DUMMYFUNCTION("""COMPUTED_VALUE"""),0.4666666666666667) -> 0.46666667 | H25: =IFERROR(__xludf.DUMMYFUNCTION("""COMPUTED_VALUE"""),35509.0) -> 35509 | I25: =IFERROR(__xludf.DUMMYFUNCTION("""COMPUTED_VALUE"""),22.280555555555555) -> 22.280556 | J25: =IFERROR(__xludf.DUMMYFUNCTION("""COMPUTED_VALUE"""),92.0) -> 92 | K25: =IFERROR(__xludf.DUMMYFUNCTION("""COMPUTED_VALUE"""),7.0) -> 7 | L25: =IFERROR(__xludf.DUMMYFUNCTION("""COMPUTED_VALUE"""),"Action-Adventure") -> Action-Adventure | M25: =NOT(ISNA(VLOOKUP(A25,PC!A:A,1,FALSE))) -> FALSE | N25: =NOT(ISNA(VLOOKUP(A25,'Game Pass Premium'!A:A,1,FALSE))) -> FALSE | O25: =NOT(ISNA(VLOOKUP(A25,'Game Pass Essential'!A:A,1,FALSE))) -> FALSE
A26: =IFERROR(__xludf.DUMMYFUNCTION("""COMPUTED_VALUE"""),"Forza Horizon 5") -> Forza Horizon 5 | B26: =IFERROR(__xludf.DUMMYFUNCTION("""COMPUTED_VALUE"""),"Xbox / PC") -> Xbox / PC | C26: =IFERROR(__xludf.DUMMYFUNCTION("""COMPUTED_VALUE"""),"Yes") -> Yes | D26: =IFERROR(__xludf.DUMMYFUNCTION("""COMPUTED_VALUE"""),"Active") -> Active | E26: =IFERROR(__xludf.DUMMYFUNCTION("""COMPUTED_VALUE"""),44509.0) -> 44509 | G26: =IFERROR(__xludf.DUMMYFUNCTION("""COMPUTED_VALUE"""),58.9) -> 58.9 | H26: =IFERROR(__xludf.DUMMYFUNCTION("""COMPUTED_VALUE"""),44509.0) -> 44509 | I26: =IFERROR(__xludf.DUMMYFUNCTION("""COMPUTED_VALUE"""),0.0) -> 0 | J26: =IFERROR(__xludf.DUMMYFUNCTION("""COMPUTED_VALUE"""),91.5) -> 91.5 | K26: =IFERROR(__xludf.DUMMYFUNCTION("""COMPUTED_VALUE"""),17.0) -> 17 | L26: =IFERROR(__xludf.DUMMYFUNCTION("""COMPUTED_VALUE"""),"Racing") -> Racing | M26: =NOT(ISNA(VLOOKUP(A26,PC!A:A,1,FALSE))) -> TRUE | N26: =NOT(ISNA(VLOOKUP(A26,'Game Pass Premium'!A:A,1,FALSE))) -> TRUE | O26: =NOT(ISNA(VLOOKUP(A26,'Game Pass Essential'!A:A,1,FALSE))) -> FALSE
A27: =IFERROR(__xludf.DUMMYFUNCTION("""COMPUTED_VALUE"""),"Disco Elysium") -> Disco Elysium | B27: =IFERROR(__xludf.DUMMYFUNCTION("""COMPUTED_VALUE"""),"Xbox / PC") -> Xbox / PC | C27: =IFERROR(__xludf.DUMMYFUNCTION("""COMPUTED_VALUE"""),"Yes") -> Yes | D27: =IFERROR(__xludf.DUMMYFUNCTION("""COMPUTED_VALUE"""),"Active") -> Active | E27: =IFERROR(__xludf.DUMMYFUNCTION("""COMPUTED_VALUE"""),46100.0) -> 46100 | G27: =IFERROR(__xludf.DUMMYFUNCTION("""COMPUTED_VALUE"""),6.566666666666667) -> 6.5666667 | H27: =IFERROR(__xludf.DUMMYFUNCTION("""COMPUTED_VALUE"""),43753.0) -> 43753 | I27: =IFERROR(__xludf.DUMMYFUNCTION("""COMPUTED_VALUE"""),6.427777777777778) -> 6.4277778 | J27: =IFERROR(__xludf.DUMMYFUNCTION("""COMPUTED_VALUE"""),91.0) -> 91 | K27: =IFERROR(__xludf.DUMMYFUNCTION("""COMPUTED_VALUE"""),23.0) -> 23 | L27: =IFERROR(__xludf.DUMMYFUNCTION("""COMPUTED_VALUE"""),"RPG") -> RPG | M27: =NOT(ISNA(VLOOKUP(A27,PC!A:A,1,FALSE))) -> TRUE | N27: =NOT(ISNA(VLOOKUP(A27,'Game Pass Premium'!A:A,1,FALSE))) -> TRUE | O27: =NOT(ISNA(VLOOKUP(A27,'Game Pass Essential'!A:A,1,FALSE))) -> FALSE
A28: =IFERROR(__xludf.DUMMYFUNCTION("""COMPUTED_VALUE"""),"Conquests of the Longbow: The Legend of Robin Hood") -> Conquests of the Longbow: The Legend of Robin Hood | B28: =IFERROR(__xludf.DUMMYFUNCTION("""COMPUTED_VALUE"""),"Xbox / PC") -> Xbox / PC | C28: =IFERROR(__xludf.DUMMYFUNCTION("""COMPUTED_VALUE"""),"Yes") -> Yes | D28: =IFERROR(__xludf.DUMMYFUNCTION("""COMPUTED_VALUE"""),"Active") -> Active | E28: =IFERROR(__xludf.DUMMYFUNCTION("""COMPUTED_VALUE"""),45798.0) -> 45798 | G28: =IFERROR(__xludf.DUMMYFUNCTION("""COMPUTED_VALUE"""),16.5) -> 16.5 | H28: =IFERROR(__xludf.DUMMYFUNCTION("""COMPUTED_VALUE"""),33616.0) -> 33616 | I28: =IFERROR(__xludf.DUMMYFUNCTION("""COMPUTED_VALUE"""),33.355555555555554) -> 33.355556 | J28: =IFERROR(__xludf.DUMMYFUNCTION("""COMPUTED_VALUE"""),91.0) -> 91 | K28: =IFERROR(__xludf.DUMMYFUNCTION("""COMPUTED_VALUE"""),6.0) -> 6 | L28: =IFERROR(__xludf.DUMMYFUNCTION("""COMPUTED_VALUE"""),"Action‑Adventure") -> Action‑Adventure | M28: =NOT(ISNA(VLOOKUP(A28,PC!A:A,1,FALSE))) -> TRUE | N28: =NOT(ISNA(VLOOKUP(A28,'Game Pass Premium'!A:A,1,FALSE))) -> TRUE | O28: =NOT(ISNA(VLOOKUP(A28,'Game Pass Essential'!A:A,1,FALSE))) -> FALSE
A29: =IFERROR(__xludf.DUMMYFUNCTION("""COMPUTED_VALUE"""),"Resident Evil 2 (2019)") -> Resident Evil 2 (2019) | B29: =IFERROR(__xludf.DUMMYFUNCTION("""COMPUTED_VALUE"""),"Xbox / PC") -> Xbox / PC | C29: =IFERROR(__xludf.DUMMYFUNCTION("""COMPUTED_VALUE"""),"Yes") -> Yes | D29: =IFERROR(__xludf.DUMMYFUNCTION("""COMPUTED_VALUE"""),"Active") -> Active | E29: =IFERROR(__xludf.DUMMYFUNCTION("""COMPUTED_VALUE"""),45307.0) -> 45307 | G29: =IFERROR(__xludf.DUMMYFUNCTION("""COMPUTED_VALUE"""),32.66666666666667) -> 32.666667 | H29: =IFERROR(__xludf.DUMMYFUNCTION("""COMPUTED_VALUE"""),43480.0) -> 43480 | I29: =IFERROR(__xludf.DUMMYFUNCTION("""COMPUTED_VALUE"""),5.002777777777778) -> 5.0027778 | J29: =IFERROR(__xludf.DUMMYFUNCTION("""COMPUTED_VALUE"""),91.0) -> 91 | K29: =IFERROR(__xludf.DUMMYFUNCTION("""COMPUTED_VALUE"""),9.0) -> 9 | L29: =IFERROR(__xludf.DUMMYFUNCTION("""COMPUTED_VALUE"""),"Shooter") -> Shooter | M29: =NOT(ISNA(VLOOKUP(A29,PC!A:A,1,FALSE))) -> TRUE | N29: =NOT(ISNA(VLOOKUP(A29,'Game Pass Premium'!A:A,1,FALSE))) -> TRUE | O29: =NOT(ISNA(VLOOKUP(A29,'Game Pass Essential'!A:A,1,FALSE))) -> FALSE
A30: =IFERROR(__xludf.DUMMYFUNCTION("""COMPUTED_VALUE"""),"Halo: Reach") -> Halo: Reach | B30: =IFERROR(__xludf.DUMMYFUNCTION("""COMPUTED_VALUE"""),"Xbox / PC") -> Xbox / PC | D30: =IFERROR(__xludf.DUMMYFUNCTION("""COMPUTED_VALUE"""),"Active") -> Active | E30: =IFERROR(__xludf.DUMMYFUNCTION("""COMPUTED_VALUE"""),43802.0) -> 43802 | G30: =IFERROR(__xludf.DUMMYFUNCTION("""COMPUTED_VALUE"""),82.1) -> 82.1 | H30: =IFERROR(__xludf.DUMMYFUNCTION("""COMPUTED_VALUE"""),40435.0) -> 40435 | I30: =IFERROR(__xludf.DUMMYFUNCTION("""COMPUTED_VALUE"""),9.219444444444445) -> 9.2194444 | J30: =IFERROR(__xludf.DUMMYFUNCTION("""COMPUTED_VALUE"""),91.0) -> 91 | K30: =IFERROR(__xludf.DUMMYFUNCTION("""COMPUTED_VALUE"""),8.0) -> 8 | L30: =IFERROR(__xludf.DUMMYFUNCTION("""COMPUTED_VALUE"""),"Shooter") -> Shooter | M30: =NOT(ISNA(VLOOKUP(A30,PC!A:A,1,FALSE))) -> TRUE | N30: =NOT(ISNA(VLOOKUP(A30,'Game Pass Premium'!A:A,1,FALSE))) -> TRUE | O30: =NOT(ISNA(VLOOKUP(A30,'Game Pass Essential'!A:A,1,FALSE))) -> FALSE
A31: =IFERROR(__xludf.DUMMYFUNCTION("""COMPUTED_VALUE"""),"Gears of War 3") -> Gears of War 3 | B31: =IFERROR(__xludf.DUMMYFUNCTION("""COMPUTED_VALUE"""),"Xbox") -> Xbox | C31: =IFERROR(__xludf.DUMMYFUNCTION("""COMPUTED_VALUE"""),"Yes") -> Yes | D31: =IFERROR(__xludf.DUMMYFUNCTION("""COMPUTED_VALUE"""),"Active") -> Active | E31: =IFERROR(__xludf.DUMMYFUNCTION("""COMPUTED_VALUE"""),42887.0) -> 42887 | G31: =IFERROR(__xludf.DUMMYFUNCTION("""COMPUTED_VALUE"""),112.16666666666666) -> 112.16667 | H31: =IFERROR(__xludf.DUMMYFUNCTION("""COMPUTED_VALUE"""),40806.0) -> 40806 | I31: =IFERROR(__xludf.DUMMYFUNCTION("""COMPUTED_VALUE"""),5.697222222222222) -> 5.6972222 | J31: =IFERROR(__xludf.DUMMYFUNCTION("""COMPUTED_VALUE"""),91.0) -> 91 | K31: =IFERROR(__xludf.DUMMYFUNCTION("""COMPUTED_VALUE"""),9.5) -> 9.5 | L31: =IFERROR(__xludf.DUMMYFUNCTION("""COMPUTED_VALUE"""),"Shooter") -> Shooter | M31: =NOT(ISNA(VLOOKUP(A31,PC!A:A,1,FALSE))) -> FALSE | N31: =NOT(ISNA(VLOOKUP(A31,'Game Pass Premium'!A:A,1,FALSE))) -> TRUE | O31: =NOT(ISNA(VLOOKUP(A31,'Game Pass Essential'!A:A,1,FALSE))) -> FALSE
A32: =IFERROR(__xludf.DUMMYFUNCTION("""COMPUTED_VALUE"""),"Dragon Age: Origins") -> Dragon Age: Origins | B32: =IFERROR(__xludf.DUMMYFUNCTION("""COMPUTED_VALUE"""),"XB360/OG Xbox") -> XB360/OG Xbox | D32: =IFERROR(__xludf.DUMMYFUNCTION("""COMPUTED_VALUE"""),"GwG Permanent") -> GwG Permanent | E32: =IFERROR(__xludf.DUMMYFUNCTION("""COMPUTED_VALUE"""),42902.0) -> 42902 | F32: =IFERROR(__xludf.DUMMYFUNCTION("""COMPUTED_VALUE"""),42916.0) -> 42916 | G32: =IFERROR(__xludf.DUMMYFUNCTION("""COMPUTED_VALUE"""),0.4666666666666667) -> 0.46666667 | H32: =IFERROR(__xludf.DUMMYFUNCTION("""COMPUTED_VALUE"""),40120.0) -> 40120 | I32: =IFERROR(__xludf.DUMMYFUNCTION("""COMPUTED_VALUE"""),7.6194444444444445) -> 7.6194444 | J32: =IFERROR(__xludf.DUMMYFUNCTION("""COMPUTED_VALUE"""),91.0) -> 91 | K32: =IFERROR(__xludf.DUMMYFUNCTION("""COMPUTED_VALUE"""),63.0) -> 63 | L32: =IFERROR(__xludf.DUMMYFUNCTION("""COMPUTED_VALUE"""),"RPG") -> RPG | M32: =NOT(ISNA(VLOOKUP(A32,PC!A:A,1,FALSE))) -> FALSE | N32: =NOT(ISNA(VLOOKUP(A32,'Game Pass Premium'!A:A,1,FALSE))) -> FALSE | O32: =NOT(ISNA(VLOOKUP(A32,'Game Pass Essential'!A:A,1,FALSE))) -> FALSE
A33: =IFERROR(__xludf.DUMMYFUNCTION("""COMPUTED_VALUE"""),"Borderlands 2") -> Borderlands 2 | B33: =IFERROR(__xludf.DUMMYFUNCTION("""COMPUTED_VALUE"""),"XB360/OG Xbox") -> XB360/OG Xbox | D33: =IFERROR(__xludf.DUMMYFUNCTION("""COMPUTED_VALUE"""),"GwG Permanent") -> GwG Permanent | E33: =IFERROR(__xludf.DUMMYFUNCTION("""COMPUTED_VALUE"""),42795.0) -> 42795 | F33: =IFERROR(__xludf.DUMMYFUNCTION("""COMPUTED_VALUE"""),42809.0) -> 42809 | G33: =IFERROR(__xludf.DUMMYFUNCTION("""COMPUTED_VALUE"""),0.4666666666666667) -> 0.46666667 | H33: =IFERROR(__xludf.DUMMYFUNCTION("""COMPUTED_VALUE"""),41170.0) -> 41170 | I33: =IFERROR(__xludf.DUMMYFUNCTION("""COMPUTED_VALUE"""),4.4527777777777775) -> 4.4527778 | J33: =IFERROR(__xludf.DUMMYFUNCTION("""COMPUTED_VALUE"""),91.0) -> 91 | K33: =IFERROR(__xludf.DUMMYFUNCTION("""COMPUTED_VALUE"""),25.0) -> 25 | L33: =IFERROR(__xludf.DUMMYFUNCTION("""COMPUTED_VALUE"""),"Shooter") -> Shooter | M33: =NOT(ISNA(VLOOKUP(A33,PC!A:A,1,FALSE))) -> FALSE | N33: =NOT(ISNA(VLOOKUP(A33,'Game Pass Premium'!A:A,1,FALSE))) -> FALSE | O33: =NOT(ISNA(VLOOKUP(A33,'Game Pass Essential'!A:A,1,FALSE))) -> FALSE
A34: =IFERROR(__xludf.DUMMYFUNCTION("""COMPUTED_VALUE"""),"Gears of War 2") -> Gears of War 2 | B34: =IFERROR(__xludf.DUMMYFUNCTION("""COMPUTED_VALUE"""),"XB360/OG Xbox") -> XB360/OG Xbox | D34: =IFERROR(__xludf.DUMMYFUNCTION("""COMPUTED_VALUE"""),"GwG Permanent") -> GwG Permanent | E34: =IFERROR(__xludf.DUMMYFUNCTION("""COMPUTED_VALUE"""),42416.0) -> 42416 | F34: =IFERROR(__xludf.DUMMYFUNCTION("""COMPUTED_VALUE"""),42429.0) -> 42429 | G34: =IFERROR(__xludf.DUMMYFUNCTION("""COMPUTED_VALUE"""),0.4333333333333333) -> 0.43333333 | H34: =IFERROR(__xludf.DUMMYFUNCTION("""COMPUTED_VALUE"""),39759.0) -> 39759 | I34: =IFERROR(__xludf.DUMMYFUNCTION("""COMPUTED_VALUE"""),7.275) -> 7.275 | J34: =IFERROR(__xludf.DUMMYFUNCTION("""COMPUTED_VALUE"""),91.0) -> 91 | K34: =IFERROR(__xludf.DUMMYFUNCTION("""COMPUTED_VALUE"""),9.0) -> 9 | L34: =IFERROR(__xludf.DUMMYFUNCTION("""COMPUTED_VALUE"""),"Shooter") -> Shooter | M34: =NOT(ISNA(VLOOKUP(A34,PC!A:A,1,FALSE))) -> FALSE | N34: =NOT(ISNA(VLOOKUP(A34,'Game Pass Premium'!A:A,1,FALSE))) -> TRUE | O34: =NOT(ISNA(VLOOKUP(A34,'Game Pass Essential'!A:A,1,FALSE))) -> FALSE
A35: =IFERROR(__xludf.DUMMYFUNCTION("""COMPUTED_VALUE"""),"Halo: Reach") -> Halo: Reach | B35: =IFERROR(__xludf.DUMMYFUNCTION("""COMPUTED_VALUE"""),"XB360/OG Xbox") -> XB360/OG Xbox | D35: =IFERROR(__xludf.DUMMYFUNCTION("""COMPUTED_VALUE"""),"GwG Permanent") -> GwG Permanent | E35: =IFERROR(__xludf.DUMMYFUNCTION("""COMPUTED_VALUE"""),41898.0) -> 41898 | F35: =IFERROR(__xludf.DUMMYFUNCTION("""COMPUTED_VALUE"""),41912.0) -> 41912 | G35: =IFERROR(__xludf.DUMMYFUNCTION("""COMPUTED_VALUE"""),0.4666666666666667) -> 0.46666667 | H35: =IFERROR(__xludf.DUMMYFUNCTION("""COMPUTED_VALUE"""),40435.0) -> 40435 | I35: =IFERROR(__xludf.DUMMYFUNCTION("""COMPUTED_VALUE"""),4.0055555555555555) -> 4.0055556 | J35: =IFERROR(__xludf.DUMMYFUNCTION("""COMPUTED_VALUE"""),91.0) -> 91 | K35: =IFERROR(__xludf.DUMMYFUNCTION("""COMPUTED_VALUE"""),12.0) -> 12 | L35: =IFERROR(__xludf.DUMMYFUNCTION("""COMPUTED_VALUE"""),"Shooter") -> Shooter | M35: =NOT(ISNA(VLOOKUP(A35,PC!A:A,1,FALSE))) -> TRUE | N35: =NOT(ISNA(VLOOKUP(A35,'Game Pass Premium'!A:A,1,FALSE))) -> TRUE | O35: =NOT(ISNA(VLOOKUP(A35,'Game Pass Essential'!A:A,1,FALSE))) -> FALSE
A36: =IFERROR(__xludf.DUMMYFUNCTION("""COMPUTED_VALUE"""),"Dishonored") -> Dishonored | B36: =IFERROR(__xludf.DUMMYFUNCTION("""COMPUTED_VALUE"""),"XB360/OG Xbox") -> XB360/OG Xbox | D36: =IFERROR(__xludf.DUMMYFUNCTION("""COMPUTED_VALUE"""),"GwG Permanent") -> GwG Permanent | E36: =IFERROR(__xludf.DUMMYFUNCTION("""COMPUTED_VALUE"""),41867.0) -> 41867 | F36: =IFERROR(__xludf.DUMMYFUNCTION("""COMPUTED_VALUE"""),41882.0) -> 41882 | G36: =IFERROR(__xludf.DUMMYFUNCTION("""COMPUTED_VALUE"""),0.4666666666666667) -> 0.46666667 | H36: =IFERROR(__xludf.DUMMYFUNCTION("""COMPUTED_VALUE"""),41191.0) -> 41191 | I36: =IFERROR(__xludf.DUMMYFUNCTION("""COMPUTED_VALUE"""),1.8527777777777779) -> 1.8527778 | J36: =IFERROR(__xludf.DUMMYFUNCTION("""COMPUTED_VALUE"""),91.0) -> 91 | K36: =IFERROR(__xludf.DUMMYFUNCTION("""COMPUTED_VALUE"""),13.0) -> 13 | L36: =IFERROR(__xludf.DUMMYFUNCTION("""COMPUTED_VALUE"""),"Action-Adventure") -> Action-Adventure | M36: =NOT(ISNA(VLOOKUP(A36,PC!A:A,1,FALSE))) -> FALSE | N36: =NOT(ISNA(VLOOKUP(A36,'Game Pass Premium'!A:A,1,FALSE))) -> FALSE | O36: =NOT(ISNA(VLOOKUP(A36,'Game Pass Essential'!A:A,1,FALSE))) -> FALSE
A37: =IFERROR(__xludf.DUMMYFUNCTION("""COMPUTED_VALUE"""),"Gears of War") -> Gears of War | B37: =IFERROR(__xludf.DUMMYFUNCTION("""COMPUTED_VALUE"""),"XB360/OG Xbox") -> XB360/OG Xbox | D37: =IFERROR(__xludf.DUMMYFUNCTION("""COMPUTED_VALUE"""),"GwG Permanent") -> GwG Permanent | E37: =IFERROR(__xludf.DUMMYFUNCTION("""COMPUTED_VALUE"""),41609.0) -> 41609 | F37: =IFERROR(__xludf.DUMMYFUNCTION("""COMPUTED_VALUE"""),41623.0) -> 41623 | G37: =IFERROR(__xludf.DUMMYFUNCTION("""COMPUTED_VALUE"""),0.4666666666666667) -> 0.46666667 | H37: =IFERROR(__xludf.DUMMYFUNCTION("""COMPUTED_VALUE"""),39028.0) -> 39028 | I37: =IFERROR(__xludf.DUMMYFUNCTION("""COMPUTED_VALUE"""),7.066666666666666) -> 7.0666667 | J37: =IFERROR(__xludf.DUMMYFUNCTION("""COMPUTED_VALUE"""),91.0) -> 91 | K37: =IFERROR(__xludf.DUMMYFUNCTION("""COMPUTED_VALUE"""),9.0) -> 9 | L37: =IFERROR(__xludf.DUMMYFUNCTION("""COMPUTED_VALUE"""),"Shooter") -> Shooter | M37: =NOT(ISNA(VLOOKUP(A37,PC!A:A,1,FALSE))) -> FALSE | N37: =NOT(ISNA(VLOOKUP(A37,'Game Pass Premium'!A:A,1,FALSE))) -> TRUE | O37: =NOT(ISNA(VLOOKUP(A37,'Game Pass Essential'!A:A,1,FALSE))) -> FALSE
A38: =IFERROR(__xludf.DUMMYFUNCTION("""COMPUTED_VALUE"""),"Starsand Island") -> Starsand Island | B38: =IFERROR(__xludf.DUMMYFUNCTION("""COMPUTED_VALUE"""),"Xbox / PC") -> Xbox / PC | C38: =IFERROR(__xludf.DUMMYFUNCTION("""COMPUTED_VALUE"""),"Yes") -> Yes | D38: =IFERROR(__xludf.DUMMYFUNCTION("""COMPUTED_VALUE"""),"Active") -> Active | E38: =IFERROR(__xludf.DUMMYFUNCTION("""COMPUTED_VALUE"""),46064.0) -> 46064 | G38: =IFERROR(__xludf.DUMMYFUNCTION("""COMPUTED_VALUE"""),7.833333333333334) -> 7.8333333 | H38: =IFERROR(__xludf.DUMMYFUNCTION("""COMPUTED_VALUE"""),46065.0) -> 46065 | I38: =IFERROR(__xludf.DUMMYFUNCTION("""COMPUTED_VALUE"""),-0.002777777777777778) -> -0.0027777778 | J38: =IFERROR(__xludf.DUMMYFUNCTION("""COMPUTED_VALUE"""),90.0) -> 90 | K38: =IFERROR(__xludf.DUMMYFUNCTION("""COMPUTED_VALUE"""),66.0) -> 66 | L38: =IFERROR(__xludf.DUMMYFUNCTION("""COMPUTED_VALUE"""),"Action-Adventure") -> Action-Adventure | M38: =NOT(ISNA(VLOOKUP(A38,PC!A:A,1,FALSE))) -> TRUE | N38: =NOT(ISNA(VLOOKUP(A38,'Game Pass Premium'!A:A,1,FALSE))) -> TRUE | O38: =NOT(ISNA(VLOOKUP(A38,'Game Pass Essential'!A:A,1,FALSE))) -> FALSE
A39: =IFERROR(__xludf.DUMMYFUNCTION("""COMPUTED_VALUE"""),"Dome Keeper") -> Dome Keeper | B39: =IFERROR(__xludf.DUMMYFUNCTION("""COMPUTED_VALUE"""),"Xbox / PC") -> Xbox / PC | C39: =IFERROR(__xludf.DUMMYFUNCTION("""COMPUTED_VALUE"""),"Yes") -> Yes | D39: =IFERROR(__xludf.DUMMYFUNCTION("""COMPUTED_VALUE"""),"Active") -> Active | E39: =IFERROR(__xludf.DUMMYFUNCTION("""COMPUTED_VALUE"""),46000.0) -> 46000 | G39: =IFERROR(__xludf.DUMMYFUNCTION("""COMPUTED_VALUE"""),9.899999999999999) -> 9.9 | H39: =IFERROR(__xludf.DUMMYFUNCTION("""COMPUTED_VALUE"""),44831.0) -> 44831 | I39: =IFERROR(__xludf.DUMMYFUNCTION("""COMPUTED_VALUE"""),3.2) -> 3.2 | J39: =IFERROR(__xludf.DUMMYFUNCTION("""COMPUTED_VALUE"""),90.0) -> 90 | K39: =IFERROR(__xludf.DUMMYFUNCTION("""COMPUTED_VALUE"""),5.0) -> 5 | L39: =IFERROR(__xludf.DUMMYFUNCTION("""COMPUTED_VALUE"""),"Action") -> Action | M39: =NOT(ISNA(VLOOKUP(A39,PC!A:A,1,FALSE))) -> TRUE | N39: =NOT(ISNA(VLOOKUP(A39,'Game Pass Premium'!A:A,1,FALSE))) -> TRUE | O39: =NOT(ISNA(VLOOKUP(A39,'Game Pass Essential'!A:A,1,FALSE))) -> FALSE
A40: =IFERROR(__xludf.DUMMYFUNCTION("""COMPUTED_VALUE"""),"Assassin's Creed II") -> Assassin's Creed II | B40: =IFERROR(__xludf.DUMMYFUNCTION("""COMPUTED_VALUE"""),"Xbox / PC") -> Xbox / PC | D40: =IFERROR(__xludf.DUMMYFUNCTION("""COMPUTED_VALUE"""),"Active") -> Active | E40: =IFERROR(__xludf.DUMMYFUNCTION("""COMPUTED_VALUE"""),45931.0) -> 45931 | G40: =IFERROR(__xludf.DUMMYFUNCTION("""COMPUTED_VALUE"""),12.166666666666666) -> 12.166667 | H40: =IFERROR(__xludf.DUMMYFUNCTION("""COMPUTED_VALUE"""),40134.0) -> 40134 | I40: =IFERROR(__xludf.DUMMYFUNCTION("""COMPUTED_VALUE"""),15.872222222222222) -> 15.872222 | J40: =IFERROR(__xludf.DUMMYFUNCTION("""COMPUTED_VALUE"""),90.0) -> 90 | K40: =IFERROR(__xludf.DUMMYFUNCTION("""COMPUTED_VALUE"""),19.0) -> 19 | L40: =IFERROR(__xludf.DUMMYFUNCTION("""COMPUTED_VALUE"""),"Action-Adventure") -> Action-Adventure | M40: =NOT(ISNA(VLOOKUP(A40,PC!A:A,1,FALSE))) -> TRUE | N40: =NOT(ISNA(VLOOKUP(A40,'Game Pass Premium'!A:A,1,FALSE))) -> FALSE | O40: =NOT(ISNA(VLOOKUP(A40,'Game Pass Essential'!A:A,1,FALSE))) -> FALSE
A41: =IFERROR(__xludf.DUMMYFUNCTION("""COMPUTED_VALUE"""),"Hollow Knight: Silksong") -> Hollow Knight: Silksong | B41: =IFERROR(__xludf.DUMMYFUNCTION("""COMPUTED_VALUE"""),"Xbox / PC") -> Xbox / PC | C41: =IFERROR(__xludf.DUMMYFUNCTION("""COMPUTED_VALUE"""),"Yes") -> Yes | D41: =IFERROR(__xludf.DUMMYFUNCTION("""COMPUTED_VALUE"""),"Active") -> Active | E41: =IFERROR(__xludf.DUMMYFUNCTION("""COMPUTED_VALUE"""),45904.0) -> 45904 | G41: =IFERROR(__xludf.DUMMYFUNCTION("""COMPUTED_VALUE"""),13.066666666666666) -> 13.066667 | H41: =IFERROR(__xludf.DUMMYFUNCTION("""COMPUTED_VALUE"""),45904.0) -> 45904 | I41: =IFERROR(__xludf.DUMMYFUNCTION("""COMPUTED_VALUE"""),0.0) -> 0 | J41: =IFERROR(__xludf.DUMMYFUNCTION("""COMPUTED_VALUE"""),90.0) -> 90 | K41: =IFERROR(__xludf.DUMMYFUNCTION("""COMPUTED_VALUE"""),28.0) -> 28 | L41: =IFERROR(__xludf.DUMMYFUNCTION("""COMPUTED_VALUE"""),"Metroidvania") -> Metroidvania | M41: =NOT(ISNA(VLOOKUP(A41,PC!A:A,1,FALSE))) -> TRUE | N41: =NOT(ISNA(VLOOKUP(A41,'Game Pass Premium'!A:A,1,FALSE))) -> TRUE | O41: =NOT(ISNA(VLOOKUP(A41,'Game Pass Essential'!A:A,1,FALSE))) -> FALSE
A42: =IFERROR(__xludf.DUMMYFUNCTION("""COMPUTED_VALUE"""),"Freddy Pharkas: Frontier Pharmacist") -> Freddy Pharkas: Frontier Pharmacist | B42: =IFERROR(__xludf.DUMMYFUNCTION("""COMPUTED_VALUE"""),"Xbox / PC") -> Xbox / PC | C42: =IFERROR(__xludf.DUMMYFUNCTION("""COMPUTED_VALUE"""),"Yes") -> Yes | D42: =IFERROR(__xludf.DUMMYFUNCTION("""COMPUTED_VALUE"""),"Active") -> Active | E42: =IFERROR(__xludf.DUMMYFUNCTION("""COMPUTED_VALUE"""),45798.0) -> 45798 | G42: =IFERROR(__xludf.DUMMYFUNCTION("""COMPUTED_VALUE"""),16.5) -> 16.5 | H42: =IFERROR(__xludf.DUMMYFUNCTION("""COMPUTED_VALUE"""),34121.0) -> 34121 | I42: =IFERROR(__xludf.DUMMYFUNCTION("""COMPUTED_VALUE"""),31.97222222222222) -> 31.972222 | J42: =IFERROR(__xludf.DUMMYFUNCTION("""COMPUTED_VALUE"""),90.0) -> 90 | K42: =IFERROR(__xludf.DUMMYFUNCTION("""COMPUTED_VALUE"""),17.0) -> 17 | L42: =IFERROR(__xludf.DUMMYFUNCTION("""COMPUTED_VALUE"""),"Adventure") -> Adventure | M42: =NOT(ISNA(VLOOKUP(A42,PC!A:A,1,FALSE))) -> TRUE | N42: =NOT(ISNA(VLOOKUP(A42,'Game Pass Premium'!A:A,1,FALSE))) -> TRUE | O42: =NOT(ISNA(VLOOKUP(A42,'Game Pass Essential'!A:A,1,FALSE))) -> FALSE
A43: =IFERROR(__xludf.DUMMYFUNCTION("""COMPUTED_VALUE"""),"Monster Train 2") -> Monster Train 2 | B43: =IFERROR(__xludf.DUMMYFUNCTION("""COMPUTED_VALUE"""),"Xbox / PC") -> Xbox / PC | C43: =IFERROR(__xludf.DUMMYFUNCTION("""COMPUTED_VALUE"""),"Yes") -> Yes | D43: =IFERROR(__xludf.DUMMYFUNCTION("""COMPUTED_VALUE"""),"Active") -> Active | E43: =IFERROR(__xludf.DUMMYFUNCTION("""COMPUTED_VALUE"""),45798.0) -> 45798 | G43: =IFERROR(__xludf.DUMMYFUNCTION("""COMPUTED_VALUE"""),16.5) -> 16.5 | H43: =IFERROR(__xludf.DUMMYFUNCTION("""COMPUTED_VALUE"""),45798.0) -> 45798 | I43: =IFERROR(__xludf.DUMMYFUNCTION("""COMPUTED_VALUE"""),0.0) -> 0 | J43: =IFERROR(__xludf.DUMMYFUNCTION("""COMPUTED_VALUE"""),90.0) -> 90 | K43: =IFERROR(__xludf.DUMMYFUNCTION("""COMPUTED_VALUE"""),6.0) -> 6 | L43: =IFERROR(__xludf.DUMMYFUNCTION("""COMPUTED_VALUE"""),"Card Battle") -> Card Battle | M43: =NOT(ISNA(VLOOKUP(A43,PC!A:A,1,FALSE))) -> TRUE | N43: =NOT(ISNA(VLOOKUP(A43,'Game Pass Premium'!A:A,1,FALSE))) -> TRUE | O43: =NOT(ISNA(VLOOKUP(A43,'Game Pass Essential'!A:A,1,FALSE))) -> FALSE
A44: =IFERROR(__xludf.DUMMYFUNCTION("""COMPUTED_VALUE"""),"Diablo III: Reaper of Souls - Ultimate Evil Edition") -> Diablo III: Reaper of Souls - Ultimate Evil Edition | B44: =IFERROR(__xludf.DUMMYFUNCTION("""COMPUTED_VALUE"""),"Xbox / PC") -> Xbox / PC | D44: =IFERROR(__xludf.DUMMYFUNCTION("""COMPUTED_VALUE"""),"Active") -> Active | E44: =IFERROR(__xludf.DUMMYFUNCTION("""COMPUTED_VALUE"""),45755.0) -> 45755 | G44: =IFERROR(__xludf.DUMMYFUNCTION("""COMPUTED_VALUE"""),17.933333333333334) -> 17.933333 | H44: =IFERROR(__xludf.DUMMYFUNCTION("""COMPUTED_VALUE"""),41870.0) -> 41870 | I44: =IFERROR(__xludf.DUMMYFUNCTION("""COMPUTED_VALUE"""),10.636111111111111) -> 10.636111 | J44: =IFERROR(__xludf.DUMMYFUNCTION("""COMPUTED_VALUE"""),90.0) -> 90 | K44: =IFERROR(__xludf.DUMMYFUNCTION("""COMPUTED_VALUE"""),19.0) -> 19 | L44: =IFERROR(__xludf.DUMMYFUNCTION("""COMPUTED_VALUE"""),"RPG") -> RPG | M44: =NOT(ISNA(VLOOKUP(A44,PC!A:A,1,FALSE))) -> TRUE | N44: =NOT(ISNA(VLOOKUP(A44,'Game Pass Premium'!A:A,1,FALSE))) -> TRUE | O44: =NOT(ISNA(VLOOKUP(A44,'Game Pass Essential'!A:A,1,FALSE))) -> FALSE
A45: =IFERROR(__xludf.DUMMYFUNCTION("""COMPUTED_VALUE"""),"Balatro") -> Balatro | B45: =IFERROR(__xludf.DUMMYFUNCTION("""COMPUTED_VALUE"""),"Xbox / PC") -> Xbox / PC | C45: =IFERROR(__xludf.DUMMYFUNCTION("""COMPUTED_VALUE"""),"Yes") -> Yes | D45: =IFERROR(__xludf.DUMMYFUNCTION("""COMPUTED_VALUE"""),"Active") -> Active | E45: =IFERROR(__xludf.DUMMYFUNCTION("""COMPUTED_VALUE"""),45712.0) -> 45712 | G45: =IFERROR(__xludf.DUMMYFUNCTION("""COMPUTED_VALUE"""),19.4) -> 19.4 | H45: =IFERROR(__xludf.DUMMYFUNCTION("""COMPUTED_VALUE"""),45616.0) -> 45616 | I45: =IFERROR(__xludf.DUMMYFUNCTION("""COMPUTED_VALUE"""),0.2611111111111111) -> 0.26111111 | J45: =IFERROR(__xludf.DUMMYFUNCTION("""COMPUTED_VALUE"""),90.0) -> 90 | K45: =IFERROR(__xludf.DUMMYFUNCTION("""COMPUTED_VALUE"""),7.0) -> 7 | L45: =IFERROR(__xludf.DUMMYFUNCTION("""COMPUTED_VALUE"""),"Card Battle") -> Card Battle | M45: =NOT(ISNA(VLOOKUP(A45,PC!A:A,1,FALSE))) -> TRUE | N45: =NOT(ISNA(VLOOKUP(A45,'Game Pass Premium'!A:A,1,FALSE))) -> TRUE | O45: =NOT(ISNA(VLOOKUP(A45,'Game Pass Essential'!A:A,1,FALSE))) -> FALSE
A46: =IFERROR(__xludf.DUMMYFUNCTION("""COMPUTED_VALUE"""),"Dead Space 2") -> Dead Space 2 | B46: =IFERROR(__xludf.DUMMYFUNCTION("""COMPUTED_VALUE"""),"Xbox / PC") -> Xbox / PC | C46: =IFERROR(__xludf.DUMMYFUNCTION("""COMPUTED_VALUE"""),"Yes") -> Yes | D46: =IFERROR(__xludf.DUMMYFUNCTION("""COMPUTED_VALUE"""),"Active") -> Active | E46: =IFERROR(__xludf.DUMMYFUNCTION("""COMPUTED_VALUE"""),44145.0) -> 44145 | G46: =IFERROR(__xludf.DUMMYFUNCTION("""COMPUTED_VALUE"""),70.86666666666667) -> 70.866667 | H46: =IFERROR(__xludf.DUMMYFUNCTION("""COMPUTED_VALUE"""),40568.0) -> 40568 | I46: =IFERROR(__xludf.DUMMYFUNCTION("""COMPUTED_VALUE"""),9.791666666666666) -> 9.7916667 | J46: =IFERROR(__xludf.DUMMYFUNCTION("""COMPUTED_VALUE"""),90.0) -> 90 | K46: =IFERROR(__xludf.DUMMYFUNCTION("""COMPUTED_VALUE"""),9.0) -> 9 | L46: =IFERROR(__xludf.DUMMYFUNCTION("""COMPUTED_VALUE"""),"Shooter") -> Shooter | M46: =NOT(ISNA(VLOOKUP(A46,PC!A:A,1,FALSE))) -> TRUE | N46: =NOT(ISNA(VLOOKUP(A46,'Game Pass Premium'!A:A,1,FALSE))) -> TRUE | O46: =NOT(ISNA(VLOOKUP(A46,'Game Pass Essential'!A:A,1,FALSE))) -> FALSE
A47: =IFERROR(__xludf.DUMMYFUNCTION("""COMPUTED_VALUE"""),"The Bard's Tale ARPG: Remastered and Resnarkled") -> The Bard's Tale ARPG: Remastered and Resnarkled | B47: =IFERROR(__xludf.DUMMYFUNCTION("""COMPUTED_VALUE"""),"Xbox / PC") -> Xbox / PC | C47: =IFERROR(__xludf.DUMMYFUNCTION("""COMPUTED_VALUE"""),"Touch Controls") -> Touch Controls | D47: =IFERROR(__xludf.DUMMYFUNCTION("""COMPUTED_VALUE"""),"Active") -> Active | E47: =IFERROR(__xludf.DUMMYFUNCTION("""COMPUTED_VALUE"""),44000.0) -> 44000 | G47: =IFERROR(__xludf.DUMMYFUNCTION("""COMPUTED_VALUE"""),75.6) -> 75.6 | H47: =IFERROR(__xludf.DUMMYFUNCTION("""COMPUTED_VALUE"""),44000.0) -> 44000 | I47: =IFERROR(__xludf.DUMMYFUNCTION("""COMPUTED_VALUE"""),0.0) -> 0 | J47: =IFERROR(__xludf.DUMMYFUNCTION("""COMPUTED_VALUE"""),90.0) -> 90 | K47: =IFERROR(__xludf.DUMMYFUNCTION("""COMPUTED_VALUE"""),14.0) -> 14 | L47: =IFERROR(__xludf.DUMMYFUNCTION("""COMPUTED_VALUE"""),"RPG") -> RPG | M47: =NOT(ISNA(VLOOKUP(A47,PC!A:A,1,FALSE))) -> TRUE | N47: =NOT(ISNA(VLOOKUP(A47,'Game Pass Premium'!A:A,1,FALSE))) -> TRUE | O47: =NOT(ISNA(VLOOKUP(A47,'Game Pass Essential'!A:A,1,FALSE))) -> FALSE
A48: =IFERROR(__xludf.DUMMYFUNCTION("""COMPUTED_VALUE"""),"Ori and the Will of the Wisps") -> Ori and the Will of the Wisps | B48: =IFERROR(__xludf.DUMMYFUNCTION("""COMPUTED_VALUE"""),"Xbox / PC") -> Xbox / PC | C48: =IFERROR(__xludf.DUMMYFUNCTION("""COMPUTED_VALUE"""),"Yes") -> Yes | D48: =IFERROR(__xludf.DUMMYFUNCTION("""COMPUTED_VALUE"""),"Active") -> Active | E48: =IFERROR(__xludf.DUMMYFUNCTION("""COMPUTED_VALUE"""),43901.0) -> 43901 | G48: =IFERROR(__xludf.DUMMYFUNCTION("""COMPUTED_VALUE"""),78.83333333333334) -> 78.833333 | H48: =IFERROR(__xludf.DUMMYFUNCTION("""COMPUTED_VALUE"""),43901.0) -> 43901 | I48: =IFERROR(__xludf.DUMMYFUNCTION("""COMPUTED_VALUE"""),0.0) -> 0 | J48: =IFERROR(__xludf.DUMMYFUNCTION("""COMPUTED_VALUE"""),90.0) -> 90 | K48: =IFERROR(__xludf.DUMMYFUNCTION("""COMPUTED_VALUE"""),11.0) -> 11 | L48: =IFERROR(__xludf.DUMMYFUNCTION("""COMPUTED_VALUE"""),"Platformer") -> Platformer | M48: =NOT(ISNA(VLOOKUP(A48,PC!A:A,1,FALSE))) -> TRUE | N48: =NOT(ISNA(VLOOKUP(A48,'Game Pass Premium'!A:A,1,FALSE))) -> TRUE | O48: =NOT(ISNA(VLOOKUP(A48,'Game Pass Essential'!A:A,1,FALSE))) -> TRUE
A49: =IFERROR(__xludf.DUMMYFUNCTION("""COMPUTED_VALUE"""),"Mass Effect") -> Mass Effect | B49: =IFERROR(__xludf.DUMMYFUNCTION("""COMPUTED_VALUE"""),"Xbox / PC") -> Xbox / PC | D49: =IFERROR(__xludf.DUMMYFUNCTION("""COMPUTED_VALUE"""),"Active") -> Active | E49: =IFERROR(__xludf.DUMMYFUNCTION("""COMPUTED_VALUE"""),43070.0) -> 43070 | G49: =IFERROR(__xludf.DUMMYFUNCTION("""COMPUTED_VALUE"""),106.16666666666666) -> 106.16667 | H49: =IFERROR(__xludf.DUMMYFUNCTION("""COMPUTED_VALUE"""),39406.0) -> 39406 | I49: =IFERROR(__xludf.DUMMYFUNCTION("""COMPUTED_VALUE"""),10.030555555555555) -> 10.030556 | J49: =IFERROR(__xludf.DUMMYFUNCTION("""COMPUTED_VALUE"""),90.0) -> 90 | K49: =IFERROR(__xludf.DUMMYFUNCTION("""COMPUTED_VALUE"""),17.0) -> 17 | L49: =IFERROR(__xludf.DUMMYFUNCTION("""COMPUTED_VALUE"""),"Shooter") -> Shooter | M49: =NOT(ISNA(VLOOKUP(A49,PC!A:A,1,FALSE))) -> TRUE | N49: =NOT(ISNA(VLOOKUP(A49,'Game Pass Premium'!A:A,1,FALSE))) -> TRUE | O49: =NOT(ISNA(VLOOKUP(A49,'Game Pass Essential'!A:A,1,FALSE))) -> FALSE
A50: =IFERROR(__xludf.DUMMYFUNCTION("""COMPUTED_VALUE"""),"Dead Space 2") -> Dead Space 2 | B50: =IFERROR(__xludf.DUMMYFUNCTION("""COMPUTED_VALUE"""),"XB360/OG Xbox") -> XB360/OG Xbox | D50: =IFERROR(__xludf.DUMMYFUNCTION("""COMPUTED_VALUE"""),"GwG Permanent") -> GwG Permanent | E50: =IFERROR(__xludf.DUMMYFUNCTION("""COMPUTED_VALUE"""),43206.0) -> 43206 | F50: =IFERROR(__xludf.DUMMYFUNCTION("""COMPUTED_VALUE"""),43220.0) -> 43220 | G50: =IFERROR(__xludf.DUMMYFUNCTION("""COMPUTED_VALUE"""),0.4666666666666667) -> 0.46666667 | H50: =IFERROR(__xludf.DUMMYFUNCTION("""COMPUTED_VALUE"""),40568.0) -> 40568 | I50: =IFERROR(__xludf.DUMMYFUNCTION("""COMPUTED_VALUE"""),7.225) -> 7.225 | J50: =IFERROR(__xludf.DUMMYFUNCTION("""COMPUTED_VALUE"""),90.0) -> 90 | K50: =IFERROR(__xludf.DUMMYFUNCTION("""COMPUTED_VALUE"""),9.0) -> 9 | L50: =IFERROR(__xludf.DUMMYFUNCTION("""COMPUTED_VALUE"""),"Action-Adventure") -> Action-Adventure | M50: =NOT(ISNA(VLOOKUP(A50,PC!A:A,1,FALSE))) -> TRUE | N50: =NOT(ISNA(VLOOKUP(A50,'Game Pass Premium'!A:A,1,FALSE))) -> TRUE | O50: =NOT(ISNA(VLOOKUP(A50,'Game Pass Essential'!A:A,1,FALSE))) -> FALSE
A51: =IFERROR(__xludf.DUMMYFUNCTION("""COMPUTED_VALUE"""),"NiGHTS into Dreams") -> NiGHTS into Dreams | B51: =IFERROR(__xludf.DUMMYFUNCTION("""COMPUTED_VALUE"""),"XB360/OG Xbox") -> XB360/OG Xbox | D51: =IFERROR(__xludf.DUMMYFUNCTION("""COMPUTED_VALUE"""),"GwG Permanent") -> GwG Permanent | E51: =IFERROR(__xludf.DUMMYFUNCTION("""COMPUTED_VALUE"""),43040.0) -> 43040 | F51: =IFERROR(__xludf.DUMMYFUNCTION("""COMPUTED_VALUE"""),43054.0) -> 43054 | G51: =IFERROR(__xludf.DUMMYFUNCTION("""COMPUTED_VALUE"""),0.4666666666666667) -> 0.46666667 | H51: =IFERROR(__xludf.DUMMYFUNCTION("""COMPUTED_VALUE"""),33503.0) -> 33503 | I51: =IFERROR(__xludf.DUMMYFUNCTION("""COMPUTED_VALUE"""),26.108333333333334) -> 26.108333 | J51: =IFERROR(__xludf.DUMMYFUNCTION("""COMPUTED_VALUE"""),90.0) -> 90 | K51: =IFERROR(__xludf.DUMMYFUNCTION("""COMPUTED_VALUE"""),4.0) -> 4 | L51: =IFERROR(__xludf.DUMMYFUNCTION("""COMPUTED_VALUE"""),"Platformer") -> Platformer | M51: =NOT(ISNA(VLOOKUP(A51,PC!A:A,1,FALSE))) -> FALSE | N51: =NOT(ISNA(VLOOKUP(A51,'Game Pass Premium'!A:A,1,FALSE))) -> FALSE | O51: =NOT(ISNA(VLOOKUP(A51,'Game Pass Essential'!A:A,1,FALSE))) -> FALSE
A52: =IFERROR(__xludf.DUMMYFUNCTION("""COMPUTED_VALUE"""),"Bayonetta") -> Bayonetta | B52: =IFERROR(__xludf.DUMMYFUNCTION("""COMPUTED_VALUE"""),"XB360/OG Xbox") -> XB360/OG Xbox | D52: =IFERROR(__xludf.DUMMYFUNCTION("""COMPUTED_VALUE"""),"GwG Permanent") -> GwG Permanent | E52: =IFERROR(__xludf.DUMMYFUNCTION("""COMPUTED_VALUE"""),42948.0) -> 42948 | F52: =IFERROR(__xludf.DUMMYFUNCTION("""COMPUTED_VALUE"""),42962.0) -> 42962 | G52: =IFERROR(__xludf.DUMMYFUNCTION("""COMPUTED_VALUE"""),0.4666666666666667) -> 0.46666667 | H52: =IFERROR(__xludf.DUMMYFUNCTION("""COMPUTED_VALUE"""),40183.0) -> 40183 | I52: =IFERROR(__xludf.DUMMYFUNCTION("""COMPUTED_VALUE"""),7.572222222222222) -> 7.5722222 | J52: =IFERROR(__xludf.DUMMYFUNCTION("""COMPUTED_VALUE"""),90.0) -> 90 | K52: =IFERROR(__xludf.DUMMYFUNCTION("""COMPUTED_VALUE"""),12.0) -> 12 | L52: =IFERROR(__xludf.DUMMYFUNCTION("""COMPUTED_VALUE"""),"Action‑Adventure") -> Action‑Adventure | M52: =NOT(ISNA(VLOOKUP(A52,PC!A:A,1,FALSE))) -> FALSE | N52: =NOT(ISNA(VLOOKUP(A52,'Game Pass Premium'!A:A,1,FALSE))) -> FALSE | O52: =NOT(ISNA(VLOOKUP(A52,'Game Pass Essential'!A:A,1,FALSE))) -> FALSE
A53: =IFERROR(__xludf.DUMMYFUNCTION("""COMPUTED_VALUE"""),"Super Street Fighter IV: Arcade Edition") -> Super Street Fighter IV: Arcade Edition | B53: =IFERROR(__xludf.DUMMYFUNCTION("""COMPUTED_VALUE"""),"XB360/OG Xbox") -> XB360/OG Xbox | D53: =IFERROR(__xludf.DUMMYFUNCTION("""COMPUTED_VALUE"""),"GwG Permanent") -> GwG Permanent | E53: =IFERROR(__xludf.DUMMYFUNCTION("""COMPUTED_VALUE"""),41806.0) -> 41806 | F53: =IFERROR(__xludf.DUMMYFUNCTION("""COMPUTED_VALUE"""),41820.0) -> 41820 | G53: =IFERROR(__xludf.DUMMYFUNCTION("""COMPUTED_VALUE"""),0.4666666666666667) -> 0.46666667 | H53: =IFERROR(__xludf.DUMMYFUNCTION("""COMPUTED_VALUE"""),40660.0) -> 40660 | I53: =IFERROR(__xludf.DUMMYFUNCTION("""COMPUTED_VALUE"""),3.136111111111111) -> 3.1361111 | J53: =IFERROR(__xludf.DUMMYFUNCTION("""COMPUTED_VALUE"""),90.0) -> 90 | K53: =IFERROR(__xludf.DUMMYFUNCTION("""COMPUTED_VALUE"""),8.0) -> 8 | L53: =IFERROR(__xludf.DUMMYFUNCTION("""COMPUTED_VALUE"""),"Fighting") -> Fighting | M53: =NOT(ISNA(VLOOKUP(A53,PC!A:A,1,FALSE))) -> FALSE | N53: =NOT(ISNA(VLOOKUP(A53,'Game Pass Premium'!A:A,1,FALSE))) -> FALSE | O53: =NOT(ISNA(VLOOKUP(A53,'Game Pass Essential'!A:A,1,FALSE))) -> FALSE
